Workbook
Name LC_LabTargets_Array: 'Lab Calculator'!$P$3:$P$177
Name LC_HideOption: 'Lab Calculator'!$E$1
Name LC_LabNamesOrder_Array: 'Lab Calculator'!$A$3:$A$177
Name MS_Labs_Array: EXPORT!$B$5:$E$216
Name RelicValidation: #REF!
Name LC_LabLvls_Array: 'Lab Calculator'!$C$3:$C$177
Name RelicValidation: IDS!$F$7
Name LABS_LabSearchStartPoint: DVT_Laboratory!$B$3
Name LABS_LabName_Array: DVT_Laboratory!$B$1:$LO$1
Name MS_LabNamesOrder_Array: EXPORT!$B$5:$B$177
Name RelicID: IDS!$E$9
Name RelicID: #REF!
Name MS_LabDisc_LabVal: 'Master Sheet'!$C$7
Name LABS_LabLevel_Array: DVT_Laboratory!$A$3:$A$102
Name IDS_MOD_GENERATOR_ASSIST_MULT_CAP: LAMBDA('_IDS'!$BM$4)
Name IDS_MOD_GENERATOR_NAME: LAMBDA(preset, OFFSET('_IDS'!$BM$8, MATCH(preset, '_IDS'!$BL$7:$BL$23, 0)-1, 0, 1, 1))
Name IDS_MOD_CANNON_NAME: LAMBDA(preset, OFFSET('_IDS'!$BC$8, MATCH(preset, '_IDS'!$BB$7:$BB$23, 0)-1, 0, 1, 1))
Name IDS_MOD_CORE_RARITY: LAMBDA(name, IFERROR(OFFSET('_IDS'!$BQ$29, MATCH(name, '_IDS'!$BQ$27:$BQ, 0)-1, 0, 1, 1)))
Name IDS_MOD_CORE_NAME: LAMBDA(preset, OFFSET('_IDS'!$BR$8, MATCH(preset, '_IDS'!$BQ$7:$BQ$23, 0)-1, 0, 1, 1))
Name IDS_WS_CASH_LEVEL: LAMBDA(ws_name, IF('_IDS'!$G$1="✅", IFERROR(VLOOKUP(ws_name, '_IDS'!$F$2:$Q, 3, FALSE), 0), 0))
Name IDS_MOD_GENERATOR_LEVEL: LAMBDA(name, OFFSET('_IDS'!$BM$29, MATCH(name, '_IDS'!$BL$27:$BL, 0)-1, 0, 1, 1))
Name IDS_THEMES_BOOST: LAMBDA('_IDS'!$AY$2)
Name IDS_MOD_CORE_BONUS: LAMBDA(name, OFFSET('_IDS'!$BS$29, MATCH(name, '_IDS'!$BQ$27:$BQ, 0)-1, 0, 1, 1))
Name IDS_MOD_ARMOR_LEVEL: LAMBDA(name, OFFSET('_IDS'!$BH$29, MATCH(name, '_IDS'!$BG$27:$BG, 0)-1, 0, 1, 1))
Name IDS_MOD_CORE_ASSIST_SUBSTAT_CAP: LAMBDA('_IDS'!$BR$5)
Name IDS_MOD_ARMOR_SUBSTATS: LAMBDA(name, IFERROR(OFFSET('_IDS'!$BG$31, MATCH(name, '_IDS'!$BG$27:$BG, 0)-1, 0, 8, 4)))
Name LABDURATION_SINGLE_ADJUSTED_FORMATED: LAMBDA(lab_name, lab_level, XLOOKUP(lab_level,LR_LabLevel_Array,OFFSET(LR_LabSearchStartPoint,0,MATCH(lab_name,LR_LabName_Array,0),100,1),"N/F",0,1))
Name IDS_MOD_GENERATOR_ASSIST_LEVEL: LAMBDA('_IDS'!$BN$2)
Name IDS_MOD_GENERATOR_RARITY: LAMBDA(name, IFERROR(OFFSET('_IDS'!$BL$29, MATCH(name, '_IDS'!$BL$27:$BL, 0)-1, 0, 1, 1)))
Name IDS_CARDS_IN_PRESET: LAMBDA(preset, card_name, COUNTIF(OFFSET('_IDS'!$AH$3, 0, MATCH(preset, '_IDS'!$AH$2:$AL$2, 0)-1, 30, 1) , card_name) > 0)
Name IDS_PS_TIER_PB: LAMBDA(tiername, VLOOKUP(TierName, '_IDS'!$BZ$3:$CA, 2, FALSE))
Name IDS_WS_COIN_LEVEL: LAMBDA(ws_name, IF('_IDS'!$G$1="✅", IFERROR(VLOOKUP(ws_name, '_IDS'!$F$2:$Q, 2, FALSE), 0), 0))
Name IDS_MOD_ARMOR_ASSIST_MULT_CAP: LAMBDA('_IDS'!$BH$4)
Name IDS_BOT_VALUE: LAMBDA(bot_name, bot_property, LET( off, (MATCH(bot_name, '_IDS'!$AS$2:$AS$17, 0) - 1), VLOOKUP(bot_property, OFFSET('_IDS'!$AU$2, off, 0, 4, 2), 2, FALSE) ))
Name IDS_MOD_CANNON_ASSIST_NAME: LAMBDA(preset, OFFSET('_IDS'!$BC$9, MATCH(preset, '_IDS'!$BB$7:$BB$23, 0)-1, 0, 1, 1))
Name IDS_MOD_CORE_ASSIST_LEVEL: LAMBDA('_IDS'!$BS$2)
Name IDS_CARD_PRESET: LAMBDA(preset, OFFSET('_IDS'!$AH$3, 0, MATCH(preset, '_IDS'!$AH$2:$AL$2, 0)-1, 27, 1))
Name IDS_MOD_CANNON_ASSIST_LEVEL: LAMBDA('_IDS'!$BD$2)
Name IDS_PS_COIN_MULTIPLIER: LAMBDA('_IDS'!$CE$14)
Name IDS_MOD_CANNON_ASSIST_SUBSTAT_CAP: LAMBDA('_IDS'!$BC$5)
Name RELIC_STAT: LAMBDA(relic_name, IF(RelicValidation="✅", VLOOKUP(relic_name,'_IDS'!$A$1:$B,2,FALSE), 0))
Name IDS_MOD_CANNON_SUBSTATS: LAMBDA(name, IFERROR(OFFSET('_IDS'!$BB$31, MATCH(name, '_IDS'!$BB$27:$BB, 0)-1, 0, 8, 4)))
Name IDS_MOD_CORE_LEVEL: LAMBDA(name, OFFSET('_IDS'!$BR$29, MATCH(name, '_IDS'!$BQ$27:$BQ, 0)-1, 0, 1, 1))
Name IDS_MOD_CORE_ASSIST_MULT_CAP: LAMBDA('_IDS'!$BR$4)
Name IDS_BOT_OWN: LAMBDA(bot_name, LET( off, (MATCH(bot_name, '_IDS'!$AS$2:$AS$17, 0) - 1), OFFSET('_IDS'!$AS$5, off, 0, 1, 1) ))
Name LAB_SPEED_TOTAL: LAMBDA((1+('Master Sheet'!$C$8*0.02))*(1+'Master Sheet'!$BK$5))
Name IDS_UW_LEVEL: LAMBDA(uw_name, uw_stat, LET( off, (MATCH(uw_name, '_IDS'!$Z$2:$Z$37, 0) - 1), VLOOKUP(uw_stat, OFFSET('_IDS'!$AB$2, off, 0, 4, 3), 3, FALSE) ))
Name IDS_MOD_ARMOR_NAME: LAMBDA(preset, OFFSET('_IDS'!$BH$8, MATCH(preset, '_IDS'!$BG$7:$BG$23, 0)-1, 0, 1, 1))
Name IDS_MOD_CANNON_RARITY: LAMBDA(name, IFERROR(OFFSET('_IDS'!$BB$29, MATCH(name, '_IDS'!$BB$27:$BB, 0)-1, 0, 1, 1)))
Name IDS_LAB_GODLBOXED_COUNT: LAMBDA(SUMPRODUCT(--('_IDS'!$B$2:$B='_IDS'!$D$2:$D),--('_IDS'!$D$2:$D<>"")))
Name IDS_WSE_PRESET_LEVEL: LAMBDA(preset, wse_name, IF('_IDS'!$G$1="✅", IFERROR(OFFSET('_IDS'!$T$4, MATCH(wse_name, '_IDS'!$R$4:$R, 0)-1, MATCH(preset, '_IDS'!$T$2:$X$2, 0)-1, 1, 1), 0), 0))
Name IDS_CARD_LEVEL: LAMBDA(card_name, IF(VLOOKUP(card_name,'_IDS'!$AE$2:$AG$31, 2, FALSE)="Locked", 1, VLOOKUP(card_name,'_IDS'!$AE$2:$AG, 2, FALSE)))
Name IDS_WS_LEVEL: LAMBDA(ws_name, MAX(IDS_WS_COIN_LEVEL(ws_name), IDS_WS_CASH_LEVEL(ws_name)))
Name IDS_GUARDIAN_LEVEL: LAMBDA(guardian_name, guardian_stat, LET( off, (MATCH(guardian_name, '_IDS'!$BU$2:$BU, 0) - 1), VLOOKUP(guardian_stat, OFFSET('_IDS'!$BW$2, off, 0, 4, 3), 3, FALSE) ))
Name IDS_MOD_GENERATOR_ASSIST_SUBSTAT_CAP: LAMBDA('_IDS'!$BM$5)
Name LABDURATION_SINGLE_ADJUSTED: LAMBDA(lab_name, lab_level, DVT_LAB_DURATION(lab_name, lab_level) / LAB_SPEED_TOTAL())
Name DVT_MODULE_SHARDS_COST_CUMMULATIVE: LAMBDA(level, IF(level <=1, 0, SUM(ARRAYFORMULA(DVT_MODULE_SHARDS_COST(ROW(INDIRECT("1:"&level)))))))
Name IDS_UW_VALUE: LAMBDA(uw_name, uw_stat, LET( off, (MATCH(uw_name, '_IDS'!$Z$2:$Z$37, 0) - 1), VLOOKUP(uw_stat, OFFSET('_IDS'!$AB$2, off, 0, 4, 2), 2, FALSE) ))
Name IDS_MOD_CORE_SUBSTATS: LAMBDA(name, IFERROR(OFFSET('_IDS'!$BQ$31, MATCH(name, '_IDS'!$BQ$27:$BQ, 0)-1, 0, 8, 4)))
Name IDS_VAULT_STAT: LAMBDA(vault_stat, IFERROR(IF('_IDS'!$AR$1="✅", VLOOKUP(vault_stat,'_IDS'!$AP$2:$AQ,2,FALSE), 0), 0))

Sheet Home Page
B2: Laboratory
B4: =HYPERLINK("https://docs.google.com/spreadsheets/d/165-JujisYPpKi3RWew9O5gptDJ6rgr-71BbyoQafoaU/copy", "Laboratory Initial Link") -> Laboratory Initial Link | G4: Sheet Tab | H4: Creator | I4: Main Contributor | J4: Helpers
G6: IDS | H6: @Mattew | I6: @Mattew | J6: @Bisse
B7: Latest remote version : | G7: Master Sheet | H7: @TC Team | I7: @Mattew
B8: =IFERROR(__xludf.DUMMYFUNCTION("IMPORTRANGE(""165-JujisYPpKi3RWew9O5gptDJ6rgr-71BbyoQafoaU"", ""'Home Page'!B12:C13"")"),"v2.5.7") -> v2.5.7 | C8: =IFERROR(__xludf.DUMMYFUNCTION("""COMPUTED_VALUE"""),"fix: Add x7 and x8 Boost to Lab Planner") -> fix: Add x7 and x8 Boost to Lab Planner | G8: Lab Calculator | H8: @Yornola | I8: @Mattew | J8: @TC Team
B9: =IFERROR(__xludf.DUMMYFUNCTION("""COMPUTED_VALUE"""),"v2.5.6") -> v2.5.6 | C9: =IFERROR(__xludf.DUMMYFUNCTION("""COMPUTED_VALUE"""),"fix: Tier List Speed Boost not hidden") -> fix: Tier List Speed Boost not hidden | G9: Lab Planner | H9: @JayCee101 | I9: @JayCee101
G10: Tier List | H10: @Audacious, @minionek | I10: @Mattew, @Alan M | J10: @1410c, @IGotSlain, @Iver, @zAlpha
B11: Version Change : | G11: Lab Boost Calculator | H11: @GodzillasDaddy | I11: @GodzillasDaddy
B12: v2.5.7 | C12: fix: Add x7 and x8 Boost to Lab Planner | G12: Short Lab Path | H12: @Garikover | I12: @Garikover | J12: @Mattew
B13: v2.5.6 | C13: fix: Tier List Speed Boost not hidden | G13: Goldbox Path | H13: @QuietFanta | I13: @QuietFanta
B14: v2.5.5 | C14: fix: Updated Lab Planner UI for readability. | G14: Interactive Thorns | H14: @phoenix345 | I14: @phoenix345 | J14: @Mattew, @xiao_shaa
B15: v2.5.4 | C15: fix: Lab Planner Gem Rush - missing BC labs | G15: ELS BC Reduction | H15: @yournicknm | I15: @yournicknm
B16: v2.5.3 | C16: fix: UW Labs in Gold Box Path | G16: Elites Spawncap | J16: @Mattew
B17: v2.5.2 | C17: fix: Lab Planner Gem Rush
B18: v2.5.1 | C18: fix: PB Grabber for Gold/Short Path | G18: Tab colors explanation
B19: v2.5 | C19: feat: Saving Gems by Gold Boxing
B20: v2.4.7 | C20: feat: Enhanced the Tier List Script to be way faster | G20: Home Page | H20: Input Tabs | I20: Local Tools | J20: Static Data
B21: v2.4.6 | C21: fix: Short Lab Path pulling Tier dropdown from Player&Stuff
B22: v2.4.5 | C22: fix: Goldbox Path pulling Tier dropdown from Player&Stuff
B23: v2.4.4 | C23: fix: Labs Speed double dipping in Duration | G23: Enjoying those sheets? You can support me by using my creator code for any in game or webstore purchases. My creator code is : SHEETLORD
B24: v2.4.3 | C24: feat: cost limit added to Goldbox Path
B25: v2.4.2 | C25: fix: Goldbox Path Ignores Target Levels
B26: v2.4.1 | C26: feat: Updated Rush Gem calculation
B27: v2.4 | C27: feat: Goldbox Path
B28: v2.3.2 | C28: feature: Update Lab Boost Calculator for x7 and x8 boosts | G28: Want to support someone else ? Here is the creator code list
B29: v2.3.2 | C29: fix: Lab Speed Relic formula
B30: v2.3.1 | C30: fix: Minor tweaks to Lab Boost Calculator | G30: =IFERROR(__xludf.DUMMYFUNCTION("IMPORTRANGE(""1eCPPuQOE3Pyh8HhnApEMK3RFIutkUjWd61ppVImwWk8"", ""_Giveaway_summary!A1:A2"")"),"⚠️ 1 Giveaway(s) running - 22 Mar") -> ⚠️ 1 Giveaway(s) running - 22 Mar
B31: v2.3 | C31: feat: Tier List (@Audacious, @minionek, @Alan M) | G31: =IFERROR(__xludf.DUMMYFUNCTION("""COMPUTED_VALUE"""),"Giveaway Details") -> Giveaway Details
B32: v2.2.4 | C32: feat: Thorns Calc now reads Thorns Substats
B33: v2.2.3 | C33: fix: Lab Planner 4 and 5 looked at wrong lab boost cell
B34: v2.2.2 | C34: feat: Enhanced Short Lab Path with "ignore targets"
B35: v2.2.1 | C35: feat: Lab Planner switch between time and date mode
B36: v2.2 | C36: Add: Short Lab Path
B37: v2.1.5.2 | C37: fix: Lab Calc filter (For real this time)
B38: v2.1.5.1 | C38: fix: Lab Calc filter
B39: v2.1.5 | C39: feat: Added a CPH column to Lab Calculator
B40: v2.1.4 | C40: fix: Interactive Thorns Elites+PCm for SF
B41: v2.1.3 | C41: fix: BC max lab levels on Calculator
B42: v2.1.2 | C42: feat: Fleets in Thorns Calculations
B43: v2.1.1 | C43: fix: Elite Defense labs -> Elite Health
... B57: v1.0 | C57: Initial Version

Sheet IDS
B2: The IDS System | I2: Looking for the Import script ? Just run it as you were doing it before, but from IDS Master. It will let you import every new versions at once!
B4: This Sheet ID is : | C4: 1jojOg_XIJCzm1LCYWu2F4KCtErjUIdKuFL1PiKzA0OE
B6: IDS Master's ID ➡️ | C6: 1HOIkxWbbciTIAzVruaahEGADlM8rS0-w86uBXj4PwNQ | D6: =IFERROR(__xludf.DUMMYFUNCTION("IFERROR(C6.url, IFS(LEFT(C6,8)=""https://"", C6, LEN(C6)=44, ""https://docs.google.com/spreadsheets/d/"" & C6 & ""/edit"", TRUE, C6))"),"https://docs.google.com/spreadsheets/d/1HOIkxWbbciTIAzVruaahEGADlM8rS0-w86uBXj4PwNQ/edit") -> https://docs.google.com/spreadsheets/d/1HOIkxWbbciTIAzVruaahEGADlM8rS0-w86uBXj4PwNQ/edit | E6: =IFERROR(__xludf.DUMMYFUNCTION("IF(D6<>"""", IF(IMPORTRANGE(D6,""EXPORT!A1"") = F6, ""✅"", ""Wrong ID or Version""), """")"),"✅") -> ✅ | F6: v2
B7: =HYPERLINK("https://docs.google.com/spreadsheets/d/1osjoqKmMwtOWs7Up3e21-3ofN1RHOjsgKV6y3dc6rgE/copy", "1️⃣ Copy Me") -> 1️⃣ Copy Me | C7: =IFS( ISERROR(E6), "3️⃣ Click on #REF! and then AUTHORISE ↗", E6="", "2️⃣ Please input your IDS Master's ID here ⤴️", E6="✅", HYPERLINK(D6, "Go to my IDS Master Sheet"), TRUE, "") -> Go to my IDS Master Sheet | E7: ✅ | I7: Issues
I8: Mobile Users If you are on mobile, you will not be able to do STEP 3. There is a workaround you can do still : You need to edit the viewing permissions to "anyone with the link" of all your IDs sheets If you have any other trouble, let us know in the #effective-path Discord's channel. I say us, but don't ask Fanta. Fanta hates IDS.
B9: How to use
B10: STEP 1: Click on the Copy Me link and create your copy of the IDS Master. STEP 2: Copy the ID (you will find it in the IDS tab) of your newly created sheet and paste it in the light gray area. STEP 3: Wait a little bit, the F5 cell will show "Loading...", and after few seconds it will display "#REF!". Click on the cell, and "Authorize" to let this sheet access the other one.
B19: And that's it! The IDS are setuped. You can now fill sub IDS in the IDS Master with sub IDS sheets (Laboratory, Workshop, ...) just like you did in here. Every time you will change a value (let's say, a lab level in Laboratory Sheet) the change will be propagated to every other sheet using the IDS Master automatically.
B23: Is it mandatory ?
B24: No, it is not really mandatory but it is the best practice I would recommend. You should be able to override everything using the Master Sheet. But that's not how this is supposed to be used.

Sheet Master Sheet
B1: Labs | C1: Level | D1: Target | E1: Max | G1: Labs | H1: Level | I1: Target | J1: Max | L1: Labs | M1: Level | N1: Target | O1: Max | Q1: Labs | R1: Level | S1: Target | T1: Max | V1: Labs | W1: Level | X1: Target | Y1: Max | AA1: Labs | AB1: Level | AC1: Target | AD1: Max | AF1: Labs | AG1: Level | AH1: Target | AI1: Max | AK1: Labs | AL1: Level | AM1: Target | AN1: Max | AP1: Labs | AQ1: Level | AR1: Target | AS1: Max | AU1: Labs | AV1: Level | AW1: Target | AX1: Max | AZ1: Labs | BA1: Level | BB1: Target | BC1: Max | BE1: Workshop Upgrade | BF1: ¢ Level | BG1: $ Level | BH1: Max | BJ1: Card Name | BK1: Level | BL1: Mastery
A2: ="("&ROUND(C43/E43*100,0)&"%)" -> (31%) | B2: Game Speed | C2: 7 | D2: 7 | E2: =COUNTA(OFFSET(DVT_Laboratory!$B$3, 0, MATCH(B2,DVT_Laboratory!$B$1:BM$1, 0)-1, 100, 1)) -> 7 | F2: ="("&ROUND(H43/J43*100,0)&"%)" -> (50%) | G2: Damage | H2: 69 | J2: =COUNTA(OFFSET(DVT_Laboratory!$B$3, 0, MATCH(G2,DVT_Laboratory!$B$1:BM$1, 0)-1, 100, 1)) -> 100 | K2: ="("&ROUND(M43/O43*100,0)&"%)" -> (58%) | L2: Health | M2: 68 | O2: =COUNTA(OFFSET(DVT_Laboratory!$B$3, 0, MATCH(L2,DVT_Laboratory!$B$1:BM$1, 0)-1, 100, 1)) -> 100 | P2: ="("&ROUND(R43/T43*100,0)&"%)" -> (35%) | Q2: Cash Bonus | R2: 33 | T2: =COUNTA(OFFSET(DVT_Laboratory!$B$3, 0, MATCH(Q2,DVT_Laboratory!$B$1:BM$1, 0)-1, 100, 1)) -> 99 | U2: ="("&ROUND(W43/Y43*100,0)&"%)" -> (42%) | V2: Missile Despawn Time | W2: 0 | Y2: =COUNTA(OFFSET(DVT_Laboratory!$B$3, 0, MATCH(V2,DVT_Laboratory!$B$1:BM$1, 0)-1, 100, 1)) -> 20 | Z2: ="("&ROUND(AB43/AD43*100,0)&"%)" -> (9%) | AA2: Second Wind Blast | AB2: 4 | AD2: =COUNTA(OFFSET(DVT_Laboratory!$B$3, 0, MATCH(AA2,DVT_Laboratory!$B$1:BM$1, 0)-1, 100, 1)) -> 4 | AE2: ="("&ROUND(AG43/AI43*100,0)&"%)" -> (39%) | AF2: Unlock Perks | AG2: 1 | AI2: =COUNTA(OFFSET(DVT_Laboratory!$B$3, 0, MATCH(AF2,DVT_Laboratory!$B$1:BM$1, 0)-1, 100, 1)) -> 1 | AJ2: ="("&ROUND(AL43/AN43*100,0)&"%)" -> (35%) | AK2: Flame Bot - Cooldown | AL2: 25 | AN2: =COUNTA(OFFSET(DVT_Laboratory!$B$3, 0, MATCH(AK2,DVT_Laboratory!$B$1:BM$1, 0)-1, 100, 1)) -> 25 | AO2: ="("&ROUND(AQ43/AS43*100,0)&"%)" -> (0%) | AP2: Common Enemy Health | AQ2: 0 | AS2: =COUNTA(OFFSET(DVT_Laboratory!$B$3, 0, MATCH(AP2,DVT_Laboratory!$B$1:BM$1, 0)-1, 100, 1)) -> 30 | AT2: ="("&ROUND(AV43/AX43*100,0)&"%)" -> (48%) | AU2: Common Drop Chance | AV2: 10 | AX2: =COUNTA(OFFSET(DVT_Laboratory!$B$3, 0, MATCH(AU2,DVT_Laboratory!$B$1:BM$1, 0)-1, 100, 1)) -> 10 | AY2: ="("&ROUND(BA43/BC43*100,0)&"%)" -> (0%) | AZ2: Battle Condition Reduction | BA2: 0 | BC2: =COUNTA(OFFSET(DVT_Laboratory!$B$3, 0, MATCH(AZ2,DVT_Laboratory!$B$1:BM$1, 0)-1, 100, 1)) -> 10 | BD2: OTHERS - WORKSHOP | BE2: Thorn Damage | BF2: =IDS_WS_COIN_LEVEL(BE2) -> 99 | BG2: =IDS_WS_CASH_LEVEL(BE2) -> 99 | BH2: 99 | BI2: OTHERS | BJ2: Plasma Cannon | BK2: =IDS_CARD_LEVEL(BJ2) -> 7 | BL2: =IDS_CARD_MASTERY(BJ2) -> FALSE
B3: Starting Cash | C3: 6 | E3: =COUNTA(OFFSET(DVT_Laboratory!$B$3, 0, MATCH(B3,DVT_Laboratory!$B$1:BM$1, 0)-1, 100, 1)) -> 99 | G3: Attack Speed | H3: 75 | J3: =COUNTA(OFFSET(DVT_Laboratory!$B$3, 0, MATCH(G3,DVT_Laboratory!$B$1:BM$1, 0)-1, 100, 1)) -> 99 | L3: Health Regen | M3: 68 | O3: =COUNTA(OFFSET(DVT_Laboratory!$B$3, 0, MATCH(L3,DVT_Laboratory!$B$1:BM$1, 0)-1, 100, 1)) -> 100 | Q3: Cash / Wave | R3: 8 | T3: =COUNTA(OFFSET(DVT_Laboratory!$B$3, 0, MATCH(Q3,DVT_Laboratory!$B$1:BM$1, 0)-1, 100, 1)) -> 99 | V3: Missiles Explosion | W3: 0 | Y3: =COUNTA(OFFSET(DVT_Laboratory!$B$3, 0, MATCH(V3,DVT_Laboratory!$B$1:BM$1, 0)-1, 100, 1)) -> 1 | AA3: Double Death Ray | AB3: 6 | AD3: =COUNTA(OFFSET(DVT_Laboratory!$B$3, 0, MATCH(AA3,DVT_Laboratory!$B$1:BM$1, 0)-1, 100, 1)) -> 30 | AF3: Waves Required | AG3: 13 | AH3: 17 | AI3: =COUNTA(OFFSET(DVT_Laboratory!$B$3, 0, MATCH(AF3,DVT_Laboratory!$B$1:BM$1, 0)-1, 100, 1)) -> 100 | AK3: Thunder Bot - Cooldown | AL3: 0 | AN3: =COUNTA(OFFSET(DVT_Laboratory!$B$3, 0, MATCH(AK3,DVT_Laboratory!$B$1:BM$1, 0)-1, 100, 1)) -> 25 | AP3: Common Enemy Attack | AQ3: 0 | AS3: =COUNTA(OFFSET(DVT_Laboratory!$B$3, 0, MATCH(AP3,DVT_Laboratory!$B$1:BM$1, 0)-1, 100, 1)) -> 30 | AU3: Reroll Shards | AV3: 100 | AW3: 100 | AX3: =COUNTA(OFFSET(DVT_Laboratory!$B$3, 0, MATCH(AU3,DVT_Laboratory!$B$1:BM$1, 0)-1, 100, 1)) -> 100 | AZ3: Knockback Resistance | BA3: 0 | BC3: =COUNTA(OFFSET(DVT_Laboratory!$B$3, 0, MATCH(AZ3,DVT_Laboratory!$B$1:BM$1, 0)-1, 100, 1)) -> 20
B4: Workshop Attack Discount | C4: 27 | E4: =COUNTA(OFFSET(DVT_Laboratory!$B$3, 0, MATCH(B4,DVT_Laboratory!$B$1:BM$1, 0)-1, 100, 1)) -> 99 | G4: Critical Factor | H4: 83 | J4: =COUNTA(OFFSET(DVT_Laboratory!$B$3, 0, MATCH(G4,DVT_Laboratory!$B$1:BM$1, 0)-1, 100, 1)) -> 99 | L4: Defense Absolute | M4: 14 | N4: 14 | O4: =COUNTA(OFFSET(DVT_Laboratory!$B$3, 0, MATCH(L4,DVT_Laboratory!$B$1:BM$1, 0)-1, 100, 1)) -> 100 | Q4: Coins / Kill Bonus | R4: 87 | T4: =COUNTA(OFFSET(DVT_Laboratory!$B$3, 0, MATCH(Q4,DVT_Laboratory!$B$1:BM$1, 0)-1, 100, 1)) -> 99 | V4: Missile Radius | W4: 0 | Y4: =COUNTA(OFFSET(DVT_Laboratory!$B$3, 0, MATCH(V4,DVT_Laboratory!$B$1:BM$1, 0)-1, 100, 1)) -> 20 | AA4: Extra Orb Adjuster | AB4: 1 | AD4: =COUNTA(OFFSET(DVT_Laboratory!$B$3, 0, MATCH(AA4,DVT_Laboratory!$B$1:BM$1, 0)-1, 100, 1)) -> 1 | AF4: Auto Pick Perks | AG4: 1 | AI4: =COUNTA(OFFSET(DVT_Laboratory!$B$3, 0, MATCH(AF4,DVT_Laboratory!$B$1:BM$1, 0)-1, 100, 1)) -> 1 | AK4: Gold Bot - Cooldown | AL4: 21 | AN4: =COUNTA(OFFSET(DVT_Laboratory!$B$3, 0, MATCH(AK4,DVT_Laboratory!$B$1:BM$1, 0)-1, 100, 1)) -> 25 | AP4: Fast Enemy Health | AQ4: 0 | AS4: =COUNTA(OFFSET(DVT_Laboratory!$B$3, 0, MATCH(AP4,DVT_Laboratory!$B$1:BM$1, 0)-1, 100, 1)) -> 30 | AU4: Daily Mission Shards | AV4: 50 | AW4: 50 | AX4: =COUNTA(OFFSET(DVT_Laboratory!$B$3, 0, MATCH(AU4,DVT_Laboratory!$B$1:BM$1, 0)-1, 100, 1)) -> 50 | AZ4: Thorns Resistance | BA4: 0 | BC4: =COUNTA(OFFSET(DVT_Laboratory!$B$3, 0, MATCH(AZ4,DVT_Laboratory!$B$1:BM$1, 0)-1, 100, 1)) -> 20 | BJ4: =IF('_IDS'!AH1="✅", HYPERLINK('_IDS'!AG1, "Go to my Relic Sheet"), "Relic") -> Relic | BK4: Bonus
A5: MAIN RESEARCHES | B5: Workshop Defense Discount | C5: 28 | E5: =COUNTA(OFFSET(DVT_Laboratory!$B$3, 0, MATCH(B5,DVT_Laboratory!$B$1:BM$1, 0)-1, 100, 1)) -> 99 | F5: ATTACK | G5: Range | H5: 33 | J5: =COUNTA(OFFSET(DVT_Laboratory!$B$3, 0, MATCH(G5,DVT_Laboratory!$B$1:BM$1, 0)-1, 100, 1)) -> 80 | K5: DEFENSE | L5: Defense % | M5: 28 | N5: 28 | O5: =COUNTA(OFFSET(DVT_Laboratory!$B$3, 0, MATCH(L5,DVT_Laboratory!$B$1:BM$1, 0)-1, 100, 1)) -> 50 | P5: UTILITY | Q5: Coins / Wave | R5: 6 | T5: =COUNTA(OFFSET(DVT_Laboratory!$B$3, 0, MATCH(Q5,DVT_Laboratory!$B$1:BM$1, 0)-1, 100, 1)) -> 99 | U5: ULTIMATE WEAPONS | V5: Chrono Field Duration | W5: 30 | Y5: =COUNTA(OFFSET(DVT_Laboratory!$B$3, 0, MATCH(V5,DVT_Laboratory!$B$1:BM$1, 0)-1, 100, 1)) -> 30 | Z5: CARDS | AA5: Extra Extra Orbs | AB5: 2 | AD5: =COUNTA(OFFSET(DVT_Laboratory!$B$3, 0, MATCH(AA5,DVT_Laboratory!$B$1:BM$1, 0)-1, 100, 1)) -> 2 | AE5: PERKS | AF5: Standard Perks Bonus | AG5: 25 | AI5: =COUNTA(OFFSET(DVT_Laboratory!$B$3, 0, MATCH(AF5,DVT_Laboratory!$B$1:BM$1, 0)-1, 100, 1)) -> 25 | AJ5: BOTS | AK5: Amp Bot - Cooldown | AL5: 0 | AN5: =COUNTA(OFFSET(DVT_Laboratory!$B$3, 0, MATCH(AK5,DVT_Laboratory!$B$1:BM$1, 0)-1, 100, 1)) -> 25 | AO5: ENEMIES | AP5: Fast Enemy Attack | AQ5: 0 | AS5: =COUNTA(OFFSET(DVT_Laboratory!$B$3, 0, MATCH(AP5,DVT_Laboratory!$B$1:BM$1, 0)-1, 100, 1)) -> 30 | AT5: MODULES | AU5: Module Shards Cost | AV5: 30 | AX5: =COUNTA(OFFSET(DVT_Laboratory!$B$3, 0, MATCH(AU5,DVT_Laboratory!$B$1:BM$1, 0)-1, 100, 1)) -> 30 | AY5: BATTLE CONDITION | AZ5: Orb Resistance | BA5: 0 | BC5: =COUNTA(OFFSET(DVT_Laboratory!$B$3, 0, MATCH(AZ5,DVT_Laboratory!$B$1:BM$1, 0)-1, 100, 1)) -> 20 | BJ5: Lab Speed | BK5: =IDS_RELIC_STAT(BJ5) -> 0.395
B6: Workshop Utility Discount | C6: 41 | E6: =COUNTA(OFFSET(DVT_Laboratory!$B$3, 0, MATCH(B6,DVT_Laboratory!$B$1:BM$1, 0)-1, 100, 1)) -> 99 | G6: Damage / Meter | H6: 16 | J6: =COUNTA(OFFSET(DVT_Laboratory!$B$3, 0, MATCH(G6,DVT_Laboratory!$B$1:BM$1, 0)-1, 100, 1)) -> 99 | L6: Orbs Speed | M6: 20 | O6: =COUNTA(OFFSET(DVT_Laboratory!$B$3, 0, MATCH(L6,DVT_Laboratory!$B$1:BM$1, 0)-1, 100, 1)) -> 20 | Q6: Interest | R6: 11 | T6: =COUNTA(OFFSET(DVT_Laboratory!$B$3, 0, MATCH(Q6,DVT_Laboratory!$B$1:BM$1, 0)-1, 100, 1)) -> 99 | V6: Chrono Field Damage Reduction | W6: 1 | Y6: =COUNTA(OFFSET(DVT_Laboratory!$B$3, 0, MATCH(V6,DVT_Laboratory!$B$1:BM$1, 0)-1, 100, 1)) -> 1 | AA6: Energy Shield Extra Hit | AB6: 2 | AD6: =COUNTA(OFFSET(DVT_Laboratory!$B$3, 0, MATCH(AA6,DVT_Laboratory!$B$1:BM$1, 0)-1, 100, 1)) -> 2 | AF6: Perk Option Quantity | AG6: 2 | AI6: =COUNTA(OFFSET(DVT_Laboratory!$B$3, 0, MATCH(AF6,DVT_Laboratory!$B$1:BM$1, 0)-1, 100, 1)) -> 2 | AK6: Flame Bot - Burn Stack | AL6: 0 | AN6: =COUNTA(OFFSET(DVT_Laboratory!$B$3, 0, MATCH(AK6,DVT_Laboratory!$B$1:BM$1, 0)-1, 100, 1)) -> 5 | AP6: Fast Enemy Speed | AQ6: 0 | AS6: =COUNTA(OFFSET(DVT_Laboratory!$B$3, 0, MATCH(AP6,DVT_Laboratory!$B$1:BM$1, 0)-1, 100, 1)) -> 30 | AU6: Module Coin Cost | AV6: 23 | AX6: =COUNTA(OFFSET(DVT_Laboratory!$B$3, 0, MATCH(AU6,DVT_Laboratory!$B$1:BM$1, 0)-1, 100, 1)) -> 30 | AZ6: Plasma Cannon Resistance | BA6: 0 | BC6: =COUNTA(OFFSET(DVT_Laboratory!$B$3, 0, MATCH(AZ6,DVT_Laboratory!$B$1:BM$1, 0)-1, 100, 1)) -> 20 | BJ6: Thorns | BK6: =IDS_RELIC_STAT(BJ6) -> 0.09
B7: Labs Coin Discount | C7: 68 | E7: =COUNTA(OFFSET(DVT_Laboratory!$B$3, 0, MATCH(B7,DVT_Laboratory!$B$1:BM$1, 0)-1, 100, 1)) -> 99 | G7: Super Crit Chance | H7: 9 | J7: =COUNTA(OFFSET(DVT_Laboratory!$B$3, 0, MATCH(G7,DVT_Laboratory!$B$1:BM$1, 0)-1, 100, 1)) -> 50 | L7: Land Mine Damage | M7: 0 | O7: =COUNTA(OFFSET(DVT_Laboratory!$B$3, 0, MATCH(L7,DVT_Laboratory!$B$1:BM$1, 0)-1, 100, 1)) -> 20 | Q7: Max Interest | R7: 8 | T7: =COUNTA(OFFSET(DVT_Laboratory!$B$3, 0, MATCH(Q7,DVT_Laboratory!$B$1:BM$1, 0)-1, 100, 1)) -> 15 | V7: Chrono Field Reduction % | W7: 20 | Y7: =COUNTA(OFFSET(DVT_Laboratory!$B$3, 0, MATCH(V7,DVT_Laboratory!$B$1:BM$1, 0)-1, 100, 1)) -> 30 | AA7: Super Tower Bonus | AB7: 0 | AD7: =COUNTA(OFFSET(DVT_Laboratory!$B$3, 0, MATCH(AA7,DVT_Laboratory!$B$1:BM$1, 0)-1, 100, 1)) -> 30 | AF7: First Perk Choice | AG7: 1 | AI7: =COUNTA(OFFSET(DVT_Laboratory!$B$3, 0, MATCH(AF7,DVT_Laboratory!$B$1:BM$1, 0)-1, 100, 1)) -> 1 | AK7: Thunder Bot - Linger Time | AL7: 0 | AN7: =COUNTA(OFFSET(DVT_Laboratory!$B$3, 0, MATCH(AK7,DVT_Laboratory!$B$1:BM$1, 0)-1, 100, 1)) -> 20 | AP7: Tank Enemy Health | AQ7: 0 | AS7: =COUNTA(OFFSET(DVT_Laboratory!$B$3, 0, MATCH(AP7,DVT_Laboratory!$B$1:BM$1, 0)-1, 100, 1)) -> 30 | AU7: Rare Drop Chance | AV7: 10 | AW7: 10 | AX7: =COUNTA(OFFSET(DVT_Laboratory!$B$3, 0, MATCH(AU7,DVT_Laboratory!$B$1:BM$1, 0)-1, 100, 1)) -> 10 | AZ7: Death Ray Resistance | BA7: 0 | BC7: =COUNTA(OFFSET(DVT_Laboratory!$B$3, 0, MATCH(AZ7,DVT_Laboratory!$B$1:BM$1, 0)-1, 100, 1)) -> 20
B8: Labs Speed | C8: 91 | E8: =COUNTA(OFFSET(DVT_Laboratory!$B$3, 0, MATCH(B8,DVT_Laboratory!$B$1:BM$1, 0)-1, 100, 1)) -> 99 | G8: Super Crit Multi | H8: 13 | J8: =COUNTA(OFFSET(DVT_Laboratory!$B$3, 0, MATCH(G8,DVT_Laboratory!$B$1:BM$1, 0)-1, 100, 1)) -> 40 | L8: Land Mine Decay | M8: 13 | O8: =COUNTA(OFFSET(DVT_Laboratory!$B$3, 0, MATCH(L8,DVT_Laboratory!$B$1:BM$1, 0)-1, 100, 1)) -> 35 | Q8: Package After Boss | R8: 1 | T8: =COUNTA(OFFSET(DVT_Laboratory!$B$3, 0, MATCH(Q8,DVT_Laboratory!$B$1:BM$1, 0)-1, 100, 1)) -> 1 | V8: Swamp Radius | W8: 0 | Y8: =COUNTA(OFFSET(DVT_Laboratory!$B$3, 0, MATCH(V8,DVT_Laboratory!$B$1:BM$1, 0)-1, 100, 1)) -> 30 | AA8: Recharge Second Wind | AB8: 7 | AD8: =COUNTA(OFFSET(DVT_Laboratory!$B$3, 0, MATCH(AA8,DVT_Laboratory!$B$1:BM$1, 0)-1, 100, 1)) -> 7 | AF8: Ban Perks | AG8: 6 | AI8: =COUNTA(OFFSET(DVT_Laboratory!$B$3, 0, MATCH(AF8,DVT_Laboratory!$B$1:BM$1, 0)-1, 100, 1)) -> 8 | AK8: Gold Bot - Duration | AL8: 12 | AN8: =COUNTA(OFFSET(DVT_Laboratory!$B$3, 0, MATCH(AK8,DVT_Laboratory!$B$1:BM$1, 0)-1, 100, 1)) -> 20 | AP8: Tank Enemy Attack | AQ8: 0 | AS8: =COUNTA(OFFSET(DVT_Laboratory!$B$3, 0, MATCH(AP8,DVT_Laboratory!$B$1:BM$1, 0)-1, 100, 1)) -> 30 | AU8: Unmerge Module | AV8: 1 | AX8: =COUNTA(OFFSET(DVT_Laboratory!$B$3, 0, MATCH(AU8,DVT_Laboratory!$B$1:BM$1, 0)-1, 100, 1)) -> 1 | AZ8: Armored Enemies | BA8: 0 | BC8: =COUNTA(OFFSET(DVT_Laboratory!$B$3, 0, MATCH(AZ8,DVT_Laboratory!$B$1:BM$1, 0)-1, 100, 1)) -> 20 | BJ8: =IF('_IDS'!$AK$1="✅", HYPERLINK('_IDS'!AJ1, "Go to my Vault Sheet"), "Vault") -> Vault | BK8: Bonus
B9: Buy Multiplier | C9: 4 | E9: =COUNTA(OFFSET(DVT_Laboratory!$B$3, 0, MATCH(B9,DVT_Laboratory!$B$1:BM$1, 0)-1, 100, 1)) -> 4 | G9: Max Rend Armor Multiplier | H9: 0 | J9: =COUNTA(OFFSET(DVT_Laboratory!$B$3, 0, MATCH(G9,DVT_Laboratory!$B$1:BM$1, 0)-1, 100, 1)) -> 30 | L9: Shockwave Size | M9: 10 | O9: =COUNTA(OFFSET(DVT_Laboratory!$B$3, 0, MATCH(L9,DVT_Laboratory!$B$1:BM$1, 0)-1, 100, 1)) -> 20 | Q9: Recovery Package Amount | R9: 0 | T9: =COUNTA(OFFSET(DVT_Laboratory!$B$3, 0, MATCH(Q9,DVT_Laboratory!$B$1:BM$1, 0)-1, 100, 1)) -> 20 | V9: Swamp Stun | W9: 0 | Y9: =COUNTA(OFFSET(DVT_Laboratory!$B$3, 0, MATCH(V9,DVT_Laboratory!$B$1:BM$1, 0)-1, 100, 1)) -> 1 | AA9: Recharge Demon Mode | AB9: 4 | AD9: =COUNTA(OFFSET(DVT_Laboratory!$B$3, 0, MATCH(AA9,DVT_Laboratory!$B$1:BM$1, 0)-1, 100, 1)) -> 7 | AF9: Improve Trade-off Perks | AG9: 10 | AI9: =COUNTA(OFFSET(DVT_Laboratory!$B$3, 0, MATCH(AF9,DVT_Laboratory!$B$1:BM$1, 0)-1, 100, 1)) -> 10 | AK9: Amp Bot - Duration | AL9: 0 | AN9: =COUNTA(OFFSET(DVT_Laboratory!$B$3, 0, MATCH(AK9,DVT_Laboratory!$B$1:BM$1, 0)-1, 100, 1)) -> 20 | AP9: Ranged Enemy Health | AQ9: 0 | AS9: =COUNTA(OFFSET(DVT_Laboratory!$B$3, 0, MATCH(AP9,DVT_Laboratory!$B$1:BM$1, 0)-1, 100, 1)) -> 30 | AU9: Shatter Shards | AV9: 5 | AX9: =COUNTA(OFFSET(DVT_Laboratory!$B$3, 0, MATCH(AU9,DVT_Laboratory!$B$1:BM$1, 0)-1, 100, 1)) -> 5 | AZ9: Enemy Speed | BA9: 0 | BC9: =COUNTA(OFFSET(DVT_Laboratory!$B$3, 0, MATCH(AZ9,DVT_Laboratory!$B$1:BM$1, 0)-1, 100, 1)) -> 20 | BJ9: Thorn Damage | BK9: =IDS_VAULT_STAT(BJ9) -> 0
B10: More Round Stats | C10: 1 | E10: =COUNTA(OFFSET(DVT_Laboratory!$B$3, 0, MATCH(B10,DVT_Laboratory!$B$1:BM$1, 0)-1, 100, 1)) -> 1 | G10: Light Speed Shots | H10: 1 | J10: =COUNTA(OFFSET(DVT_Laboratory!$B$3, 0, MATCH(G10,DVT_Laboratory!$B$1:BM$1, 0)-1, 100, 1)) -> 1 | L10: Orb Boss Hit | M10: 10 | O10: =COUNTA(OFFSET(DVT_Laboratory!$B$3, 0, MATCH(L10,DVT_Laboratory!$B$1:BM$1, 0)-1, 100, 1)) -> 10 | Q10: Recovery Package Max | R10: 0 | T10: =COUNTA(OFFSET(DVT_Laboratory!$B$3, 0, MATCH(Q10,DVT_Laboratory!$B$1:BM$1, 0)-1, 100, 1)) -> 20 | V10: Swamp Stun Chance | W10: 0 | Y10: =COUNTA(OFFSET(DVT_Laboratory!$B$3, 0, MATCH(V10,DVT_Laboratory!$B$1:BM$1, 0)-1, 100, 1)) -> 30 | AA10: Recharge Nuke | AB10: 2 | AD10: =COUNTA(OFFSET(DVT_Laboratory!$B$3, 0, MATCH(AA10,DVT_Laboratory!$B$1:BM$1, 0)-1, 100, 1)) -> 7 | AF10: Auto Pick Ranking | AG10: 12 | AI10: =COUNTA(OFFSET(DVT_Laboratory!$B$3, 0, MATCH(AF10,DVT_Laboratory!$B$1:BM$1, 0)-1, 100, 1)) -> 32 | AP10: Ranged Enemy Attack | AQ10: 0 | AS10: =COUNTA(OFFSET(DVT_Laboratory!$B$3, 0, MATCH(AP10,DVT_Laboratory!$B$1:BM$1, 0)-1, 100, 1)) -> 30 | AU10: Cannon Effect Bans | AV10: 0 | AX10: =COUNTA(OFFSET(DVT_Laboratory!$B$3, 0, MATCH(AU10,DVT_Laboratory!$B$1:BM$1, 0)-1, 100, 1)) -> 4 | AZ10: More Enemies | BA10: 0 | BC10: =COUNTA(OFFSET(DVT_Laboratory!$B$3, 0, MATCH(AZ10,DVT_Laboratory!$B$1:BM$1, 0)-1, 100, 1)) -> 20
B11: Target Priority | C11: 2 | E11: =COUNTA(OFFSET(DVT_Laboratory!$B$3, 0, MATCH(B11,DVT_Laboratory!$B$1:BM$1, 0)-1, 100, 1)) -> 2 | L11: Wall Health | M11: 50 | O11: =COUNTA(OFFSET(DVT_Laboratory!$B$3, 0, MATCH(L11,DVT_Laboratory!$B$1:BM$1, 0)-1, 100, 1)) -> 50 | Q11: Recovery Package Chance | R11: 20 | T11: =COUNTA(OFFSET(DVT_Laboratory!$B$3, 0, MATCH(Q11,DVT_Laboratory!$B$1:BM$1, 0)-1, 100, 1)) -> 20 | V11: Swamp Stun Time | W11: 0 | Y11: =COUNTA(OFFSET(DVT_Laboratory!$B$3, 0, MATCH(V11,DVT_Laboratory!$B$1:BM$1, 0)-1, 100, 1)) -> 30 | AA11: Damage Mastery | AB11: 0 | AD11: =COUNTA(OFFSET(DVT_Laboratory!$B$3, 0, MATCH("Card Mastery",DVT_Laboratory!$B$1:BM$1, 0)-1, 100, 1)) -> 9 | AP11: Boss Health | AQ11: 0 | AS11: =COUNTA(OFFSET(DVT_Laboratory!$B$3, 0, MATCH(AP11,DVT_Laboratory!$B$1:BM$1, 0)-1, 100, 1)) -> 30 | AU11: Armor Effect Bans | AV11: 2 | AX11: =COUNTA(OFFSET(DVT_Laboratory!$B$3, 0, MATCH(AU11,DVT_Laboratory!$B$1:BM$1, 0)-1, 100, 1)) -> 4 | AZ11: Enemy Attack Speed | BA11: 0 | BC11: =COUNTA(OFFSET(DVT_Laboratory!$B$3, 0, MATCH(AZ11,DVT_Laboratory!$B$1:BM$1, 0)-1, 100, 1)) -> 20
B12: Card Presets | C12: 1 | E12: =COUNTA(OFFSET(DVT_Laboratory!$B$3, 0, MATCH(B12,DVT_Laboratory!$B$1:BM$1, 0)-1, 100, 1)) -> 1 | L12: Wall Rebuild | M12: 9 | O12: =COUNTA(OFFSET(DVT_Laboratory!$B$3, 0, MATCH(L12,DVT_Laboratory!$B$1:BM$1, 0)-1, 100, 1)) -> 20 | Q12: Enemy Attack Level Skip | R12: 20 | T12: =COUNTA(OFFSET(DVT_Laboratory!$B$3, 0, MATCH(Q12,DVT_Laboratory!$B$1:BM$1, 0)-1, 100, 1)) -> 20 | V12: Golden Tower Bonus | W12: 22 | Y12: =COUNTA(OFFSET(DVT_Laboratory!$B$3, 0, MATCH(V12,DVT_Laboratory!$B$1:BM$1, 0)-1, 100, 1)) -> 25 | AA12: Attack Speed Mastery | AB12: 0 | AD12: =COUNTA(OFFSET(DVT_Laboratory!$B$3, 0, MATCH("Card Mastery",DVT_Laboratory!$B$1:BM$1, 0)-1, 100, 1)) -> 9 | AP12: Boss Attack | AQ12: 0 | AS12: =COUNTA(OFFSET(DVT_Laboratory!$B$3, 0, MATCH(AP12,DVT_Laboratory!$B$1:BM$1, 0)-1, 100, 1)) -> 30 | AU12: Generator Effect Bans | AV12: 1 | AX12: =COUNTA(OFFSET(DVT_Laboratory!$B$3, 0, MATCH(AU12,DVT_Laboratory!$B$1:BM$1, 0)-1, 100, 1)) -> 3 | AZ12: Fast's Ultimate | BA12: 0 | BC12: =COUNTA(OFFSET(DVT_Laboratory!$B$3, 0, MATCH(AZ12,DVT_Laboratory!$B$1:BM$1, 0)-1, 100, 1)) -> 10
B13: Workshop Respec | C13: 1 | E13: =COUNTA(OFFSET(DVT_Laboratory!$B$3, 0, MATCH(B13,DVT_Laboratory!$B$1:BM$1, 0)-1, 100, 1)) -> 1 | L13: Wall Regen | M13: 21 | O13: =COUNTA(OFFSET(DVT_Laboratory!$B$3, 0, MATCH(L13,DVT_Laboratory!$B$1:BM$1, 0)-1, 100, 1)) -> 30 | Q13: Enemy Health Level Skip | R13: 20 | T13: =COUNTA(OFFSET(DVT_Laboratory!$B$3, 0, MATCH(Q13,DVT_Laboratory!$B$1:BM$1, 0)-1, 100, 1)) -> 20 | V13: Golden Tower Duration | W13: 19 | Y13: =COUNTA(OFFSET(DVT_Laboratory!$B$3, 0, MATCH(V13,DVT_Laboratory!$B$1:BM$1, 0)-1, 100, 1)) -> 20 | AA13: Health Mastery | AB13: 0 | AD13: =COUNTA(OFFSET(DVT_Laboratory!$B$3, 0, MATCH("Card Mastery",DVT_Laboratory!$B$1:BM$1, 0)-1, 100, 1)) -> 9 | AP13: Protector Health | AQ13: 0 | AS13: =COUNTA(OFFSET(DVT_Laboratory!$B$3, 0, MATCH(AP13,DVT_Laboratory!$B$1:BM$1, 0)-1, 100, 1)) -> 30 | AU13: Core Effect Bans | AV13: 4 | AX13: =COUNTA(OFFSET(DVT_Laboratory!$B$3, 0, MATCH(AU13,DVT_Laboratory!$B$1:BM$1, 0)-1, 100, 1)) -> 7 | AZ13: Ranged Ultimate | BA13: 0 | BC13: =COUNTA(OFFSET(DVT_Laboratory!$B$3, 0, MATCH(AZ13,DVT_Laboratory!$B$1:BM$1, 0)-1, 100, 1)) -> 10
B14: Reroll Daily Mission | C14: 1 | E14: =COUNTA(OFFSET(DVT_Laboratory!$B$3, 0, MATCH(B14,DVT_Laboratory!$B$1:BM$1, 0)-1, 100, 1)) -> 1 | L14: Wall Thorns | M14: 15 | O14: =COUNTA(OFFSET(DVT_Laboratory!$B$3, 0, MATCH(L14,DVT_Laboratory!$B$1:BM$1, 0)-1, 100, 1)) -> 20 | V14: Chain Lightning Shock | W14: 1 | Y14: =COUNTA(OFFSET(DVT_Laboratory!$B$3, 0, MATCH(V14,DVT_Laboratory!$B$1:BM$1, 0)-1, 100, 1)) -> 1 | AA14: Health Regen Mastery | AB14: 0 | AD14: =COUNTA(OFFSET(DVT_Laboratory!$B$3, 0, MATCH("Card Mastery",DVT_Laboratory!$B$1:BM$1, 0)-1, 100, 1)) -> 9 | AP14: Protector Radius | AQ14: 0 | AS14: =COUNTA(OFFSET(DVT_Laboratory!$B$3, 0, MATCH(AP14,DVT_Laboratory!$B$1:BM$1, 0)-1, 100, 1)) -> 30 | AU14: Assist Module Substats - Cannon | AV14: 0 | AX14: =COUNTA(OFFSET(DVT_Laboratory!$B$3, 0, MATCH(AU14,DVT_Laboratory!$B$1:BM$1, 0)-1, 100, 1)) -> 30 | AZ14: Boss's Ultimate | BA14: 0 | BC14: =COUNTA(OFFSET(DVT_Laboratory!$B$3, 0, MATCH(AZ14,DVT_Laboratory!$B$1:BM$1, 0)-1, 100, 1)) -> 10
B15: Workshop Enhancements | C15: 1 | E15: =COUNTA(OFFSET(DVT_Laboratory!$B$3, 0, MATCH(B15,DVT_Laboratory!$B$1:BM$1, 0)-1, 100, 1)) -> 1 | L15: Wall Invincibility | M15: 0 | O15: =COUNTA(OFFSET(DVT_Laboratory!$B$3, 0, MATCH(L15,DVT_Laboratory!$B$1:BM$1, 0)-1, 100, 1)) -> 10 | V15: Shock Chance | W15: 14 | Y15: =COUNTA(OFFSET(DVT_Laboratory!$B$3, 0, MATCH(V15,DVT_Laboratory!$B$1:BM$1, 0)-1, 100, 1)) -> 30 | AA15: Range Mastery | AB15: 0 | AD15: =COUNTA(OFFSET(DVT_Laboratory!$B$3, 0, MATCH("Card Mastery",DVT_Laboratory!$B$1:BM$1, 0)-1, 100, 1)) -> 9 | AP15: Protector Damage Reduction | AQ15: 0 | AS15: =COUNTA(OFFSET(DVT_Laboratory!$B$3, 0, MATCH(AP15,DVT_Laboratory!$B$1:BM$1, 0)-1, 100, 1)) -> 20 | AU15: Assist Module Substats - Armor | AV15: 0 | AX15: =COUNTA(OFFSET(DVT_Laboratory!$B$3, 0, MATCH(AU15,DVT_Laboratory!$B$1:BM$1, 0)-1, 100, 1)) -> 30 | AZ15: Basic's Ultimate | BA15: 0 | BC15: =COUNTA(OFFSET(DVT_Laboratory!$B$3, 0, MATCH(AZ15,DVT_Laboratory!$B$1:BM$1, 0)-1, 100, 1)) -> 10
B16: Enhancement Attack - Coin Discount | C16: 0 | E16: =COUNTA(OFFSET(DVT_Laboratory!$B$3, 0, MATCH(B16,DVT_Laboratory!$B$1:BM$1, 0)-1, 100, 1)) -> 100 | L16: Wall Fortification | M16: 47 | O16: =COUNTA(OFFSET(DVT_Laboratory!$B$3, 0, MATCH(L16,DVT_Laboratory!$B$1:BM$1, 0)-1, 100, 1)) -> 60 | V16: Shock Multiplier | W16: 14 | Y16: =COUNTA(OFFSET(DVT_Laboratory!$B$3, 0, MATCH(V16,DVT_Laboratory!$B$1:BM$1, 0)-1, 100, 1)) -> 14 | AA16: Cash Mastery | AB16: 1 | AD16: =COUNTA(OFFSET(DVT_Laboratory!$B$3, 0, MATCH("Card Mastery",DVT_Laboratory!$B$1:BM$1, 0)-1, 100, 1)) -> 9 | AP16: Ray Enemy Attack | AQ16: 0 | AS16: =COUNTA(OFFSET(DVT_Laboratory!$B$3, 0, MATCH(AP16,DVT_Laboratory!$B$1:BM$1, 0)-1, 100, 1)) -> 30 | AU16: Assist Module Substats - Generator | AV16: 0 | AX16: =COUNTA(OFFSET(DVT_Laboratory!$B$3, 0, MATCH(AU16,DVT_Laboratory!$B$1:BM$1, 0)-1, 100, 1)) -> 30 | AZ16: Tank's Ultimate | BA16: 0 | BC16: =COUNTA(OFFSET(DVT_Laboratory!$B$3, 0, MATCH(AZ16,DVT_Laboratory!$B$1:BM$1, 0)-1, 100, 1)) -> 10
B17: Enhancement Defense - Coin Discount | C17: 0 | E17: =COUNTA(OFFSET(DVT_Laboratory!$B$3, 0, MATCH(B17,DVT_Laboratory!$B$1:BM$1, 0)-1, 100, 1)) -> 100 | L17: Garlic Thorns | M17: 10 | O17: =COUNTA(OFFSET(DVT_Laboratory!$B$3, 0, MATCH(L17,DVT_Laboratory!$B$1:BM$1, 0)-1, 100, 1)) -> 10 | V17: Death Wave Health | W17: 30 | Y17: =COUNTA(OFFSET(DVT_Laboratory!$B$3, 0, MATCH(V17,DVT_Laboratory!$B$1:BM$1, 0)-1, 100, 1)) -> 30 | AA17: Coins Mastery | AB17: 0 | AD17: =COUNTA(OFFSET(DVT_Laboratory!$B$3, 0, MATCH("Card Mastery",DVT_Laboratory!$B$1:BM$1, 0)-1, 100, 1)) -> 9 | AP17: Ray Enemy Health | AQ17: 0 | AS17: =COUNTA(OFFSET(DVT_Laboratory!$B$3, 0, MATCH(AP17,DVT_Laboratory!$B$1:BM$1, 0)-1, 100, 1)) -> 30 | AU17: Assist Module Substats - Core | AV17: 0 | AX17: =COUNTA(OFFSET(DVT_Laboratory!$B$3, 0, MATCH(AU17,DVT_Laboratory!$B$1:BM$1, 0)-1, 100, 1)) -> 30 | AZ17: Protector's Ultimate | BA17: 0 | BC17: =COUNTA(OFFSET(DVT_Laboratory!$B$3, 0, MATCH(AZ17,DVT_Laboratory!$B$1:BM$1, 0)-1, 100, 1)) -> 10
B18: Enhancement Utility - Coin Discount | C18: 0 | E18: =COUNTA(OFFSET(DVT_Laboratory!$B$3, 0, MATCH(B18,DVT_Laboratory!$B$1:BM$1, 0)-1, 100, 1)) -> 100 | V18: Death Wave Coin Bonus | W18: 20 | Y18: =COUNTA(OFFSET(DVT_Laboratory!$B$3, 0, MATCH(V18,DVT_Laboratory!$B$1:BM$1, 0)-1, 100, 1)) -> 20 | AA18: Slow Aura Mastery | AB18: 0 | AD18: =COUNTA(OFFSET(DVT_Laboratory!$B$3, 0, MATCH("Card Mastery",DVT_Laboratory!$B$1:BM$1, 0)-1, 100, 1)) -> 9 | AP18: Vampire Enemy Attack | AQ18: 0 | AS18: =COUNTA(OFFSET(DVT_Laboratory!$B$3, 0, MATCH(AP18,DVT_Laboratory!$B$1:BM$1, 0)-1, 100, 1)) -> 30 | AU18: Assist Module Bonus - Cannon | AV18: 0 | AX18: =COUNTA(OFFSET(DVT_Laboratory!$B$3, 0, MATCH(AU18,DVT_Laboratory!$B$1:BM$1, 0)-1, 100, 1)) -> 30 | AZ18: Ultimate Weapon Durations | BA18: 0 | BC18: =COUNTA(OFFSET(DVT_Laboratory!$B$3, 0, MATCH(AZ18,DVT_Laboratory!$B$1:BM$1, 0)-1, 100, 1)) -> 10
V19: Inner Mine Blast Radius | W19: 0 | Y19: =COUNTA(OFFSET(DVT_Laboratory!$B$3, 0, MATCH(V19,DVT_Laboratory!$B$1:BM$1, 0)-1, 100, 1)) -> 20 | AA19: Critical Chance Mastery | AB19: 0 | AD19: =COUNTA(OFFSET(DVT_Laboratory!$B$3, 0, MATCH("Card Mastery",DVT_Laboratory!$B$1:BM$1, 0)-1, 100, 1)) -> 9 | AP19: Vampire Enemy Health | AQ19: 0 | AS19: =COUNTA(OFFSET(DVT_Laboratory!$B$3, 0, MATCH(AP19,DVT_Laboratory!$B$1:BM$1, 0)-1, 100, 1)) -> 30 | AU19: Assist Module Bonus - Armor | AV19: 0 | AX19: =COUNTA(OFFSET(DVT_Laboratory!$B$3, 0, MATCH(AU19,DVT_Laboratory!$B$1:BM$1, 0)-1, 100, 1)) -> 30 | AZ19: Death Defy Down | BA19: 0 | BC19: =COUNTA(OFFSET(DVT_Laboratory!$B$3, 0, MATCH(AZ19,DVT_Laboratory!$B$1:BM$1, 0)-1, 100, 1)) -> 10
V20: Inner Mine Rotation Speed | W20: 0 | Y20: =COUNTA(OFFSET(DVT_Laboratory!$B$3, 0, MATCH(V20,DVT_Laboratory!$B$1:BM$1, 0)-1, 100, 1)) -> 20 | AA20: Enemy Balance Mastery | AB20: 0 | AD20: =COUNTA(OFFSET(DVT_Laboratory!$B$3, 0, MATCH("Card Mastery",DVT_Laboratory!$B$1:BM$1, 0)-1, 100, 1)) -> 9 | AP20: Scatter Enemy Attack | AQ20: 0 | AS20: =COUNTA(OFFSET(DVT_Laboratory!$B$3, 0, MATCH(AP20,DVT_Laboratory!$B$1:BM$1, 0)-1, 100, 1)) -> 30 | AU20: Assist Module Bonus - Generator | AV20: 0 | AX20: =COUNTA(OFFSET(DVT_Laboratory!$B$3, 0, MATCH(AU20,DVT_Laboratory!$B$1:BM$1, 0)-1, 100, 1)) -> 30 | AZ20: Energy Shields Down | BA20: 0 | BC20: =COUNTA(OFFSET(DVT_Laboratory!$B$3, 0, MATCH(AZ20,DVT_Laboratory!$B$1:BM$1, 0)-1, 100, 1)) -> 10
V21: Chrono Field Range | W21: 17 | Y21: =COUNTA(OFFSET(DVT_Laboratory!$B$3, 0, MATCH(V21,DVT_Laboratory!$B$1:BM$1, 0)-1, 100, 1)) -> 20 | AA21: Extra Defense Mastery | AB21: 0 | AD21: =COUNTA(OFFSET(DVT_Laboratory!$B$3, 0, MATCH("Card Mastery",DVT_Laboratory!$B$1:BM$1, 0)-1, 100, 1)) -> 9 | AP21: Scatter Enemy Health | AQ21: 0 | AS21: =COUNTA(OFFSET(DVT_Laboratory!$B$3, 0, MATCH(AP21,DVT_Laboratory!$B$1:BM$1, 0)-1, 100, 1)) -> 30 | AU21: Assist Module Bonus - Core | AV21: 0 | AX21: =COUNTA(OFFSET(DVT_Laboratory!$B$3, 0, MATCH(AU21,DVT_Laboratory!$B$1:BM$1, 0)-1, 100, 1)) -> 30 | AZ21: Enemy Level Skip Reduction | BA21: 0 | BC21: =COUNTA(OFFSET(DVT_Laboratory!$B$3, 0, MATCH(AZ21,DVT_Laboratory!$B$1:BM$1, 0)-1, 100, 1)) -> 10
V22: Missile Amplifier | W22: 0 | Y22: =COUNTA(OFFSET(DVT_Laboratory!$B$3, 0, MATCH(V22,DVT_Laboratory!$B$1:BM$1, 0)-1, 100, 1)) -> 25 | AA22: Fortress Mastery | AB22: 0 | AD22: =COUNTA(OFFSET(DVT_Laboratory!$B$3, 0, MATCH("Card Mastery",DVT_Laboratory!$B$1:BM$1, 0)-1, 100, 1)) -> 9 | AP22: Ranged Enemy Range | AQ22: 0 | AS22: =COUNTA(OFFSET(DVT_Laboratory!$B$3, 0, MATCH(AP22,DVT_Laboratory!$B$1:BM$1, 0)-1, 100, 1)) -> 30
V23: Missile Barrage | W23: 0 | Y23: =COUNTA(OFFSET(DVT_Laboratory!$B$3, 0, MATCH(V23,DVT_Laboratory!$B$1:BM$1, 0)-1, 100, 1)) -> 1 | AA23: Free Upgrades Mastery | AB23: 0 | AD23: =COUNTA(OFFSET(DVT_Laboratory!$B$3, 0, MATCH("Card Mastery",DVT_Laboratory!$B$1:BM$1, 0)-1, 100, 1)) -> 9
V24: Missile Barrage Quantity | W24: 0 | Y24: =COUNTA(OFFSET(DVT_Laboratory!$B$3, 0, MATCH(V24,DVT_Laboratory!$B$1:BM$1, 0)-1, 100, 1)) -> 6 | AA24: Extra Orb Mastery | AB24: 0 | AD24: =COUNTA(OFFSET(DVT_Laboratory!$B$3, 0, MATCH("Card Mastery",DVT_Laboratory!$B$1:BM$1, 0)-1, 100, 1)) -> 9
V25: Inner Mine Stun | W25: 0 | Y25: =COUNTA(OFFSET(DVT_Laboratory!$B$3, 0, MATCH(V25,DVT_Laboratory!$B$1:BM$1, 0)-1, 100, 1)) -> 1 | AA25: Plasma Cannon Mastery | AB25: 0 | AD25: =COUNTA(OFFSET(DVT_Laboratory!$B$3, 0, MATCH("Card Mastery",DVT_Laboratory!$B$1:BM$1, 0)-1, 100, 1)) -> 9
V26: Black Hole Damage | W26: 10 | Y26: =COUNTA(OFFSET(DVT_Laboratory!$B$3, 0, MATCH(V26,DVT_Laboratory!$B$1:BM$1, 0)-1, 100, 1)) -> 10 | AA26: Critical Coin Mastery | AB26: 0 | AD26: =COUNTA(OFFSET(DVT_Laboratory!$B$3, 0, MATCH("Card Mastery",DVT_Laboratory!$B$1:BM$1, 0)-1, 100, 1)) -> 9
V27: Extra Black Hole | W27: 1 | Y27: =COUNTA(OFFSET(DVT_Laboratory!$B$3, 0, MATCH(V27,DVT_Laboratory!$B$1:BM$1, 0)-1, 100, 1)) -> 1 | AA27: Wave Skip Mastery | AB27: 0 | AD27: =COUNTA(OFFSET(DVT_Laboratory!$B$3, 0, MATCH("Card Mastery",DVT_Laboratory!$B$1:BM$1, 0)-1, 100, 1)) -> 9
V28: Black Hole Coin Bonus | W28: 20 | Y28: =COUNTA(OFFSET(DVT_Laboratory!$B$3, 0, MATCH(V28,DVT_Laboratory!$B$1:BM$1, 0)-1, 100, 1)) -> 20 | AA28: Intro Sprint Mastery | AB28: 0 | AD28: =COUNTA(OFFSET(DVT_Laboratory!$B$3, 0, MATCH("Card Mastery",DVT_Laboratory!$B$1:BM$1, 0)-1, 100, 1)) -> 9
V29: Spotlight Coin Bonus | W29: 20 | Y29: =COUNTA(OFFSET(DVT_Laboratory!$B$3, 0, MATCH(V29,DVT_Laboratory!$B$1:BM$1, 0)-1, 100, 1)) -> 20 | AA29: Land Mine Stun Mastery | AB29: 0 | AD29: =COUNTA(OFFSET(DVT_Laboratory!$B$3, 0, MATCH("Card Mastery",DVT_Laboratory!$B$1:BM$1, 0)-1, 100, 1)) -> 9
V30: Spotlight Missiles | W30: 1 | Y30: =COUNTA(OFFSET(DVT_Laboratory!$B$3, 0, MATCH(V30,DVT_Laboratory!$B$1:BM$1, 0)-1, 100, 1)) -> 18 | AA30: Recovery Package Chance Mastery | AB30: 3 | AD30: =COUNTA(OFFSET(DVT_Laboratory!$B$3, 0, MATCH("Card Mastery",DVT_Laboratory!$B$1:BM$1, 0)-1, 100, 1)) -> 9
V31: Black Hole Disable Ranged Enemies | W31: 1 | Y31: =COUNTA(OFFSET(DVT_Laboratory!$B$3, 0, MATCH(V31,DVT_Laboratory!$B$1:BM$1, 0)-1, 100, 1)) -> 1 | AA31: Death Ray Mastery | AB31: 0 | AD31: =COUNTA(OFFSET(DVT_Laboratory!$B$3, 0, MATCH("Card Mastery",DVT_Laboratory!$B$1:BM$1, 0)-1, 100, 1)) -> 9
V32: Recharge Missile Barrage | W32: 0 | Y32: =COUNTA(OFFSET(DVT_Laboratory!$B$3, 0, MATCH(V32,DVT_Laboratory!$B$1:BM$1, 0)-1, 100, 1)) -> 7 | AA32: Energy Net Mastery | AB32: 0 | AD32: =COUNTA(OFFSET(DVT_Laboratory!$B$3, 0, MATCH("Card Mastery",DVT_Laboratory!$B$1:BM$1, 0)-1, 100, 1)) -> 9
V33: Swamp Rend | W33: 0 | Y33: =COUNTA(OFFSET(DVT_Laboratory!$B$3, 0, MATCH(V33,DVT_Laboratory!$B$1:BM$1, 0)-1, 100, 1)) -> 30 | AA33: Super Tower Mastery | AB33: 0 | AD33: =COUNTA(OFFSET(DVT_Laboratory!$B$3, 0, MATCH("Card Mastery",DVT_Laboratory!$B$1:BM$1, 0)-1, 100, 1)) -> 9
V34: Swamp Rend - Additional Enemies | W34: 0 | Y34: =COUNTA(OFFSET(DVT_Laboratory!$B$3, 0, MATCH(V34,DVT_Laboratory!$B$1:BM$1, 0)-1, 100, 1)) -> 6 | AA34: Second Wind Mastery | AB34: 0 | AD34: =COUNTA(OFFSET(DVT_Laboratory!$B$3, 0, MATCH("Card Mastery",DVT_Laboratory!$B$1:BM$1, 0)-1, 100, 1)) -> 9
... V40: Inner Land Mine - Chrono Jump | W40: 0 | Y40: =COUNTA(OFFSET(DVT_Laboratory!$B$3, 0, MATCH(V40,DVT_Laboratory!$B$1:BM$1, 0)-1, 100, 1)) -> 10 | AA40: Nuke Mastery | AB40: 0 | AD40: =COUNTA(OFFSET(DVT_Laboratory!$B$3, 0, MATCH("Card Mastery",DVT_Laboratory!$B$1:BM$1, 0)-1, 100, 1)) -> 9
AA41: Area of Effect Mastery | AB41: 0 | AD41: =COUNTA(OFFSET(DVT_Laboratory!$B$3, 0, MATCH("Card Mastery",DVT_Laboratory!$B$1:BM$1, 0)-1, 100, 1)) -> 9
C43: =SUM(C2:C42) -> 279 | D43: =SUM(D2:D42) -> 7 | E43: =SUM(E2:E42) -> 912 | H43: =SUM(H2:H42) -> 299 | I43: =SUM(I2:I42) -> 0 | J43: =SUM(J2:J42) -> 598 | M43: =SUM(M2:M42) -> 383 | N43: =SUM(N2:N42) -> 42 | O43: =SUM(O2:O42) -> 655 | R43: =SUM(R2:R42) -> 214 | S43: =SUM(S2:S42) -> 0 | T43: =SUM(T2:T42) -> 611 | W43: =SUM(W2:W42) -> 284 | X43: =SUM(X2:X42) -> 0 | Y43: =SUM(Y2:Y42) -> 669 | AB43: =SUM(AB2:AB42) -> 32 | AC43: =SUM(AC2:AC42) -> 0 | AD43: =SUM(AD2:AD42) -> 369 | AG43: =SUM(AG2:AG42) -> 71 | AH43: =SUM(AH2:AH42) -> 17 | AI43: =SUM(AI2:AI42) -> 180 | AL43: =SUM(AL2:AL42) -> 58 | AM43: =SUM(AM2:AM42) -> 0 | AN43: =SUM(AN2:AN42) -> 165 | AQ43: =SUM(AQ2:AQ42) -> 0 | AR43: =SUM(AR2:AR42) -> 0 | AS43: =SUM(AS2:AS42) -> 620 | AV43: =SUM(AV2:AV42) -> 236 | AW43: =SUM(AW2:AW42) -> 160 | AX43: =SUM(AX2:AX42) -> 494 | BA43: =SUM(BA2:BA42) -> 0 | BB43: =SUM(BB2:BB42) -> 0 | BC43: =SUM(BC2:BC42) -> 290

Sheet _IDS
A1: =IFERROR(__xludf.DUMMYFUNCTION("IMPORTRANGE(IF(IDS!E6=""✅"", IDS!D6, ""1osjoqKmMwtOWs7Up3e21-3ofN1RHOjsgKV6y3dc6rgE""), ""_IDS!A1:CE212"")"),"Labs") -> Labs | B1: =IFERROR(__xludf.DUMMYFUNCTION("""COMPUTED_VALUE"""),"https://docs.google.com/spreadsheets/d/1jojOg_XIJCzm1LCYWu2F4KCtErjUIdKuFL1PiKzA0OE/edit") -> https://docs.google.com/spreadsheets/d/1jojOg_XIJCzm1LCYWu2F4KCtErjUIdKuFL1PiKzA0OE/edit | C1: =IFERROR(__xludf.DUMMYFUNCTION("""COMPUTED_VALUE"""),"✅") -> ✅ | D1: =IFERROR(__xludf.DUMMYFUNCTION("""COMPUTED_VALUE"""),"v2.5.7") -> v2.5.7 | E1: =IFERROR(__xludf.DUMMYFUNCTION("""COMPUTED_VALUE"""),"WS") -> WS | F1: =IFERROR(__xludf.DUMMYFUNCTION("""COMPUTED_VALUE"""),"https://docs.google.com/spreadsheets/d/1huHJMcyg1uRJEeRYqAgWzMc5TodPPplVZEFhwBiIeEs/edit") -> https://docs.google.com/spreadsheets/d/1huHJMcyg1uRJEeRYqAgWzMc5TodPPplVZEFhwBiIeEs/edit | G1: =IFERROR(__xludf.DUMMYFUNCTION("""COMPUTED_VALUE"""),"✅") -> ✅ | H1: =IFERROR(__xludf.DUMMYFUNCTION("""COMPUTED_VALUE"""),"v2.3.1") -> v2.3.1 | R1: =IFERROR(__xludf.DUMMYFUNCTION("""COMPUTED_VALUE"""),"WS+") -> WS+ | Z1: =IFERROR(__xludf.DUMMYFUNCTION("""COMPUTED_VALUE"""),"UWs") -> UWs | AA1: =IFERROR(__xludf.DUMMYFUNCTION("""COMPUTED_VALUE"""),"https://docs.google.com/spreadsheets/d/1VTRhVyt28cxrjCRcgVkQr2R_u4g9irfJTHy1cfftlIE/edit") -> https://docs.google.com/spreadsheets/d/1VTRhVyt28cxrjCRcgVkQr2R_u4g9irfJTHy1cfftlIE/edit | AB1: =IFERROR(__xludf.DUMMYFUNCTION("""COMPUTED_VALUE"""),"✅") -> ✅ | AC1: =IFERROR(__xludf.DUMMYFUNCTION("""COMPUTED_VALUE"""),"v2.1.3") -> v2.1.3 | AE1: =IFERROR(__xludf.DUMMYFUNCTION("""COMPUTED_VALUE"""),"Cards") -> Cards | AF1: =IFERROR(__xludf.DUMMYFUNCTION("""COMPUTED_VALUE"""),"https://docs.google.com/spreadsheets/d/1HMQwNLTvcw7aXmjjL7cXmZSdjAF_62ehWpwDIdjqEGs/edit") -> https://docs.google.com/spreadsheets/d/1HMQwNLTvcw7aXmjjL7cXmZSdjAF_62ehWpwDIdjqEGs/edit | AG1: =IFERROR(__xludf.DUMMYFUNCTION("""COMPUTED_VALUE"""),"✅") -> ✅ | AH1: =IFERROR(__xludf.DUMMYFUNCTION("""COMPUTED_VALUE"""),"Cards Presets") -> Cards Presets | AI1: =IFERROR(__xludf.DUMMYFUNCTION("""COMPUTED_VALUE"""),"v2.2.3") -> v2.2.3 | AJ1: =IFERROR(__xludf.DUMMYFUNCTION("""COMPUTED_VALUE"""),17.0) -> 17 | AM1: =IFERROR(__xludf.DUMMYFUNCTION("""COMPUTED_VALUE"""),"Relics") -> Relics | AN1: =IFERROR(__xludf.DUMMYFUNCTION("""COMPUTED_VALUE"""),"https://docs.google.com/spreadsheets/d/1Dll0IofJTWYkzhzhRWx1aA-_xtO3i_1iD65nAP6R_Ec/edit") -> https://docs.google.com/spreadsheets/d/1Dll0IofJTWYkzhzhRWx1aA-_xtO3i_1iD65nAP6R_Ec/edit | AO1: =IFERROR(__xludf.DUMMYFUNCTION("""COMPUTED_VALUE"""),"✅") -> ✅ | AP1: =IFERROR(__xludf.DUMMYFUNCTION("""COMPUTED_VALUE"""),"Vault") -> Vault | AR1: =IFERROR(__xludf.DUMMYFUNCTION("""COMPUTED_VALUE"""),"") | AS1: =IFERROR(__xludf.DUMMYFUNCTION("""COMPUTED_VALUE"""),"Bots") -> Bots | AT1: =IFERROR(__xludf.DUMMYFUNCTION("""COMPUTED_VALUE"""),"https://docs.google.com/spreadsheets/d/1H3PYvtIH7kId6WswEeMmrx7u5_g1GlkNPJtJhkASrbs/edit") -> https://docs.google.com/spreadsheets/d/1H3PYvtIH7kId6WswEeMmrx7u5_g1GlkNPJtJhkASrbs/edit | AU1: =IFERROR(__xludf.DUMMYFUNCTION("""COMPUTED_VALUE"""),"✅") -> ✅ | AV1: =IFERROR(__xludf.DUMMYFUNCTION("""COMPUTED_VALUE"""),"v2.2.1") -> v2.2.1 | AY1: =IFERROR(__xludf.DUMMYFUNCTION("""COMPUTED_VALUE"""),"Themes & Songs") -> Themes & Songs | AZ1: =IFERROR(__xludf.DUMMYFUNCTION("""COMPUTED_VALUE"""),"https://docs.google.com/spreadsheets/d/19KliigQhAeXztRPa9cSGZ7n9Q-REp4dyqMNI9d-UB0k/edit") -> https://docs.google.com/spreadsheets/d/19KliigQhAeXztRPa9cSGZ7n9Q-REp4dyqMNI9d-UB0k/edit | BA1: =IFERROR(__xludf.DUMMYFUNCTION("""COMPUTED_VALUE"""),"✅") -> ✅ | BB1: =IFERROR(__xludf.DUMMYFUNCTION("""COMPUTED_VALUE"""),"Modules") -> Modules | BC1: =IFERROR(__xludf.DUMMYFUNCTION("""COMPUTED_VALUE"""),"https://docs.google.com/spreadsheets/d/1rOoSY6TK918myJ6Mn6zO4rmUaFbPu6qJnGI17kc9DzQ/edit") -> https://docs.google.com/spreadsheets/d/1rOoSY6TK918myJ6Mn6zO4rmUaFbPu6qJnGI17kc9DzQ/edit | BD1: =IFERROR(__xludf.DUMMYFUNCTION("""COMPUTED_VALUE"""),"✅") -> ✅ | BE1: =IFERROR(__xludf.DUMMYFUNCTION("""COMPUTED_VALUE"""),"v5.13") -> v5.13 | BU1: =IFERROR(__xludf.DUMMYFUNCTION("""COMPUTED_VALUE"""),"Guardians") -> Guardians | BV1: =IFERROR(__xludf.DUMMYFUNCTION("""COMPUTED_VALUE"""),"https://docs.google.com/spreadsheets/d/1J4UPKzR9MLY_zzM7u7SzmyclgTEYX_PUvBcua4EbsSU/edit") -> https://docs.google.com/spreadsheets/d/1J4UPKzR9MLY_zzM7u7SzmyclgTEYX_PUvBcua4EbsSU/edit | BW1: =IFERROR(__xludf.DUMMYFUNCTION("""COMPUTED_VALUE"""),"✅") -> ✅ | BX1: =IFERROR(__xludf.DUMMYFUNCTION("""COMPUTED_VALUE"""),"v2.3.6") -> v2.3.6 | BZ1: =IFERROR(__xludf.DUMMYFUNCTION("""COMPUTED_VALUE"""),"Player & Stuff") -> Player & Stuff | CA1: =IFERROR(__xludf.DUMMYFUNCTION("""COMPUTED_VALUE"""),"https://docs.google.com/spreadsheets/d/1NpLNfHLQFsJ_WyMnxP9jMtzg3gVaMfOxydrTUG0YsuM/edit") -> https://docs.google.com/spreadsheets/d/1NpLNfHLQFsJ_WyMnxP9jMtzg3gVaMfOxydrTUG0YsuM/edit | CB1: =IFERROR(__xludf.DUMMYFUNCTION("""COMPUTED_VALUE"""),"✅") -> ✅ | CC1: =IFERROR(__xludf.DUMMYFUNCTION("""COMPUTED_VALUE"""),"v3.5.3") -> v3.5.3
A2: =IFERROR(__xludf.DUMMYFUNCTION("""COMPUTED_VALUE"""),"Game Speed") -> Game Speed | B2: =IFERROR(__xludf.DUMMYFUNCTION("""COMPUTED_VALUE"""),7.0) -> 7 | C2: =IFERROR(__xludf.DUMMYFUNCTION("""COMPUTED_VALUE"""),7.0) -> 7 | D2: =IFERROR(__xludf.DUMMYFUNCTION("""COMPUTED_VALUE"""),7.0) -> 7 | E2: =IFERROR(__xludf.DUMMYFUNCTION("""COMPUTED_VALUE"""),"U") -> U | F2: =IFERROR(__xludf.DUMMYFUNCTION("""COMPUTED_VALUE"""),"Workshop Upgrade") -> Workshop Upgrade | G2: =IFERROR(__xludf.DUMMYFUNCTION("""COMPUTED_VALUE"""),"Farming") -> Farming | I2: =IFERROR(__xludf.DUMMYFUNCTION("""COMPUTED_VALUE"""),"Tourney") -> Tourney | K2: =IFERROR(__xludf.DUMMYFUNCTION("""COMPUTED_VALUE"""),"Preset 3") -> Preset 3 | M2: =IFERROR(__xludf.DUMMYFUNCTION("""COMPUTED_VALUE"""),"Preset 4") -> Preset 4 | O2: =IFERROR(__xludf.DUMMYFUNCTION("""COMPUTED_VALUE"""),"Preset 5") -> Preset 5 | R2: =IFERROR(__xludf.DUMMYFUNCTION("""COMPUTED_VALUE"""),"Workshop Enhancement") -> Workshop Enhancement | T2: =IFERROR(__xludf.DUMMYFUNCTION("""COMPUTED_VALUE"""),"Farming") -> Farming | U2: =IFERROR(__xludf.DUMMYFUNCTION("""COMPUTED_VALUE"""),"Tourney") -> Tourney | V2: =IFERROR(__xludf.DUMMYFUNCTION("""COMPUTED_VALUE"""),"Preset 3") -> Preset 3 | W2: =IFERROR(__xludf.DUMMYFUNCTION("""COMPUTED_VALUE"""),"Preset 4") -> Preset 4 | X2: =IFERROR(__xludf.DUMMYFUNCTION("""COMPUTED_VALUE"""),"Preset 5") -> Preset 5 | Y2: =IFERROR(__xludf.DUMMYFUNCTION("""COMPUTED_VALUE"""),"7 q") -> 7 q | Z2: =IFERROR(__xludf.DUMMYFUNCTION("""COMPUTED_VALUE"""),"Chain Lightning") -> Chain Lightning | AB2: =IFERROR(__xludf.DUMMYFUNCTION("""COMPUTED_VALUE"""),"Damage") -> Damage | AC2: =IFERROR(__xludf.DUMMYFUNCTION("""COMPUTED_VALUE"""),898.0) -> 898 | AD2: =IFERROR(__xludf.DUMMYFUNCTION("""COMPUTED_VALUE"""),"19 | x898 | Cost 302 ⧌ | Next 362 ⧌") -> 19 | x898 | Cost 302 ⧌ | Next 362 ⧌ | AE2: =IFERROR(__xludf.DUMMYFUNCTION("""COMPUTED_VALUE"""),"Damage") -> Damage | AF2: =IFERROR(__xludf.DUMMYFUNCTION("""COMPUTED_VALUE"""),7.0) -> 7 | AG2: =IFERROR(__xludf.DUMMYFUNCTION("""COMPUTED_VALUE"""),FALSE) -> FALSE | AH2: =IFERROR(__xludf.DUMMYFUNCTION("""COMPUTED_VALUE"""),"Farming") -> Farming | AI2: =IFERROR(__xludf.DUMMYFUNCTION("""COMPUTED_VALUE"""),"Tourney") -> Tourney | AJ2: =IFERROR(__xludf.DUMMYFUNCTION("""COMPUTED_VALUE"""),"Preset 3") -> Preset 3 | AK2: =IFERROR(__xludf.DUMMYFUNCTION("""COMPUTED_VALUE"""),"Preset 4") -> Preset 4 | AL2: =IFERROR(__xludf.DUMMYFUNCTION("""COMPUTED_VALUE"""),"Preset 5") -> Preset 5 | AM2: =IFERROR(__xludf.DUMMYFUNCTION("""COMPUTED_VALUE"""),"Relics") -> Relics | AN2: =IFERROR(__xludf.DUMMYFUNCTION("""COMPUTED_VALUE"""),"Owned") -> Owned | AO2: =IFERROR(__xludf.DUMMYFUNCTION("""COMPUTED_VALUE"""),"v2.3.7") -> v2.3.7 | AP2: =IFERROR(__xludf.DUMMYFUNCTION("""COMPUTED_VALUE"""),"Keys spent") -> Keys spent | AQ2: =IFERROR(__xludf.DUMMYFUNCTION("""COMPUTED_VALUE"""),0.0) -> 0 | AS2: =IFERROR(__xludf.DUMMYFUNCTION("""COMPUTED_VALUE"""),"Flame Bot") -> Flame Bot | AU2: =IFERROR(__xludf.DUMMYFUNCTION("""COMPUTED_VALUE"""),"Damage R.") -> Damage R. | AV2: =IFERROR(__xludf.DUMMYFUNCTION("""COMPUTED_VALUE"""),0.3500000000000001) -> 0.35 | AW2: =IFERROR(__xludf.DUMMYFUNCTION("""COMPUTED_VALUE"""),"05 | 35% | Cost 260 ⧓ | Next 300 ⧓") -> 05 | 35% | Cost 260 ⧓ | Next 300 ⧓ | AY2: =IFERROR(__xludf.DUMMYFUNCTION("""COMPUTED_VALUE"""),1.682) -> 1.682 | BA2: =IFERROR(__xludf.DUMMYFUNCTION("""COMPUTED_VALUE"""),"v2.2.3") -> v2.2.3 | BB2: =IFERROR(__xludf.DUMMYFUNCTION("""COMPUTED_VALUE"""),"Assist Slot") -> Assist Slot | BC2: =IFERROR(__xludf.DUMMYFUNCTION("""COMPUTED_VALUE"""),FALSE) -> FALSE | BD2: =IFERROR(__xludf.DUMMYFUNCTION("""COMPUTED_VALUE"""),0.0) -> 0 | BG2: =IFERROR(__xludf.DUMMYFUNCTION("""COMPUTED_VALUE"""),"Assist Slot") -> Assist Slot | BH2: =IFERROR(__xludf.DUMMYFUNCTION("""COMPUTED_VALUE"""),TRUE) -> TRUE | BI2: =IFERROR(__xludf.DUMMYFUNCTION("""COMPUTED_VALUE"""),41.0) -> 41 | BL2: =IFERROR(__xludf.DUMMYFUNCTION("""COMPUTED_VALUE"""),"Assist Slot") -> Assist Slot | BM2: =IFERROR(__xludf.DUMMYFUNCTION("""COMPUTED_VALUE"""),TRUE) -> TRUE | BN2: =IFERROR(__xludf.DUMMYFUNCTION("""COMPUTED_VALUE"""),97.0) -> 97 | BQ2: =IFERROR(__xludf.DUMMYFUNCTION("""COMPUTED_VALUE"""),"Assist Slot") -> Assist Slot | BR2: =IFERROR(__xludf.DUMMYFUNCTION("""COMPUTED_VALUE"""),TRUE) -> TRUE | BS2: =IFERROR(__xludf.DUMMYFUNCTION("""COMPUTED_VALUE"""),101.0) -> 101 | BU2: =IFERROR(__xludf.DUMMYFUNCTION("""COMPUTED_VALUE"""),"Attack") -> Attack | BW2: =IFERROR(__xludf.DUMMYFUNCTION("""COMPUTED_VALUE"""),"Percentage") -> Percentage | BX2: =IFERROR(__xludf.DUMMYFUNCTION("""COMPUTED_VALUE"""),0.01) -> 0.01 | BY2: =IFERROR(__xludf.DUMMYFUNCTION("""COMPUTED_VALUE"""),"00 | 1% | Cost 0 ⧈ | Next 25 ⧈") -> 00 | 1% | Cost 0 ⧈ | Next 25 ⧈ | BZ2: =IFERROR(__xludf.DUMMYFUNCTION("""COMPUTED_VALUE"""),"Tier") -> Tier | CA2: =IFERROR(__xludf.DUMMYFUNCTION("""COMPUTED_VALUE"""),"Wave") -> Wave | CB2: =IFERROR(__xludf.DUMMYFUNCTION("""COMPUTED_VALUE"""),"P") -> P | CD2: =IFERROR(__xludf.DUMMYFUNCTION("""COMPUTED_VALUE"""),"Stat") -> Stat | CE2: =IFERROR(__xludf.DUMMYFUNCTION("""COMPUTED_VALUE"""),"Value") -> Value
A3: =IFERROR(__xludf.DUMMYFUNCTION("""COMPUTED_VALUE"""),"Starting Cash") -> Starting Cash | B3: =IFERROR(__xludf.DUMMYFUNCTION("""COMPUTED_VALUE"""),6.0) -> 6 | D3: =IFERROR(__xludf.DUMMYFUNCTION("""COMPUTED_VALUE"""),99.0) -> 99 | G3: =IFERROR(__xludf.DUMMYFUNCTION("""COMPUTED_VALUE"""),"¢ Level") -> ¢ Level | H3: =IFERROR(__xludf.DUMMYFUNCTION("""COMPUTED_VALUE"""),"$ Level") -> $ Level | I3: =IFERROR(__xludf.DUMMYFUNCTION("""COMPUTED_VALUE"""),"¢ Level") -> ¢ Level | J3: =IFERROR(__xludf.DUMMYFUNCTION("""COMPUTED_VALUE"""),"$ Level") -> $ Level | K3: =IFERROR(__xludf.DUMMYFUNCTION("""COMPUTED_VALUE"""),"¢ Level") -> ¢ Level | L3: =IFERROR(__xludf.DUMMYFUNCTION("""COMPUTED_VALUE"""),"$ Level") -> $ Level | M3: =IFERROR(__xludf.DUMMYFUNCTION("""COMPUTED_VALUE"""),"¢ Level") -> ¢ Level | N3: =IFERROR(__xludf.DUMMYFUNCTION("""COMPUTED_VALUE"""),"$ Level") -> $ Level | O3: =IFERROR(__xludf.DUMMYFUNCTION("""COMPUTED_VALUE"""),"¢ Level") -> ¢ Level | P3: =IFERROR(__xludf.DUMMYFUNCTION("""COMPUTED_VALUE"""),"$ Level") -> $ Level | Q3: =IFERROR(__xludf.DUMMYFUNCTION("""COMPUTED_VALUE"""),"Max") -> Max | T3: =IFERROR(__xludf.DUMMYFUNCTION("""COMPUTED_VALUE"""),"WS+") -> WS+ | U3: =IFERROR(__xludf.DUMMYFUNCTION("""COMPUTED_VALUE"""),"WS+") -> WS+ | V3: =IFERROR(__xludf.DUMMYFUNCTION("""COMPUTED_VALUE"""),"WS+") -> WS+ | W3: =IFERROR(__xludf.DUMMYFUNCTION("""COMPUTED_VALUE"""),"WS+") -> WS+ | X3: =IFERROR(__xludf.DUMMYFUNCTION("""COMPUTED_VALUE"""),"WS+") -> WS+ | Y3: =IFERROR(__xludf.DUMMYFUNCTION("""COMPUTED_VALUE"""),"Max") -> Max | AB3: =IFERROR(__xludf.DUMMYFUNCTION("""COMPUTED_VALUE"""),"Quantity") -> Quantity | AC3: =IFERROR(__xludf.DUMMYFUNCTION("""COMPUTED_VALUE"""),4.0) -> 4 | AD3: =IFERROR(__xludf.DUMMYFUNCTION("""COMPUTED_VALUE"""),"03 | #4 | Cost 150 ⧌ | Next 400 ⧌") -> 03 | #4 | Cost 150 ⧌ | Next 400 ⧌ | AE3: =IFERROR(__xludf.DUMMYFUNCTION("""COMPUTED_VALUE"""),"Attack Speed") -> Attack Speed | AF3: =IFERROR(__xludf.DUMMYFUNCTION("""COMPUTED_VALUE"""),7.0) -> 7 | AG3: =IFERROR(__xludf.DUMMYFUNCTION("""COMPUTED_VALUE"""),FALSE) -> FALSE | AH3: =IFERROR(__xludf.DUMMYFUNCTION("""COMPUTED_VALUE"""),"Enemy Balance") -> Enemy Balance | AI3: =IFERROR(__xludf.DUMMYFUNCTION("""COMPUTED_VALUE"""),"Attack Speed") -> Attack Speed | AM3: =IFERROR(__xludf.DUMMYFUNCTION("""COMPUTED_VALUE"""),"Event Relics") -> Event Relics | AN3: =IFERROR(__xludf.DUMMYFUNCTION("""COMPUTED_VALUE"""),112.0) -> 112 | AU3: =IFERROR(__xludf.DUMMYFUNCTION("""COMPUTED_VALUE"""),"Cooldown") -> Cooldown | AV3: =IFERROR(__xludf.DUMMYFUNCTION("""COMPUTED_VALUE"""),51.0) -> 51 | AW3: =IFERROR(__xludf.DUMMYFUNCTION("""COMPUTED_VALUE"""),"08 | 51s | Cost 380 ⧓ | Next 420 ⧓") -> 08 | 51s | Cost 380 ⧓ | Next 420 ⧓ | BB3: =IFERROR(__xludf.DUMMYFUNCTION("""COMPUTED_VALUE"""),"Rarity Cap") -> Rarity Cap | BC3: =IFERROR(__xludf.DUMMYFUNCTION("""COMPUTED_VALUE"""),"Epic") -> Epic | BG3: =IFERROR(__xludf.DUMMYFUNCTION("""COMPUTED_VALUE"""),"Rarity Cap") -> Rarity Cap | BH3: =IFERROR(__xludf.DUMMYFUNCTION("""COMPUTED_VALUE"""),"Epic") -> Epic | BL3: =IFERROR(__xludf.DUMMYFUNCTION("""COMPUTED_VALUE"""),"Rarity Cap") -> Rarity Cap | BM3: =IFERROR(__xludf.DUMMYFUNCTION("""COMPUTED_VALUE"""),"Epic") -> Epic | BQ3: =IFERROR(__xludf.DUMMYFUNCTION("""COMPUTED_VALUE"""),"Rarity Cap") -> Rarity Cap | BR3: =IFERROR(__xludf.DUMMYFUNCTION("""COMPUTED_VALUE"""),"Epic") -> Epic | BW3: =IFERROR(__xludf.DUMMYFUNCTION("""COMPUTED_VALUE"""),"Cooldown") -> Cooldown | BX3: =IFERROR(__xludf.DUMMYFUNCTION("""COMPUTED_VALUE"""),120.0) -> 120 | BY3: =IFERROR(__xludf.DUMMYFUNCTION("""COMPUTED_VALUE"""),"00 | 120s | Cost 0 ⧈ | Next 1 ⧈") -> 00 | 120s | Cost 0 ⧈ | Next 1 ⧈ | BZ3: =IFERROR(__xludf.DUMMYFUNCTION("""COMPUTED_VALUE"""),"Tier 1") -> Tier 1 | CA3: =IFERROR(__xludf.DUMMYFUNCTION("""COMPUTED_VALUE"""),10210.0) -> 10210 | CB3: =IFERROR(__xludf.DUMMYFUNCTION("""COMPUTED_VALUE"""),TRUE) -> TRUE | CD3: =IFERROR(__xludf.DUMMYFUNCTION("""COMPUTED_VALUE"""),"Player ID") -> Player ID | CE3: =IFERROR(__xludf.DUMMYFUNCTION("""COMPUTED_VALUE"""),"4C64DCF66976FD33") -> 4C64DCF66976FD33
A4: =IFERROR(__xludf.DUMMYFUNCTION("""COMPUTED_VALUE"""),"Workshop Attack Discount") -> Workshop Attack Discount | B4: =IFERROR(__xludf.DUMMYFUNCTION("""COMPUTED_VALUE"""),27.0) -> 27 | D4: =IFERROR(__xludf.DUMMYFUNCTION("""COMPUTED_VALUE"""),99.0) -> 99 | F4: =IFERROR(__xludf.DUMMYFUNCTION("""COMPUTED_VALUE"""),"Damage") -> Damage | G4: =IFERROR(__xludf.DUMMYFUNCTION("""COMPUTED_VALUE"""),5750.0) -> 5750 | H4: =IFERROR(__xludf.DUMMYFUNCTION("""COMPUTED_VALUE"""),6000.0) -> 6000 | I4: =IFERROR(__xludf.DUMMYFUNCTION("""COMPUTED_VALUE"""),5750.0) -> 5750 | J4: =IFERROR(__xludf.DUMMYFUNCTION("""COMPUTED_VALUE"""),6000.0) -> 6000 | Q4: =IFERROR(__xludf.DUMMYFUNCTION("""COMPUTED_VALUE"""),6000.0) -> 6000 | R4: =IFERROR(__xludf.DUMMYFUNCTION("""COMPUTED_VALUE"""),"Damage +") -> Damage + | S4: =IFERROR(__xludf.DUMMYFUNCTION("""COMPUTED_VALUE"""),1.56) -> 1.56 | T4: =IFERROR(__xludf.DUMMYFUNCTION("""COMPUTED_VALUE"""),56.0) -> 56 | U4: =IFERROR(__xludf.DUMMYFUNCTION("""COMPUTED_VALUE"""),56.0) -> 56 | Y4: =IFERROR(__xludf.DUMMYFUNCTION("""COMPUTED_VALUE"""),400.0) -> 400 | Z4: =IFERROR(__xludf.DUMMYFUNCTION("""COMPUTED_VALUE"""),TRUE) -> TRUE | AA4: =IFERROR(__xludf.DUMMYFUNCTION("""COMPUTED_VALUE"""),"UW Unlocked") -> UW Unlocked | AB4: =IFERROR(__xludf.DUMMYFUNCTION("""COMPUTED_VALUE"""),"Chance") -> Chance | AC4: =IFERROR(__xludf.DUMMYFUNCTION("""COMPUTED_VALUE"""),0.17) -> 0.17 | AD4: =IFERROR(__xludf.DUMMYFUNCTION("""COMPUTED_VALUE"""),"08 | 17.0% | Cost 134 ⧌ | Next 152 ⧌") -> 08 | 17.0% | Cost 134 ⧌ | Next 152 ⧌ | AE4: =IFERROR(__xludf.DUMMYFUNCTION("""COMPUTED_VALUE"""),"Health") -> Health | AF4: =IFERROR(__xludf.DUMMYFUNCTION("""COMPUTED_VALUE"""),7.0) -> 7 | AG4: =IFERROR(__xludf.DUMMYFUNCTION("""COMPUTED_VALUE"""),FALSE) -> FALSE | AH4: =IFERROR(__xludf.DUMMYFUNCTION("""COMPUTED_VALUE"""),"Extra Defense") -> Extra Defense | AI4: =IFERROR(__xludf.DUMMYFUNCTION("""COMPUTED_VALUE"""),"Damage") -> Damage | AM4: =IFERROR(__xludf.DUMMYFUNCTION("""COMPUTED_VALUE"""),"Guild Relics") -> Guild Relics | AN4: =IFERROR(__xludf.DUMMYFUNCTION("""COMPUTED_VALUE"""),13.0) -> 13 | AP4: =IFERROR(__xludf.DUMMYFUNCTION("""COMPUTED_VALUE"""),"Total Bonuses") -> Total Bonuses | AQ4: =IFERROR(__xludf.DUMMYFUNCTION("""COMPUTED_VALUE"""),"Active") -> Active | AU4: =IFERROR(__xludf.DUMMYFUNCTION("""COMPUTED_VALUE"""),"Damage") -> Damage | AV4: =IFERROR(__xludf.DUMMYFUNCTION("""COMPUTED_VALUE"""),50.0) -> 50 | AW4: =IFERROR(__xludf.DUMMYFUNCTION("""COMPUTED_VALUE"""),"00 | x50 | Cost 0 ⧓ | Next 100 ⧓") -> 00 | x50 | Cost 0 ⧓ | Next 100 ⧓ | BB4: =IFERROR(__xludf.DUMMYFUNCTION("""COMPUTED_VALUE"""),"Multiplier Cap") -> Multiplier Cap | BC4: =IFERROR(__xludf.DUMMYFUNCTION("""COMPUTED_VALUE"""),0.01) -> 0.01 | BD4: =IFERROR(__xludf.DUMMYFUNCTION("""COMPUTED_VALUE"""),"00 | 1% | Cost 0 ⧌ | Next 15 ⧌") -> 00 | 1% | Cost 0 ⧌ | Next 15 ⧌ | BG4: =IFERROR(__xludf.DUMMYFUNCTION("""COMPUTED_VALUE"""),"Multiplier Cap") -> Multiplier Cap | BH4: =IFERROR(__xludf.DUMMYFUNCTION("""COMPUTED_VALUE"""),0.01) -> 0.01 | BI4: =IFERROR(__xludf.DUMMYFUNCTION("""COMPUTED_VALUE"""),"00 | 1% | Cost 0 ⧌ | Next 15 ⧌") -> 00 | 1% | Cost 0 ⧌ | Next 15 ⧌ | BL4: =IFERROR(__xludf.DUMMYFUNCTION("""COMPUTED_VALUE"""),"Multiplier Cap") -> Multiplier Cap | BM4: =IFERROR(__xludf.DUMMYFUNCTION("""COMPUTED_VALUE"""),0.1) -> 0.1 | BN4: =IFERROR(__xludf.DUMMYFUNCTION("""COMPUTED_VALUE"""),"09 | 10% | Cost 39 ⧌ | Next 42 ⧌") -> 09 | 10% | Cost 39 ⧌ | Next 42 ⧌ | BQ4: =IFERROR(__xludf.DUMMYFUNCTION("""COMPUTED_VALUE"""),"Multiplier Cap") -> Multiplier Cap | BR4: =IFERROR(__xludf.DUMMYFUNCTION("""COMPUTED_VALUE"""),0.1) -> 0.1 | BS4: =IFERROR(__xludf.DUMMYFUNCTION("""COMPUTED_VALUE"""),"09 | 10% | Cost 39 ⧌ | Next 42 ⧌") -> 09 | 10% | Cost 39 ⧌ | Next 42 ⧌ | BU4: =IFERROR(__xludf.DUMMYFUNCTION("""COMPUTED_VALUE"""),TRUE) -> TRUE | BV4: =IFERROR(__xludf.DUMMYFUNCTION("""COMPUTED_VALUE"""),"Unlocked") -> Unlocked | BW4: =IFERROR(__xludf.DUMMYFUNCTION("""COMPUTED_VALUE"""),"Targets") -> Targets | BX4: =IFERROR(__xludf.DUMMYFUNCTION("""COMPUTED_VALUE"""),1.0) -> 1 | BY4: =IFERROR(__xludf.DUMMYFUNCTION("""COMPUTED_VALUE"""),"00 | 1 | Cost 0 ⧈ | Next 100 ⧈") -> 00 | 1 | Cost 0 ⧈ | Next 100 ⧈ | BZ4: =IFERROR(__xludf.DUMMYFUNCTION("""COMPUTED_VALUE"""),"Tier 2") -> Tier 2 | CA4: =IFERROR(__xludf.DUMMYFUNCTION("""COMPUTED_VALUE"""),5628.0) -> 5628 | CD4: =IFERROR(__xludf.DUMMYFUNCTION("""COMPUTED_VALUE"""),"Farming Tier") -> Farming Tier | CE4: =IFERROR(__xludf.DUMMYFUNCTION("""COMPUTED_VALUE"""),"Tier 14") -> Tier 14
A5: =IFERROR(__xludf.DUMMYFUNCTION("""COMPUTED_VALUE"""),"Workshop Defense Discount") -> Workshop Defense Discount | B5: =IFERROR(__xludf.DUMMYFUNCTION("""COMPUTED_VALUE"""),28.0) -> 28 | D5: =IFERROR(__xludf.DUMMYFUNCTION("""COMPUTED_VALUE"""),99.0) -> 99 | F5: =IFERROR(__xludf.DUMMYFUNCTION("""COMPUTED_VALUE"""),"Attack Speed") -> Attack Speed | G5: =IFERROR(__xludf.DUMMYFUNCTION("""COMPUTED_VALUE"""),99.0) -> 99 | H5: =IFERROR(__xludf.DUMMYFUNCTION("""COMPUTED_VALUE"""),99.0) -> 99 | I5: =IFERROR(__xludf.DUMMYFUNCTION("""COMPUTED_VALUE"""),99.0) -> 99 | J5: =IFERROR(__xludf.DUMMYFUNCTION("""COMPUTED_VALUE"""),99.0) -> 99 | Q5: =IFERROR(__xludf.DUMMYFUNCTION("""COMPUTED_VALUE"""),99.0) -> 99 | R5: =IFERROR(__xludf.DUMMYFUNCTION("""COMPUTED_VALUE"""),"Rend Armor Mult +") -> Rend Armor Mult + | S5: =IFERROR(__xludf.DUMMYFUNCTION("""COMPUTED_VALUE"""),1.21) -> 1.21 | T5: =IFERROR(__xludf.DUMMYFUNCTION("""COMPUTED_VALUE"""),21.0) -> 21 | U5: =IFERROR(__xludf.DUMMYFUNCTION("""COMPUTED_VALUE"""),21.0) -> 21 | Y5: =IFERROR(__xludf.DUMMYFUNCTION("""COMPUTED_VALUE"""),400.0) -> 400 | Z5: =IFERROR(__xludf.DUMMYFUNCTION("""COMPUTED_VALUE"""),"UW+") -> UW+ | AB5: =IFERROR(__xludf.DUMMYFUNCTION("""COMPUTED_VALUE"""),"Smite") -> Smite | AC5: =IFERROR(__xludf.DUMMYFUNCTION("""COMPUTED_VALUE"""),"Locked") -> Locked | AD5: =IFERROR(__xludf.DUMMYFUNCTION("""COMPUTED_VALUE"""),"Lo | Locked") -> Lo | Locked | AE5: =IFERROR(__xludf.DUMMYFUNCTION("""COMPUTED_VALUE"""),"Health Regen") -> Health Regen | AF5: =IFERROR(__xludf.DUMMYFUNCTION("""COMPUTED_VALUE"""),7.0) -> 7 | AG5: =IFERROR(__xludf.DUMMYFUNCTION("""COMPUTED_VALUE"""),FALSE) -> FALSE | AH5: =IFERROR(__xludf.DUMMYFUNCTION("""COMPUTED_VALUE"""),"Health") -> Health | AI5: =IFERROR(__xludf.DUMMYFUNCTION("""COMPUTED_VALUE"""),"Berserker") -> Berserker | AM5: =IFERROR(__xludf.DUMMYFUNCTION("""COMPUTED_VALUE"""),"Other Relics") -> Other Relics | AN5: =IFERROR(__xludf.DUMMYFUNCTION("""COMPUTED_VALUE"""),22.0) -> 22 | AP5: =IFERROR(__xludf.DUMMYFUNCTION("""COMPUTED_VALUE"""),"Misc.") -> Misc. | AS5: =IFERROR(__xludf.DUMMYFUNCTION("""COMPUTED_VALUE"""),TRUE) -> TRUE | AT5: =IFERROR(__xludf.DUMMYFUNCTION("""COMPUTED_VALUE"""),"Unlocked") -> Unlocked | AU5: =IFERROR(__xludf.DUMMYFUNCTION("""COMPUTED_VALUE"""),"Range") -> Range | AV5: =IFERROR(__xludf.DUMMYFUNCTION("""COMPUTED_VALUE"""),46.0) -> 46 | AW5: =IFERROR(__xludf.DUMMYFUNCTION("""COMPUTED_VALUE"""),"04 | 46m | Cost 220 ⧓ | Next 260 ⧓") -> 04 | 46m | Cost 220 ⧓ | Next 260 ⧓ | BB5: =IFERROR(__xludf.DUMMYFUNCTION("""COMPUTED_VALUE"""),"Substat Cap") -> Substat Cap | BC5: =IFERROR(__xludf.DUMMYFUNCTION("""COMPUTED_VALUE"""),0.01) -> 0.01 | BD5: =IFERROR(__xludf.DUMMYFUNCTION("""COMPUTED_VALUE"""),"00 | 1% | Cost 0 ⧌ | Next 15 ⧌") -> 00 | 1% | Cost 0 ⧌ | Next 15 ⧌ | BG5: =IFERROR(__xludf.DUMMYFUNCTION("""COMPUTED_VALUE"""),"Substat Cap") -> Substat Cap | BH5: =IFERROR(__xludf.DUMMYFUNCTION("""COMPUTED_VALUE"""),0.1) -> 0.1 | BI5: =IFERROR(__xludf.DUMMYFUNCTION("""COMPUTED_VALUE"""),"09 | 10% | Cost 39 ⧌ | Next 42 ⧌") -> 09 | 10% | Cost 39 ⧌ | Next 42 ⧌ | BL5: =IFERROR(__xludf.DUMMYFUNCTION("""COMPUTED_VALUE"""),"Substat Cap") -> Substat Cap | BM5: =IFERROR(__xludf.DUMMYFUNCTION("""COMPUTED_VALUE"""),0.1) -> 0.1 | BN5: =IFERROR(__xludf.DUMMYFUNCTION("""COMPUTED_VALUE"""),"09 | 10% | Cost 39 ⧌ | Next 42 ⧌") -> 09 | 10% | Cost 39 ⧌ | Next 42 ⧌ | BQ5: =IFERROR(__xludf.DUMMYFUNCTION("""COMPUTED_VALUE"""),"Substat Cap") -> Substat Cap | BR5: =IFERROR(__xludf.DUMMYFUNCTION("""COMPUTED_VALUE"""),0.1) -> 0.1 | BS5: =IFERROR(__xludf.DUMMYFUNCTION("""COMPUTED_VALUE"""),"09 | 10% | Cost 39 ⧌ | Next 42 ⧌") -> 09 | 10% | Cost 39 ⧌ | Next 42 ⧌ | BU5: =IFERROR(__xludf.DUMMYFUNCTION("""COMPUTED_VALUE"""),"Ally") -> Ally | BW5: =IFERROR(__xludf.DUMMYFUNCTION("""COMPUTED_VALUE"""),"Recovery Amount") -> Recovery Amount | BX5: =IFERROR(__xludf.DUMMYFUNCTION("""COMPUTED_VALUE"""),0.01) -> 0.01 | BY5: =IFERROR(__xludf.DUMMYFUNCTION("""COMPUTED_VALUE"""),"00 | 1% | Cost 0 ⧈ | Next 10 ⧈") -> 00 | 1% | Cost 0 ⧈ | Next 10 ⧈ | BZ5: =IFERROR(__xludf.DUMMYFUNCTION("""COMPUTED_VALUE"""),"Tier 3") -> Tier 3 | CA5: =IFERROR(__xludf.DUMMYFUNCTION("""COMPUTED_VALUE"""),5402.0) -> 5402 | CD5: =IFERROR(__xludf.DUMMYFUNCTION("""COMPUTED_VALUE"""),"Tourney League") -> Tourney League | CE5: =IFERROR(__xludf.DUMMYFUNCTION("""COMPUTED_VALUE"""),"Legends") -> Legends
A6: =IFERROR(__xludf.DUMMYFUNCTION("""COMPUTED_VALUE"""),"Workshop Utility Discount") -> Workshop Utility Discount | B6: =IFERROR(__xludf.DUMMYFUNCTION("""COMPUTED_VALUE"""),41.0) -> 41 | D6: =IFERROR(__xludf.DUMMYFUNCTION("""COMPUTED_VALUE"""),99.0) -> 99 | F6: =IFERROR(__xludf.DUMMYFUNCTION("""COMPUTED_VALUE"""),"Critical Chance") -> Critical Chance | G6: =IFERROR(__xludf.DUMMYFUNCTION("""COMPUTED_VALUE"""),79.0) -> 79 | H6: =IFERROR(__xludf.DUMMYFUNCTION("""COMPUTED_VALUE"""),79.0) -> 79 | I6: =IFERROR(__xludf.DUMMYFUNCTION("""COMPUTED_VALUE"""),79.0) -> 79 | J6: =IFERROR(__xludf.DUMMYFUNCTION("""COMPUTED_VALUE"""),79.0) -> 79 | Q6: =IFERROR(__xludf.DUMMYFUNCTION("""COMPUTED_VALUE"""),79.0) -> 79 | R6: =IFERROR(__xludf.DUMMYFUNCTION("""COMPUTED_VALUE"""),"Critical Factor +") -> Critical Factor + | S6: =IFERROR(__xludf.DUMMYFUNCTION("""COMPUTED_VALUE"""),1.6) -> 1.6 | T6: =IFERROR(__xludf.DUMMYFUNCTION("""COMPUTED_VALUE"""),60.0) -> 60 | U6: =IFERROR(__xludf.DUMMYFUNCTION("""COMPUTED_VALUE"""),60.0) -> 60 | Y6: =IFERROR(__xludf.DUMMYFUNCTION("""COMPUTED_VALUE"""),400.0) -> 400 | Z6: =IFERROR(__xludf.DUMMYFUNCTION("""COMPUTED_VALUE"""),"Smart Missiles") -> Smart Missiles | AB6: =IFERROR(__xludf.DUMMYFUNCTION("""COMPUTED_VALUE"""),"Damage") -> Damage | AC6: =IFERROR(__xludf.DUMMYFUNCTION("""COMPUTED_VALUE"""),10.0) -> 10 | AD6: =IFERROR(__xludf.DUMMYFUNCTION("""COMPUTED_VALUE"""),"00 | x10 | Cost 0 ⧌ | Next 5 ⧌") -> 00 | x10 | Cost 0 ⧌ | Next 5 ⧌ | AE6: =IFERROR(__xludf.DUMMYFUNCTION("""COMPUTED_VALUE"""),"Range") -> Range | AF6: =IFERROR(__xludf.DUMMYFUNCTION("""COMPUTED_VALUE"""),7.0) -> 7 | AG6: =IFERROR(__xludf.DUMMYFUNCTION("""COMPUTED_VALUE"""),FALSE) -> FALSE | AH6: =IFERROR(__xludf.DUMMYFUNCTION("""COMPUTED_VALUE"""),"Coins") -> Coins | AI6: =IFERROR(__xludf.DUMMYFUNCTION("""COMPUTED_VALUE"""),"Critical Chance") -> Critical Chance | AM6: =IFERROR(__xludf.DUMMYFUNCTION("""COMPUTED_VALUE"""),"Total Relics") -> Total Relics | AN6: =IFERROR(__xludf.DUMMYFUNCTION("""COMPUTED_VALUE"""),147.0) -> 147 | AP6: =IFERROR(__xludf.DUMMYFUNCTION("""COMPUTED_VALUE"""),"Bot Range") -> Bot Range | AQ6: =IFERROR(__xludf.DUMMYFUNCTION("""COMPUTED_VALUE"""),0.0) -> 0 | AS6: =IFERROR(__xludf.DUMMYFUNCTION("""COMPUTED_VALUE"""),"Thunder Bot") -> Thunder Bot | AU6: =IFERROR(__xludf.DUMMYFUNCTION("""COMPUTED_VALUE"""),"Duration") -> Duration | AV6: =IFERROR(__xludf.DUMMYFUNCTION("""COMPUTED_VALUE"""),5.0) -> 5 | AW6: =IFERROR(__xludf.DUMMYFUNCTION("""COMPUTED_VALUE"""),"00 | 5.0s | Cost 0 ⧓ | Next 100 ⧓") -> 00 | 5.0s | Cost 0 ⧓ | Next 100 ⧓ | BE6: =IFERROR(__xludf.DUMMYFUNCTION("""COMPUTED_VALUE"""),0.4444444444444444) -> 0.44444444 | BW6: =IFERROR(__xludf.DUMMYFUNCTION("""COMPUTED_VALUE"""),"Max Recovery") -> Max Recovery | BX6: =IFERROR(__xludf.DUMMYFUNCTION("""COMPUTED_VALUE"""),1.1) -> 1.1 | BY6: =IFERROR(__xludf.DUMMYFUNCTION("""COMPUTED_VALUE"""),"00 | 1.1x | Cost 0 ⧈ | Next 1 ⧈") -> 00 | 1.1x | Cost 0 ⧈ | Next 1 ⧈ | BZ6: =IFERROR(__xludf.DUMMYFUNCTION("""COMPUTED_VALUE"""),"Tier 4") -> Tier 4 | CA6: =IFERROR(__xludf.DUMMYFUNCTION("""COMPUTED_VALUE"""),6310.0) -> 6310 | CB6: =IFERROR(__xludf.DUMMYFUNCTION("""COMPUTED_VALUE"""),TRUE) -> TRUE | CD6: =IFERROR(__xludf.DUMMYFUNCTION("""COMPUTED_VALUE"""),"Lifetime Coins") -> Lifetime Coins | CE6: =IFERROR(__xludf.DUMMYFUNCTION("""COMPUTED_VALUE"""),3.57E12) -> 3570000000000
A7: =IFERROR(__xludf.DUMMYFUNCTION("""COMPUTED_VALUE"""),"Labs Coin Discount") -> Labs Coin Discount | B7: =IFERROR(__xludf.DUMMYFUNCTION("""COMPUTED_VALUE"""),68.0) -> 68 | D7: =IFERROR(__xludf.DUMMYFUNCTION("""COMPUTED_VALUE"""),99.0) -> 99 | F7: =IFERROR(__xludf.DUMMYFUNCTION("""COMPUTED_VALUE"""),"Critical Factor") -> Critical Factor | G7: =IFERROR(__xludf.DUMMYFUNCTION("""COMPUTED_VALUE"""),150.0) -> 150 | H7: =IFERROR(__xludf.DUMMYFUNCTION("""COMPUTED_VALUE"""),150.0) -> 150 | I7: =IFERROR(__xludf.DUMMYFUNCTION("""COMPUTED_VALUE"""),150.0) -> 150 | J7: =IFERROR(__xludf.DUMMYFUNCTION("""COMPUTED_VALUE"""),150.0) -> 150 | Q7: =IFERROR(__xludf.DUMMYFUNCTION("""COMPUTED_VALUE"""),150.0) -> 150 | R7: =IFERROR(__xludf.DUMMYFUNCTION("""COMPUTED_VALUE"""),"Damage / Meter +") -> Damage / Meter + | S7: =IFERROR(__xludf.DUMMYFUNCTION("""COMPUTED_VALUE"""),1.17) -> 1.17 | T7: =IFERROR(__xludf.DUMMYFUNCTION("""COMPUTED_VALUE"""),17.0) -> 17 | U7: =IFERROR(__xludf.DUMMYFUNCTION("""COMPUTED_VALUE"""),17.0) -> 17 | Y7: =IFERROR(__xludf.DUMMYFUNCTION("""COMPUTED_VALUE"""),400.0) -> 400 | AB7: =IFERROR(__xludf.DUMMYFUNCTION("""COMPUTED_VALUE"""),"Quantity") -> Quantity | AC7: =IFERROR(__xludf.DUMMYFUNCTION("""COMPUTED_VALUE"""),5.0) -> 5 | AD7: =IFERROR(__xludf.DUMMYFUNCTION("""COMPUTED_VALUE"""),"00 | #5 | Cost 0 ⧌ | Next 4 ⧌") -> 00 | #5 | Cost 0 ⧌ | Next 4 ⧌ | AE7: =IFERROR(__xludf.DUMMYFUNCTION("""COMPUTED_VALUE"""),"Cash") -> Cash | AF7: =IFERROR(__xludf.DUMMYFUNCTION("""COMPUTED_VALUE"""),7.0) -> 7 | AG7: =IFERROR(__xludf.DUMMYFUNCTION("""COMPUTED_VALUE"""),TRUE) -> TRUE | AH7: =IFERROR(__xludf.DUMMYFUNCTION("""COMPUTED_VALUE"""),"Plasma Cannon") -> Plasma Cannon | AI7: =IFERROR(__xludf.DUMMYFUNCTION("""COMPUTED_VALUE"""),"Health") -> Health | AP7: =IFERROR(__xludf.DUMMYFUNCTION("""COMPUTED_VALUE"""),"Discount Enhancements") -> Discount Enhancements | AQ7: =IFERROR(__xludf.DUMMYFUNCTION("""COMPUTED_VALUE"""),0.0) -> 0 | AU7: =IFERROR(__xludf.DUMMYFUNCTION("""COMPUTED_VALUE"""),"Cooldown") -> Cooldown | AV7: =IFERROR(__xludf.DUMMYFUNCTION("""COMPUTED_VALUE"""),120.0) -> 120 | AW7: =IFERROR(__xludf.DUMMYFUNCTION("""COMPUTED_VALUE"""),"00 | 120s | Cost 0 ⧓ | Next 100 ⧓") -> 00 | 120s | Cost 0 ⧓ | Next 100 ⧓ | BB7: =IFERROR(__xludf.DUMMYFUNCTION("""COMPUTED_VALUE"""),"Farming") -> Farming | BG7: =IFERROR(__xludf.DUMMYFUNCTION("""COMPUTED_VALUE"""),"Farming") -> Farming | BL7: =IFERROR(__xludf.DUMMYFUNCTION("""COMPUTED_VALUE"""),"Farming") -> Farming | BQ7: =IFERROR(__xludf.DUMMYFUNCTION("""COMPUTED_VALUE"""),"Farming") -> Farming | BU7: =IFERROR(__xludf.DUMMYFUNCTION("""COMPUTED_VALUE"""),TRUE) -> TRUE | BV7: =IFERROR(__xludf.DUMMYFUNCTION("""COMPUTED_VALUE"""),"Unlocked") -> Unlocked | BW7: =IFERROR(__xludf.DUMMYFUNCTION("""COMPUTED_VALUE"""),"Cooldown") -> Cooldown | BX7: =IFERROR(__xludf.DUMMYFUNCTION("""COMPUTED_VALUE"""),120.0) -> 120 | BY7: =IFERROR(__xludf.DUMMYFUNCTION("""COMPUTED_VALUE"""),"00 | 120s | Cost 0 ⧈ | Next 1 ⧈") -> 00 | 120s | Cost 0 ⧈ | Next 1 ⧈ | BZ7: =IFERROR(__xludf.DUMMYFUNCTION("""COMPUTED_VALUE"""),"Tier 5") -> Tier 5 | CA7: =IFERROR(__xludf.DUMMYFUNCTION("""COMPUTED_VALUE"""),7593.0) -> 7593 | CD7: =IFERROR(__xludf.DUMMYFUNCTION("""COMPUTED_VALUE"""),"Stones") -> Stones | CE7: =IFERROR(__xludf.DUMMYFUNCTION("""COMPUTED_VALUE"""),200.0) -> 200
A8: =IFERROR(__xludf.DUMMYFUNCTION("""COMPUTED_VALUE"""),"Labs Speed") -> Labs Speed | B8: =IFERROR(__xludf.DUMMYFUNCTION("""COMPUTED_VALUE"""),91.0) -> 91 | D8: =IFERROR(__xludf.DUMMYFUNCTION("""COMPUTED_VALUE"""),99.0) -> 99 | E8: =IFERROR(__xludf.DUMMYFUNCTION("""COMPUTED_VALUE"""),TRUE) -> TRUE | F8: =IFERROR(__xludf.DUMMYFUNCTION("""COMPUTED_VALUE"""),"Range") -> Range | G8: =IFERROR(__xludf.DUMMYFUNCTION("""COMPUTED_VALUE"""),79.0) -> 79 | H8: =IFERROR(__xludf.DUMMYFUNCTION("""COMPUTED_VALUE"""),79.0) -> 79 | I8: =IFERROR(__xludf.DUMMYFUNCTION("""COMPUTED_VALUE"""),79.0) -> 79 | J8: =IFERROR(__xludf.DUMMYFUNCTION("""COMPUTED_VALUE"""),79.0) -> 79 | Q8: =IFERROR(__xludf.DUMMYFUNCTION("""COMPUTED_VALUE"""),79.0) -> 79 | R8: =IFERROR(__xludf.DUMMYFUNCTION("""COMPUTED_VALUE"""),"Super Crit Multi +") -> Super Crit Multi + | S8: =IFERROR(__xludf.DUMMYFUNCTION("""COMPUTED_VALUE"""),1.57) -> 1.57 | T8: =IFERROR(__xludf.DUMMYFUNCTION("""COMPUTED_VALUE"""),57.0) -> 57 | U8: =IFERROR(__xludf.DUMMYFUNCTION("""COMPUTED_VALUE"""),57.0) -> 57 | Y8: =IFERROR(__xludf.DUMMYFUNCTION("""COMPUTED_VALUE"""),400.0) -> 400 | Z8: =IFERROR(__xludf.DUMMYFUNCTION("""COMPUTED_VALUE"""),FALSE) -> FALSE | AA8: =IFERROR(__xludf.DUMMYFUNCTION("""COMPUTED_VALUE"""),"UW Locked") -> UW Locked | AB8: =IFERROR(__xludf.DUMMYFUNCTION("""COMPUTED_VALUE"""),"Cooldown") -> Cooldown | AC8: =IFERROR(__xludf.DUMMYFUNCTION("""COMPUTED_VALUE"""),180.0) -> 180 | AD8: =IFERROR(__xludf.DUMMYFUNCTION("""COMPUTED_VALUE"""),"00 | 180s | Cost 0 ⧌ | Next 8 ⧌") -> 00 | 180s | Cost 0 ⧌ | Next 8 ⧌ | AE8: =IFERROR(__xludf.DUMMYFUNCTION("""COMPUTED_VALUE"""),"Coins") -> Coins | AF8: =IFERROR(__xludf.DUMMYFUNCTION("""COMPUTED_VALUE"""),7.0) -> 7 | AG8: =IFERROR(__xludf.DUMMYFUNCTION("""COMPUTED_VALUE"""),FALSE) -> FALSE | AH8: =IFERROR(__xludf.DUMMYFUNCTION("""COMPUTED_VALUE"""),"Attack Speed") -> Attack Speed | AI8: =IFERROR(__xludf.DUMMYFUNCTION("""COMPUTED_VALUE"""),"Health Regen") -> Health Regen | AM8: =IFERROR(__xludf.DUMMYFUNCTION("""COMPUTED_VALUE"""),"Total Bonuses") -> Total Bonuses | AN8: =IFERROR(__xludf.DUMMYFUNCTION("""COMPUTED_VALUE"""),"Active") -> Active | AP8: =IFERROR(__xludf.DUMMYFUNCTION("""COMPUTED_VALUE"""),"Discount Rerolls") -> Discount Rerolls | AQ8: =IFERROR(__xludf.DUMMYFUNCTION("""COMPUTED_VALUE"""),0.0) -> 0 | AU8: =IFERROR(__xludf.DUMMYFUNCTION("""COMPUTED_VALUE"""),"Linger") -> Linger | AV8: =IFERROR(__xludf.DUMMYFUNCTION("""COMPUTED_VALUE"""),0.2) -> 0.2 | AW8: =IFERROR(__xludf.DUMMYFUNCTION("""COMPUTED_VALUE"""),"00 | 20% | Cost 0 ⧓ | Next 100 ⧓") -> 00 | 20% | Cost 0 ⧓ | Next 100 ⧓ | BB8: =IFERROR(__xludf.DUMMYFUNCTION("""COMPUTED_VALUE"""),"Primary Slot") -> Primary Slot | BC8: =IFERROR(__xludf.DUMMYFUNCTION("""COMPUTED_VALUE"""),"Amplifying Strike") -> Amplifying Strike | BG8: =IFERROR(__xludf.DUMMYFUNCTION("""COMPUTED_VALUE"""),"Primary Slot") -> Primary Slot | BH8: =IFERROR(__xludf.DUMMYFUNCTION("""COMPUTED_VALUE"""),"Sharp Fortitude") -> Sharp Fortitude | BL8: =IFERROR(__xludf.DUMMYFUNCTION("""COMPUTED_VALUE"""),"Primary Slot") -> Primary Slot | BM8: =IFERROR(__xludf.DUMMYFUNCTION("""COMPUTED_VALUE"""),"Singularity Harness") -> Singularity Harness | BQ8: =IFERROR(__xludf.DUMMYFUNCTION("""COMPUTED_VALUE"""),"Primary Slot") -> Primary Slot | BR8: =IFERROR(__xludf.DUMMYFUNCTION("""COMPUTED_VALUE"""),"Primordial Collapse") -> Primordial Collapse | BU8: =IFERROR(__xludf.DUMMYFUNCTION("""COMPUTED_VALUE"""),"Bounty") -> Bounty | BW8: =IFERROR(__xludf.DUMMYFUNCTION("""COMPUTED_VALUE"""),"Multiplier") -> Multiplier | BX8: =IFERROR(__xludf.DUMMYFUNCTION("""COMPUTED_VALUE"""),0.01) -> 0.01 | BY8: =IFERROR(__xludf.DUMMYFUNCTION("""COMPUTED_VALUE"""),"00 | 0.01x | Cost 0 ⧈ | Next 1 ⧈") -> 00 | 0.01x | Cost 0 ⧈ | Next 1 ⧈ | BZ8: =IFERROR(__xludf.DUMMYFUNCTION("""COMPUTED_VALUE"""),"Tier 6") -> Tier 6 | CA8: =IFERROR(__xludf.DUMMYFUNCTION("""COMPUTED_VALUE"""),8252.0) -> 8252 | CD8: =IFERROR(__xludf.DUMMYFUNCTION("""COMPUTED_VALUE"""),"Gems") -> Gems | CE8: =IFERROR(__xludf.DUMMYFUNCTION("""COMPUTED_VALUE"""),326.0) -> 326
A9: =IFERROR(__xludf.DUMMYFUNCTION("""COMPUTED_VALUE"""),"Buy Multiplier") -> Buy Multiplier | B9: =IFERROR(__xludf.DUMMYFUNCTION("""COMPUTED_VALUE"""),4.0) -> 4 | D9: =IFERROR(__xludf.DUMMYFUNCTION("""COMPUTED_VALUE"""),4.0) -> 4 | F9: =IFERROR(__xludf.DUMMYFUNCTION("""COMPUTED_VALUE"""),"Damage / Meter") -> Damage / Meter | G9: =IFERROR(__xludf.DUMMYFUNCTION("""COMPUTED_VALUE"""),180.0) -> 180 | H9: =IFERROR(__xludf.DUMMYFUNCTION("""COMPUTED_VALUE"""),200.0) -> 200 | I9: =IFERROR(__xludf.DUMMYFUNCTION("""COMPUTED_VALUE"""),180.0) -> 180 | J9: =IFERROR(__xludf.DUMMYFUNCTION("""COMPUTED_VALUE"""),200.0) -> 200 | Q9: =IFERROR(__xludf.DUMMYFUNCTION("""COMPUTED_VALUE"""),200.0) -> 200 | R9: =IFERROR(__xludf.DUMMYFUNCTION("""COMPUTED_VALUE"""),"Attack Speed +") -> Attack Speed + | S9: =IFERROR(__xludf.DUMMYFUNCTION("""COMPUTED_VALUE"""),1.13) -> 1.13 | T9: =IFERROR(__xludf.DUMMYFUNCTION("""COMPUTED_VALUE"""),13.0) -> 13 | U9: =IFERROR(__xludf.DUMMYFUNCTION("""COMPUTED_VALUE"""),13.0) -> 13 | Y9: =IFERROR(__xludf.DUMMYFUNCTION("""COMPUTED_VALUE"""),75.0) -> 75 | Z9: =IFERROR(__xludf.DUMMYFUNCTION("""COMPUTED_VALUE"""),"UW+") -> UW+ | AB9: =IFERROR(__xludf.DUMMYFUNCTION("""COMPUTED_VALUE"""),"Cover Fire") -> Cover Fire | AC9: =IFERROR(__xludf.DUMMYFUNCTION("""COMPUTED_VALUE"""),"Locked") -> Locked | AD9: =IFERROR(__xludf.DUMMYFUNCTION("""COMPUTED_VALUE"""),"Lo | Locked") -> Lo | Locked | AE9: =IFERROR(__xludf.DUMMYFUNCTION("""COMPUTED_VALUE"""),"Slow Aura") -> Slow Aura | AF9: =IFERROR(__xludf.DUMMYFUNCTION("""COMPUTED_VALUE"""),7.0) -> 7 | AG9: =IFERROR(__xludf.DUMMYFUNCTION("""COMPUTED_VALUE"""),FALSE) -> FALSE | AH9: =IFERROR(__xludf.DUMMYFUNCTION("""COMPUTED_VALUE"""),"Wave Skip") -> Wave Skip | AI9: =IFERROR(__xludf.DUMMYFUNCTION("""COMPUTED_VALUE"""),"Plasma Cannon") -> Plasma Cannon | AM9: =IFERROR(__xludf.DUMMYFUNCTION("""COMPUTED_VALUE"""),"Misc.") -> Misc. | AP9: =IFERROR(__xludf.DUMMYFUNCTION("""COMPUTED_VALUE"""),"Additional Card Slot") -> Additional Card Slot | AQ9: =IFERROR(__xludf.DUMMYFUNCTION("""COMPUTED_VALUE"""),0.0) -> 0 | AS9: =IFERROR(__xludf.DUMMYFUNCTION("""COMPUTED_VALUE"""),FALSE) -> FALSE | AT9: =IFERROR(__xludf.DUMMYFUNCTION("""COMPUTED_VALUE"""),"Locked") -> Locked | AU9: =IFERROR(__xludf.DUMMYFUNCTION("""COMPUTED_VALUE"""),"Range") -> Range | AV9: =IFERROR(__xludf.DUMMYFUNCTION("""COMPUTED_VALUE"""),25.0) -> 25 | AW9: =IFERROR(__xludf.DUMMYFUNCTION("""COMPUTED_VALUE"""),"00 | 25m | Cost 0 ⧓ | Next 100 ⧓") -> 00 | 25m | Cost 0 ⧓ | Next 100 ⧓ | BB9: =IFERROR(__xludf.DUMMYFUNCTION("""COMPUTED_VALUE"""),"Assist Slot") -> Assist Slot | BG9: =IFERROR(__xludf.DUMMYFUNCTION("""COMPUTED_VALUE"""),"Assist Slot") -> Assist Slot | BH9: =IFERROR(__xludf.DUMMYFUNCTION("""COMPUTED_VALUE"""),"Orbital Augment") -> Orbital Augment | BL9: =IFERROR(__xludf.DUMMYFUNCTION("""COMPUTED_VALUE"""),"Assist Slot") -> Assist Slot | BM9: =IFERROR(__xludf.DUMMYFUNCTION("""COMPUTED_VALUE"""),"Pulsar Harvester") -> Pulsar Harvester | BQ9: =IFERROR(__xludf.DUMMYFUNCTION("""COMPUTED_VALUE"""),"Assist Slot") -> Assist Slot | BR9: =IFERROR(__xludf.DUMMYFUNCTION("""COMPUTED_VALUE"""),"Dimension Core") -> Dimension Core | BW9: =IFERROR(__xludf.DUMMYFUNCTION("""COMPUTED_VALUE"""),"Cooldown") -> Cooldown | BX9: =IFERROR(__xludf.DUMMYFUNCTION("""COMPUTED_VALUE"""),120.0) -> 120 | BY9: =IFERROR(__xludf.DUMMYFUNCTION("""COMPUTED_VALUE"""),"00 | 120s | Cost 0 ⧈ | Next 2 ⧈") -> 00 | 120s | Cost 0 ⧈ | Next 2 ⧈ | BZ9: =IFERROR(__xludf.DUMMYFUNCTION("""COMPUTED_VALUE"""),"Tier 7") -> Tier 7 | CA9: =IFERROR(__xludf.DUMMYFUNCTION("""COMPUTED_VALUE"""),7854.0) -> 7854 | CB9: =IFERROR(__xludf.DUMMYFUNCTION("""COMPUTED_VALUE"""),TRUE) -> TRUE
A10: =IFERROR(__xludf.DUMMYFUNCTION("""COMPUTED_VALUE"""),"More Round Stats") -> More Round Stats | B10: =IFERROR(__xludf.DUMMYFUNCTION("""COMPUTED_VALUE"""),1.0) -> 1 | D10: =IFERROR(__xludf.DUMMYFUNCTION("""COMPUTED_VALUE"""),1.0) -> 1 | E10: =IFERROR(__xludf.DUMMYFUNCTION("""COMPUTED_VALUE"""),TRUE) -> TRUE | F10: =IFERROR(__xludf.DUMMYFUNCTION("""COMPUTED_VALUE"""),"Multishot Chance") -> Multishot Chance | G10: =IFERROR(__xludf.DUMMYFUNCTION("""COMPUTED_VALUE"""),99.0) -> 99 | H10: =IFERROR(__xludf.DUMMYFUNCTION("""COMPUTED_VALUE"""),99.0) -> 99 | I10: =IFERROR(__xludf.DUMMYFUNCTION("""COMPUTED_VALUE"""),99.0) -> 99 | J10: =IFERROR(__xludf.DUMMYFUNCTION("""COMPUTED_VALUE"""),99.0) -> 99 | Q10: =IFERROR(__xludf.DUMMYFUNCTION("""COMPUTED_VALUE"""),99.0) -> 99 | R10: =IFERROR(__xludf.DUMMYFUNCTION("""COMPUTED_VALUE"""),"Health +") -> Health + | S10: =IFERROR(__xludf.DUMMYFUNCTION("""COMPUTED_VALUE"""),1.62) -> 1.62 | T10: =IFERROR(__xludf.DUMMYFUNCTION("""COMPUTED_VALUE"""),62.0) -> 62 | U10: =IFERROR(__xludf.DUMMYFUNCTION("""COMPUTED_VALUE"""),62.0) -> 62 | Y10: =IFERROR(__xludf.DUMMYFUNCTION("""COMPUTED_VALUE"""),400.0) -> 400 | Z10: =IFERROR(__xludf.DUMMYFUNCTION("""COMPUTED_VALUE"""),"Death Wave") -> Death Wave | AB10: =IFERROR(__xludf.DUMMYFUNCTION("""COMPUTED_VALUE"""),"Damage") -> Damage | AC10: =IFERROR(__xludf.DUMMYFUNCTION("""COMPUTED_VALUE"""),63.0) -> 63 | AD10: =IFERROR(__xludf.DUMMYFUNCTION("""COMPUTED_VALUE"""),"08 | x63 | Cost 47 ⧌ | Next 53 ⧌") -> 08 | x63 | Cost 47 ⧌ | Next 53 ⧌ | AE10: =IFERROR(__xludf.DUMMYFUNCTION("""COMPUTED_VALUE"""),"Critical Chance") -> Critical Chance | AF10: =IFERROR(__xludf.DUMMYFUNCTION("""COMPUTED_VALUE"""),7.0) -> 7 | AG10: =IFERROR(__xludf.DUMMYFUNCTION("""COMPUTED_VALUE"""),FALSE) -> FALSE | AH10: =IFERROR(__xludf.DUMMYFUNCTION("""COMPUTED_VALUE"""),"Health Regen") -> Health Regen | AI10: =IFERROR(__xludf.DUMMYFUNCTION("""COMPUTED_VALUE"""),"Wave Skip") -> Wave Skip | AM10: =IFERROR(__xludf.DUMMYFUNCTION("""COMPUTED_VALUE"""),"Lab Speed") -> Lab Speed | AN10: =IFERROR(__xludf.DUMMYFUNCTION("""COMPUTED_VALUE"""),0.395) -> 0.395 | AP10: =IFERROR(__xludf.DUMMYFUNCTION("""COMPUTED_VALUE"""),"Workshop Respec Discount") -> Workshop Respec Discount | AQ10: =IFERROR(__xludf.DUMMYFUNCTION("""COMPUTED_VALUE"""),0.0) -> 0 | AS10: =IFERROR(__xludf.DUMMYFUNCTION("""COMPUTED_VALUE"""),"Golden Bot") -> Golden Bot | AU10: =IFERROR(__xludf.DUMMYFUNCTION("""COMPUTED_VALUE"""),"Duration") -> Duration | AV10: =IFERROR(__xludf.DUMMYFUNCTION("""COMPUTED_VALUE"""),26.0) -> 26 | AW10: =IFERROR(__xludf.DUMMYFUNCTION("""COMPUTED_VALUE"""),"12 | 26.0s | Cost 540 ⧓ | Next 580 ⧓") -> 12 | 26.0s | Cost 540 ⧓ | Next 580 ⧓ | BU10: =IFERROR(__xludf.DUMMYFUNCTION("""COMPUTED_VALUE"""),FALSE) -> FALSE | BV10: =IFERROR(__xludf.DUMMYFUNCTION("""COMPUTED_VALUE"""),"Locked") -> Locked | BW10: =IFERROR(__xludf.DUMMYFUNCTION("""COMPUTED_VALUE"""),"Targets") -> Targets | BX10: =IFERROR(__xludf.DUMMYFUNCTION("""COMPUTED_VALUE"""),1.0) -> 1 | BY10: =IFERROR(__xludf.DUMMYFUNCTION("""COMPUTED_VALUE"""),"00 | 1 | Cost 0 ⧈ | Next 100 ⧈") -> 00 | 1 | Cost 0 ⧈ | Next 100 ⧈ | BZ10: =IFERROR(__xludf.DUMMYFUNCTION("""COMPUTED_VALUE"""),"Tier 8") -> Tier 8 | CA10: =IFERROR(__xludf.DUMMYFUNCTION("""COMPUTED_VALUE"""),8119.0) -> 8119 | CD10: =IFERROR(__xludf.DUMMYFUNCTION("""COMPUTED_VALUE"""),"Premium Packs") -> Premium Packs | CE10: =IFERROR(__xludf.DUMMYFUNCTION("""COMPUTED_VALUE"""),"Unlocked") -> Unlocked
A11: =IFERROR(__xludf.DUMMYFUNCTION("""COMPUTED_VALUE"""),"Target Priority") -> Target Priority | B11: =IFERROR(__xludf.DUMMYFUNCTION("""COMPUTED_VALUE"""),2.0) -> 2 | D11: =IFERROR(__xludf.DUMMYFUNCTION("""COMPUTED_VALUE"""),2.0) -> 2 | F11: =IFERROR(__xludf.DUMMYFUNCTION("""COMPUTED_VALUE"""),"Multishot Targets") -> Multishot Targets | G11: =IFERROR(__xludf.DUMMYFUNCTION("""COMPUTED_VALUE"""),7.0) -> 7 | H11: =IFERROR(__xludf.DUMMYFUNCTION("""COMPUTED_VALUE"""),7.0) -> 7 | I11: =IFERROR(__xludf.DUMMYFUNCTION("""COMPUTED_VALUE"""),7.0) -> 7 | J11: =IFERROR(__xludf.DUMMYFUNCTION("""COMPUTED_VALUE"""),7.0) -> 7 | Q11: =IFERROR(__xludf.DUMMYFUNCTION("""COMPUTED_VALUE"""),7.0) -> 7 | R11: =IFERROR(__xludf.DUMMYFUNCTION("""COMPUTED_VALUE"""),"Health Regen +") -> Health Regen + | S11: =IFERROR(__xludf.DUMMYFUNCTION("""COMPUTED_VALUE"""),1.6) -> 1.6 | T11: =IFERROR(__xludf.DUMMYFUNCTION("""COMPUTED_VALUE"""),60.0) -> 60 | U11: =IFERROR(__xludf.DUMMYFUNCTION("""COMPUTED_VALUE"""),60.0) -> 60 | Y11: =IFERROR(__xludf.DUMMYFUNCTION("""COMPUTED_VALUE"""),400.0) -> 400 | AB11: =IFERROR(__xludf.DUMMYFUNCTION("""COMPUTED_VALUE"""),"Quantity") -> Quantity | AC11: =IFERROR(__xludf.DUMMYFUNCTION("""COMPUTED_VALUE"""),3.0) -> 3 | AD11: =IFERROR(__xludf.DUMMYFUNCTION("""COMPUTED_VALUE"""),"02 | #3 | Cost 500 ⧌ | Next 850 ⧌") -> 02 | #3 | Cost 500 ⧌ | Next 850 ⧌ | AE11: =IFERROR(__xludf.DUMMYFUNCTION("""COMPUTED_VALUE"""),"Enemy Balance") -> Enemy Balance | AF11: =IFERROR(__xludf.DUMMYFUNCTION("""COMPUTED_VALUE"""),7.0) -> 7 | AG11: =IFERROR(__xludf.DUMMYFUNCTION("""COMPUTED_VALUE"""),FALSE) -> FALSE | AH11: =IFERROR(__xludf.DUMMYFUNCTION("""COMPUTED_VALUE"""),"Wave Accelerator") -> Wave Accelerator | AI11: =IFERROR(__xludf.DUMMYFUNCTION("""COMPUTED_VALUE"""),"Energy Shield") -> Energy Shield | AM11: =IFERROR(__xludf.DUMMYFUNCTION("""COMPUTED_VALUE"""),"Bot Range") -> Bot Range | AN11: =IFERROR(__xludf.DUMMYFUNCTION("""COMPUTED_VALUE"""),9.0) -> 9 | AP11: =IFERROR(__xludf.DUMMYFUNCTION("""COMPUTED_VALUE"""),"Bot Respec Discount") -> Bot Respec Discount | AQ11: =IFERROR(__xludf.DUMMYFUNCTION("""COMPUTED_VALUE"""),0.0) -> 0 | AU11: =IFERROR(__xludf.DUMMYFUNCTION("""COMPUTED_VALUE"""),"Cooldown") -> Cooldown | AV11: =IFERROR(__xludf.DUMMYFUNCTION("""COMPUTED_VALUE"""),111.0) -> 111 | AW11: =IFERROR(__xludf.DUMMYFUNCTION("""COMPUTED_VALUE"""),"03 | 111s | Cost 180 ⧓ | Next 220 ⧓") -> 03 | 111s | Cost 180 ⧓ | Next 220 ⧓ | BB11: =IFERROR(__xludf.DUMMYFUNCTION("""COMPUTED_VALUE"""),"Tourney") -> Tourney | BG11: =IFERROR(__xludf.DUMMYFUNCTION("""COMPUTED_VALUE"""),"Tourney") -> Tourney | BL11: =IFERROR(__xludf.DUMMYFUNCTION("""COMPUTED_VALUE"""),"Tourney") -> Tourney | BQ11: =IFERROR(__xludf.DUMMYFUNCTION("""COMPUTED_VALUE"""),"Tourney") -> Tourney | BU11: =IFERROR(__xludf.DUMMYFUNCTION("""COMPUTED_VALUE"""),"Fetch") -> Fetch | BW11: =IFERROR(__xludf.DUMMYFUNCTION("""COMPUTED_VALUE"""),"Cooldown") -> Cooldown | BX11: =IFERROR(__xludf.DUMMYFUNCTION("""COMPUTED_VALUE"""),88.0) -> 88 | BY11: =IFERROR(__xludf.DUMMYFUNCTION("""COMPUTED_VALUE"""),"32 | 88.0s | Cost 64 ⧈ | Next 66 ⧈") -> 32 | 88.0s | Cost 64 ⧈ | Next 66 ⧈ | BZ11: =IFERROR(__xludf.DUMMYFUNCTION("""COMPUTED_VALUE"""),"Tier 9") -> Tier 9 | CA11: =IFERROR(__xludf.DUMMYFUNCTION("""COMPUTED_VALUE"""),6985.0) -> 6985 | CD11: =IFERROR(__xludf.DUMMYFUNCTION("""COMPUTED_VALUE"""),"Disable Ads") -> Disable Ads | CE11: =IFERROR(__xludf.DUMMYFUNCTION("""COMPUTED_VALUE"""),TRUE) -> TRUE
A12: =IFERROR(__xludf.DUMMYFUNCTION("""COMPUTED_VALUE"""),"Card Presets") -> Card Presets | B12: =IFERROR(__xludf.DUMMYFUNCTION("""COMPUTED_VALUE"""),1.0) -> 1 | D12: =IFERROR(__xludf.DUMMYFUNCTION("""COMPUTED_VALUE"""),1.0) -> 1 | E12: =IFERROR(__xludf.DUMMYFUNCTION("""COMPUTED_VALUE"""),TRUE) -> TRUE | F12: =IFERROR(__xludf.DUMMYFUNCTION("""COMPUTED_VALUE"""),"Rapid Fire Chance") -> Rapid Fire Chance | G12: =IFERROR(__xludf.DUMMYFUNCTION("""COMPUTED_VALUE"""),85.0) -> 85 | H12: =IFERROR(__xludf.DUMMYFUNCTION("""COMPUTED_VALUE"""),85.0) -> 85 | I12: =IFERROR(__xludf.DUMMYFUNCTION("""COMPUTED_VALUE"""),85.0) -> 85 | J12: =IFERROR(__xludf.DUMMYFUNCTION("""COMPUTED_VALUE"""),85.0) -> 85 | Q12: =IFERROR(__xludf.DUMMYFUNCTION("""COMPUTED_VALUE"""),85.0) -> 85 | R12: =IFERROR(__xludf.DUMMYFUNCTION("""COMPUTED_VALUE"""),"Defense Absolute +") -> Defense Absolute + | S12: =IFERROR(__xludf.DUMMYFUNCTION("""COMPUTED_VALUE"""),1.0) -> 1 | T12: =IFERROR(__xludf.DUMMYFUNCTION("""COMPUTED_VALUE"""),0.0) -> 0 | U12: =IFERROR(__xludf.DUMMYFUNCTION("""COMPUTED_VALUE"""),0.0) -> 0 | Y12: =IFERROR(__xludf.DUMMYFUNCTION("""COMPUTED_VALUE"""),400.0) -> 400 | Z12: =IFERROR(__xludf.DUMMYFUNCTION("""COMPUTED_VALUE"""),TRUE) -> TRUE | AA12: =IFERROR(__xludf.DUMMYFUNCTION("""COMPUTED_VALUE"""),"UW Unlocked") -> UW Unlocked | AB12: =IFERROR(__xludf.DUMMYFUNCTION("""COMPUTED_VALUE"""),"Cooldown") -> Cooldown | AC12: =IFERROR(__xludf.DUMMYFUNCTION("""COMPUTED_VALUE"""),180.0) -> 180 | AD12: =IFERROR(__xludf.DUMMYFUNCTION("""COMPUTED_VALUE"""),"12 | 180s | Cost 184 ⧌ | Next 200 ⧌") -> 12 | 180s | Cost 184 ⧌ | Next 200 ⧌ | AE12: =IFERROR(__xludf.DUMMYFUNCTION("""COMPUTED_VALUE"""),"Extra Defense") -> Extra Defense | AF12: =IFERROR(__xludf.DUMMYFUNCTION("""COMPUTED_VALUE"""),7.0) -> 7 | AG12: =IFERROR(__xludf.DUMMYFUNCTION("""COMPUTED_VALUE"""),FALSE) -> FALSE | AH12: =IFERROR(__xludf.DUMMYFUNCTION("""COMPUTED_VALUE"""),"Critical Coin") -> Critical Coin | AI12: =IFERROR(__xludf.DUMMYFUNCTION("""COMPUTED_VALUE"""),"Ultimate Crit") -> Ultimate Crit | AM12: =IFERROR(__xludf.DUMMYFUNCTION("""COMPUTED_VALUE"""),"Damage‎ ") -> Damage‎ | AP12: =IFERROR(__xludf.DUMMYFUNCTION("""COMPUTED_VALUE"""),"Ad Gems Stack") -> Ad Gems Stack | AQ12: =IFERROR(__xludf.DUMMYFUNCTION("""COMPUTED_VALUE"""),1.0) -> 1 | AU12: =IFERROR(__xludf.DUMMYFUNCTION("""COMPUTED_VALUE"""),"Bonus") -> Bonus | AV12: =IFERROR(__xludf.DUMMYFUNCTION("""COMPUTED_VALUE"""),6.200000000000004) -> 6.2 | AW12: =IFERROR(__xludf.DUMMYFUNCTION("""COMPUTED_VALUE"""),"21 | x6.2 | Cost 900 ⧓ | Next 940 ⧓") -> 21 | x6.2 | Cost 900 ⧓ | Next 940 ⧓ | BB12: =IFERROR(__xludf.DUMMYFUNCTION("""COMPUTED_VALUE"""),"Primary Slot") -> Primary Slot | BC12: =IFERROR(__xludf.DUMMYFUNCTION("""COMPUTED_VALUE"""),"Amplifying Strike") -> Amplifying Strike | BG12: =IFERROR(__xludf.DUMMYFUNCTION("""COMPUTED_VALUE"""),"Primary Slot") -> Primary Slot | BH12: =IFERROR(__xludf.DUMMYFUNCTION("""COMPUTED_VALUE"""),"Sharp Fortitude") -> Sharp Fortitude | BL12: =IFERROR(__xludf.DUMMYFUNCTION("""COMPUTED_VALUE"""),"Primary Slot") -> Primary Slot | BM12: =IFERROR(__xludf.DUMMYFUNCTION("""COMPUTED_VALUE"""),"Project Funding") -> Project Funding | BQ12: =IFERROR(__xludf.DUMMYFUNCTION("""COMPUTED_VALUE"""),"Primary Slot") -> Primary Slot | BR12: =IFERROR(__xludf.DUMMYFUNCTION("""COMPUTED_VALUE"""),"Primordial Collapse") -> Primordial Collapse | BW12: =IFERROR(__xludf.DUMMYFUNCTION("""COMPUTED_VALUE"""),"Find Chance") -> Find Chance | BX12: =IFERROR(__xludf.DUMMYFUNCTION("""COMPUTED_VALUE"""),0.3700000000000002) -> 0.37 | BY12: =IFERROR(__xludf.DUMMYFUNCTION("""COMPUTED_VALUE"""),"27 | 37% | Cost 150 ⧈ | Next 155 ⧈") -> 27 | 37% | Cost 150 ⧈ | Next 155 ⧈ | BZ12: =IFERROR(__xludf.DUMMYFUNCTION("""COMPUTED_VALUE"""),"Tier 10") -> Tier 10 | CA12: =IFERROR(__xludf.DUMMYFUNCTION("""COMPUTED_VALUE"""),11300.0) -> 11300 | CB12: =IFERROR(__xludf.DUMMYFUNCTION("""COMPUTED_VALUE"""),TRUE) -> TRUE | CD12: =IFERROR(__xludf.DUMMYFUNCTION("""COMPUTED_VALUE"""),"Starter Pack") -> Starter Pack | CE12: =IFERROR(__xludf.DUMMYFUNCTION("""COMPUTED_VALUE"""),TRUE) -> TRUE
A13: =IFERROR(__xludf.DUMMYFUNCTION("""COMPUTED_VALUE"""),"Workshop Respec") -> Workshop Respec | B13: =IFERROR(__xludf.DUMMYFUNCTION("""COMPUTED_VALUE"""),1.0) -> 1 | D13: =IFERROR(__xludf.DUMMYFUNCTION("""COMPUTED_VALUE"""),1.0) -> 1 | F13: =IFERROR(__xludf.DUMMYFUNCTION("""COMPUTED_VALUE"""),"Rapid Fire Duration") -> Rapid Fire Duration | G13: =IFERROR(__xludf.DUMMYFUNCTION("""COMPUTED_VALUE"""),99.0) -> 99 | H13: =IFERROR(__xludf.DUMMYFUNCTION("""COMPUTED_VALUE"""),99.0) -> 99 | I13: =IFERROR(__xludf.DUMMYFUNCTION("""COMPUTED_VALUE"""),99.0) -> 99 | J13: =IFERROR(__xludf.DUMMYFUNCTION("""COMPUTED_VALUE"""),99.0) -> 99 | Q13: =IFERROR(__xludf.DUMMYFUNCTION("""COMPUTED_VALUE"""),99.0) -> 99 | R13: =IFERROR(__xludf.DUMMYFUNCTION("""COMPUTED_VALUE"""),"Land Mine Damage +") -> Land Mine Damage + | S13: =IFERROR(__xludf.DUMMYFUNCTION("""COMPUTED_VALUE"""),2.08) -> 2.08 | T13: =IFERROR(__xludf.DUMMYFUNCTION("""COMPUTED_VALUE"""),18.0) -> 18 | U13: =IFERROR(__xludf.DUMMYFUNCTION("""COMPUTED_VALUE"""),18.0) -> 18 | Y13: =IFERROR(__xludf.DUMMYFUNCTION("""COMPUTED_VALUE"""),400.0) -> 400 | Z13: =IFERROR(__xludf.DUMMYFUNCTION("""COMPUTED_VALUE"""),"UW+") -> UW+ | AB13: =IFERROR(__xludf.DUMMYFUNCTION("""COMPUTED_VALUE"""),"Kill Wall") -> Kill Wall | AC13: =IFERROR(__xludf.DUMMYFUNCTION("""COMPUTED_VALUE"""),"Locked") -> Locked | AD13: =IFERROR(__xludf.DUMMYFUNCTION("""COMPUTED_VALUE"""),"Lo | Locked") -> Lo | Locked | AE13: =IFERROR(__xludf.DUMMYFUNCTION("""COMPUTED_VALUE"""),"Fortress") -> Fortress | AF13: =IFERROR(__xludf.DUMMYFUNCTION("""COMPUTED_VALUE"""),7.0) -> 7 | AG13: =IFERROR(__xludf.DUMMYFUNCTION("""COMPUTED_VALUE"""),FALSE) -> FALSE | AH13: =IFERROR(__xludf.DUMMYFUNCTION("""COMPUTED_VALUE"""),"Second Wind") -> Second Wind | AI13: =IFERROR(__xludf.DUMMYFUNCTION("""COMPUTED_VALUE"""),"Extra Orb") -> Extra Orb | AM13: =IFERROR(__xludf.DUMMYFUNCTION("""COMPUTED_VALUE"""),"Damage") -> Damage | AN13: =IFERROR(__xludf.DUMMYFUNCTION("""COMPUTED_VALUE"""),0.5399999999999999) -> 0.54 | AP13: =IFERROR(__xludf.DUMMYFUNCTION("""COMPUTED_VALUE"""),"Attack") -> Attack | AS13: =IFERROR(__xludf.DUMMYFUNCTION("""COMPUTED_VALUE"""),TRUE) -> TRUE | AT13: =IFERROR(__xludf.DUMMYFUNCTION("""COMPUTED_VALUE"""),"Unlocked") -> Unlocked | AU13: =IFERROR(__xludf.DUMMYFUNCTION("""COMPUTED_VALUE"""),"Range") -> Range | AV13: =IFERROR(__xludf.DUMMYFUNCTION("""COMPUTED_VALUE"""),50.0) -> 50 | AW13: =IFERROR(__xludf.DUMMYFUNCTION("""COMPUTED_VALUE"""),"15 | 50m | Cost 660 ⧓ | Maxed") -> 15 | 50m | Cost 660 ⧓ | Maxed | BB13: =IFERROR(__xludf.DUMMYFUNCTION("""COMPUTED_VALUE"""),"Assist Slot") -> Assist Slot | BG13: =IFERROR(__xludf.DUMMYFUNCTION("""COMPUTED_VALUE"""),"Assist Slot") -> Assist Slot | BH13: =IFERROR(__xludf.DUMMYFUNCTION("""COMPUTED_VALUE"""),"Anti-Cube Portal") -> Anti-Cube Portal | BL13: =IFERROR(__xludf.DUMMYFUNCTION("""COMPUTED_VALUE"""),"Assist Slot") -> Assist Slot | BM13: =IFERROR(__xludf.DUMMYFUNCTION("""COMPUTED_VALUE"""),"Galaxy Compressor") -> Galaxy Compressor | BQ13: =IFERROR(__xludf.DUMMYFUNCTION("""COMPUTED_VALUE"""),"Assist Slot") -> Assist Slot | BR13: =IFERROR(__xludf.DUMMYFUNCTION("""COMPUTED_VALUE"""),"Dimension Core") -> Dimension Core | BU13: =IFERROR(__xludf.DUMMYFUNCTION("""COMPUTED_VALUE"""),TRUE) -> TRUE | BV13: =IFERROR(__xludf.DUMMYFUNCTION("""COMPUTED_VALUE"""),"Unlocked") -> Unlocked | BW13: =IFERROR(__xludf.DUMMYFUNCTION("""COMPUTED_VALUE"""),"Double Find Chance") -> Double Find Chance | BX13: =IFERROR(__xludf.DUMMYFUNCTION("""COMPUTED_VALUE"""),0.10999999999999999) -> 0.11 | BY13: =IFERROR(__xludf.DUMMYFUNCTION("""COMPUTED_VALUE"""),"09 | 11% | Cost 50 ⧈ | Next 55 ⧈") -> 09 | 11% | Cost 50 ⧈ | Next 55 ⧈ | BZ13: =IFERROR(__xludf.DUMMYFUNCTION("""COMPUTED_VALUE"""),"Tier 11") -> Tier 11 | CA13: =IFERROR(__xludf.DUMMYFUNCTION("""COMPUTED_VALUE"""),11538.0) -> 11538 | CD13: =IFERROR(__xludf.DUMMYFUNCTION("""COMPUTED_VALUE"""),"Epic Pack") -> Epic Pack | CE13: =IFERROR(__xludf.DUMMYFUNCTION("""COMPUTED_VALUE"""),TRUE) -> TRUE
A14: =IFERROR(__xludf.DUMMYFUNCTION("""COMPUTED_VALUE"""),"Reroll Daily Mission") -> Reroll Daily Mission | B14: =IFERROR(__xludf.DUMMYFUNCTION("""COMPUTED_VALUE"""),1.0) -> 1 | D14: =IFERROR(__xludf.DUMMYFUNCTION("""COMPUTED_VALUE"""),1.0) -> 1 | E14: =IFERROR(__xludf.DUMMYFUNCTION("""COMPUTED_VALUE"""),TRUE) -> TRUE | F14: =IFERROR(__xludf.DUMMYFUNCTION("""COMPUTED_VALUE"""),"Bounce Shot Chance") -> Bounce Shot Chance | G14: =IFERROR(__xludf.DUMMYFUNCTION("""COMPUTED_VALUE"""),85.0) -> 85 | H14: =IFERROR(__xludf.DUMMYFUNCTION("""COMPUTED_VALUE"""),85.0) -> 85 | I14: =IFERROR(__xludf.DUMMYFUNCTION("""COMPUTED_VALUE"""),85.0) -> 85 | J14: =IFERROR(__xludf.DUMMYFUNCTION("""COMPUTED_VALUE"""),85.0) -> 85 | Q14: =IFERROR(__xludf.DUMMYFUNCTION("""COMPUTED_VALUE"""),85.0) -> 85 | R14: =IFERROR(__xludf.DUMMYFUNCTION("""COMPUTED_VALUE"""),"Wall Health +") -> Wall Health + | S14: =IFERROR(__xludf.DUMMYFUNCTION("""COMPUTED_VALUE"""),1.5899999999999999) -> 1.59 | T14: =IFERROR(__xludf.DUMMYFUNCTION("""COMPUTED_VALUE"""),59.0) -> 59 | U14: =IFERROR(__xludf.DUMMYFUNCTION("""COMPUTED_VALUE"""),59.0) -> 59 | Y14: =IFERROR(__xludf.DUMMYFUNCTION("""COMPUTED_VALUE"""),400.0) -> 400 | Z14: =IFERROR(__xludf.DUMMYFUNCTION("""COMPUTED_VALUE"""),"Chrono Field") -> Chrono Field | AB14: =IFERROR(__xludf.DUMMYFUNCTION("""COMPUTED_VALUE"""),"Duration") -> Duration | AC14: =IFERROR(__xludf.DUMMYFUNCTION("""COMPUTED_VALUE"""),20.0) -> 20 | AD14: =IFERROR(__xludf.DUMMYFUNCTION("""COMPUTED_VALUE"""),"15 | 20s | Cost 131 ⧌ | Next 140 ⧌") -> 15 | 20s | Cost 131 ⧌ | Next 140 ⧌ | AE14: =IFERROR(__xludf.DUMMYFUNCTION("""COMPUTED_VALUE"""),"Free Upgrades") -> Free Upgrades | AF14: =IFERROR(__xludf.DUMMYFUNCTION("""COMPUTED_VALUE"""),7.0) -> 7 | AG14: =IFERROR(__xludf.DUMMYFUNCTION("""COMPUTED_VALUE"""),FALSE) -> FALSE | AH14: =IFERROR(__xludf.DUMMYFUNCTION("""COMPUTED_VALUE"""),"Energy Shield") -> Energy Shield | AI14: =IFERROR(__xludf.DUMMYFUNCTION("""COMPUTED_VALUE"""),"Recovery Package Chance") -> Recovery Package Chance | AM14: =IFERROR(__xludf.DUMMYFUNCTION("""COMPUTED_VALUE"""),"Ultimate Damage") -> Ultimate Damage | AN14: =IFERROR(__xludf.DUMMYFUNCTION("""COMPUTED_VALUE"""),0.22000000000000003) -> 0.22 | AP14: =IFERROR(__xludf.DUMMYFUNCTION("""COMPUTED_VALUE"""),"Damage") -> Damage | AQ14: =IFERROR(__xludf.DUMMYFUNCTION("""COMPUTED_VALUE"""),0.0) -> 0 | AS14: =IFERROR(__xludf.DUMMYFUNCTION("""COMPUTED_VALUE"""),"Amplify Bot") -> Amplify Bot | AU14: =IFERROR(__xludf.DUMMYFUNCTION("""COMPUTED_VALUE"""),"Duration") -> Duration | AV14: =IFERROR(__xludf.DUMMYFUNCTION("""COMPUTED_VALUE"""),20.0) -> 20 | AW14: =IFERROR(__xludf.DUMMYFUNCTION("""COMPUTED_VALUE"""),"00 | 20.0s | Cost 0 ⧓ | Next 100 ⧓") -> 00 | 20.0s | Cost 0 ⧓ | Next 100 ⧓ | BU14: =IFERROR(__xludf.DUMMYFUNCTION("""COMPUTED_VALUE"""),"Summon") -> Summon | BW14: =IFERROR(__xludf.DUMMYFUNCTION("""COMPUTED_VALUE"""),"Cooldown") -> Cooldown | BX14: =IFERROR(__xludf.DUMMYFUNCTION("""COMPUTED_VALUE"""),90.0) -> 90 | BY14: =IFERROR(__xludf.DUMMYFUNCTION("""COMPUTED_VALUE"""),"50 | 90s | Cost 99 ⧈ | Next 101 ⧈") -> 50 | 90s | Cost 99 ⧈ | Next 101 ⧈ | BZ14: =IFERROR(__xludf.DUMMYFUNCTION("""COMPUTED_VALUE"""),"Tier 12") -> Tier 12 | CA14: =IFERROR(__xludf.DUMMYFUNCTION("""COMPUTED_VALUE"""),10006.0) -> 10006 | CD14: =IFERROR(__xludf.DUMMYFUNCTION("""COMPUTED_VALUE"""),"Coin Multiplier") -> Coin Multiplier | CE14: =IFERROR(__xludf.DUMMYFUNCTION("""COMPUTED_VALUE"""),"x9") -> x9
A15: =IFERROR(__xludf.DUMMYFUNCTION("""COMPUTED_VALUE"""),"Workshop Enhancements") -> Workshop Enhancements | B15: =IFERROR(__xludf.DUMMYFUNCTION("""COMPUTED_VALUE"""),1.0) -> 1 | D15: =IFERROR(__xludf.DUMMYFUNCTION("""COMPUTED_VALUE"""),1.0) -> 1 | F15: =IFERROR(__xludf.DUMMYFUNCTION("""COMPUTED_VALUE"""),"Bounce Shot Targets") -> Bounce Shot Targets | G15: =IFERROR(__xludf.DUMMYFUNCTION("""COMPUTED_VALUE"""),5.0) -> 5 | H15: =IFERROR(__xludf.DUMMYFUNCTION("""COMPUTED_VALUE"""),7.0) -> 7 | I15: =IFERROR(__xludf.DUMMYFUNCTION("""COMPUTED_VALUE"""),5.0) -> 5 | J15: =IFERROR(__xludf.DUMMYFUNCTION("""COMPUTED_VALUE"""),7.0) -> 7 | Q15: =IFERROR(__xludf.DUMMYFUNCTION("""COMPUTED_VALUE"""),7.0) -> 7 | R15: =IFERROR(__xludf.DUMMYFUNCTION("""COMPUTED_VALUE"""),"Orb Size +") -> Orb Size + | S15: =IFERROR(__xludf.DUMMYFUNCTION("""COMPUTED_VALUE"""),1.2) -> 1.2 | T15: =IFERROR(__xludf.DUMMYFUNCTION("""COMPUTED_VALUE"""),20.0) -> 20 | U15: =IFERROR(__xludf.DUMMYFUNCTION("""COMPUTED_VALUE"""),20.0) -> 20 | Y15: =IFERROR(__xludf.DUMMYFUNCTION("""COMPUTED_VALUE"""),200.0) -> 200 | AB15: =IFERROR(__xludf.DUMMYFUNCTION("""COMPUTED_VALUE"""),"Speed Reduction") -> Speed Reduction | AC15: =IFERROR(__xludf.DUMMYFUNCTION("""COMPUTED_VALUE"""),0.5) -> 0.5 | AD15: =IFERROR(__xludf.DUMMYFUNCTION("""COMPUTED_VALUE"""),"06 | 50% | Cost 150 ⧌ | Next 200 ⧌") -> 06 | 50% | Cost 150 ⧌ | Next 200 ⧌ | AE15: =IFERROR(__xludf.DUMMYFUNCTION("""COMPUTED_VALUE"""),"Extra Orb") -> Extra Orb | AF15: =IFERROR(__xludf.DUMMYFUNCTION("""COMPUTED_VALUE"""),7.0) -> 7 | AG15: =IFERROR(__xludf.DUMMYFUNCTION("""COMPUTED_VALUE"""),FALSE) -> FALSE | AH15: =IFERROR(__xludf.DUMMYFUNCTION("""COMPUTED_VALUE"""),"Recovery Package Chance") -> Recovery Package Chance | AI15: =IFERROR(__xludf.DUMMYFUNCTION("""COMPUTED_VALUE"""),"Extra Defense") -> Extra Defense | AM15: =IFERROR(__xludf.DUMMYFUNCTION("""COMPUTED_VALUE"""),"Attack Speed") -> Attack Speed | AN15: =IFERROR(__xludf.DUMMYFUNCTION("""COMPUTED_VALUE"""),0.05) -> 0.05 | AP15: =IFERROR(__xludf.DUMMYFUNCTION("""COMPUTED_VALUE"""),"Ultimate Weapon Damage") -> Ultimate Weapon Damage | AQ15: =IFERROR(__xludf.DUMMYFUNCTION("""COMPUTED_VALUE"""),0.0) -> 0 | AU15: =IFERROR(__xludf.DUMMYFUNCTION("""COMPUTED_VALUE"""),"Cooldown") -> Cooldown | AV15: =IFERROR(__xludf.DUMMYFUNCTION("""COMPUTED_VALUE"""),120.0) -> 120 | AW15: =IFERROR(__xludf.DUMMYFUNCTION("""COMPUTED_VALUE"""),"00 | 120s | Cost 0 ⧓ | Next 100 ⧓") -> 00 | 120s | Cost 0 ⧓ | Next 100 ⧓ | BB15: =IFERROR(__xludf.DUMMYFUNCTION("""COMPUTED_VALUE"""),"Testing") -> Testing | BG15: =IFERROR(__xludf.DUMMYFUNCTION("""COMPUTED_VALUE"""),"Testing") -> Testing | BL15: =IFERROR(__xludf.DUMMYFUNCTION("""COMPUTED_VALUE"""),"Testing") -> Testing | BQ15: =IFERROR(__xludf.DUMMYFUNCTION("""COMPUTED_VALUE"""),"Testing") -> Testing | BW15: =IFERROR(__xludf.DUMMYFUNCTION("""COMPUTED_VALUE"""),"Duration") -> Duration | BX15: =IFERROR(__xludf.DUMMYFUNCTION("""COMPUTED_VALUE"""),24.0) -> 24 | BY15: =IFERROR(__xludf.DUMMYFUNCTION("""COMPUTED_VALUE"""),"19 | 24s| Cost 195 ⧈ | Next 205 ⧈") -> 19 | 24s| Cost 195 ⧈ | Next 205 ⧈ | BZ15: =IFERROR(__xludf.DUMMYFUNCTION("""COMPUTED_VALUE"""),"Tier 13") -> Tier 13 | CA15: =IFERROR(__xludf.DUMMYFUNCTION("""COMPUTED_VALUE"""),6908.0) -> 6908 | CB15: =IFERROR(__xludf.DUMMYFUNCTION("""COMPUTED_VALUE"""),TRUE) -> TRUE
A16: =IFERROR(__xludf.DUMMYFUNCTION("""COMPUTED_VALUE"""),"Enhancement Attack - Coin Discount") -> Enhancement Attack - Coin Discount | B16: =IFERROR(__xludf.DUMMYFUNCTION("""COMPUTED_VALUE"""),0.0) -> 0 | D16: =IFERROR(__xludf.DUMMYFUNCTION("""COMPUTED_VALUE"""),100.0) -> 100 | F16: =IFERROR(__xludf.DUMMYFUNCTION("""COMPUTED_VALUE"""),"Bounce Shot Range") -> Bounce Shot Range | G16: =IFERROR(__xludf.DUMMYFUNCTION("""COMPUTED_VALUE"""),60.0) -> 60 | H16: =IFERROR(__xludf.DUMMYFUNCTION("""COMPUTED_VALUE"""),60.0) -> 60 | I16: =IFERROR(__xludf.DUMMYFUNCTION("""COMPUTED_VALUE"""),60.0) -> 60 | J16: =IFERROR(__xludf.DUMMYFUNCTION("""COMPUTED_VALUE"""),60.0) -> 60 | Q16: =IFERROR(__xludf.DUMMYFUNCTION("""COMPUTED_VALUE"""),60.0) -> 60 | R16: =IFERROR(__xludf.DUMMYFUNCTION("""COMPUTED_VALUE"""),"Cash Bonus +") -> Cash Bonus + | S16: =IFERROR(__xludf.DUMMYFUNCTION("""COMPUTED_VALUE"""),1.44) -> 1.44 | T16: =IFERROR(__xludf.DUMMYFUNCTION("""COMPUTED_VALUE"""),44.0) -> 44 | U16: =IFERROR(__xludf.DUMMYFUNCTION("""COMPUTED_VALUE"""),44.0) -> 44 | Y16: =IFERROR(__xludf.DUMMYFUNCTION("""COMPUTED_VALUE"""),400.0) -> 400 | Z16: =IFERROR(__xludf.DUMMYFUNCTION("""COMPUTED_VALUE"""),TRUE) -> TRUE | AA16: =IFERROR(__xludf.DUMMYFUNCTION("""COMPUTED_VALUE"""),"UW Unlocked") -> UW Unlocked | AB16: =IFERROR(__xludf.DUMMYFUNCTION("""COMPUTED_VALUE"""),"Cooldown") -> Cooldown | AC16: =IFERROR(__xludf.DUMMYFUNCTION("""COMPUTED_VALUE"""),60.0) -> 60 | AD16: =IFERROR(__xludf.DUMMYFUNCTION("""COMPUTED_VALUE"""),"12 | 60s | Cost 241 ⧌ | Maxed") -> 12 | 60s | Cost 241 ⧌ | Maxed | AE16: =IFERROR(__xludf.DUMMYFUNCTION("""COMPUTED_VALUE"""),"Plasma Cannon") -> Plasma Cannon | AF16: =IFERROR(__xludf.DUMMYFUNCTION("""COMPUTED_VALUE"""),7.0) -> 7 | AG16: =IFERROR(__xludf.DUMMYFUNCTION("""COMPUTED_VALUE"""),FALSE) -> FALSE | AH16: =IFERROR(__xludf.DUMMYFUNCTION("""COMPUTED_VALUE"""),"Intro Sprint") -> Intro Sprint | AI16: =IFERROR(__xludf.DUMMYFUNCTION("""COMPUTED_VALUE"""),"Slow Aura") -> Slow Aura | AM16: =IFERROR(__xludf.DUMMYFUNCTION("""COMPUTED_VALUE"""),"Crit Chance") -> Crit Chance | AN16: =IFERROR(__xludf.DUMMYFUNCTION("""COMPUTED_VALUE"""),0.06) -> 0.06 | AP16: =IFERROR(__xludf.DUMMYFUNCTION("""COMPUTED_VALUE"""),"Attack Speed") -> Attack Speed | AQ16: =IFERROR(__xludf.DUMMYFUNCTION("""COMPUTED_VALUE"""),0.0) -> 0 | AU16: =IFERROR(__xludf.DUMMYFUNCTION("""COMPUTED_VALUE"""),"Bonus") -> Bonus | AV16: =IFERROR(__xludf.DUMMYFUNCTION("""COMPUTED_VALUE"""),3.5) -> 3.5 | AW16: =IFERROR(__xludf.DUMMYFUNCTION("""COMPUTED_VALUE"""),"00 | x3.5 | Cost 0 ⧓ | Next 100 ⧓") -> 00 | x3.5 | Cost 0 ⧓ | Next 100 ⧓ | BB16: =IFERROR(__xludf.DUMMYFUNCTION("""COMPUTED_VALUE"""),"Primary Slot") -> Primary Slot | BC16: =IFERROR(__xludf.DUMMYFUNCTION("""COMPUTED_VALUE"""),"Being Annihilator") -> Being Annihilator | BG16: =IFERROR(__xludf.DUMMYFUNCTION("""COMPUTED_VALUE"""),"Primary Slot") -> Primary Slot | BH16: =IFERROR(__xludf.DUMMYFUNCTION("""COMPUTED_VALUE"""),"Sharp Fortitude") -> Sharp Fortitude | BL16: =IFERROR(__xludf.DUMMYFUNCTION("""COMPUTED_VALUE"""),"Primary Slot") -> Primary Slot | BM16: =IFERROR(__xludf.DUMMYFUNCTION("""COMPUTED_VALUE"""),"Galaxy Compressor") -> Galaxy Compressor | BQ16: =IFERROR(__xludf.DUMMYFUNCTION("""COMPUTED_VALUE"""),"Primary Slot") -> Primary Slot | BR16: =IFERROR(__xludf.DUMMYFUNCTION("""COMPUTED_VALUE"""),"Dimension Core") -> Dimension Core | BU16: =IFERROR(__xludf.DUMMYFUNCTION("""COMPUTED_VALUE"""),TRUE) -> TRUE | BV16: =IFERROR(__xludf.DUMMYFUNCTION("""COMPUTED_VALUE"""),"Unlocked") -> Unlocked | BW16: =IFERROR(__xludf.DUMMYFUNCTION("""COMPUTED_VALUE"""),"Cash Bonus") -> Cash Bonus | BX16: =IFERROR(__xludf.DUMMYFUNCTION("""COMPUTED_VALUE"""),1.0) -> 1 | BY16: =IFERROR(__xludf.DUMMYFUNCTION("""COMPUTED_VALUE"""),"00 | 1.0x | Cost 0 ⧈ | Next 100 ⧈") -> 00 | 1.0x | Cost 0 ⧈ | Next 100 ⧈ | BZ16: =IFERROR(__xludf.DUMMYFUNCTION("""COMPUTED_VALUE"""),"Tier 14") -> Tier 14 | CA16: =IFERROR(__xludf.DUMMYFUNCTION("""COMPUTED_VALUE"""),5761.0) -> 5761
A17: =IFERROR(__xludf.DUMMYFUNCTION("""COMPUTED_VALUE"""),"Enhancement Defense - Coin Discount") -> Enhancement Defense - Coin Discount | B17: =IFERROR(__xludf.DUMMYFUNCTION("""COMPUTED_VALUE"""),0.0) -> 0 | D17: =IFERROR(__xludf.DUMMYFUNCTION("""COMPUTED_VALUE"""),100.0) -> 100 | E17: =IFERROR(__xludf.DUMMYFUNCTION("""COMPUTED_VALUE"""),TRUE) -> TRUE | F17: =IFERROR(__xludf.DUMMYFUNCTION("""COMPUTED_VALUE"""),"Super Critical Chance") -> Super Critical Chance | G17: =IFERROR(__xludf.DUMMYFUNCTION("""COMPUTED_VALUE"""),100.0) -> 100 | H17: =IFERROR(__xludf.DUMMYFUNCTION("""COMPUTED_VALUE"""),100.0) -> 100 | I17: =IFERROR(__xludf.DUMMYFUNCTION("""COMPUTED_VALUE"""),100.0) -> 100 | J17: =IFERROR(__xludf.DUMMYFUNCTION("""COMPUTED_VALUE"""),100.0) -> 100 | Q17: =IFERROR(__xludf.DUMMYFUNCTION("""COMPUTED_VALUE"""),100.0) -> 100 | R17: =IFERROR(__xludf.DUMMYFUNCTION("""COMPUTED_VALUE"""),"Coin Bonus +") -> Coin Bonus + | S17: =IFERROR(__xludf.DUMMYFUNCTION("""COMPUTED_VALUE"""),1.33) -> 1.33 | T17: =IFERROR(__xludf.DUMMYFUNCTION("""COMPUTED_VALUE"""),33.0) -> 33 | U17: =IFERROR(__xludf.DUMMYFUNCTION("""COMPUTED_VALUE"""),33.0) -> 33 | Y17: =IFERROR(__xludf.DUMMYFUNCTION("""COMPUTED_VALUE"""),200.0) -> 200 | Z17: =IFERROR(__xludf.DUMMYFUNCTION("""COMPUTED_VALUE"""),"UW+") -> UW+ | AB17: =IFERROR(__xludf.DUMMYFUNCTION("""COMPUTED_VALUE"""),"Chrono Loop") -> Chrono Loop | AC17: =IFERROR(__xludf.DUMMYFUNCTION("""COMPUTED_VALUE"""),"Locked") -> Locked | AD17: =IFERROR(__xludf.DUMMYFUNCTION("""COMPUTED_VALUE"""),"Lo | Locked") -> Lo | Locked | AE17: =IFERROR(__xludf.DUMMYFUNCTION("""COMPUTED_VALUE"""),"Critical Coin") -> Critical Coin | AF17: =IFERROR(__xludf.DUMMYFUNCTION("""COMPUTED_VALUE"""),7.0) -> 7 | AG17: =IFERROR(__xludf.DUMMYFUNCTION("""COMPUTED_VALUE"""),FALSE) -> FALSE | AH17: =IFERROR(__xludf.DUMMYFUNCTION("""COMPUTED_VALUE"""),"Extra Orb") -> Extra Orb | AI17: =IFERROR(__xludf.DUMMYFUNCTION("""COMPUTED_VALUE"""),"Energy Net") -> Energy Net | AM17: =IFERROR(__xludf.DUMMYFUNCTION("""COMPUTED_VALUE"""),"Crit Factor") -> Crit Factor | AN17: =IFERROR(__xludf.DUMMYFUNCTION("""COMPUTED_VALUE"""),0.5) -> 0.5 | AP17: =IFERROR(__xludf.DUMMYFUNCTION("""COMPUTED_VALUE"""),"Critical Chance") -> Critical Chance | AQ17: =IFERROR(__xludf.DUMMYFUNCTION("""COMPUTED_VALUE"""),0.0) -> 0 | AS17: =IFERROR(__xludf.DUMMYFUNCTION("""COMPUTED_VALUE"""),FALSE) -> FALSE | AT17: =IFERROR(__xludf.DUMMYFUNCTION("""COMPUTED_VALUE"""),"Locked") -> Locked | AU17: =IFERROR(__xludf.DUMMYFUNCTION("""COMPUTED_VALUE"""),"Range") -> Range | AV17: =IFERROR(__xludf.DUMMYFUNCTION("""COMPUTED_VALUE"""),25.0) -> 25 | AW17: =IFERROR(__xludf.DUMMYFUNCTION("""COMPUTED_VALUE"""),"00 | 25m | Cost 0 ⧓ | Next 100 ⧓") -> 00 | 25m | Cost 0 ⧓ | Next 100 ⧓ | BB17: =IFERROR(__xludf.DUMMYFUNCTION("""COMPUTED_VALUE"""),"Assist Slot") -> Assist Slot | BG17: =IFERROR(__xludf.DUMMYFUNCTION("""COMPUTED_VALUE"""),"Assist Slot") -> Assist Slot | BL17: =IFERROR(__xludf.DUMMYFUNCTION("""COMPUTED_VALUE"""),"Assist Slot") -> Assist Slot | BM17: =IFERROR(__xludf.DUMMYFUNCTION("""COMPUTED_VALUE"""),"Restorative Bonus") -> Restorative Bonus | BQ17: =IFERROR(__xludf.DUMMYFUNCTION("""COMPUTED_VALUE"""),"Assist Slot") -> Assist Slot | BR17: =IFERROR(__xludf.DUMMYFUNCTION("""COMPUTED_VALUE"""),"Om Chip") -> Om Chip | BU17: =IFERROR(__xludf.DUMMYFUNCTION("""COMPUTED_VALUE"""),"Scout") -> Scout | BW17: =IFERROR(__xludf.DUMMYFUNCTION("""COMPUTED_VALUE"""),"Cooldown") -> Cooldown | BX17: =IFERROR(__xludf.DUMMYFUNCTION("""COMPUTED_VALUE"""),105.0) -> 105 | BY17: =IFERROR(__xludf.DUMMYFUNCTION("""COMPUTED_VALUE"""),"00 | 105s | Cost 0 ⧈ | Next 1 ⧈") -> 00 | 105s | Cost 0 ⧈ | Next 1 ⧈ | BZ17: =IFERROR(__xludf.DUMMYFUNCTION("""COMPUTED_VALUE"""),"Tier 15") -> Tier 15 | CA17: =IFERROR(__xludf.DUMMYFUNCTION("""COMPUTED_VALUE"""),4859.0) -> 4859
A18: =IFERROR(__xludf.DUMMYFUNCTION("""COMPUTED_VALUE"""),"Enhancement Utility - Coin Discount") -> Enhancement Utility - Coin Discount | B18: =IFERROR(__xludf.DUMMYFUNCTION("""COMPUTED_VALUE"""),0.0) -> 0 | D18: =IFERROR(__xludf.DUMMYFUNCTION("""COMPUTED_VALUE"""),100.0) -> 100 | F18: =IFERROR(__xludf.DUMMYFUNCTION("""COMPUTED_VALUE"""),"Super Critical Mult") -> Super Critical Mult | G18: =IFERROR(__xludf.DUMMYFUNCTION("""COMPUTED_VALUE"""),100.0) -> 100 | H18: =IFERROR(__xludf.DUMMYFUNCTION("""COMPUTED_VALUE"""),120.0) -> 120 | I18: =IFERROR(__xludf.DUMMYFUNCTION("""COMPUTED_VALUE"""),100.0) -> 100 | J18: =IFERROR(__xludf.DUMMYFUNCTION("""COMPUTED_VALUE"""),120.0) -> 120 | Q18: =IFERROR(__xludf.DUMMYFUNCTION("""COMPUTED_VALUE"""),120.0) -> 120 | R18: =IFERROR(__xludf.DUMMYFUNCTION("""COMPUTED_VALUE"""),"Cells / Kill Bonus +") -> Cells / Kill Bonus + | S18: =IFERROR(__xludf.DUMMYFUNCTION("""COMPUTED_VALUE"""),1.25) -> 1.25 | T18: =IFERROR(__xludf.DUMMYFUNCTION("""COMPUTED_VALUE"""),25.0) -> 25 | U18: =IFERROR(__xludf.DUMMYFUNCTION("""COMPUTED_VALUE"""),25.0) -> 25 | Y18: =IFERROR(__xludf.DUMMYFUNCTION("""COMPUTED_VALUE"""),200.0) -> 200 | Z18: =IFERROR(__xludf.DUMMYFUNCTION("""COMPUTED_VALUE"""),"Inner Land Mines") -> Inner Land Mines | AB18: =IFERROR(__xludf.DUMMYFUNCTION("""COMPUTED_VALUE"""),"Damage") -> Damage | AC18: =IFERROR(__xludf.DUMMYFUNCTION("""COMPUTED_VALUE"""),10.0) -> 10 | AD18: =IFERROR(__xludf.DUMMYFUNCTION("""COMPUTED_VALUE"""),"00 | x10 | Cost 0 ⧌ | Next 5 ⧌") -> 00 | x10 | Cost 0 ⧌ | Next 5 ⧌ | AE18: =IFERROR(__xludf.DUMMYFUNCTION("""COMPUTED_VALUE"""),"Wave Skip") -> Wave Skip | AF18: =IFERROR(__xludf.DUMMYFUNCTION("""COMPUTED_VALUE"""),7.0) -> 7 | AG18: =IFERROR(__xludf.DUMMYFUNCTION("""COMPUTED_VALUE"""),FALSE) -> FALSE | AH18: =IFERROR(__xludf.DUMMYFUNCTION("""COMPUTED_VALUE"""),"Cash") -> Cash | AI18: =IFERROR(__xludf.DUMMYFUNCTION("""COMPUTED_VALUE"""),"Land Mine Stun") -> Land Mine Stun | AM18: =IFERROR(__xludf.DUMMYFUNCTION("""COMPUTED_VALUE"""),"Damage / Meter") -> Damage / Meter | AN18: =IFERROR(__xludf.DUMMYFUNCTION("""COMPUTED_VALUE"""),0.42999999999999994) -> 0.43 | AP18: =IFERROR(__xludf.DUMMYFUNCTION("""COMPUTED_VALUE"""),"Critical Factor") -> Critical Factor | AQ18: =IFERROR(__xludf.DUMMYFUNCTION("""COMPUTED_VALUE"""),0.0) -> 0 | BW18: =IFERROR(__xludf.DUMMYFUNCTION("""COMPUTED_VALUE"""),"Range Bonus") -> Range Bonus | BX18: =IFERROR(__xludf.DUMMYFUNCTION("""COMPUTED_VALUE"""),2.0) -> 2 | BY18: =IFERROR(__xludf.DUMMYFUNCTION("""COMPUTED_VALUE"""),"00 | 2.0x | Cost 0 ⧈ | Next 10 ⧈") -> 00 | 2.0x | Cost 0 ⧈ | Next 10 ⧈ | BZ18: =IFERROR(__xludf.DUMMYFUNCTION("""COMPUTED_VALUE"""),"Tier 16") -> Tier 16 | CA18: =IFERROR(__xludf.DUMMYFUNCTION("""COMPUTED_VALUE"""),3578.0) -> 3578 | CB18: =IFERROR(__xludf.DUMMYFUNCTION("""COMPUTED_VALUE"""),TRUE) -> TRUE
A19: =IFERROR(__xludf.DUMMYFUNCTION("""COMPUTED_VALUE"""),"Damage") -> Damage | B19: =IFERROR(__xludf.DUMMYFUNCTION("""COMPUTED_VALUE"""),69.0) -> 69 | D19: =IFERROR(__xludf.DUMMYFUNCTION("""COMPUTED_VALUE"""),100.0) -> 100 | E19: =IFERROR(__xludf.DUMMYFUNCTION("""COMPUTED_VALUE"""),TRUE) -> TRUE | F19: =IFERROR(__xludf.DUMMYFUNCTION("""COMPUTED_VALUE"""),"Rend Armor Chance") -> Rend Armor Chance | G19: =IFERROR(__xludf.DUMMYFUNCTION("""COMPUTED_VALUE"""),80.0) -> 80 | H19: =IFERROR(__xludf.DUMMYFUNCTION("""COMPUTED_VALUE"""),299.0) -> 299 | I19: =IFERROR(__xludf.DUMMYFUNCTION("""COMPUTED_VALUE"""),80.0) -> 80 | J19: =IFERROR(__xludf.DUMMYFUNCTION("""COMPUTED_VALUE"""),299.0) -> 299 | Q19: =IFERROR(__xludf.DUMMYFUNCTION("""COMPUTED_VALUE"""),299.0) -> 299 | R19: =IFERROR(__xludf.DUMMYFUNCTION("""COMPUTED_VALUE"""),"Free Upgrades +") -> Free Upgrades + | S19: =IFERROR(__xludf.DUMMYFUNCTION("""COMPUTED_VALUE"""),1.12) -> 1.12 | T19: =IFERROR(__xludf.DUMMYFUNCTION("""COMPUTED_VALUE"""),12.0) -> 12 | U19: =IFERROR(__xludf.DUMMYFUNCTION("""COMPUTED_VALUE"""),12.0) -> 12 | Y19: =IFERROR(__xludf.DUMMYFUNCTION("""COMPUTED_VALUE"""),100.0) -> 100 | AB19: =IFERROR(__xludf.DUMMYFUNCTION("""COMPUTED_VALUE"""),"Quantity") -> Quantity | AC19: =IFERROR(__xludf.DUMMYFUNCTION("""COMPUTED_VALUE"""),3.0) -> 3 | AD19: =IFERROR(__xludf.DUMMYFUNCTION("""COMPUTED_VALUE"""),"00 | #3 | Cost 0 ⧌ | Next 50 ⧌") -> 00 | #3 | Cost 0 ⧌ | Next 50 ⧌ | AE19: =IFERROR(__xludf.DUMMYFUNCTION("""COMPUTED_VALUE"""),"Intro Sprint") -> Intro Sprint | AF19: =IFERROR(__xludf.DUMMYFUNCTION("""COMPUTED_VALUE"""),7.0) -> 7 | AG19: =IFERROR(__xludf.DUMMYFUNCTION("""COMPUTED_VALUE"""),TRUE) -> TRUE | AH19: =IFERROR(__xludf.DUMMYFUNCTION("""COMPUTED_VALUE"""),"Free Upgrades") -> Free Upgrades | AI19: =IFERROR(__xludf.DUMMYFUNCTION("""COMPUTED_VALUE"""),"Second Wind") -> Second Wind | AM19: =IFERROR(__xludf.DUMMYFUNCTION("""COMPUTED_VALUE"""),"Super Critical Chance") -> Super Critical Chance | AN19: =IFERROR(__xludf.DUMMYFUNCTION("""COMPUTED_VALUE"""),0.04) -> 0.04 | AP19: =IFERROR(__xludf.DUMMYFUNCTION("""COMPUTED_VALUE"""),"Damage / Meter") -> Damage / Meter | AQ19: =IFERROR(__xludf.DUMMYFUNCTION("""COMPUTED_VALUE"""),0.0) -> 0 | BB19: =IFERROR(__xludf.DUMMYFUNCTION("""COMPUTED_VALUE"""),"Placeholder 4th preset") -> Placeholder 4th preset | BG19: =IFERROR(__xludf.DUMMYFUNCTION("""COMPUTED_VALUE"""),"Placeholder 4th preset") -> Placeholder 4th preset | BL19: =IFERROR(__xludf.DUMMYFUNCTION("""COMPUTED_VALUE"""),"Placeholder 4th preset") -> Placeholder 4th preset | BQ19: =IFERROR(__xludf.DUMMYFUNCTION("""COMPUTED_VALUE"""),"Placeholder 4th preset") -> Placeholder 4th preset | BU19: =IFERROR(__xludf.DUMMYFUNCTION("""COMPUTED_VALUE"""),FALSE) -> FALSE | BV19: =IFERROR(__xludf.DUMMYFUNCTION("""COMPUTED_VALUE"""),"Locked") -> Locked | BW19: =IFERROR(__xludf.DUMMYFUNCTION("""COMPUTED_VALUE"""),"Duration") -> Duration | BX19: =IFERROR(__xludf.DUMMYFUNCTION("""COMPUTED_VALUE"""),5.0) -> 5 | BY19: =IFERROR(__xludf.DUMMYFUNCTION("""COMPUTED_VALUE"""),"00 | 5s | Cost 0 ⧈ | Next 10 ⧈") -> 00 | 5s | Cost 0 ⧈ | Next 10 ⧈ | BZ19: =IFERROR(__xludf.DUMMYFUNCTION("""COMPUTED_VALUE"""),"Tier 17") -> Tier 17 | CA19: =IFERROR(__xludf.DUMMYFUNCTION("""COMPUTED_VALUE"""),2010.0) -> 2010
A20: =IFERROR(__xludf.DUMMYFUNCTION("""COMPUTED_VALUE"""),"Attack Speed") -> Attack Speed | B20: =IFERROR(__xludf.DUMMYFUNCTION("""COMPUTED_VALUE"""),75.0) -> 75 | D20: =IFERROR(__xludf.DUMMYFUNCTION("""COMPUTED_VALUE"""),99.0) -> 99 | F20: =IFERROR(__xludf.DUMMYFUNCTION("""COMPUTED_VALUE"""),"Rend Armor Mult") -> Rend Armor Mult | G20: =IFERROR(__xludf.DUMMYFUNCTION("""COMPUTED_VALUE"""),70.0) -> 70 | H20: =IFERROR(__xludf.DUMMYFUNCTION("""COMPUTED_VALUE"""),299.0) -> 299 | I20: =IFERROR(__xludf.DUMMYFUNCTION("""COMPUTED_VALUE"""),70.0) -> 70 | J20: =IFERROR(__xludf.DUMMYFUNCTION("""COMPUTED_VALUE"""),299.0) -> 299 | Q20: =IFERROR(__xludf.DUMMYFUNCTION("""COMPUTED_VALUE"""),299.0) -> 299 | R20: =IFERROR(__xludf.DUMMYFUNCTION("""COMPUTED_VALUE"""),"Recovery Package +") -> Recovery Package + | S20: =IFERROR(__xludf.DUMMYFUNCTION("""COMPUTED_VALUE"""),1.42) -> 1.42 | T20: =IFERROR(__xludf.DUMMYFUNCTION("""COMPUTED_VALUE"""),42.0) -> 42 | U20: =IFERROR(__xludf.DUMMYFUNCTION("""COMPUTED_VALUE"""),42.0) -> 42 | Y20: =IFERROR(__xludf.DUMMYFUNCTION("""COMPUTED_VALUE"""),300.0) -> 300 | Z20: =IFERROR(__xludf.DUMMYFUNCTION("""COMPUTED_VALUE"""),FALSE) -> FALSE | AA20: =IFERROR(__xludf.DUMMYFUNCTION("""COMPUTED_VALUE"""),"UW Locked") -> UW Locked | AB20: =IFERROR(__xludf.DUMMYFUNCTION("""COMPUTED_VALUE"""),"Cooldown") -> Cooldown | AC20: =IFERROR(__xludf.DUMMYFUNCTION("""COMPUTED_VALUE"""),200.0) -> 200 | AD20: =IFERROR(__xludf.DUMMYFUNCTION("""COMPUTED_VALUE"""),"00 | 200s | Cost 0 ⧌ | Next 8 ⧌") -> 00 | 200s | Cost 0 ⧌ | Next 8 ⧌ | AE20: =IFERROR(__xludf.DUMMYFUNCTION("""COMPUTED_VALUE"""),"Land Mine Stun") -> Land Mine Stun | AF20: =IFERROR(__xludf.DUMMYFUNCTION("""COMPUTED_VALUE"""),7.0) -> 7 | AG20: =IFERROR(__xludf.DUMMYFUNCTION("""COMPUTED_VALUE"""),FALSE) -> FALSE | AM20: =IFERROR(__xludf.DUMMYFUNCTION("""COMPUTED_VALUE"""),"Super Critical Mult") -> Super Critical Mult | AN20: =IFERROR(__xludf.DUMMYFUNCTION("""COMPUTED_VALUE"""),0.05) -> 0.05 | AP20: =IFERROR(__xludf.DUMMYFUNCTION("""COMPUTED_VALUE"""),"Multishot Chance") -> Multishot Chance | AQ20: =IFERROR(__xludf.DUMMYFUNCTION("""COMPUTED_VALUE"""),0.0) -> 0 | BZ20: =IFERROR(__xludf.DUMMYFUNCTION("""COMPUTED_VALUE"""),"Tier 18") -> Tier 18 | CA20: =IFERROR(__xludf.DUMMYFUNCTION("""COMPUTED_VALUE"""),348.0) -> 348
A21: =IFERROR(__xludf.DUMMYFUNCTION("""COMPUTED_VALUE"""),"Critical Factor") -> Critical Factor | B21: =IFERROR(__xludf.DUMMYFUNCTION("""COMPUTED_VALUE"""),83.0) -> 83 | D21: =IFERROR(__xludf.DUMMYFUNCTION("""COMPUTED_VALUE"""),99.0) -> 99 | E21: =IFERROR(__xludf.DUMMYFUNCTION("""COMPUTED_VALUE""")," ") | F21: =IFERROR(__xludf.DUMMYFUNCTION("""COMPUTED_VALUE"""),"Health") -> Health | G21: =IFERROR(__xludf.DUMMYFUNCTION("""COMPUTED_VALUE"""),5700.0) -> 5700 | H21: =IFERROR(__xludf.DUMMYFUNCTION("""COMPUTED_VALUE"""),6000.0) -> 6000 | I21: =IFERROR(__xludf.DUMMYFUNCTION("""COMPUTED_VALUE"""),5700.0) -> 5700 | J21: =IFERROR(__xludf.DUMMYFUNCTION("""COMPUTED_VALUE"""),6000.0) -> 6000 | Q21: =IFERROR(__xludf.DUMMYFUNCTION("""COMPUTED_VALUE"""),6000.0) -> 6000 | R21: =IFERROR(__xludf.DUMMYFUNCTION("""COMPUTED_VALUE"""),"Enemy Level Skips +") -> Enemy Level Skips + | S21: =IFERROR(__xludf.DUMMYFUNCTION("""COMPUTED_VALUE"""),1.15) -> 1.15 | T21: =IFERROR(__xludf.DUMMYFUNCTION("""COMPUTED_VALUE"""),15.0) -> 15 | U21: =IFERROR(__xludf.DUMMYFUNCTION("""COMPUTED_VALUE"""),15.0) -> 15 | Y21: =IFERROR(__xludf.DUMMYFUNCTION("""COMPUTED_VALUE"""),60.0) -> 60 | Z21: =IFERROR(__xludf.DUMMYFUNCTION("""COMPUTED_VALUE"""),"UW+") -> UW+ | AB21: =IFERROR(__xludf.DUMMYFUNCTION("""COMPUTED_VALUE"""),"Charged Mines") -> Charged Mines | AC21: =IFERROR(__xludf.DUMMYFUNCTION("""COMPUTED_VALUE"""),"Locked") -> Locked | AD21: =IFERROR(__xludf.DUMMYFUNCTION("""COMPUTED_VALUE"""),"Lo | Locked") -> Lo | Locked | AE21: =IFERROR(__xludf.DUMMYFUNCTION("""COMPUTED_VALUE"""),"Recovery Package Chance") -> Recovery Package Chance | AF21: =IFERROR(__xludf.DUMMYFUNCTION("""COMPUTED_VALUE"""),7.0) -> 7 | AG21: =IFERROR(__xludf.DUMMYFUNCTION("""COMPUTED_VALUE"""),TRUE) -> TRUE | AM21: =IFERROR(__xludf.DUMMYFUNCTION("""COMPUTED_VALUE"""),"Rend Armor Mult") -> Rend Armor Mult | AN21: =IFERROR(__xludf.DUMMYFUNCTION("""COMPUTED_VALUE"""),0.0) -> 0 | AP21: =IFERROR(__xludf.DUMMYFUNCTION("""COMPUTED_VALUE"""),"Rapid Fire Chance") -> Rapid Fire Chance | AQ21: =IFERROR(__xludf.DUMMYFUNCTION("""COMPUTED_VALUE"""),0.0) -> 0 | BZ21: =IFERROR(__xludf.DUMMYFUNCTION("""COMPUTED_VALUE"""),"Tier 19") -> Tier 19 | CA21: =IFERROR(__xludf.DUMMYFUNCTION("""COMPUTED_VALUE"""),52.0) -> 52 | CB21: =IFERROR(__xludf.DUMMYFUNCTION("""COMPUTED_VALUE"""),FALSE) -> FALSE
A22: =IFERROR(__xludf.DUMMYFUNCTION("""COMPUTED_VALUE"""),"Range") -> Range | B22: =IFERROR(__xludf.DUMMYFUNCTION("""COMPUTED_VALUE"""),33.0) -> 33 | D22: =IFERROR(__xludf.DUMMYFUNCTION("""COMPUTED_VALUE"""),80.0) -> 80 | F22: =IFERROR(__xludf.DUMMYFUNCTION("""COMPUTED_VALUE"""),"Health Regen") -> Health Regen | G22: =IFERROR(__xludf.DUMMYFUNCTION("""COMPUTED_VALUE"""),6000.0) -> 6000 | H22: =IFERROR(__xludf.DUMMYFUNCTION("""COMPUTED_VALUE"""),6000.0) -> 6000 | I22: =IFERROR(__xludf.DUMMYFUNCTION("""COMPUTED_VALUE"""),6000.0) -> 6000 | J22: =IFERROR(__xludf.DUMMYFUNCTION("""COMPUTED_VALUE"""),6000.0) -> 6000 | Q22: =IFERROR(__xludf.DUMMYFUNCTION("""COMPUTED_VALUE"""),6000.0) -> 6000 | Z22: =IFERROR(__xludf.DUMMYFUNCTION("""COMPUTED_VALUE"""),"Golden Tower") -> Golden Tower | AB22: =IFERROR(__xludf.DUMMYFUNCTION("""COMPUTED_VALUE"""),"Multiplier") -> Multiplier | AC22: =IFERROR(__xludf.DUMMYFUNCTION("""COMPUTED_VALUE"""),14.600000000000005) -> 14.6 | AD22: =IFERROR(__xludf.DUMMYFUNCTION("""COMPUTED_VALUE"""),"12 | x14.6 | Cost 162 ⧌ | Next 250 ⧌") -> 12 | x14.6 | Cost 162 ⧌ | Next 250 ⧌ | AE22: =IFERROR(__xludf.DUMMYFUNCTION("""COMPUTED_VALUE"""),"Death Ray") -> Death Ray | AF22: =IFERROR(__xludf.DUMMYFUNCTION("""COMPUTED_VALUE"""),7.0) -> 7 | AG22: =IFERROR(__xludf.DUMMYFUNCTION("""COMPUTED_VALUE"""),FALSE) -> FALSE | AM22: =IFERROR(__xludf.DUMMYFUNCTION("""COMPUTED_VALUE"""),"Defense") -> Defense | AP22: =IFERROR(__xludf.DUMMYFUNCTION("""COMPUTED_VALUE"""),"Bounce Shot Chance") -> Bounce Shot Chance | AQ22: =IFERROR(__xludf.DUMMYFUNCTION("""COMPUTED_VALUE"""),0.0) -> 0 | BZ22: =IFERROR(__xludf.DUMMYFUNCTION("""COMPUTED_VALUE"""),"Tier 20") -> Tier 20 | CA22: =IFERROR(__xludf.DUMMYFUNCTION("""COMPUTED_VALUE"""),0.0) -> 0
A23: =IFERROR(__xludf.DUMMYFUNCTION("""COMPUTED_VALUE"""),"Damage / Meter") -> Damage / Meter | B23: =IFERROR(__xludf.DUMMYFUNCTION("""COMPUTED_VALUE"""),16.0) -> 16 | D23: =IFERROR(__xludf.DUMMYFUNCTION("""COMPUTED_VALUE"""),99.0) -> 99 | E23: =IFERROR(__xludf.DUMMYFUNCTION("""COMPUTED_VALUE"""),TRUE) -> TRUE | F23: =IFERROR(__xludf.DUMMYFUNCTION("""COMPUTED_VALUE"""),"Defense %") -> Defense % | G23: =IFERROR(__xludf.DUMMYFUNCTION("""COMPUTED_VALUE"""),99.0) -> 99 | H23: =IFERROR(__xludf.DUMMYFUNCTION("""COMPUTED_VALUE"""),99.0) -> 99 | I23: =IFERROR(__xludf.DUMMYFUNCTION("""COMPUTED_VALUE"""),99.0) -> 99 | J23: =IFERROR(__xludf.DUMMYFUNCTION("""COMPUTED_VALUE"""),99.0) -> 99 | Q23: =IFERROR(__xludf.DUMMYFUNCTION("""COMPUTED_VALUE"""),99.0) -> 99 | AB23: =IFERROR(__xludf.DUMMYFUNCTION("""COMPUTED_VALUE"""),"Duration") -> Duration | AC23: =IFERROR(__xludf.DUMMYFUNCTION("""COMPUTED_VALUE"""),22.0) -> 22 | AD23: =IFERROR(__xludf.DUMMYFUNCTION("""COMPUTED_VALUE"""),"07 | 22s | Cost 59 ⧌ | Next 68 ⧌") -> 07 | 22s | Cost 59 ⧌ | Next 68 ⧌ | AE23: =IFERROR(__xludf.DUMMYFUNCTION("""COMPUTED_VALUE"""),"Energy Net") -> Energy Net | AF23: =IFERROR(__xludf.DUMMYFUNCTION("""COMPUTED_VALUE"""),7.0) -> 7 | AG23: =IFERROR(__xludf.DUMMYFUNCTION("""COMPUTED_VALUE"""),FALSE) -> FALSE | AM23: =IFERROR(__xludf.DUMMYFUNCTION("""COMPUTED_VALUE"""),"Health") -> Health | AN23: =IFERROR(__xludf.DUMMYFUNCTION("""COMPUTED_VALUE"""),0.51) -> 0.51 | AP23: =IFERROR(__xludf.DUMMYFUNCTION("""COMPUTED_VALUE"""),"Super Crit Chance") -> Super Crit Chance | AQ23: =IFERROR(__xludf.DUMMYFUNCTION("""COMPUTED_VALUE"""),0.0) -> 0 | BB23: =IFERROR(__xludf.DUMMYFUNCTION("""COMPUTED_VALUE"""),"Placeholder 5th preset") -> Placeholder 5th preset | BG23: =IFERROR(__xludf.DUMMYFUNCTION("""COMPUTED_VALUE"""),"Placeholder 5th preset") -> Placeholder 5th preset | BL23: =IFERROR(__xludf.DUMMYFUNCTION("""COMPUTED_VALUE"""),"Placeholder 5th preset") -> Placeholder 5th preset | BQ23: =IFERROR(__xludf.DUMMYFUNCTION("""COMPUTED_VALUE"""),"Placeholder 5th preset") -> Placeholder 5th preset | BZ23: =IFERROR(__xludf.DUMMYFUNCTION("""COMPUTED_VALUE"""),"Tier 21") -> Tier 21 | CA23: =IFERROR(__xludf.DUMMYFUNCTION("""COMPUTED_VALUE"""),0.0) -> 0
A24: =IFERROR(__xludf.DUMMYFUNCTION("""COMPUTED_VALUE"""),"Super Crit Chance") -> Super Crit Chance | B24: =IFERROR(__xludf.DUMMYFUNCTION("""COMPUTED_VALUE"""),9.0) -> 9 | D24: =IFERROR(__xludf.DUMMYFUNCTION("""COMPUTED_VALUE"""),50.0) -> 50 | F24: =IFERROR(__xludf.DUMMYFUNCTION("""COMPUTED_VALUE"""),"Defense Absolute") -> Defense Absolute | G24: =IFERROR(__xludf.DUMMYFUNCTION("""COMPUTED_VALUE"""),5000.0) -> 5000 | H24: =IFERROR(__xludf.DUMMYFUNCTION("""COMPUTED_VALUE"""),5000.0) -> 5000 | I24: =IFERROR(__xludf.DUMMYFUNCTION("""COMPUTED_VALUE"""),5000.0) -> 5000 | J24: =IFERROR(__xludf.DUMMYFUNCTION("""COMPUTED_VALUE"""),5000.0) -> 5000 | Q24: =IFERROR(__xludf.DUMMYFUNCTION("""COMPUTED_VALUE"""),5000.0) -> 5000 | Z24: =IFERROR(__xludf.DUMMYFUNCTION("""COMPUTED_VALUE"""),TRUE) -> TRUE | AA24: =IFERROR(__xludf.DUMMYFUNCTION("""COMPUTED_VALUE"""),"UW Unlocked") -> UW Unlocked | AB24: =IFERROR(__xludf.DUMMYFUNCTION("""COMPUTED_VALUE"""),"Cooldown") -> Cooldown | AC24: =IFERROR(__xludf.DUMMYFUNCTION("""COMPUTED_VALUE"""),180.0) -> 180 | AD24: =IFERROR(__xludf.DUMMYFUNCTION("""COMPUTED_VALUE"""),"12 | 180s | Cost 208 ⧌ | Next 226 ⧌") -> 12 | 180s | Cost 208 ⧌ | Next 226 ⧌ | AE24: =IFERROR(__xludf.DUMMYFUNCTION("""COMPUTED_VALUE"""),"Super Tower") -> Super Tower | AF24: =IFERROR(__xludf.DUMMYFUNCTION("""COMPUTED_VALUE"""),7.0) -> 7 | AG24: =IFERROR(__xludf.DUMMYFUNCTION("""COMPUTED_VALUE"""),FALSE) -> FALSE | AM24: =IFERROR(__xludf.DUMMYFUNCTION("""COMPUTED_VALUE"""),"Health Regen") -> Health Regen | AN24: =IFERROR(__xludf.DUMMYFUNCTION("""COMPUTED_VALUE"""),0.22999999999999998) -> 0.23 | AP24: =IFERROR(__xludf.DUMMYFUNCTION("""COMPUTED_VALUE"""),"Super Crit Mult") -> Super Crit Mult | AQ24: =IFERROR(__xludf.DUMMYFUNCTION("""COMPUTED_VALUE"""),0.0) -> 0
A25: =IFERROR(__xludf.DUMMYFUNCTION("""COMPUTED_VALUE"""),"Super Crit Multi") -> Super Crit Multi | B25: =IFERROR(__xludf.DUMMYFUNCTION("""COMPUTED_VALUE"""),13.0) -> 13 | D25: =IFERROR(__xludf.DUMMYFUNCTION("""COMPUTED_VALUE"""),40.0) -> 40 | E25: =IFERROR(__xludf.DUMMYFUNCTION("""COMPUTED_VALUE"""),TRUE) -> TRUE | F25: =IFERROR(__xludf.DUMMYFUNCTION("""COMPUTED_VALUE"""),"Thorn Damage") -> Thorn Damage | G25: =IFERROR(__xludf.DUMMYFUNCTION("""COMPUTED_VALUE"""),99.0) -> 99 | H25: =IFERROR(__xludf.DUMMYFUNCTION("""COMPUTED_VALUE"""),99.0) -> 99 | I25: =IFERROR(__xludf.DUMMYFUNCTION("""COMPUTED_VALUE"""),99.0) -> 99 | J25: =IFERROR(__xludf.DUMMYFUNCTION("""COMPUTED_VALUE"""),99.0) -> 99 | Q25: =IFERROR(__xludf.DUMMYFUNCTION("""COMPUTED_VALUE"""),99.0) -> 99 | Z25: =IFERROR(__xludf.DUMMYFUNCTION("""COMPUTED_VALUE"""),"UW+") -> UW+ | AB25: =IFERROR(__xludf.DUMMYFUNCTION("""COMPUTED_VALUE"""),"Golden Combo") -> Golden Combo | AC25: =IFERROR(__xludf.DUMMYFUNCTION("""COMPUTED_VALUE"""),"Locked") -> Locked | AD25: =IFERROR(__xludf.DUMMYFUNCTION("""COMPUTED_VALUE"""),"Lo | Locked") -> Lo | Locked | AE25: =IFERROR(__xludf.DUMMYFUNCTION("""COMPUTED_VALUE"""),"Second Wind") -> Second Wind | AF25: =IFERROR(__xludf.DUMMYFUNCTION("""COMPUTED_VALUE"""),7.0) -> 7 | AG25: =IFERROR(__xludf.DUMMYFUNCTION("""COMPUTED_VALUE"""),FALSE) -> FALSE | AM25: =IFERROR(__xludf.DUMMYFUNCTION("""COMPUTED_VALUE"""),"Defense %") -> Defense % | AN25: =IFERROR(__xludf.DUMMYFUNCTION("""COMPUTED_VALUE"""),0.04) -> 0.04 | AP25: =IFERROR(__xludf.DUMMYFUNCTION("""COMPUTED_VALUE"""),"Rend Armor Chance") -> Rend Armor Chance | AQ25: =IFERROR(__xludf.DUMMYFUNCTION("""COMPUTED_VALUE"""),0.0) -> 0
A26: =IFERROR(__xludf.DUMMYFUNCTION("""COMPUTED_VALUE"""),"Max Rend Armor Multiplier") -> Max Rend Armor Multiplier | B26: =IFERROR(__xludf.DUMMYFUNCTION("""COMPUTED_VALUE"""),0.0) -> 0 | D26: =IFERROR(__xludf.DUMMYFUNCTION("""COMPUTED_VALUE"""),30.0) -> 30 | E26: =IFERROR(__xludf.DUMMYFUNCTION("""COMPUTED_VALUE"""),TRUE) -> TRUE | F26: =IFERROR(__xludf.DUMMYFUNCTION("""COMPUTED_VALUE"""),"Lifesteal") -> Lifesteal | G26: =IFERROR(__xludf.DUMMYFUNCTION("""COMPUTED_VALUE"""),80.0) -> 80 | H26: =IFERROR(__xludf.DUMMYFUNCTION("""COMPUTED_VALUE"""),80.0) -> 80 | I26: =IFERROR(__xludf.DUMMYFUNCTION("""COMPUTED_VALUE"""),80.0) -> 80 | J26: =IFERROR(__xludf.DUMMYFUNCTION("""COMPUTED_VALUE"""),80.0) -> 80 | Q26: =IFERROR(__xludf.DUMMYFUNCTION("""COMPUTED_VALUE"""),80.0) -> 80 | Z26: =IFERROR(__xludf.DUMMYFUNCTION("""COMPUTED_VALUE"""),"Poison Swamp") -> Poison Swamp | AB26: =IFERROR(__xludf.DUMMYFUNCTION("""COMPUTED_VALUE"""),"Damage") -> Damage | AC26: =IFERROR(__xludf.DUMMYFUNCTION("""COMPUTED_VALUE"""),10.0) -> 10 | AD26: =IFERROR(__xludf.DUMMYFUNCTION("""COMPUTED_VALUE"""),"00 | x10 | Cost 0 ⧌ | Next 5 ⧌") -> 00 | x10 | Cost 0 ⧌ | Next 5 ⧌ | AE26: =IFERROR(__xludf.DUMMYFUNCTION("""COMPUTED_VALUE"""),"Demon Mode") -> Demon Mode | AF26: =IFERROR(__xludf.DUMMYFUNCTION("""COMPUTED_VALUE"""),7.0) -> 7 | AG26: =IFERROR(__xludf.DUMMYFUNCTION("""COMPUTED_VALUE"""),FALSE) -> FALSE | AM26: =IFERROR(__xludf.DUMMYFUNCTION("""COMPUTED_VALUE"""),"Defense Absolute") -> Defense Absolute | AN26: =IFERROR(__xludf.DUMMYFUNCTION("""COMPUTED_VALUE"""),0.28) -> 0.28 | AP26: =IFERROR(__xludf.DUMMYFUNCTION("""COMPUTED_VALUE"""),"Rend Armor Mult") -> Rend Armor Mult | AQ26: =IFERROR(__xludf.DUMMYFUNCTION("""COMPUTED_VALUE"""),0.0) -> 0
A27: =IFERROR(__xludf.DUMMYFUNCTION("""COMPUTED_VALUE"""),"Light Speed Shots") -> Light Speed Shots | B27: =IFERROR(__xludf.DUMMYFUNCTION("""COMPUTED_VALUE"""),1.0) -> 1 | D27: =IFERROR(__xludf.DUMMYFUNCTION("""COMPUTED_VALUE"""),1.0) -> 1 | E27: =IFERROR(__xludf.DUMMYFUNCTION("""COMPUTED_VALUE"""),TRUE) -> TRUE | F27: =IFERROR(__xludf.DUMMYFUNCTION("""COMPUTED_VALUE"""),"Knockback Chance") -> Knockback Chance | G27: =IFERROR(__xludf.DUMMYFUNCTION("""COMPUTED_VALUE"""),80.0) -> 80 | H27: =IFERROR(__xludf.DUMMYFUNCTION("""COMPUTED_VALUE"""),80.0) -> 80 | I27: =IFERROR(__xludf.DUMMYFUNCTION("""COMPUTED_VALUE"""),80.0) -> 80 | J27: =IFERROR(__xludf.DUMMYFUNCTION("""COMPUTED_VALUE"""),80.0) -> 80 | Q27: =IFERROR(__xludf.DUMMYFUNCTION("""COMPUTED_VALUE"""),80.0) -> 80 | AB27: =IFERROR(__xludf.DUMMYFUNCTION("""COMPUTED_VALUE"""),"Duration") -> Duration | AC27: =IFERROR(__xludf.DUMMYFUNCTION("""COMPUTED_VALUE"""),30.0) -> 30 | AD27: =IFERROR(__xludf.DUMMYFUNCTION("""COMPUTED_VALUE"""),"00 | 30s | Cost 0 ⧌ | Next 10 ⧌") -> 00 | 30s | Cost 0 ⧌ | Next 10 ⧌ | AE27: =IFERROR(__xludf.DUMMYFUNCTION("""COMPUTED_VALUE"""),"Energy Shield") -> Energy Shield | AF27: =IFERROR(__xludf.DUMMYFUNCTION("""COMPUTED_VALUE"""),7.0) -> 7 | AG27: =IFERROR(__xludf.DUMMYFUNCTION("""COMPUTED_VALUE"""),FALSE) -> FALSE | AM27: =IFERROR(__xludf.DUMMYFUNCTION("""COMPUTED_VALUE"""),"Thorns") -> Thorns | AN27: =IFERROR(__xludf.DUMMYFUNCTION("""COMPUTED_VALUE"""),0.09000000000000001) -> 0.09 | AP27: =IFERROR(__xludf.DUMMYFUNCTION("""COMPUTED_VALUE"""),"Defense") -> Defense | BB27: =IFERROR(__xludf.DUMMYFUNCTION("""COMPUTED_VALUE"""),"Astral Deliverance") -> Astral Deliverance | BG27: =IFERROR(__xludf.DUMMYFUNCTION("""COMPUTED_VALUE"""),"Anti-Cube Portal") -> Anti-Cube Portal | BL27: =IFERROR(__xludf.DUMMYFUNCTION("""COMPUTED_VALUE"""),"Black Hole Digestor") -> Black Hole Digestor | BQ27: =IFERROR(__xludf.DUMMYFUNCTION("""COMPUTED_VALUE"""),"Multiverse Nexus") -> Multiverse Nexus
A28: =IFERROR(__xludf.DUMMYFUNCTION("""COMPUTED_VALUE"""),"Health") -> Health | B28: =IFERROR(__xludf.DUMMYFUNCTION("""COMPUTED_VALUE"""),68.0) -> 68 | D28: =IFERROR(__xludf.DUMMYFUNCTION("""COMPUTED_VALUE"""),100.0) -> 100 | F28: =IFERROR(__xludf.DUMMYFUNCTION("""COMPUTED_VALUE"""),"Knockback Force") -> Knockback Force | G28: =IFERROR(__xludf.DUMMYFUNCTION("""COMPUTED_VALUE"""),40.0) -> 40 | H28: =IFERROR(__xludf.DUMMYFUNCTION("""COMPUTED_VALUE"""),40.0) -> 40 | I28: =IFERROR(__xludf.DUMMYFUNCTION("""COMPUTED_VALUE"""),40.0) -> 40 | J28: =IFERROR(__xludf.DUMMYFUNCTION("""COMPUTED_VALUE"""),40.0) -> 40 | Q28: =IFERROR(__xludf.DUMMYFUNCTION("""COMPUTED_VALUE"""),40.0) -> 40 | Z28: =IFERROR(__xludf.DUMMYFUNCTION("""COMPUTED_VALUE"""),FALSE) -> FALSE | AA28: =IFERROR(__xludf.DUMMYFUNCTION("""COMPUTED_VALUE"""),"UW Locked") -> UW Locked | AB28: =IFERROR(__xludf.DUMMYFUNCTION("""COMPUTED_VALUE"""),"Cooldown") -> Cooldown | AC28: =IFERROR(__xludf.DUMMYFUNCTION("""COMPUTED_VALUE"""),125.0) -> 125 | AD28: =IFERROR(__xludf.DUMMYFUNCTION("""COMPUTED_VALUE"""),"00 | 125s | Cost 0 ⧌ | Next 8 ⧌") -> 00 | 125s | Cost 0 ⧌ | Next 8 ⧌ | AE28: =IFERROR(__xludf.DUMMYFUNCTION("""COMPUTED_VALUE"""),"Wave Accelerator") -> Wave Accelerator | AF28: =IFERROR(__xludf.DUMMYFUNCTION("""COMPUTED_VALUE"""),7.0) -> 7 | AG28: =IFERROR(__xludf.DUMMYFUNCTION("""COMPUTED_VALUE"""),FALSE) -> FALSE | AM28: =IFERROR(__xludf.DUMMYFUNCTION("""COMPUTED_VALUE"""),"Knockback Force") -> Knockback Force | AN28: =IFERROR(__xludf.DUMMYFUNCTION("""COMPUTED_VALUE"""),0.24) -> 0.24 | AP28: =IFERROR(__xludf.DUMMYFUNCTION("""COMPUTED_VALUE"""),"Health") -> Health | AQ28: =IFERROR(__xludf.DUMMYFUNCTION("""COMPUTED_VALUE"""),0.0) -> 0 | BB28: =IFERROR(__xludf.DUMMYFUNCTION("""COMPUTED_VALUE"""),"Rarity") -> Rarity | BC28: =IFERROR(__xludf.DUMMYFUNCTION("""COMPUTED_VALUE"""),"Level") -> Level | BD28: =IFERROR(__xludf.DUMMYFUNCTION("""COMPUTED_VALUE"""),"Stat") -> Stat | BG28: =IFERROR(__xludf.DUMMYFUNCTION("""COMPUTED_VALUE"""),"Rarity") -> Rarity | BH28: =IFERROR(__xludf.DUMMYFUNCTION("""COMPUTED_VALUE"""),"Level") -> Level | BI28: =IFERROR(__xludf.DUMMYFUNCTION("""COMPUTED_VALUE"""),"Stat") -> Stat | BL28: =IFERROR(__xludf.DUMMYFUNCTION("""COMPUTED_VALUE"""),"Rarity") -> Rarity | BM28: =IFERROR(__xludf.DUMMYFUNCTION("""COMPUTED_VALUE"""),"Level") -> Level | BN28: =IFERROR(__xludf.DUMMYFUNCTION("""COMPUTED_VALUE"""),"Stat") -> Stat | BQ28: =IFERROR(__xludf.DUMMYFUNCTION("""COMPUTED_VALUE"""),"Rarity") -> Rarity | BR28: =IFERROR(__xludf.DUMMYFUNCTION("""COMPUTED_VALUE"""),"Level") -> Level | BS28: =IFERROR(__xludf.DUMMYFUNCTION("""COMPUTED_VALUE"""),"Stat") -> Stat
A29: =IFERROR(__xludf.DUMMYFUNCTION("""COMPUTED_VALUE"""),"Health Regen") -> Health Regen | B29: =IFERROR(__xludf.DUMMYFUNCTION("""COMPUTED_VALUE"""),68.0) -> 68 | D29: =IFERROR(__xludf.DUMMYFUNCTION("""COMPUTED_VALUE"""),100.0) -> 100 | E29: =IFERROR(__xludf.DUMMYFUNCTION("""COMPUTED_VALUE"""),TRUE) -> TRUE | F29: =IFERROR(__xludf.DUMMYFUNCTION("""COMPUTED_VALUE"""),"Orb Speed") -> Orb Speed | G29: =IFERROR(__xludf.DUMMYFUNCTION("""COMPUTED_VALUE"""),38.0) -> 38 | H29: =IFERROR(__xludf.DUMMYFUNCTION("""COMPUTED_VALUE"""),38.0) -> 38 | I29: =IFERROR(__xludf.DUMMYFUNCTION("""COMPUTED_VALUE"""),38.0) -> 38 | J29: =IFERROR(__xludf.DUMMYFUNCTION("""COMPUTED_VALUE"""),38.0) -> 38 | Q29: =IFERROR(__xludf.DUMMYFUNCTION("""COMPUTED_VALUE"""),38.0) -> 38 | Z29: =IFERROR(__xludf.DUMMYFUNCTION("""COMPUTED_VALUE"""),"UW+") -> UW+ | AB29: =IFERROR(__xludf.DUMMYFUNCTION("""COMPUTED_VALUE"""),"Death Creep") -> Death Creep | AC29: =IFERROR(__xludf.DUMMYFUNCTION("""COMPUTED_VALUE"""),"Locked") -> Locked | AD29: =IFERROR(__xludf.DUMMYFUNCTION("""COMPUTED_VALUE"""),"Lo | Locked") -> Lo | Locked | AE29: =IFERROR(__xludf.DUMMYFUNCTION("""COMPUTED_VALUE"""),"Berserker") -> Berserker | AF29: =IFERROR(__xludf.DUMMYFUNCTION("""COMPUTED_VALUE"""),7.0) -> 7 | AG29: =IFERROR(__xludf.DUMMYFUNCTION("""COMPUTED_VALUE"""),FALSE) -> FALSE | AM29: =IFERROR(__xludf.DUMMYFUNCTION("""COMPUTED_VALUE"""),"Orb Speed") -> Orb Speed | AN29: =IFERROR(__xludf.DUMMYFUNCTION("""COMPUTED_VALUE"""),0.12000000000000001) -> 0.12 | AP29: =IFERROR(__xludf.DUMMYFUNCTION("""COMPUTED_VALUE"""),"Health Regen") -> Health Regen | AQ29: =IFERROR(__xludf.DUMMYFUNCTION("""COMPUTED_VALUE"""),0.0) -> 0 | BB29: =IFERROR(__xludf.DUMMYFUNCTION("""COMPUTED_VALUE"""),"Mythic+") -> Mythic+ | BC29: =IFERROR(__xludf.DUMMYFUNCTION("""COMPUTED_VALUE"""),160.0) -> 160 | BD29: =IFERROR(__xludf.DUMMYFUNCTION("""COMPUTED_VALUE"""),8.19) -> 8.19 | BG29: =IFERROR(__xludf.DUMMYFUNCTION("""COMPUTED_VALUE"""),"Mythic+") -> Mythic+ | BH29: =IFERROR(__xludf.DUMMYFUNCTION("""COMPUTED_VALUE"""),160.0) -> 160 | BI29: =IFERROR(__xludf.DUMMYFUNCTION("""COMPUTED_VALUE"""),8.19) -> 8.19 | BL29: =IFERROR(__xludf.DUMMYFUNCTION("""COMPUTED_VALUE"""),"Legendary") -> Legendary | BM29: =IFERROR(__xludf.DUMMYFUNCTION("""COMPUTED_VALUE"""),100.0) -> 100 | BN29: =IFERROR(__xludf.DUMMYFUNCTION("""COMPUTED_VALUE"""),1.275) -> 1.275 | BQ29: =IFERROR(__xludf.DUMMYFUNCTION("""COMPUTED_VALUE"""),"Ancestral 2*") -> Ancestral 2* | BR29: =IFERROR(__xludf.DUMMYFUNCTION("""COMPUTED_VALUE"""),159.0) -> 159 | BS29: =IFERROR(__xludf.DUMMYFUNCTION("""COMPUTED_VALUE"""),11.692) -> 11.692
A30: =IFERROR(__xludf.DUMMYFUNCTION("""COMPUTED_VALUE"""),"Defense Absolute") -> Defense Absolute | B30: =IFERROR(__xludf.DUMMYFUNCTION("""COMPUTED_VALUE"""),14.0) -> 14 | C30: =IFERROR(__xludf.DUMMYFUNCTION("""COMPUTED_VALUE"""),14.0) -> 14 | D30: =IFERROR(__xludf.DUMMYFUNCTION("""COMPUTED_VALUE"""),100.0) -> 100 | F30: =IFERROR(__xludf.DUMMYFUNCTION("""COMPUTED_VALUE"""),"Orbs") -> Orbs | G30: =IFERROR(__xludf.DUMMYFUNCTION("""COMPUTED_VALUE"""),4.0) -> 4 | H30: =IFERROR(__xludf.DUMMYFUNCTION("""COMPUTED_VALUE"""),4.0) -> 4 | I30: =IFERROR(__xludf.DUMMYFUNCTION("""COMPUTED_VALUE"""),4.0) -> 4 | J30: =IFERROR(__xludf.DUMMYFUNCTION("""COMPUTED_VALUE"""),4.0) -> 4 | Q30: =IFERROR(__xludf.DUMMYFUNCTION("""COMPUTED_VALUE"""),4.0) -> 4 | Z30: =IFERROR(__xludf.DUMMYFUNCTION("""COMPUTED_VALUE"""),"Black Hole") -> Black Hole | AB30: =IFERROR(__xludf.DUMMYFUNCTION("""COMPUTED_VALUE"""),"Size") -> Size | AC30: =IFERROR(__xludf.DUMMYFUNCTION("""COMPUTED_VALUE"""),48.0) -> 48 | AD30: =IFERROR(__xludf.DUMMYFUNCTION("""COMPUTED_VALUE"""),"09 | 48m | Cost 76 ⧌ | Next 89 ⧌") -> 09 | 48m | Cost 76 ⧌ | Next 89 ⧌ | AE30: =IFERROR(__xludf.DUMMYFUNCTION("""COMPUTED_VALUE"""),"Ultimate Crit") -> Ultimate Crit | AF30: =IFERROR(__xludf.DUMMYFUNCTION("""COMPUTED_VALUE"""),7.0) -> 7 | AG30: =IFERROR(__xludf.DUMMYFUNCTION("""COMPUTED_VALUE"""),FALSE) -> FALSE | AM30: =IFERROR(__xludf.DUMMYFUNCTION("""COMPUTED_VALUE"""),"Wall Rebuild") -> Wall Rebuild | AN30: =IFERROR(__xludf.DUMMYFUNCTION("""COMPUTED_VALUE"""),2.0) -> 2 | AP30: =IFERROR(__xludf.DUMMYFUNCTION("""COMPUTED_VALUE"""),"Defense %") -> Defense % | AQ30: =IFERROR(__xludf.DUMMYFUNCTION("""COMPUTED_VALUE"""),0.0) -> 0
A31: =IFERROR(__xludf.DUMMYFUNCTION("""COMPUTED_VALUE"""),"Defense %") -> Defense % | B31: =IFERROR(__xludf.DUMMYFUNCTION("""COMPUTED_VALUE"""),28.0) -> 28 | C31: =IFERROR(__xludf.DUMMYFUNCTION("""COMPUTED_VALUE"""),28.0) -> 28 | D31: =IFERROR(__xludf.DUMMYFUNCTION("""COMPUTED_VALUE"""),50.0) -> 50 | E31: =IFERROR(__xludf.DUMMYFUNCTION("""COMPUTED_VALUE"""),TRUE) -> TRUE | F31: =IFERROR(__xludf.DUMMYFUNCTION("""COMPUTED_VALUE"""),"Shockwave Size") -> Shockwave Size | G31: =IFERROR(__xludf.DUMMYFUNCTION("""COMPUTED_VALUE"""),35.0) -> 35 | H31: =IFERROR(__xludf.DUMMYFUNCTION("""COMPUTED_VALUE"""),35.0) -> 35 | I31: =IFERROR(__xludf.DUMMYFUNCTION("""COMPUTED_VALUE"""),35.0) -> 35 | J31: =IFERROR(__xludf.DUMMYFUNCTION("""COMPUTED_VALUE"""),35.0) -> 35 | Q31: =IFERROR(__xludf.DUMMYFUNCTION("""COMPUTED_VALUE"""),35.0) -> 35 | AB31: =IFERROR(__xludf.DUMMYFUNCTION("""COMPUTED_VALUE"""),"Duration") -> Duration | AC31: =IFERROR(__xludf.DUMMYFUNCTION("""COMPUTED_VALUE"""),32.0) -> 32 | AD31: =IFERROR(__xludf.DUMMYFUNCTION("""COMPUTED_VALUE"""),"17 | 32s | Cost 224 ⧌ | Next 308 ⧌") -> 17 | 32s | Cost 224 ⧌ | Next 308 ⧌ | AE31: =IFERROR(__xludf.DUMMYFUNCTION("""COMPUTED_VALUE"""),"Nuke") -> Nuke | AF31: =IFERROR(__xludf.DUMMYFUNCTION("""COMPUTED_VALUE"""),7.0) -> 7 | AG31: =IFERROR(__xludf.DUMMYFUNCTION("""COMPUTED_VALUE"""),FALSE) -> FALSE | AM31: =IFERROR(__xludf.DUMMYFUNCTION("""COMPUTED_VALUE"""),"Utility") -> Utility | AP31: =IFERROR(__xludf.DUMMYFUNCTION("""COMPUTED_VALUE"""),"Defense Absolute") -> Defense Absolute | AQ31: =IFERROR(__xludf.DUMMYFUNCTION("""COMPUTED_VALUE"""),0.0) -> 0 | BE31: =IFERROR(__xludf.DUMMYFUNCTION("""COMPUTED_VALUE"""),"") | BG31: =IFERROR(__xludf.DUMMYFUNCTION("""COMPUTED_VALUE"""),"Orb Speed") -> Orb Speed | BH31: =IFERROR(__xludf.DUMMYFUNCTION("""COMPUTED_VALUE"""),"Legendary") -> Legendary | BI31: =IFERROR(__xludf.DUMMYFUNCTION("""COMPUTED_VALUE"""),"+1.5") -> +1.5 | BJ31: =IFERROR(__xludf.DUMMYFUNCTION("""COMPUTED_VALUE"""),1.5) -> 1.5 | BL31: =IFERROR(__xludf.DUMMYFUNCTION("""COMPUTED_VALUE"""),"Coins / Kill Bonus") -> Coins / Kill Bonus | BM31: =IFERROR(__xludf.DUMMYFUNCTION("""COMPUTED_VALUE"""),"Legendary") -> Legendary | BN31: =IFERROR(__xludf.DUMMYFUNCTION("""COMPUTED_VALUE"""),"+0.4x") -> +0.4x | BO31: =IFERROR(__xludf.DUMMYFUNCTION("""COMPUTED_VALUE"""),0.4) -> 0.4 | BQ31: =IFERROR(__xludf.DUMMYFUNCTION("""COMPUTED_VALUE"""),"Death Wave - Quantity") -> Death Wave - Quantity | BR31: =IFERROR(__xludf.DUMMYFUNCTION("""COMPUTED_VALUE"""),"Legendary") -> Legendary | BS31: =IFERROR(__xludf.DUMMYFUNCTION("""COMPUTED_VALUE"""),"+1") -> +1 | BT31: =IFERROR(__xludf.DUMMYFUNCTION("""COMPUTED_VALUE"""),1.0) -> 1
A32: =IFERROR(__xludf.DUMMYFUNCTION("""COMPUTED_VALUE"""),"Orbs Speed") -> Orbs Speed | B32: =IFERROR(__xludf.DUMMYFUNCTION("""COMPUTED_VALUE"""),20.0) -> 20 | D32: =IFERROR(__xludf.DUMMYFUNCTION("""COMPUTED_VALUE"""),20.0) -> 20 | F32: =IFERROR(__xludf.DUMMYFUNCTION("""COMPUTED_VALUE"""),"Shockwave Frequency") -> Shockwave Frequency | G32: =IFERROR(__xludf.DUMMYFUNCTION("""COMPUTED_VALUE"""),40.0) -> 40 | H32: =IFERROR(__xludf.DUMMYFUNCTION("""COMPUTED_VALUE"""),40.0) -> 40 | I32: =IFERROR(__xludf.DUMMYFUNCTION("""COMPUTED_VALUE"""),40.0) -> 40 | J32: =IFERROR(__xludf.DUMMYFUNCTION("""COMPUTED_VALUE"""),40.0) -> 40 | Q32: =IFERROR(__xludf.DUMMYFUNCTION("""COMPUTED_VALUE"""),40.0) -> 40 | Z32: =IFERROR(__xludf.DUMMYFUNCTION("""COMPUTED_VALUE"""),TRUE) -> TRUE | AA32: =IFERROR(__xludf.DUMMYFUNCTION("""COMPUTED_VALUE"""),"UW Unlocked") -> UW Unlocked | AB32: =IFERROR(__xludf.DUMMYFUNCTION("""COMPUTED_VALUE"""),"Cooldown") -> Cooldown | AC32: =IFERROR(__xludf.DUMMYFUNCTION("""COMPUTED_VALUE"""),50.0) -> 50 | AD32: =IFERROR(__xludf.DUMMYFUNCTION("""COMPUTED_VALUE"""),"15 | 50s | Cost 262 ⧌ | Maxed") -> 15 | 50s | Cost 262 ⧌ | Maxed | AE32: =IFERROR(__xludf.DUMMYFUNCTION("""COMPUTED_VALUE"""),"Area of Effect") -> Area of Effect | AF32: =IFERROR(__xludf.DUMMYFUNCTION("""COMPUTED_VALUE"""),"Locked") -> Locked | AG32: =IFERROR(__xludf.DUMMYFUNCTION("""COMPUTED_VALUE"""),FALSE) -> FALSE | AM32: =IFERROR(__xludf.DUMMYFUNCTION("""COMPUTED_VALUE"""),"Cash") -> Cash | AN32: =IFERROR(__xludf.DUMMYFUNCTION("""COMPUTED_VALUE"""),0.06) -> 0.06 | AP32: =IFERROR(__xludf.DUMMYFUNCTION("""COMPUTED_VALUE"""),"Thorn Damage") -> Thorn Damage | AQ32: =IFERROR(__xludf.DUMMYFUNCTION("""COMPUTED_VALUE"""),0.0) -> 0 | BE32: =IFERROR(__xludf.DUMMYFUNCTION("""COMPUTED_VALUE"""),"") | BG32: =IFERROR(__xludf.DUMMYFUNCTION("""COMPUTED_VALUE"""),"Shockwave Size") -> Shockwave Size | BH32: =IFERROR(__xludf.DUMMYFUNCTION("""COMPUTED_VALUE"""),"Legendary") -> Legendary | BI32: =IFERROR(__xludf.DUMMYFUNCTION("""COMPUTED_VALUE"""),"+0.3") -> +0.3 | BJ32: =IFERROR(__xludf.DUMMYFUNCTION("""COMPUTED_VALUE"""),0.3) -> 0.3 | BL32: =IFERROR(__xludf.DUMMYFUNCTION("""COMPUTED_VALUE"""),"Enemy Attack Level Skip") -> Enemy Attack Level Skip | BM32: =IFERROR(__xludf.DUMMYFUNCTION("""COMPUTED_VALUE"""),"Legendary") -> Legendary | BN32: =IFERROR(__xludf.DUMMYFUNCTION("""COMPUTED_VALUE"""),"+4%") -> +4% | BO32: =IFERROR(__xludf.DUMMYFUNCTION("""COMPUTED_VALUE"""),0.04) -> 0.04 | BQ32: =IFERROR(__xludf.DUMMYFUNCTION("""COMPUTED_VALUE"""),"Golden Tower - Bonus") -> Golden Tower - Bonus | BR32: =IFERROR(__xludf.DUMMYFUNCTION("""COMPUTED_VALUE"""),"Legendary") -> Legendary | BS32: =IFERROR(__xludf.DUMMYFUNCTION("""COMPUTED_VALUE"""),"+2x") -> +2x | BT32: =IFERROR(__xludf.DUMMYFUNCTION("""COMPUTED_VALUE"""),2.0) -> 2
A33: =IFERROR(__xludf.DUMMYFUNCTION("""COMPUTED_VALUE"""),"Land Mine Damage") -> Land Mine Damage | B33: =IFERROR(__xludf.DUMMYFUNCTION("""COMPUTED_VALUE"""),0.0) -> 0 | D33: =IFERROR(__xludf.DUMMYFUNCTION("""COMPUTED_VALUE"""),20.0) -> 20 | E33: =IFERROR(__xludf.DUMMYFUNCTION("""COMPUTED_VALUE"""),TRUE) -> TRUE | F33: =IFERROR(__xludf.DUMMYFUNCTION("""COMPUTED_VALUE"""),"Land Mine Chance") -> Land Mine Chance | G33: =IFERROR(__xludf.DUMMYFUNCTION("""COMPUTED_VALUE"""),50.0) -> 50 | H33: =IFERROR(__xludf.DUMMYFUNCTION("""COMPUTED_VALUE"""),50.0) -> 50 | I33: =IFERROR(__xludf.DUMMYFUNCTION("""COMPUTED_VALUE"""),50.0) -> 50 | J33: =IFERROR(__xludf.DUMMYFUNCTION("""COMPUTED_VALUE"""),50.0) -> 50 | Q33: =IFERROR(__xludf.DUMMYFUNCTION("""COMPUTED_VALUE"""),50.0) -> 50 | Z33: =IFERROR(__xludf.DUMMYFUNCTION("""COMPUTED_VALUE"""),"UW+") -> UW+ | AB33: =IFERROR(__xludf.DUMMYFUNCTION("""COMPUTED_VALUE"""),"Consume") -> Consume | AC33: =IFERROR(__xludf.DUMMYFUNCTION("""COMPUTED_VALUE"""),"Locked") -> Locked | AD33: =IFERROR(__xludf.DUMMYFUNCTION("""COMPUTED_VALUE"""),"Lo | Locked") -> Lo | Locked | AM33: =IFERROR(__xludf.DUMMYFUNCTION("""COMPUTED_VALUE"""),"Coins") -> Coins | AN33: =IFERROR(__xludf.DUMMYFUNCTION("""COMPUTED_VALUE"""),0.48) -> 0.48 | AP33: =IFERROR(__xludf.DUMMYFUNCTION("""COMPUTED_VALUE"""),"Knockback Chance") -> Knockback Chance | AQ33: =IFERROR(__xludf.DUMMYFUNCTION("""COMPUTED_VALUE"""),0.0) -> 0 | BE33: =IFERROR(__xludf.DUMMYFUNCTION("""COMPUTED_VALUE"""),"") | BG33: =IFERROR(__xludf.DUMMYFUNCTION("""COMPUTED_VALUE"""),"Death Defy") -> Death Defy | BH33: =IFERROR(__xludf.DUMMYFUNCTION("""COMPUTED_VALUE"""),"Legendary") -> Legendary | BI33: =IFERROR(__xludf.DUMMYFUNCTION("""COMPUTED_VALUE"""),"+1.5%") -> +1.5% | BJ33: =IFERROR(__xludf.DUMMYFUNCTION("""COMPUTED_VALUE"""),0.015) -> 0.015 | BL33: =IFERROR(__xludf.DUMMYFUNCTION("""COMPUTED_VALUE"""),"Free Utility Upgrade") -> Free Utility Upgrade | BM33: =IFERROR(__xludf.DUMMYFUNCTION("""COMPUTED_VALUE"""),"Legendary") -> Legendary | BN33: =IFERROR(__xludf.DUMMYFUNCTION("""COMPUTED_VALUE"""),"+8%") -> +8% | BO33: =IFERROR(__xludf.DUMMYFUNCTION("""COMPUTED_VALUE"""),0.08) -> 0.08 | BQ33: =IFERROR(__xludf.DUMMYFUNCTION("""COMPUTED_VALUE"""),"Black Hole - Size") -> Black Hole - Size | BR33: =IFERROR(__xludf.DUMMYFUNCTION("""COMPUTED_VALUE"""),"Legendary") -> Legendary | BS33: =IFERROR(__xludf.DUMMYFUNCTION("""COMPUTED_VALUE"""),"+8.00m") -> +8.00m | BT33: =IFERROR(__xludf.DUMMYFUNCTION("""COMPUTED_VALUE"""),8.0) -> 8
A34: =IFERROR(__xludf.DUMMYFUNCTION("""COMPUTED_VALUE"""),"Land Mine Decay") -> Land Mine Decay | B34: =IFERROR(__xludf.DUMMYFUNCTION("""COMPUTED_VALUE"""),13.0) -> 13 | D34: =IFERROR(__xludf.DUMMYFUNCTION("""COMPUTED_VALUE"""),35.0) -> 35 | F34: =IFERROR(__xludf.DUMMYFUNCTION("""COMPUTED_VALUE"""),"Land Mine Damage") -> Land Mine Damage | G34: =IFERROR(__xludf.DUMMYFUNCTION("""COMPUTED_VALUE"""),160.0) -> 160 | H34: =IFERROR(__xludf.DUMMYFUNCTION("""COMPUTED_VALUE"""),200.0) -> 200 | I34: =IFERROR(__xludf.DUMMYFUNCTION("""COMPUTED_VALUE"""),160.0) -> 160 | J34: =IFERROR(__xludf.DUMMYFUNCTION("""COMPUTED_VALUE"""),200.0) -> 200 | Q34: =IFERROR(__xludf.DUMMYFUNCTION("""COMPUTED_VALUE"""),200.0) -> 200 | Z34: =IFERROR(__xludf.DUMMYFUNCTION("""COMPUTED_VALUE"""),"Spotlight") -> Spotlight | AB34: =IFERROR(__xludf.DUMMYFUNCTION("""COMPUTED_VALUE"""),"Multiplier") -> Multiplier | AC34: =IFERROR(__xludf.DUMMYFUNCTION("""COMPUTED_VALUE"""),20.599999999999998) -> 20.6 | AD34: =IFERROR(__xludf.DUMMYFUNCTION("""COMPUTED_VALUE"""),"09 | x20.6 | Cost 95 ⧌ | Next 112 ⧌") -> 09 | x20.6 | Cost 95 ⧌ | Next 112 ⧌ | AM34: =IFERROR(__xludf.DUMMYFUNCTION("""COMPUTED_VALUE"""),"Free Attack Upgrade") -> Free Attack Upgrade | AN34: =IFERROR(__xludf.DUMMYFUNCTION("""COMPUTED_VALUE"""),0.060000000000000005) -> 0.06 | AP34: =IFERROR(__xludf.DUMMYFUNCTION("""COMPUTED_VALUE"""),"Knockback Force") -> Knockback Force | AQ34: =IFERROR(__xludf.DUMMYFUNCTION("""COMPUTED_VALUE"""),0.0) -> 0 | BE34: =IFERROR(__xludf.DUMMYFUNCTION("""COMPUTED_VALUE"""),"") | BJ34: =IFERROR(__xludf.DUMMYFUNCTION("""COMPUTED_VALUE"""),"") | BO34: =IFERROR(__xludf.DUMMYFUNCTION("""COMPUTED_VALUE"""),"") | BQ34: =IFERROR(__xludf.DUMMYFUNCTION("""COMPUTED_VALUE"""),"Spotlight - Angle") -> Spotlight - Angle
A35: =IFERROR(__xludf.DUMMYFUNCTION("""COMPUTED_VALUE"""),"Shockwave Size") -> Shockwave Size | B35: =IFERROR(__xludf.DUMMYFUNCTION("""COMPUTED_VALUE"""),10.0) -> 10 | D35: =IFERROR(__xludf.DUMMYFUNCTION("""COMPUTED_VALUE"""),20.0) -> 20 | F35: =IFERROR(__xludf.DUMMYFUNCTION("""COMPUTED_VALUE"""),"Land Mine Radius") -> Land Mine Radius | G35: =IFERROR(__xludf.DUMMYFUNCTION("""COMPUTED_VALUE"""),50.0) -> 50 | H35: =IFERROR(__xludf.DUMMYFUNCTION("""COMPUTED_VALUE"""),50.0) -> 50 | I35: =IFERROR(__xludf.DUMMYFUNCTION("""COMPUTED_VALUE"""),50.0) -> 50 | J35: =IFERROR(__xludf.DUMMYFUNCTION("""COMPUTED_VALUE"""),50.0) -> 50 | Q35: =IFERROR(__xludf.DUMMYFUNCTION("""COMPUTED_VALUE"""),50.0) -> 50 | AB35: =IFERROR(__xludf.DUMMYFUNCTION("""COMPUTED_VALUE"""),"Angle") -> Angle | AC35: =IFERROR(__xludf.DUMMYFUNCTION("""COMPUTED_VALUE"""),39.0) -> 39 | AD35: =IFERROR(__xludf.DUMMYFUNCTION("""COMPUTED_VALUE"""),"09 | 39° | Cost 93 ⧌ | Next 104 ⧌") -> 09 | 39° | Cost 93 ⧌ | Next 104 ⧌ | AM35: =IFERROR(__xludf.DUMMYFUNCTION("""COMPUTED_VALUE"""),"Free Defense Upgrade") -> Free Defense Upgrade | AN35: =IFERROR(__xludf.DUMMYFUNCTION("""COMPUTED_VALUE"""),0.03) -> 0.03 | AP35: =IFERROR(__xludf.DUMMYFUNCTION("""COMPUTED_VALUE"""),"Orb Speed") -> Orb Speed | AQ35: =IFERROR(__xludf.DUMMYFUNCTION("""COMPUTED_VALUE"""),0.0) -> 0 | BE35: =IFERROR(__xludf.DUMMYFUNCTION("""COMPUTED_VALUE"""),"") | BJ35: =IFERROR(__xludf.DUMMYFUNCTION("""COMPUTED_VALUE"""),"") | BO35: =IFERROR(__xludf.DUMMYFUNCTION("""COMPUTED_VALUE"""),"") | BQ35: =IFERROR(__xludf.DUMMYFUNCTION("""COMPUTED_VALUE"""),"Death Wave - Quantity") -> Death Wave - Quantity
A36: =IFERROR(__xludf.DUMMYFUNCTION("""COMPUTED_VALUE"""),"Orb Boss Hit") -> Orb Boss Hit | B36: =IFERROR(__xludf.DUMMYFUNCTION("""COMPUTED_VALUE"""),10.0) -> 10 | D36: =IFERROR(__xludf.DUMMYFUNCTION("""COMPUTED_VALUE"""),10.0) -> 10 | E36: =IFERROR(__xludf.DUMMYFUNCTION("""COMPUTED_VALUE"""),TRUE) -> TRUE | F36: =IFERROR(__xludf.DUMMYFUNCTION("""COMPUTED_VALUE"""),"Death Defy") -> Death Defy | G36: =IFERROR(__xludf.DUMMYFUNCTION("""COMPUTED_VALUE"""),75.0) -> 75 | H36: =IFERROR(__xludf.DUMMYFUNCTION("""COMPUTED_VALUE"""),75.0) -> 75 | I36: =IFERROR(__xludf.DUMMYFUNCTION("""COMPUTED_VALUE"""),75.0) -> 75 | J36: =IFERROR(__xludf.DUMMYFUNCTION("""COMPUTED_VALUE"""),75.0) -> 75 | Q36: =IFERROR(__xludf.DUMMYFUNCTION("""COMPUTED_VALUE"""),75.0) -> 75 | Z36: =IFERROR(__xludf.DUMMYFUNCTION("""COMPUTED_VALUE"""),TRUE) -> TRUE | AA36: =IFERROR(__xludf.DUMMYFUNCTION("""COMPUTED_VALUE"""),"UW Unlocked") -> UW Unlocked | AB36: =IFERROR(__xludf.DUMMYFUNCTION("""COMPUTED_VALUE"""),"Quantity") -> Quantity | AC36: =IFERROR(__xludf.DUMMYFUNCTION("""COMPUTED_VALUE"""),3.0) -> 3 | AD36: =IFERROR(__xludf.DUMMYFUNCTION("""COMPUTED_VALUE"""),"02 | #3 | Cost 850 ⧌ | Next 2500 ⧌") -> 02 | #3 | Cost 850 ⧌ | Next 2500 ⧌ | AM36: =IFERROR(__xludf.DUMMYFUNCTION("""COMPUTED_VALUE"""),"Free Utility Upgrade") -> Free Utility Upgrade | AN36: =IFERROR(__xludf.DUMMYFUNCTION("""COMPUTED_VALUE"""),0.04) -> 0.04 | AP36: =IFERROR(__xludf.DUMMYFUNCTION("""COMPUTED_VALUE"""),"Orbs") -> Orbs | AQ36: =IFERROR(__xludf.DUMMYFUNCTION("""COMPUTED_VALUE"""),0.0) -> 0 | BE36: =IFERROR(__xludf.DUMMYFUNCTION("""COMPUTED_VALUE"""),"") | BJ36: =IFERROR(__xludf.DUMMYFUNCTION("""COMPUTED_VALUE"""),"") | BO36: =IFERROR(__xludf.DUMMYFUNCTION("""COMPUTED_VALUE"""),"") | BQ36: =IFERROR(__xludf.DUMMYFUNCTION("""COMPUTED_VALUE"""),"Death Wave - Cooldown") -> Death Wave - Cooldown
A37: =IFERROR(__xludf.DUMMYFUNCTION("""COMPUTED_VALUE"""),"Wall Health") -> Wall Health | B37: =IFERROR(__xludf.DUMMYFUNCTION("""COMPUTED_VALUE"""),50.0) -> 50 | D37: =IFERROR(__xludf.DUMMYFUNCTION("""COMPUTED_VALUE"""),50.0) -> 50 | E37: =IFERROR(__xludf.DUMMYFUNCTION("""COMPUTED_VALUE"""),TRUE) -> TRUE | F37: =IFERROR(__xludf.DUMMYFUNCTION("""COMPUTED_VALUE"""),"Wall Health") -> Wall Health | G37: =IFERROR(__xludf.DUMMYFUNCTION("""COMPUTED_VALUE"""),1340.0) -> 1340 | H37: =IFERROR(__xludf.DUMMYFUNCTION("""COMPUTED_VALUE"""),1800.0) -> 1800 | I37: =IFERROR(__xludf.DUMMYFUNCTION("""COMPUTED_VALUE"""),1340.0) -> 1340 | J37: =IFERROR(__xludf.DUMMYFUNCTION("""COMPUTED_VALUE"""),1800.0) -> 1800 | Q37: =IFERROR(__xludf.DUMMYFUNCTION("""COMPUTED_VALUE"""),1800.0) -> 1800 | Z37: =IFERROR(__xludf.DUMMYFUNCTION("""COMPUTED_VALUE"""),"UW+") -> UW+ | AB37: =IFERROR(__xludf.DUMMYFUNCTION("""COMPUTED_VALUE"""),"Light Range") -> Light Range | AC37: =IFERROR(__xludf.DUMMYFUNCTION("""COMPUTED_VALUE"""),"Locked") -> Locked | AD37: =IFERROR(__xludf.DUMMYFUNCTION("""COMPUTED_VALUE"""),"Lo | Locked") -> Lo | Locked | AM37: =IFERROR(__xludf.DUMMYFUNCTION("""COMPUTED_VALUE"""),"Recovery Amount") -> Recovery Amount | AN37: =IFERROR(__xludf.DUMMYFUNCTION("""COMPUTED_VALUE"""),0.11) -> 0.11 | AP37: =IFERROR(__xludf.DUMMYFUNCTION("""COMPUTED_VALUE"""),"Shockwave Frequency") -> Shockwave Frequency | AQ37: =IFERROR(__xludf.DUMMYFUNCTION("""COMPUTED_VALUE"""),0.0) -> 0 | BE37: =IFERROR(__xludf.DUMMYFUNCTION("""COMPUTED_VALUE"""),"") | BJ37: =IFERROR(__xludf.DUMMYFUNCTION("""COMPUTED_VALUE"""),"") | BO37: =IFERROR(__xludf.DUMMYFUNCTION("""COMPUTED_VALUE"""),"") | BQ37: =IFERROR(__xludf.DUMMYFUNCTION("""COMPUTED_VALUE"""),"Golden Tower - Bonus") -> Golden Tower - Bonus
A38: =IFERROR(__xludf.DUMMYFUNCTION("""COMPUTED_VALUE"""),"Wall Rebuild") -> Wall Rebuild | B38: =IFERROR(__xludf.DUMMYFUNCTION("""COMPUTED_VALUE"""),9.0) -> 9 | D38: =IFERROR(__xludf.DUMMYFUNCTION("""COMPUTED_VALUE"""),20.0) -> 20 | F38: =IFERROR(__xludf.DUMMYFUNCTION("""COMPUTED_VALUE"""),"Wall Rebuild") -> Wall Rebuild | G38: =IFERROR(__xludf.DUMMYFUNCTION("""COMPUTED_VALUE"""),250.0) -> 250 | H38: =IFERROR(__xludf.DUMMYFUNCTION("""COMPUTED_VALUE"""),300.0) -> 300 | I38: =IFERROR(__xludf.DUMMYFUNCTION("""COMPUTED_VALUE"""),250.0) -> 250 | J38: =IFERROR(__xludf.DUMMYFUNCTION("""COMPUTED_VALUE"""),300.0) -> 300 | Q38: =IFERROR(__xludf.DUMMYFUNCTION("""COMPUTED_VALUE"""),300.0) -> 300 | AM38: =IFERROR(__xludf.DUMMYFUNCTION("""COMPUTED_VALUE"""),"Enemy Attack Level Skip") -> Enemy Attack Level Skip | AN38: =IFERROR(__xludf.DUMMYFUNCTION("""COMPUTED_VALUE"""),0.02) -> 0.02 | AP38: =IFERROR(__xludf.DUMMYFUNCTION("""COMPUTED_VALUE"""),"Death Defy") -> Death Defy | AQ38: =IFERROR(__xludf.DUMMYFUNCTION("""COMPUTED_VALUE"""),0.0) -> 0 | BE38: =IFERROR(__xludf.DUMMYFUNCTION("""COMPUTED_VALUE"""),"") | BJ38: =IFERROR(__xludf.DUMMYFUNCTION("""COMPUTED_VALUE"""),"") | BO38: =IFERROR(__xludf.DUMMYFUNCTION("""COMPUTED_VALUE"""),"") | BQ38: =IFERROR(__xludf.DUMMYFUNCTION("""COMPUTED_VALUE"""),"Death Wave - Damage") -> Death Wave - Damage | BR38: =IFERROR(__xludf.DUMMYFUNCTION("""COMPUTED_VALUE"""),"Common") -> Common | BS38: =IFERROR(__xludf.DUMMYFUNCTION("""COMPUTED_VALUE"""),"+8x") -> +8x | BT38: =IFERROR(__xludf.DUMMYFUNCTION("""COMPUTED_VALUE"""),8.0) -> 8
A39: =IFERROR(__xludf.DUMMYFUNCTION("""COMPUTED_VALUE"""),"Wall Regen") -> Wall Regen | B39: =IFERROR(__xludf.DUMMYFUNCTION("""COMPUTED_VALUE"""),21.0) -> 21 | D39: =IFERROR(__xludf.DUMMYFUNCTION("""COMPUTED_VALUE"""),30.0) -> 30 | E39: =IFERROR(__xludf.DUMMYFUNCTION("""COMPUTED_VALUE"""),TRUE) -> TRUE | F39: =IFERROR(__xludf.DUMMYFUNCTION("""COMPUTED_VALUE"""),"Cash Bonus") -> Cash Bonus | G39: =IFERROR(__xludf.DUMMYFUNCTION("""COMPUTED_VALUE"""),149.0) -> 149 | H39: =IFERROR(__xludf.DUMMYFUNCTION("""COMPUTED_VALUE"""),149.0) -> 149 | I39: =IFERROR(__xludf.DUMMYFUNCTION("""COMPUTED_VALUE"""),149.0) -> 149 | J39: =IFERROR(__xludf.DUMMYFUNCTION("""COMPUTED_VALUE"""),149.0) -> 149 | Q39: =IFERROR(__xludf.DUMMYFUNCTION("""COMPUTED_VALUE"""),149.0) -> 149 | AM39: =IFERROR(__xludf.DUMMYFUNCTION("""COMPUTED_VALUE"""),"Enemy Health Level Skip") -> Enemy Health Level Skip | AN39: =IFERROR(__xludf.DUMMYFUNCTION("""COMPUTED_VALUE"""),0.02) -> 0.02 | AP39: =IFERROR(__xludf.DUMMYFUNCTION("""COMPUTED_VALUE"""),"Wall Rebuild") -> Wall Rebuild | AQ39: =IFERROR(__xludf.DUMMYFUNCTION("""COMPUTED_VALUE"""),0.0) -> 0
A40: =IFERROR(__xludf.DUMMYFUNCTION("""COMPUTED_VALUE"""),"Wall Thorns") -> Wall Thorns | B40: =IFERROR(__xludf.DUMMYFUNCTION("""COMPUTED_VALUE"""),15.0) -> 15 | D40: =IFERROR(__xludf.DUMMYFUNCTION("""COMPUTED_VALUE"""),20.0) -> 20 | F40: =IFERROR(__xludf.DUMMYFUNCTION("""COMPUTED_VALUE"""),"Cash / Wave") -> Cash / Wave | G40: =IFERROR(__xludf.DUMMYFUNCTION("""COMPUTED_VALUE"""),149.0) -> 149 | H40: =IFERROR(__xludf.DUMMYFUNCTION("""COMPUTED_VALUE"""),149.0) -> 149 | I40: =IFERROR(__xludf.DUMMYFUNCTION("""COMPUTED_VALUE"""),149.0) -> 149 | J40: =IFERROR(__xludf.DUMMYFUNCTION("""COMPUTED_VALUE"""),149.0) -> 149 | Q40: =IFERROR(__xludf.DUMMYFUNCTION("""COMPUTED_VALUE"""),149.0) -> 149 | AP40: =IFERROR(__xludf.DUMMYFUNCTION("""COMPUTED_VALUE"""),"Utility") -> Utility | BB40: =IFERROR(__xludf.DUMMYFUNCTION("""COMPUTED_VALUE"""),"Being Annihilator") -> Being Annihilator | BG40: =IFERROR(__xludf.DUMMYFUNCTION("""COMPUTED_VALUE"""),"Negative Mass Projector") -> Negative Mass Projector | BL40: =IFERROR(__xludf.DUMMYFUNCTION("""COMPUTED_VALUE"""),"Galaxy Compressor") -> Galaxy Compressor | BQ40: =IFERROR(__xludf.DUMMYFUNCTION("""COMPUTED_VALUE"""),"Dimension Core") -> Dimension Core
A41: =IFERROR(__xludf.DUMMYFUNCTION("""COMPUTED_VALUE"""),"Wall Invincibility") -> Wall Invincibility | B41: =IFERROR(__xludf.DUMMYFUNCTION("""COMPUTED_VALUE"""),0.0) -> 0 | D41: =IFERROR(__xludf.DUMMYFUNCTION("""COMPUTED_VALUE"""),10.0) -> 10 | E41: =IFERROR(__xludf.DUMMYFUNCTION("""COMPUTED_VALUE"""),TRUE) -> TRUE | F41: =IFERROR(__xludf.DUMMYFUNCTION("""COMPUTED_VALUE"""),"Coin / Kill Bonus") -> Coin / Kill Bonus | G41: =IFERROR(__xludf.DUMMYFUNCTION("""COMPUTED_VALUE"""),149.0) -> 149 | H41: =IFERROR(__xludf.DUMMYFUNCTION("""COMPUTED_VALUE"""),149.0) -> 149 | I41: =IFERROR(__xludf.DUMMYFUNCTION("""COMPUTED_VALUE"""),149.0) -> 149 | J41: =IFERROR(__xludf.DUMMYFUNCTION("""COMPUTED_VALUE"""),149.0) -> 149 | Q41: =IFERROR(__xludf.DUMMYFUNCTION("""COMPUTED_VALUE"""),149.0) -> 149 | AP41: =IFERROR(__xludf.DUMMYFUNCTION("""COMPUTED_VALUE"""),"Cash") -> Cash | AQ41: =IFERROR(__xludf.DUMMYFUNCTION("""COMPUTED_VALUE"""),0.0) -> 0 | BB41: =IFERROR(__xludf.DUMMYFUNCTION("""COMPUTED_VALUE"""),"Rarity") -> Rarity | BC41: =IFERROR(__xludf.DUMMYFUNCTION("""COMPUTED_VALUE"""),"Level") -> Level | BD41: =IFERROR(__xludf.DUMMYFUNCTION("""COMPUTED_VALUE"""),"Stat") -> Stat | BG41: =IFERROR(__xludf.DUMMYFUNCTION("""COMPUTED_VALUE"""),"Rarity") -> Rarity | BH41: =IFERROR(__xludf.DUMMYFUNCTION("""COMPUTED_VALUE"""),"Level") -> Level | BI41: =IFERROR(__xludf.DUMMYFUNCTION("""COMPUTED_VALUE"""),"Stat") -> Stat | BL41: =IFERROR(__xludf.DUMMYFUNCTION("""COMPUTED_VALUE"""),"Rarity") -> Rarity | BM41: =IFERROR(__xludf.DUMMYFUNCTION("""COMPUTED_VALUE"""),"Level") -> Level | BN41: =IFERROR(__xludf.DUMMYFUNCTION("""COMPUTED_VALUE"""),"Stat") -> Stat | BQ41: =IFERROR(__xludf.DUMMYFUNCTION("""COMPUTED_VALUE"""),"Rarity") -> Rarity | BR41: =IFERROR(__xludf.DUMMYFUNCTION("""COMPUTED_VALUE"""),"Level") -> Level | BS41: =IFERROR(__xludf.DUMMYFUNCTION("""COMPUTED_VALUE"""),"Stat") -> Stat
A42: =IFERROR(__xludf.DUMMYFUNCTION("""COMPUTED_VALUE"""),"Wall Fortification") -> Wall Fortification | B42: =IFERROR(__xludf.DUMMYFUNCTION("""COMPUTED_VALUE"""),47.0) -> 47 | D42: =IFERROR(__xludf.DUMMYFUNCTION("""COMPUTED_VALUE"""),60.0) -> 60 | F42: =IFERROR(__xludf.DUMMYFUNCTION("""COMPUTED_VALUE"""),"Coin / Wave") -> Coin / Wave | G42: =IFERROR(__xludf.DUMMYFUNCTION("""COMPUTED_VALUE"""),149.0) -> 149 | H42: =IFERROR(__xludf.DUMMYFUNCTION("""COMPUTED_VALUE"""),149.0) -> 149 | I42: =IFERROR(__xludf.DUMMYFUNCTION("""COMPUTED_VALUE"""),149.0) -> 149 | J42: =IFERROR(__xludf.DUMMYFUNCTION("""COMPUTED_VALUE"""),149.0) -> 149 | Q42: =IFERROR(__xludf.DUMMYFUNCTION("""COMPUTED_VALUE"""),149.0) -> 149 | AP42: =IFERROR(__xludf.DUMMYFUNCTION("""COMPUTED_VALUE"""),"Cash / Wave") -> Cash / Wave | AQ42: =IFERROR(__xludf.DUMMYFUNCTION("""COMPUTED_VALUE"""),0.0) -> 0 | BB42: =IFERROR(__xludf.DUMMYFUNCTION("""COMPUTED_VALUE"""),"Ancestral") -> Ancestral | BC42: =IFERROR(__xludf.DUMMYFUNCTION("""COMPUTED_VALUE"""),164.0) -> 164 | BD42: =IFERROR(__xludf.DUMMYFUNCTION("""COMPUTED_VALUE"""),9.04) -> 9.04 | BG42: =IFERROR(__xludf.DUMMYFUNCTION("""COMPUTED_VALUE"""),"Legendary") -> Legendary | BH42: =IFERROR(__xludf.DUMMYFUNCTION("""COMPUTED_VALUE"""),100.0) -> 100 | BI42: =IFERROR(__xludf.DUMMYFUNCTION("""COMPUTED_VALUE"""),2.27) -> 2.27 | BL42: =IFERROR(__xludf.DUMMYFUNCTION("""COMPUTED_VALUE"""),"Mythic+") -> Mythic+ | BM42: =IFERROR(__xludf.DUMMYFUNCTION("""COMPUTED_VALUE"""),160.0) -> 160 | BN42: =IFERROR(__xludf.DUMMYFUNCTION("""COMPUTED_VALUE"""),1.665) -> 1.665 | BQ42: =IFERROR(__xludf.DUMMYFUNCTION("""COMPUTED_VALUE"""),"Ancestral") -> Ancestral | BR42: =IFERROR(__xludf.DUMMYFUNCTION("""COMPUTED_VALUE"""),159.0) -> 159 | BS42: =IFERROR(__xludf.DUMMYFUNCTION("""COMPUTED_VALUE"""),10.9) -> 10.9
A43: =IFERROR(__xludf.DUMMYFUNCTION("""COMPUTED_VALUE"""),"Garlic Thorns") -> Garlic Thorns | B43: =IFERROR(__xludf.DUMMYFUNCTION("""COMPUTED_VALUE"""),10.0) -> 10 | D43: =IFERROR(__xludf.DUMMYFUNCTION("""COMPUTED_VALUE"""),10.0) -> 10 | E43: =IFERROR(__xludf.DUMMYFUNCTION("""COMPUTED_VALUE"""),TRUE) -> TRUE | F43: =IFERROR(__xludf.DUMMYFUNCTION("""COMPUTED_VALUE"""),"Free Attack Upgrade") -> Free Attack Upgrade | G43: =IFERROR(__xludf.DUMMYFUNCTION("""COMPUTED_VALUE"""),99.0) -> 99 | H43: =IFERROR(__xludf.DUMMYFUNCTION("""COMPUTED_VALUE"""),99.0) -> 99 | I43: =IFERROR(__xludf.DUMMYFUNCTION("""COMPUTED_VALUE"""),99.0) -> 99 | J43: =IFERROR(__xludf.DUMMYFUNCTION("""COMPUTED_VALUE"""),99.0) -> 99 | Q43: =IFERROR(__xludf.DUMMYFUNCTION("""COMPUTED_VALUE"""),99.0) -> 99 | AP43: =IFERROR(__xludf.DUMMYFUNCTION("""COMPUTED_VALUE"""),"Coins / Kill") -> Coins / Kill | AQ43: =IFERROR(__xludf.DUMMYFUNCTION("""COMPUTED_VALUE"""),0.0) -> 0
A44: =IFERROR(__xludf.DUMMYFUNCTION("""COMPUTED_VALUE"""),"Cash Bonus") -> Cash Bonus | B44: =IFERROR(__xludf.DUMMYFUNCTION("""COMPUTED_VALUE"""),33.0) -> 33 | D44: =IFERROR(__xludf.DUMMYFUNCTION("""COMPUTED_VALUE"""),99.0) -> 99 | F44: =IFERROR(__xludf.DUMMYFUNCTION("""COMPUTED_VALUE"""),"Free Defense Upgrade") -> Free Defense Upgrade | G44: =IFERROR(__xludf.DUMMYFUNCTION("""COMPUTED_VALUE"""),99.0) -> 99 | H44: =IFERROR(__xludf.DUMMYFUNCTION("""COMPUTED_VALUE"""),99.0) -> 99 | I44: =IFERROR(__xludf.DUMMYFUNCTION("""COMPUTED_VALUE"""),99.0) -> 99 | J44: =IFERROR(__xludf.DUMMYFUNCTION("""COMPUTED_VALUE"""),99.0) -> 99 | Q44: =IFERROR(__xludf.DUMMYFUNCTION("""COMPUTED_VALUE"""),99.0) -> 99 | AP44: =IFERROR(__xludf.DUMMYFUNCTION("""COMPUTED_VALUE"""),"Coins / Wave") -> Coins / Wave | AQ44: =IFERROR(__xludf.DUMMYFUNCTION("""COMPUTED_VALUE"""),0.0) -> 0 | BB44: =IFERROR(__xludf.DUMMYFUNCTION("""COMPUTED_VALUE"""),"Attack Speed") -> Attack Speed | BC44: =IFERROR(__xludf.DUMMYFUNCTION("""COMPUTED_VALUE"""),"Mythic") -> Mythic | BD44: =IFERROR(__xludf.DUMMYFUNCTION("""COMPUTED_VALUE"""),"+3") -> +3 | BE44: =IFERROR(__xludf.DUMMYFUNCTION("""COMPUTED_VALUE"""),3.0) -> 3 | BJ44: =IFERROR(__xludf.DUMMYFUNCTION("""COMPUTED_VALUE"""),"") | BL44: =IFERROR(__xludf.DUMMYFUNCTION("""COMPUTED_VALUE"""),"Package Chance") -> Package Chance | BM44: =IFERROR(__xludf.DUMMYFUNCTION("""COMPUTED_VALUE"""),"Legendary") -> Legendary | BN44: =IFERROR(__xludf.DUMMYFUNCTION("""COMPUTED_VALUE"""),"+8%") -> +8% | BO44: =IFERROR(__xludf.DUMMYFUNCTION("""COMPUTED_VALUE"""),0.08) -> 0.08 | BQ44: =IFERROR(__xludf.DUMMYFUNCTION("""COMPUTED_VALUE"""),"Chain Lightning - Chance") -> Chain Lightning - Chance | BR44: =IFERROR(__xludf.DUMMYFUNCTION("""COMPUTED_VALUE"""),"Mythic") -> Mythic | BS44: =IFERROR(__xludf.DUMMYFUNCTION("""COMPUTED_VALUE"""),"+12%") -> +12% | BT44: =IFERROR(__xludf.DUMMYFUNCTION("""COMPUTED_VALUE"""),0.12) -> 0.12
A45: =IFERROR(__xludf.DUMMYFUNCTION("""COMPUTED_VALUE"""),"Cash / Wave") -> Cash / Wave | B45: =IFERROR(__xludf.DUMMYFUNCTION("""COMPUTED_VALUE"""),8.0) -> 8 | D45: =IFERROR(__xludf.DUMMYFUNCTION("""COMPUTED_VALUE"""),99.0) -> 99 | F45: =IFERROR(__xludf.DUMMYFUNCTION("""COMPUTED_VALUE"""),"Free Utility Upgrade") -> Free Utility Upgrade | G45: =IFERROR(__xludf.DUMMYFUNCTION("""COMPUTED_VALUE"""),99.0) -> 99 | H45: =IFERROR(__xludf.DUMMYFUNCTION("""COMPUTED_VALUE"""),99.0) -> 99 | I45: =IFERROR(__xludf.DUMMYFUNCTION("""COMPUTED_VALUE"""),99.0) -> 99 | J45: =IFERROR(__xludf.DUMMYFUNCTION("""COMPUTED_VALUE"""),99.0) -> 99 | Q45: =IFERROR(__xludf.DUMMYFUNCTION("""COMPUTED_VALUE"""),99.0) -> 99 | AP45: =IFERROR(__xludf.DUMMYFUNCTION("""COMPUTED_VALUE"""),"Free Attack Upgrade") -> Free Attack Upgrade | AQ45: =IFERROR(__xludf.DUMMYFUNCTION("""COMPUTED_VALUE"""),0.0) -> 0 | BB45: =IFERROR(__xludf.DUMMYFUNCTION("""COMPUTED_VALUE"""),"Multishot Targets") -> Multishot Targets | BC45: =IFERROR(__xludf.DUMMYFUNCTION("""COMPUTED_VALUE"""),"Mythic") -> Mythic | BD45: =IFERROR(__xludf.DUMMYFUNCTION("""COMPUTED_VALUE"""),"+3") -> +3 | BE45: =IFERROR(__xludf.DUMMYFUNCTION("""COMPUTED_VALUE"""),3.0) -> 3 | BJ45: =IFERROR(__xludf.DUMMYFUNCTION("""COMPUTED_VALUE"""),"") | BL45: =IFERROR(__xludf.DUMMYFUNCTION("""COMPUTED_VALUE"""),"Enemy Attack Level Skip") -> Enemy Attack Level Skip | BM45: =IFERROR(__xludf.DUMMYFUNCTION("""COMPUTED_VALUE"""),"Legendary") -> Legendary | BN45: =IFERROR(__xludf.DUMMYFUNCTION("""COMPUTED_VALUE"""),"+4%") -> +4% | BO45: =IFERROR(__xludf.DUMMYFUNCTION("""COMPUTED_VALUE"""),0.04) -> 0.04 | BQ45: =IFERROR(__xludf.DUMMYFUNCTION("""COMPUTED_VALUE"""),"Spotlight - Angle") -> Spotlight - Angle | BR45: =IFERROR(__xludf.DUMMYFUNCTION("""COMPUTED_VALUE"""),"Mythic") -> Mythic | BS45: =IFERROR(__xludf.DUMMYFUNCTION("""COMPUTED_VALUE"""),"+11°") -> +11° | BT45: =IFERROR(__xludf.DUMMYFUNCTION("""COMPUTED_VALUE"""),11.0) -> 11
A46: =IFERROR(__xludf.DUMMYFUNCTION("""COMPUTED_VALUE"""),"Coins / Kill Bonus") -> Coins / Kill Bonus | B46: =IFERROR(__xludf.DUMMYFUNCTION("""COMPUTED_VALUE"""),87.0) -> 87 | D46: =IFERROR(__xludf.DUMMYFUNCTION("""COMPUTED_VALUE"""),99.0) -> 99 | E46: =IFERROR(__xludf.DUMMYFUNCTION("""COMPUTED_VALUE"""),TRUE) -> TRUE | F46: =IFERROR(__xludf.DUMMYFUNCTION("""COMPUTED_VALUE"""),"Interest / Wave") -> Interest / Wave | G46: =IFERROR(__xludf.DUMMYFUNCTION("""COMPUTED_VALUE"""),99.0) -> 99 | H46: =IFERROR(__xludf.DUMMYFUNCTION("""COMPUTED_VALUE"""),99.0) -> 99 | I46: =IFERROR(__xludf.DUMMYFUNCTION("""COMPUTED_VALUE"""),99.0) -> 99 | J46: =IFERROR(__xludf.DUMMYFUNCTION("""COMPUTED_VALUE"""),99.0) -> 99 | Q46: =IFERROR(__xludf.DUMMYFUNCTION("""COMPUTED_VALUE"""),99.0) -> 99 | AP46: =IFERROR(__xludf.DUMMYFUNCTION("""COMPUTED_VALUE"""),"Free Defense Upgrade") -> Free Defense Upgrade | AQ46: =IFERROR(__xludf.DUMMYFUNCTION("""COMPUTED_VALUE"""),0.0) -> 0 | BB46: =IFERROR(__xludf.DUMMYFUNCTION("""COMPUTED_VALUE"""),"Critical Factor") -> Critical Factor | BC46: =IFERROR(__xludf.DUMMYFUNCTION("""COMPUTED_VALUE"""),"Mythic") -> Mythic | BD46: =IFERROR(__xludf.DUMMYFUNCTION("""COMPUTED_VALUE"""),"+12x") -> +12x | BE46: =IFERROR(__xludf.DUMMYFUNCTION("""COMPUTED_VALUE"""),12.0) -> 12 | BJ46: =IFERROR(__xludf.DUMMYFUNCTION("""COMPUTED_VALUE"""),"") | BL46: =IFERROR(__xludf.DUMMYFUNCTION("""COMPUTED_VALUE"""),"Free Utility Upgrade") -> Free Utility Upgrade | BM46: =IFERROR(__xludf.DUMMYFUNCTION("""COMPUTED_VALUE"""),"Legendary") -> Legendary | BN46: =IFERROR(__xludf.DUMMYFUNCTION("""COMPUTED_VALUE"""),"+8%") -> +8% | BO46: =IFERROR(__xludf.DUMMYFUNCTION("""COMPUTED_VALUE"""),0.08) -> 0.08 | BQ46: =IFERROR(__xludf.DUMMYFUNCTION("""COMPUTED_VALUE"""),"Spotlight - Bonus") -> Spotlight - Bonus | BR46: =IFERROR(__xludf.DUMMYFUNCTION("""COMPUTED_VALUE"""),"Mythic") -> Mythic | BS46: =IFERROR(__xludf.DUMMYFUNCTION("""COMPUTED_VALUE"""),"+15x") -> +15x | BT46: =IFERROR(__xludf.DUMMYFUNCTION("""COMPUTED_VALUE"""),15.0) -> 15
A47: =IFERROR(__xludf.DUMMYFUNCTION("""COMPUTED_VALUE"""),"Coins / Wave") -> Coins / Wave | B47: =IFERROR(__xludf.DUMMYFUNCTION("""COMPUTED_VALUE"""),6.0) -> 6 | D47: =IFERROR(__xludf.DUMMYFUNCTION("""COMPUTED_VALUE"""),99.0) -> 99 | E47: =IFERROR(__xludf.DUMMYFUNCTION("""COMPUTED_VALUE"""),TRUE) -> TRUE | F47: =IFERROR(__xludf.DUMMYFUNCTION("""COMPUTED_VALUE"""),"Recovery Amount") -> Recovery Amount | G47: =IFERROR(__xludf.DUMMYFUNCTION("""COMPUTED_VALUE"""),300.0) -> 300 | H47: =IFERROR(__xludf.DUMMYFUNCTION("""COMPUTED_VALUE"""),300.0) -> 300 | I47: =IFERROR(__xludf.DUMMYFUNCTION("""COMPUTED_VALUE"""),300.0) -> 300 | J47: =IFERROR(__xludf.DUMMYFUNCTION("""COMPUTED_VALUE"""),300.0) -> 300 | Q47: =IFERROR(__xludf.DUMMYFUNCTION("""COMPUTED_VALUE"""),300.0) -> 300 | AP47: =IFERROR(__xludf.DUMMYFUNCTION("""COMPUTED_VALUE"""),"Free Utility Upgrade") -> Free Utility Upgrade | AQ47: =IFERROR(__xludf.DUMMYFUNCTION("""COMPUTED_VALUE"""),0.0) -> 0 | BB47: =IFERROR(__xludf.DUMMYFUNCTION("""COMPUTED_VALUE"""),"Bounce Shot Chance") -> Bounce Shot Chance | BC47: =IFERROR(__xludf.DUMMYFUNCTION("""COMPUTED_VALUE"""),"Mythic") -> Mythic | BD47: =IFERROR(__xludf.DUMMYFUNCTION("""COMPUTED_VALUE"""),"+9%") -> +9% | BE47: =IFERROR(__xludf.DUMMYFUNCTION("""COMPUTED_VALUE"""),0.09) -> 0.09 | BJ47: =IFERROR(__xludf.DUMMYFUNCTION("""COMPUTED_VALUE"""),"") | BO47: =IFERROR(__xludf.DUMMYFUNCTION("""COMPUTED_VALUE"""),"") | BQ47: =IFERROR(__xludf.DUMMYFUNCTION("""COMPUTED_VALUE"""),"Chain Lightning - Quantity") -> Chain Lightning - Quantity | BR47: =IFERROR(__xludf.DUMMYFUNCTION("""COMPUTED_VALUE"""),"Mythic") -> Mythic | BS47: =IFERROR(__xludf.DUMMYFUNCTION("""COMPUTED_VALUE"""),"+3") -> +3 | BT47: =IFERROR(__xludf.DUMMYFUNCTION("""COMPUTED_VALUE"""),3.0) -> 3
A48: =IFERROR(__xludf.DUMMYFUNCTION("""COMPUTED_VALUE"""),"Interest") -> Interest | B48: =IFERROR(__xludf.DUMMYFUNCTION("""COMPUTED_VALUE"""),11.0) -> 11 | D48: =IFERROR(__xludf.DUMMYFUNCTION("""COMPUTED_VALUE"""),99.0) -> 99 | F48: =IFERROR(__xludf.DUMMYFUNCTION("""COMPUTED_VALUE"""),"Max Amount") -> Max Amount | G48: =IFERROR(__xludf.DUMMYFUNCTION("""COMPUTED_VALUE"""),300.0) -> 300 | H48: =IFERROR(__xludf.DUMMYFUNCTION("""COMPUTED_VALUE"""),500.0) -> 500 | I48: =IFERROR(__xludf.DUMMYFUNCTION("""COMPUTED_VALUE"""),300.0) -> 300 | J48: =IFERROR(__xludf.DUMMYFUNCTION("""COMPUTED_VALUE"""),500.0) -> 500 | Q48: =IFERROR(__xludf.DUMMYFUNCTION("""COMPUTED_VALUE"""),500.0) -> 500 | AP48: =IFERROR(__xludf.DUMMYFUNCTION("""COMPUTED_VALUE"""),"Interest / Wave") -> Interest / Wave | AQ48: =IFERROR(__xludf.DUMMYFUNCTION("""COMPUTED_VALUE"""),0.0) -> 0 | BE48: =IFERROR(__xludf.DUMMYFUNCTION("""COMPUTED_VALUE"""),"") | BJ48: =IFERROR(__xludf.DUMMYFUNCTION("""COMPUTED_VALUE"""),"") | BO48: =IFERROR(__xludf.DUMMYFUNCTION("""COMPUTED_VALUE"""),"") | BQ48: =IFERROR(__xludf.DUMMYFUNCTION("""COMPUTED_VALUE"""),"Chain Lightning - Damage") -> Chain Lightning - Damage | BR48: =IFERROR(__xludf.DUMMYFUNCTION("""COMPUTED_VALUE"""),"Legendary") -> Legendary | BS48: =IFERROR(__xludf.DUMMYFUNCTION("""COMPUTED_VALUE"""),"+50x") -> +50x | BT48: =IFERROR(__xludf.DUMMYFUNCTION("""COMPUTED_VALUE"""),50.0) -> 50
A49: =IFERROR(__xludf.DUMMYFUNCTION("""COMPUTED_VALUE"""),"Max Interest") -> Max Interest | B49: =IFERROR(__xludf.DUMMYFUNCTION("""COMPUTED_VALUE"""),8.0) -> 8 | D49: =IFERROR(__xludf.DUMMYFUNCTION("""COMPUTED_VALUE"""),15.0) -> 15 | F49: =IFERROR(__xludf.DUMMYFUNCTION("""COMPUTED_VALUE"""),"Package Chance") -> Package Chance | G49: =IFERROR(__xludf.DUMMYFUNCTION("""COMPUTED_VALUE"""),60.0) -> 60 | H49: =IFERROR(__xludf.DUMMYFUNCTION("""COMPUTED_VALUE"""),60.0) -> 60 | I49: =IFERROR(__xludf.DUMMYFUNCTION("""COMPUTED_VALUE"""),60.0) -> 60 | J49: =IFERROR(__xludf.DUMMYFUNCTION("""COMPUTED_VALUE"""),60.0) -> 60 | Q49: =IFERROR(__xludf.DUMMYFUNCTION("""COMPUTED_VALUE"""),60.0) -> 60 | AP49: =IFERROR(__xludf.DUMMYFUNCTION("""COMPUTED_VALUE"""),"Recovery Amount") -> Recovery Amount | AQ49: =IFERROR(__xludf.DUMMYFUNCTION("""COMPUTED_VALUE"""),0.0) -> 0 | BE49: =IFERROR(__xludf.DUMMYFUNCTION("""COMPUTED_VALUE"""),"") | BJ49: =IFERROR(__xludf.DUMMYFUNCTION("""COMPUTED_VALUE"""),"") | BO49: =IFERROR(__xludf.DUMMYFUNCTION("""COMPUTED_VALUE"""),"") | BQ49: =IFERROR(__xludf.DUMMYFUNCTION("""COMPUTED_VALUE"""),"Chrono Field - Cooldown") -> Chrono Field - Cooldown
A50: =IFERROR(__xludf.DUMMYFUNCTION("""COMPUTED_VALUE"""),"Package After Boss") -> Package After Boss | B50: =IFERROR(__xludf.DUMMYFUNCTION("""COMPUTED_VALUE"""),1.0) -> 1 | D50: =IFERROR(__xludf.DUMMYFUNCTION("""COMPUTED_VALUE"""),1.0) -> 1 | E50: =IFERROR(__xludf.DUMMYFUNCTION("""COMPUTED_VALUE"""),TRUE) -> TRUE | F50: =IFERROR(__xludf.DUMMYFUNCTION("""COMPUTED_VALUE"""),"Enemy Attack Level Skip") -> Enemy Attack Level Skip | G50: =IFERROR(__xludf.DUMMYFUNCTION("""COMPUTED_VALUE"""),330.0) -> 330 | H50: =IFERROR(__xludf.DUMMYFUNCTION("""COMPUTED_VALUE"""),699.0) -> 699 | I50: =IFERROR(__xludf.DUMMYFUNCTION("""COMPUTED_VALUE"""),330.0) -> 330 | J50: =IFERROR(__xludf.DUMMYFUNCTION("""COMPUTED_VALUE"""),699.0) -> 699 | Q50: =IFERROR(__xludf.DUMMYFUNCTION("""COMPUTED_VALUE"""),699.0) -> 699 | AP50: =IFERROR(__xludf.DUMMYFUNCTION("""COMPUTED_VALUE"""),"Max Recovery") -> Max Recovery | AQ50: =IFERROR(__xludf.DUMMYFUNCTION("""COMPUTED_VALUE"""),0.0) -> 0 | BE50: =IFERROR(__xludf.DUMMYFUNCTION("""COMPUTED_VALUE"""),"") | BJ50: =IFERROR(__xludf.DUMMYFUNCTION("""COMPUTED_VALUE"""),"") | BO50: =IFERROR(__xludf.DUMMYFUNCTION("""COMPUTED_VALUE"""),"") | BQ50: =IFERROR(__xludf.DUMMYFUNCTION("""COMPUTED_VALUE"""),"Chrono Field - Speed Reduction") -> Chrono Field - Speed Reduction
A51: =IFERROR(__xludf.DUMMYFUNCTION("""COMPUTED_VALUE"""),"Recovery Package Amount") -> Recovery Package Amount | B51: =IFERROR(__xludf.DUMMYFUNCTION("""COMPUTED_VALUE"""),0.0) -> 0 | D51: =IFERROR(__xludf.DUMMYFUNCTION("""COMPUTED_VALUE"""),20.0) -> 20 | F51: =IFERROR(__xludf.DUMMYFUNCTION("""COMPUTED_VALUE"""),"Enemy Health Level Skip") -> Enemy Health Level Skip | G51: =IFERROR(__xludf.DUMMYFUNCTION("""COMPUTED_VALUE"""),320.0) -> 320 | H51: =IFERROR(__xludf.DUMMYFUNCTION("""COMPUTED_VALUE"""),699.0) -> 699 | I51: =IFERROR(__xludf.DUMMYFUNCTION("""COMPUTED_VALUE"""),320.0) -> 320 | J51: =IFERROR(__xludf.DUMMYFUNCTION("""COMPUTED_VALUE"""),699.0) -> 699 | Q51: =IFERROR(__xludf.DUMMYFUNCTION("""COMPUTED_VALUE"""),699.0) -> 699 | AP51: =IFERROR(__xludf.DUMMYFUNCTION("""COMPUTED_VALUE"""),"Enemy Attack Skip") -> Enemy Attack Skip | AQ51: =IFERROR(__xludf.DUMMYFUNCTION("""COMPUTED_VALUE"""),0.0) -> 0 | BE51: =IFERROR(__xludf.DUMMYFUNCTION("""COMPUTED_VALUE"""),"") | BJ51: =IFERROR(__xludf.DUMMYFUNCTION("""COMPUTED_VALUE"""),"") | BO51: =IFERROR(__xludf.DUMMYFUNCTION("""COMPUTED_VALUE"""),"") | BT51: =IFERROR(__xludf.DUMMYFUNCTION("""COMPUTED_VALUE"""),"")
A52: =IFERROR(__xludf.DUMMYFUNCTION("""COMPUTED_VALUE"""),"Recovery Package Max") -> Recovery Package Max | B52: =IFERROR(__xludf.DUMMYFUNCTION("""COMPUTED_VALUE"""),0.0) -> 0 | D52: =IFERROR(__xludf.DUMMYFUNCTION("""COMPUTED_VALUE"""),20.0) -> 20 | AP52: =IFERROR(__xludf.DUMMYFUNCTION("""COMPUTED_VALUE"""),"Enemy Health Skip") -> Enemy Health Skip | AQ52: =IFERROR(__xludf.DUMMYFUNCTION("""COMPUTED_VALUE"""),0.0) -> 0
A53: =IFERROR(__xludf.DUMMYFUNCTION("""COMPUTED_VALUE"""),"Recovery Package Chance") -> Recovery Package Chance | B53: =IFERROR(__xludf.DUMMYFUNCTION("""COMPUTED_VALUE"""),20.0) -> 20 | D53: =IFERROR(__xludf.DUMMYFUNCTION("""COMPUTED_VALUE"""),20.0) -> 20 | AP53: =IFERROR(__xludf.DUMMYFUNCTION("""COMPUTED_VALUE"""),"Unlocks") -> Unlocks | BB53: =IFERROR(__xludf.DUMMYFUNCTION("""COMPUTED_VALUE"""),"Death Penalty") -> Death Penalty | BG53: =IFERROR(__xludf.DUMMYFUNCTION("""COMPUTED_VALUE"""),"Space Displacer") -> Space Displacer | BL53: =IFERROR(__xludf.DUMMYFUNCTION("""COMPUTED_VALUE"""),"Singularity Harness") -> Singularity Harness | BQ53: =IFERROR(__xludf.DUMMYFUNCTION("""COMPUTED_VALUE"""),"Harmony Conductor") -> Harmony Conductor
A54: =IFERROR(__xludf.DUMMYFUNCTION("""COMPUTED_VALUE"""),"Enemy Attack Level Skip") -> Enemy Attack Level Skip | B54: =IFERROR(__xludf.DUMMYFUNCTION("""COMPUTED_VALUE"""),20.0) -> 20 | D54: =IFERROR(__xludf.DUMMYFUNCTION("""COMPUTED_VALUE"""),20.0) -> 20 | AP54: =IFERROR(__xludf.DUMMYFUNCTION("""COMPUTED_VALUE"""),"Demon Mode Automation") -> Demon Mode Automation | AQ54: =IFERROR(__xludf.DUMMYFUNCTION("""COMPUTED_VALUE"""),FALSE) -> FALSE | BB54: =IFERROR(__xludf.DUMMYFUNCTION("""COMPUTED_VALUE"""),"Rarity") -> Rarity | BC54: =IFERROR(__xludf.DUMMYFUNCTION("""COMPUTED_VALUE"""),"Level") -> Level | BD54: =IFERROR(__xludf.DUMMYFUNCTION("""COMPUTED_VALUE"""),"Stat") -> Stat | BG54: =IFERROR(__xludf.DUMMYFUNCTION("""COMPUTED_VALUE"""),"Rarity") -> Rarity | BH54: =IFERROR(__xludf.DUMMYFUNCTION("""COMPUTED_VALUE"""),"Level") -> Level | BI54: =IFERROR(__xludf.DUMMYFUNCTION("""COMPUTED_VALUE"""),"Stat") -> Stat | BL54: =IFERROR(__xludf.DUMMYFUNCTION("""COMPUTED_VALUE"""),"Rarity") -> Rarity | BM54: =IFERROR(__xludf.DUMMYFUNCTION("""COMPUTED_VALUE"""),"Level") -> Level | BN54: =IFERROR(__xludf.DUMMYFUNCTION("""COMPUTED_VALUE"""),"Stat") -> Stat | BQ54: =IFERROR(__xludf.DUMMYFUNCTION("""COMPUTED_VALUE"""),"Rarity") -> Rarity | BR54: =IFERROR(__xludf.DUMMYFUNCTION("""COMPUTED_VALUE"""),"Level") -> Level | BS54: =IFERROR(__xludf.DUMMYFUNCTION("""COMPUTED_VALUE"""),"Stat") -> Stat
A55: =IFERROR(__xludf.DUMMYFUNCTION("""COMPUTED_VALUE"""),"Enemy Health Level Skip") -> Enemy Health Level Skip | B55: =IFERROR(__xludf.DUMMYFUNCTION("""COMPUTED_VALUE"""),20.0) -> 20 | D55: =IFERROR(__xludf.DUMMYFUNCTION("""COMPUTED_VALUE"""),20.0) -> 20 | AP55: =IFERROR(__xludf.DUMMYFUNCTION("""COMPUTED_VALUE"""),"Smart Demon Mode Automation") -> Smart Demon Mode Automation | AQ55: =IFERROR(__xludf.DUMMYFUNCTION("""COMPUTED_VALUE"""),FALSE) -> FALSE | BB55: =IFERROR(__xludf.DUMMYFUNCTION("""COMPUTED_VALUE"""),"Mythic+") -> Mythic+ | BC55: =IFERROR(__xludf.DUMMYFUNCTION("""COMPUTED_VALUE"""),160.0) -> 160 | BD55: =IFERROR(__xludf.DUMMYFUNCTION("""COMPUTED_VALUE"""),8.19) -> 8.19 | BG55: =IFERROR(__xludf.DUMMYFUNCTION("""COMPUTED_VALUE"""),"Ancestral 2*") -> Ancestral 2* | BH55: =IFERROR(__xludf.DUMMYFUNCTION("""COMPUTED_VALUE"""),163.0) -> 163 | BI55: =IFERROR(__xludf.DUMMYFUNCTION("""COMPUTED_VALUE"""),9.467) -> 9.467 | BL55: =IFERROR(__xludf.DUMMYFUNCTION("""COMPUTED_VALUE"""),"Ancestral") -> Ancestral | BM55: =IFERROR(__xludf.DUMMYFUNCTION("""COMPUTED_VALUE"""),161.0) -> 161 | BN55: =IFERROR(__xludf.DUMMYFUNCTION("""COMPUTED_VALUE"""),1.68) -> 1.68 | BQ55: =IFERROR(__xludf.DUMMYFUNCTION("""COMPUTED_VALUE"""),"Ancestral 5*") -> Ancestral 5* | BR55: =IFERROR(__xludf.DUMMYFUNCTION("""COMPUTED_VALUE"""),159.0) -> 159 | BS55: =IFERROR(__xludf.DUMMYFUNCTION("""COMPUTED_VALUE"""),12.88) -> 12.88
A56: =IFERROR(__xludf.DUMMYFUNCTION("""COMPUTED_VALUE"""),"Missile Despawn Time") -> Missile Despawn Time | B56: =IFERROR(__xludf.DUMMYFUNCTION("""COMPUTED_VALUE"""),0.0) -> 0 | D56: =IFERROR(__xludf.DUMMYFUNCTION("""COMPUTED_VALUE"""),20.0) -> 20 | AP56: =IFERROR(__xludf.DUMMYFUNCTION("""COMPUTED_VALUE"""),"Free Mission Reroll") -> Free Mission Reroll | AQ56: =IFERROR(__xludf.DUMMYFUNCTION("""COMPUTED_VALUE"""),FALSE) -> FALSE
A57: =IFERROR(__xludf.DUMMYFUNCTION("""COMPUTED_VALUE"""),"Missiles Explosion") -> Missiles Explosion | B57: =IFERROR(__xludf.DUMMYFUNCTION("""COMPUTED_VALUE"""),0.0) -> 0 | D57: =IFERROR(__xludf.DUMMYFUNCTION("""COMPUTED_VALUE"""),1.0) -> 1 | AP57: =IFERROR(__xludf.DUMMYFUNCTION("""COMPUTED_VALUE"""),"Nuke Automation") -> Nuke Automation | AQ57: =IFERROR(__xludf.DUMMYFUNCTION("""COMPUTED_VALUE"""),FALSE) -> FALSE | BB57: =IFERROR(__xludf.DUMMYFUNCTION("""COMPUTED_VALUE"""),"MultiShot Chance") -> MultiShot Chance | BC57: =IFERROR(__xludf.DUMMYFUNCTION("""COMPUTED_VALUE"""),"Mythic") -> Mythic | BD57: =IFERROR(__xludf.DUMMYFUNCTION("""COMPUTED_VALUE"""),"+10%") -> +10% | BE57: =IFERROR(__xludf.DUMMYFUNCTION("""COMPUTED_VALUE"""),0.1) -> 0.1 | BJ57: =IFERROR(__xludf.DUMMYFUNCTION("""COMPUTED_VALUE"""),"") | BL57: =IFERROR(__xludf.DUMMYFUNCTION("""COMPUTED_VALUE"""),"Free Utility Upgrade") -> Free Utility Upgrade | BM57: =IFERROR(__xludf.DUMMYFUNCTION("""COMPUTED_VALUE"""),"Mythic") -> Mythic | BN57: =IFERROR(__xludf.DUMMYFUNCTION("""COMPUTED_VALUE"""),"+10%") -> +10% | BO57: =IFERROR(__xludf.DUMMYFUNCTION("""COMPUTED_VALUE"""),0.1) -> 0.1 | BT57: =IFERROR(__xludf.DUMMYFUNCTION("""COMPUTED_VALUE"""),"")
A58: =IFERROR(__xludf.DUMMYFUNCTION("""COMPUTED_VALUE"""),"Missile Radius") -> Missile Radius | B58: =IFERROR(__xludf.DUMMYFUNCTION("""COMPUTED_VALUE"""),0.0) -> 0 | D58: =IFERROR(__xludf.DUMMYFUNCTION("""COMPUTED_VALUE"""),20.0) -> 20 | AP58: =IFERROR(__xludf.DUMMYFUNCTION("""COMPUTED_VALUE"""),"Smart Nuke Automation") -> Smart Nuke Automation | AQ58: =IFERROR(__xludf.DUMMYFUNCTION("""COMPUTED_VALUE"""),FALSE) -> FALSE | BB58: =IFERROR(__xludf.DUMMYFUNCTION("""COMPUTED_VALUE"""),"Bounce Shot Chance") -> Bounce Shot Chance | BC58: =IFERROR(__xludf.DUMMYFUNCTION("""COMPUTED_VALUE"""),"Mythic") -> Mythic | BD58: =IFERROR(__xludf.DUMMYFUNCTION("""COMPUTED_VALUE"""),"+9%") -> +9% | BE58: =IFERROR(__xludf.DUMMYFUNCTION("""COMPUTED_VALUE"""),0.09) -> 0.09 | BJ58: =IFERROR(__xludf.DUMMYFUNCTION("""COMPUTED_VALUE"""),"") | BL58: =IFERROR(__xludf.DUMMYFUNCTION("""COMPUTED_VALUE"""),"Coins / Kill Bonus") -> Coins / Kill Bonus | BM58: =IFERROR(__xludf.DUMMYFUNCTION("""COMPUTED_VALUE"""),"Mythic") -> Mythic | BN58: =IFERROR(__xludf.DUMMYFUNCTION("""COMPUTED_VALUE"""),"+0.5x") -> +0.5x | BO58: =IFERROR(__xludf.DUMMYFUNCTION("""COMPUTED_VALUE"""),0.5) -> 0.5 | BT58: =IFERROR(__xludf.DUMMYFUNCTION("""COMPUTED_VALUE"""),"")
A59: =IFERROR(__xludf.DUMMYFUNCTION("""COMPUTED_VALUE"""),"Chrono Field Duration") -> Chrono Field Duration | B59: =IFERROR(__xludf.DUMMYFUNCTION("""COMPUTED_VALUE"""),30.0) -> 30 | D59: =IFERROR(__xludf.DUMMYFUNCTION("""COMPUTED_VALUE"""),30.0) -> 30 | AP59: =IFERROR(__xludf.DUMMYFUNCTION("""COMPUTED_VALUE"""),"Workshop Presets") -> Workshop Presets | AQ59: =IFERROR(__xludf.DUMMYFUNCTION("""COMPUTED_VALUE"""),FALSE) -> FALSE | BB59: =IFERROR(__xludf.DUMMYFUNCTION("""COMPUTED_VALUE"""),"Bounce Shot Targets") -> Bounce Shot Targets | BC59: =IFERROR(__xludf.DUMMYFUNCTION("""COMPUTED_VALUE"""),"Mythic") -> Mythic | BD59: =IFERROR(__xludf.DUMMYFUNCTION("""COMPUTED_VALUE"""),"+3") -> +3 | BE59: =IFERROR(__xludf.DUMMYFUNCTION("""COMPUTED_VALUE"""),3.0) -> 3 | BJ59: =IFERROR(__xludf.DUMMYFUNCTION("""COMPUTED_VALUE"""),"") | BL59: =IFERROR(__xludf.DUMMYFUNCTION("""COMPUTED_VALUE"""),"Enemy Health Level Skip") -> Enemy Health Level Skip | BM59: =IFERROR(__xludf.DUMMYFUNCTION("""COMPUTED_VALUE"""),"Mythic") -> Mythic | BN59: =IFERROR(__xludf.DUMMYFUNCTION("""COMPUTED_VALUE"""),"+6%") -> +6% | BO59: =IFERROR(__xludf.DUMMYFUNCTION("""COMPUTED_VALUE"""),0.06) -> 0.06 | BT59: =IFERROR(__xludf.DUMMYFUNCTION("""COMPUTED_VALUE"""),"")
A60: =IFERROR(__xludf.DUMMYFUNCTION("""COMPUTED_VALUE"""),"Chrono Field Damage Reduction") -> Chrono Field Damage Reduction | B60: =IFERROR(__xludf.DUMMYFUNCTION("""COMPUTED_VALUE"""),1.0) -> 1 | D60: =IFERROR(__xludf.DUMMYFUNCTION("""COMPUTED_VALUE"""),1.0) -> 1 | AP60: =IFERROR(__xludf.DUMMYFUNCTION("""COMPUTED_VALUE"""),"Missile Barrage Automation") -> Missile Barrage Automation | AQ60: =IFERROR(__xludf.DUMMYFUNCTION("""COMPUTED_VALUE"""),FALSE) -> FALSE | BB60: =IFERROR(__xludf.DUMMYFUNCTION("""COMPUTED_VALUE"""),"Multishot Targets") -> Multishot Targets | BC60: =IFERROR(__xludf.DUMMYFUNCTION("""COMPUTED_VALUE"""),"Mythic") -> Mythic | BD60: =IFERROR(__xludf.DUMMYFUNCTION("""COMPUTED_VALUE"""),"+3") -> +3 | BE60: =IFERROR(__xludf.DUMMYFUNCTION("""COMPUTED_VALUE"""),3.0) -> 3 | BJ60: =IFERROR(__xludf.DUMMYFUNCTION("""COMPUTED_VALUE"""),"") | BL60: =IFERROR(__xludf.DUMMYFUNCTION("""COMPUTED_VALUE"""),"Enemy Attack Level Skip") -> Enemy Attack Level Skip | BM60: =IFERROR(__xludf.DUMMYFUNCTION("""COMPUTED_VALUE"""),"Ancestral") -> Ancestral | BN60: =IFERROR(__xludf.DUMMYFUNCTION("""COMPUTED_VALUE"""),"+8%") -> +8% | BO60: =IFERROR(__xludf.DUMMYFUNCTION("""COMPUTED_VALUE"""),0.08) -> 0.08 | BT60: =IFERROR(__xludf.DUMMYFUNCTION("""COMPUTED_VALUE"""),"")
A61: =IFERROR(__xludf.DUMMYFUNCTION("""COMPUTED_VALUE"""),"Chrono Field Reduction %") -> Chrono Field Reduction % | B61: =IFERROR(__xludf.DUMMYFUNCTION("""COMPUTED_VALUE"""),20.0) -> 20 | D61: =IFERROR(__xludf.DUMMYFUNCTION("""COMPUTED_VALUE"""),30.0) -> 30 | AP61: =IFERROR(__xludf.DUMMYFUNCTION("""COMPUTED_VALUE"""),"Smart Missile Barrage Automation") -> Smart Missile Barrage Automation | AQ61: =IFERROR(__xludf.DUMMYFUNCTION("""COMPUTED_VALUE"""),FALSE) -> FALSE | BE61: =IFERROR(__xludf.DUMMYFUNCTION("""COMPUTED_VALUE"""),"") | BJ61: =IFERROR(__xludf.DUMMYFUNCTION("""COMPUTED_VALUE"""),"") | BL61: =IFERROR(__xludf.DUMMYFUNCTION("""COMPUTED_VALUE"""),"Package Chance") -> Package Chance | BM61: =IFERROR(__xludf.DUMMYFUNCTION("""COMPUTED_VALUE"""),"Mythic") -> Mythic | BN61: =IFERROR(__xludf.DUMMYFUNCTION("""COMPUTED_VALUE"""),"+11%") -> +11% | BO61: =IFERROR(__xludf.DUMMYFUNCTION("""COMPUTED_VALUE"""),0.11) -> 0.11 | BT61: =IFERROR(__xludf.DUMMYFUNCTION("""COMPUTED_VALUE"""),"")
A62: =IFERROR(__xludf.DUMMYFUNCTION("""COMPUTED_VALUE"""),"Swamp Radius") -> Swamp Radius | B62: =IFERROR(__xludf.DUMMYFUNCTION("""COMPUTED_VALUE"""),0.0) -> 0 | D62: =IFERROR(__xludf.DUMMYFUNCTION("""COMPUTED_VALUE"""),30.0) -> 30 | AP62: =IFERROR(__xludf.DUMMYFUNCTION("""COMPUTED_VALUE"""),"Daily Mission - Set Shard Type") -> Daily Mission - Set Shard Type | AQ62: =IFERROR(__xludf.DUMMYFUNCTION("""COMPUTED_VALUE"""),FALSE) -> FALSE | BE62: =IFERROR(__xludf.DUMMYFUNCTION("""COMPUTED_VALUE"""),"") | BJ62: =IFERROR(__xludf.DUMMYFUNCTION("""COMPUTED_VALUE"""),"") | BO62: =IFERROR(__xludf.DUMMYFUNCTION("""COMPUTED_VALUE"""),"") | BT62: =IFERROR(__xludf.DUMMYFUNCTION("""COMPUTED_VALUE"""),"")
A63: =IFERROR(__xludf.DUMMYFUNCTION("""COMPUTED_VALUE"""),"Swamp Stun") -> Swamp Stun | B63: =IFERROR(__xludf.DUMMYFUNCTION("""COMPUTED_VALUE"""),0.0) -> 0 | D63: =IFERROR(__xludf.DUMMYFUNCTION("""COMPUTED_VALUE"""),1.0) -> 1 | AP63: =IFERROR(__xludf.DUMMYFUNCTION("""COMPUTED_VALUE"""),"Auto Shatter Rare Modules") -> Auto Shatter Rare Modules | AQ63: =IFERROR(__xludf.DUMMYFUNCTION("""COMPUTED_VALUE"""),FALSE) -> FALSE | BE63: =IFERROR(__xludf.DUMMYFUNCTION("""COMPUTED_VALUE"""),"") | BJ63: =IFERROR(__xludf.DUMMYFUNCTION("""COMPUTED_VALUE"""),"") | BO63: =IFERROR(__xludf.DUMMYFUNCTION("""COMPUTED_VALUE"""),"") | BT63: =IFERROR(__xludf.DUMMYFUNCTION("""COMPUTED_VALUE"""),"")
A64: =IFERROR(__xludf.DUMMYFUNCTION("""COMPUTED_VALUE"""),"Swamp Stun Chance") -> Swamp Stun Chance | B64: =IFERROR(__xludf.DUMMYFUNCTION("""COMPUTED_VALUE"""),0.0) -> 0 | D64: =IFERROR(__xludf.DUMMYFUNCTION("""COMPUTED_VALUE"""),30.0) -> 30 | AP64: =IFERROR(__xludf.DUMMYFUNCTION("""COMPUTED_VALUE"""),"Auto Restart Run") -> Auto Restart Run | AQ64: =IFERROR(__xludf.DUMMYFUNCTION("""COMPUTED_VALUE"""),FALSE) -> FALSE | BE64: =IFERROR(__xludf.DUMMYFUNCTION("""COMPUTED_VALUE"""),"") | BJ64: =IFERROR(__xludf.DUMMYFUNCTION("""COMPUTED_VALUE"""),"") | BO64: =IFERROR(__xludf.DUMMYFUNCTION("""COMPUTED_VALUE"""),"") | BT64: =IFERROR(__xludf.DUMMYFUNCTION("""COMPUTED_VALUE"""),"")
A65: =IFERROR(__xludf.DUMMYFUNCTION("""COMPUTED_VALUE"""),"Swamp Stun Time") -> Swamp Stun Time | B65: =IFERROR(__xludf.DUMMYFUNCTION("""COMPUTED_VALUE"""),0.0) -> 0 | D65: =IFERROR(__xludf.DUMMYFUNCTION("""COMPUTED_VALUE"""),30.0) -> 30 | AP65: =IFERROR(__xludf.DUMMYFUNCTION("""COMPUTED_VALUE"""),"Auto Charge Berzerker") -> Auto Charge Berzerker | AQ65: =IFERROR(__xludf.DUMMYFUNCTION("""COMPUTED_VALUE"""),FALSE) -> FALSE
A66: =IFERROR(__xludf.DUMMYFUNCTION("""COMPUTED_VALUE"""),"Golden Tower Bonus") -> Golden Tower Bonus | B66: =IFERROR(__xludf.DUMMYFUNCTION("""COMPUTED_VALUE"""),22.0) -> 22 | D66: =IFERROR(__xludf.DUMMYFUNCTION("""COMPUTED_VALUE"""),25.0) -> 25 | AP66: =IFERROR(__xludf.DUMMYFUNCTION("""COMPUTED_VALUE"""),"Damage Cap Slider") -> Damage Cap Slider | AQ66: =IFERROR(__xludf.DUMMYFUNCTION("""COMPUTED_VALUE"""),FALSE) -> FALSE | BB66: =IFERROR(__xludf.DUMMYFUNCTION("""COMPUTED_VALUE"""),"Havoc Bringer") -> Havoc Bringer | BG66: =IFERROR(__xludf.DUMMYFUNCTION("""COMPUTED_VALUE"""),"Wormhole Redirector") -> Wormhole Redirector | BL66: =IFERROR(__xludf.DUMMYFUNCTION("""COMPUTED_VALUE"""),"Pulsar Harvester") -> Pulsar Harvester | BQ66: =IFERROR(__xludf.DUMMYFUNCTION("""COMPUTED_VALUE"""),"Om Chip") -> Om Chip
A67: =IFERROR(__xludf.DUMMYFUNCTION("""COMPUTED_VALUE"""),"Golden Tower Duration") -> Golden Tower Duration | B67: =IFERROR(__xludf.DUMMYFUNCTION("""COMPUTED_VALUE"""),19.0) -> 19 | D67: =IFERROR(__xludf.DUMMYFUNCTION("""COMPUTED_VALUE"""),20.0) -> 20 | AP67: =IFERROR(__xludf.DUMMYFUNCTION("""COMPUTED_VALUE"""),"Bot Presets") -> Bot Presets | AQ67: =IFERROR(__xludf.DUMMYFUNCTION("""COMPUTED_VALUE"""),FALSE) -> FALSE | BB67: =IFERROR(__xludf.DUMMYFUNCTION("""COMPUTED_VALUE"""),"Rarity") -> Rarity | BC67: =IFERROR(__xludf.DUMMYFUNCTION("""COMPUTED_VALUE"""),"Level") -> Level | BD67: =IFERROR(__xludf.DUMMYFUNCTION("""COMPUTED_VALUE"""),"Stat") -> Stat | BG67: =IFERROR(__xludf.DUMMYFUNCTION("""COMPUTED_VALUE"""),"Rarity") -> Rarity | BH67: =IFERROR(__xludf.DUMMYFUNCTION("""COMPUTED_VALUE"""),"Level") -> Level | BI67: =IFERROR(__xludf.DUMMYFUNCTION("""COMPUTED_VALUE"""),"Stat") -> Stat | BL67: =IFERROR(__xludf.DUMMYFUNCTION("""COMPUTED_VALUE"""),"Rarity") -> Rarity | BM67: =IFERROR(__xludf.DUMMYFUNCTION("""COMPUTED_VALUE"""),"Level") -> Level | BN67: =IFERROR(__xludf.DUMMYFUNCTION("""COMPUTED_VALUE"""),"Stat") -> Stat | BQ67: =IFERROR(__xludf.DUMMYFUNCTION("""COMPUTED_VALUE"""),"Rarity") -> Rarity | BR67: =IFERROR(__xludf.DUMMYFUNCTION("""COMPUTED_VALUE"""),"Level") -> Level | BS67: =IFERROR(__xludf.DUMMYFUNCTION("""COMPUTED_VALUE"""),"Stat") -> Stat
A68: =IFERROR(__xludf.DUMMYFUNCTION("""COMPUTED_VALUE"""),"Chain Lightning Shock") -> Chain Lightning Shock | B68: =IFERROR(__xludf.DUMMYFUNCTION("""COMPUTED_VALUE"""),1.0) -> 1 | D68: =IFERROR(__xludf.DUMMYFUNCTION("""COMPUTED_VALUE"""),1.0) -> 1 | AP68: =IFERROR(__xludf.DUMMYFUNCTION("""COMPUTED_VALUE"""),"Workshop Orb Adjuster") -> Workshop Orb Adjuster | AQ68: =IFERROR(__xludf.DUMMYFUNCTION("""COMPUTED_VALUE"""),FALSE) -> FALSE | BB68: =IFERROR(__xludf.DUMMYFUNCTION("""COMPUTED_VALUE"""),"Ancestral") -> Ancestral | BC68: =IFERROR(__xludf.DUMMYFUNCTION("""COMPUTED_VALUE"""),164.0) -> 164 | BD68: =IFERROR(__xludf.DUMMYFUNCTION("""COMPUTED_VALUE"""),9.04) -> 9.04 | BG68: =IFERROR(__xludf.DUMMYFUNCTION("""COMPUTED_VALUE"""),"Mythic+") -> Mythic+ | BH68: =IFERROR(__xludf.DUMMYFUNCTION("""COMPUTED_VALUE"""),160.0) -> 160 | BI68: =IFERROR(__xludf.DUMMYFUNCTION("""COMPUTED_VALUE"""),8.19) -> 8.19 | BL68: =IFERROR(__xludf.DUMMYFUNCTION("""COMPUTED_VALUE"""),"Ancestral 1*") -> Ancestral 1* | BM68: =IFERROR(__xludf.DUMMYFUNCTION("""COMPUTED_VALUE"""),161.0) -> 161 | BN68: =IFERROR(__xludf.DUMMYFUNCTION("""COMPUTED_VALUE"""),1.707) -> 1.707 | BQ68: =IFERROR(__xludf.DUMMYFUNCTION("""COMPUTED_VALUE"""),"Ancestral") -> Ancestral | BR68: =IFERROR(__xludf.DUMMYFUNCTION("""COMPUTED_VALUE"""),159.0) -> 159 | BS68: =IFERROR(__xludf.DUMMYFUNCTION("""COMPUTED_VALUE"""),10.9) -> 10.9
A69: =IFERROR(__xludf.DUMMYFUNCTION("""COMPUTED_VALUE"""),"Shock Chance") -> Shock Chance | B69: =IFERROR(__xludf.DUMMYFUNCTION("""COMPUTED_VALUE"""),14.0) -> 14 | D69: =IFERROR(__xludf.DUMMYFUNCTION("""COMPUTED_VALUE"""),30.0) -> 30 | AP69: =IFERROR(__xludf.DUMMYFUNCTION("""COMPUTED_VALUE"""),"Bot Cooldown Sliders") -> Bot Cooldown Sliders | AQ69: =IFERROR(__xludf.DUMMYFUNCTION("""COMPUTED_VALUE"""),FALSE) -> FALSE
A70: =IFERROR(__xludf.DUMMYFUNCTION("""COMPUTED_VALUE"""),"Shock Multiplier") -> Shock Multiplier | B70: =IFERROR(__xludf.DUMMYFUNCTION("""COMPUTED_VALUE"""),14.0) -> 14 | D70: =IFERROR(__xludf.DUMMYFUNCTION("""COMPUTED_VALUE"""),14.0) -> 14 | BE70: =IFERROR(__xludf.DUMMYFUNCTION("""COMPUTED_VALUE"""),"") | BG70: =IFERROR(__xludf.DUMMYFUNCTION("""COMPUTED_VALUE"""),"Defense %") -> Defense % | BH70: =IFERROR(__xludf.DUMMYFUNCTION("""COMPUTED_VALUE"""),"Legendary") -> Legendary | BI70: =IFERROR(__xludf.DUMMYFUNCTION("""COMPUTED_VALUE"""),"+5%") -> +5% | BJ70: =IFERROR(__xludf.DUMMYFUNCTION("""COMPUTED_VALUE"""),0.05) -> 0.05 | BL70: =IFERROR(__xludf.DUMMYFUNCTION("""COMPUTED_VALUE"""),"Free Utility Upgrade") -> Free Utility Upgrade | BM70: =IFERROR(__xludf.DUMMYFUNCTION("""COMPUTED_VALUE"""),"Ancestral") -> Ancestral | BN70: =IFERROR(__xludf.DUMMYFUNCTION("""COMPUTED_VALUE"""),"+12%") -> +12% | BO70: =IFERROR(__xludf.DUMMYFUNCTION("""COMPUTED_VALUE"""),0.12) -> 0.12 | BQ70: =IFERROR(__xludf.DUMMYFUNCTION("""COMPUTED_VALUE"""),"Chrono Field - Duration") -> Chrono Field - Duration | BR70: =IFERROR(__xludf.DUMMYFUNCTION("""COMPUTED_VALUE"""),"Mythic") -> Mythic | BS70: =IFERROR(__xludf.DUMMYFUNCTION("""COMPUTED_VALUE"""),"+7s") -> +7s | BT70: =IFERROR(__xludf.DUMMYFUNCTION("""COMPUTED_VALUE"""),7.0) -> 7
A71: =IFERROR(__xludf.DUMMYFUNCTION("""COMPUTED_VALUE"""),"Death Wave Health") -> Death Wave Health | B71: =IFERROR(__xludf.DUMMYFUNCTION("""COMPUTED_VALUE"""),30.0) -> 30 | D71: =IFERROR(__xludf.DUMMYFUNCTION("""COMPUTED_VALUE"""),30.0) -> 30 | BE71: =IFERROR(__xludf.DUMMYFUNCTION("""COMPUTED_VALUE"""),"") | BG71: =IFERROR(__xludf.DUMMYFUNCTION("""COMPUTED_VALUE"""),"Wall Health") -> Wall Health | BH71: =IFERROR(__xludf.DUMMYFUNCTION("""COMPUTED_VALUE"""),"Legendary") -> Legendary | BI71: =IFERROR(__xludf.DUMMYFUNCTION("""COMPUTED_VALUE"""),"+40%") -> +40% | BJ71: =IFERROR(__xludf.DUMMYFUNCTION("""COMPUTED_VALUE"""),0.4) -> 0.4 | BL71: =IFERROR(__xludf.DUMMYFUNCTION("""COMPUTED_VALUE"""),"Enemy Attack Level Skip") -> Enemy Attack Level Skip | BM71: =IFERROR(__xludf.DUMMYFUNCTION("""COMPUTED_VALUE"""),"Ancestral") -> Ancestral | BN71: =IFERROR(__xludf.DUMMYFUNCTION("""COMPUTED_VALUE"""),"+8%") -> +8% | BO71: =IFERROR(__xludf.DUMMYFUNCTION("""COMPUTED_VALUE"""),0.08) -> 0.08 | BQ71: =IFERROR(__xludf.DUMMYFUNCTION("""COMPUTED_VALUE"""),"Spotlight - Bonus") -> Spotlight - Bonus | BR71: =IFERROR(__xludf.DUMMYFUNCTION("""COMPUTED_VALUE"""),"Mythic") -> Mythic | BS71: =IFERROR(__xludf.DUMMYFUNCTION("""COMPUTED_VALUE"""),"+15x") -> +15x | BT71: =IFERROR(__xludf.DUMMYFUNCTION("""COMPUTED_VALUE"""),15.0) -> 15
A72: =IFERROR(__xludf.DUMMYFUNCTION("""COMPUTED_VALUE"""),"Death Wave Coin Bonus") -> Death Wave Coin Bonus | B72: =IFERROR(__xludf.DUMMYFUNCTION("""COMPUTED_VALUE"""),20.0) -> 20 | D72: =IFERROR(__xludf.DUMMYFUNCTION("""COMPUTED_VALUE"""),20.0) -> 20 | BE72: =IFERROR(__xludf.DUMMYFUNCTION("""COMPUTED_VALUE"""),"") | BG72: =IFERROR(__xludf.DUMMYFUNCTION("""COMPUTED_VALUE"""),"Health Regen") -> Health Regen | BH72: =IFERROR(__xludf.DUMMYFUNCTION("""COMPUTED_VALUE"""),"Legendary") -> Legendary | BI72: =IFERROR(__xludf.DUMMYFUNCTION("""COMPUTED_VALUE"""),"+100%") -> +100% | BJ72: =IFERROR(__xludf.DUMMYFUNCTION("""COMPUTED_VALUE"""),1.0) -> 1 | BL72: =IFERROR(__xludf.DUMMYFUNCTION("""COMPUTED_VALUE"""),"Coins / Kill Bonus") -> Coins / Kill Bonus | BM72: =IFERROR(__xludf.DUMMYFUNCTION("""COMPUTED_VALUE"""),"Ancestral") -> Ancestral | BN72: =IFERROR(__xludf.DUMMYFUNCTION("""COMPUTED_VALUE"""),"+0.6x") -> +0.6x | BO72: =IFERROR(__xludf.DUMMYFUNCTION("""COMPUTED_VALUE"""),0.6) -> 0.6 | BQ72: =IFERROR(__xludf.DUMMYFUNCTION("""COMPUTED_VALUE"""),"Spotlight - Angle") -> Spotlight - Angle | BR72: =IFERROR(__xludf.DUMMYFUNCTION("""COMPUTED_VALUE"""),"Epic") -> Epic | BS72: =IFERROR(__xludf.DUMMYFUNCTION("""COMPUTED_VALUE"""),"+3°") -> +3° | BT72: =IFERROR(__xludf.DUMMYFUNCTION("""COMPUTED_VALUE"""),3.0) -> 3
A73: =IFERROR(__xludf.DUMMYFUNCTION("""COMPUTED_VALUE"""),"Inner Mine Blast Radius") -> Inner Mine Blast Radius | B73: =IFERROR(__xludf.DUMMYFUNCTION("""COMPUTED_VALUE"""),0.0) -> 0 | D73: =IFERROR(__xludf.DUMMYFUNCTION("""COMPUTED_VALUE"""),20.0) -> 20 | BE73: =IFERROR(__xludf.DUMMYFUNCTION("""COMPUTED_VALUE"""),"") | BJ73: =IFERROR(__xludf.DUMMYFUNCTION("""COMPUTED_VALUE"""),"") | BL73: =IFERROR(__xludf.DUMMYFUNCTION("""COMPUTED_VALUE"""),"Enemy Health Level Skip") -> Enemy Health Level Skip | BM73: =IFERROR(__xludf.DUMMYFUNCTION("""COMPUTED_VALUE"""),"Ancestral") -> Ancestral | BN73: =IFERROR(__xludf.DUMMYFUNCTION("""COMPUTED_VALUE"""),"+8%") -> +8% | BO73: =IFERROR(__xludf.DUMMYFUNCTION("""COMPUTED_VALUE"""),0.08) -> 0.08 | BQ73: =IFERROR(__xludf.DUMMYFUNCTION("""COMPUTED_VALUE"""),"Chain Lightning - Chance") -> Chain Lightning - Chance | BR73: =IFERROR(__xludf.DUMMYFUNCTION("""COMPUTED_VALUE"""),"Rare") -> Rare | BS73: =IFERROR(__xludf.DUMMYFUNCTION("""COMPUTED_VALUE"""),"+4%") -> +4% | BT73: =IFERROR(__xludf.DUMMYFUNCTION("""COMPUTED_VALUE"""),0.04) -> 0.04
A74: =IFERROR(__xludf.DUMMYFUNCTION("""COMPUTED_VALUE"""),"Inner Mine Rotation Speed") -> Inner Mine Rotation Speed | B74: =IFERROR(__xludf.DUMMYFUNCTION("""COMPUTED_VALUE"""),0.0) -> 0 | D74: =IFERROR(__xludf.DUMMYFUNCTION("""COMPUTED_VALUE"""),20.0) -> 20 | BE74: =IFERROR(__xludf.DUMMYFUNCTION("""COMPUTED_VALUE"""),"") | BJ74: =IFERROR(__xludf.DUMMYFUNCTION("""COMPUTED_VALUE"""),"") | BL74: =IFERROR(__xludf.DUMMYFUNCTION("""COMPUTED_VALUE"""),"Package Chance") -> Package Chance | BM74: =IFERROR(__xludf.DUMMYFUNCTION("""COMPUTED_VALUE"""),"Epic") -> Epic | BN74: =IFERROR(__xludf.DUMMYFUNCTION("""COMPUTED_VALUE"""),"+5%") -> +5% | BO74: =IFERROR(__xludf.DUMMYFUNCTION("""COMPUTED_VALUE"""),0.05) -> 0.05 | BT74: =IFERROR(__xludf.DUMMYFUNCTION("""COMPUTED_VALUE"""),"")
A75: =IFERROR(__xludf.DUMMYFUNCTION("""COMPUTED_VALUE"""),"Chrono Field Range") -> Chrono Field Range | B75: =IFERROR(__xludf.DUMMYFUNCTION("""COMPUTED_VALUE"""),17.0) -> 17 | D75: =IFERROR(__xludf.DUMMYFUNCTION("""COMPUTED_VALUE"""),20.0) -> 20 | BE75: =IFERROR(__xludf.DUMMYFUNCTION("""COMPUTED_VALUE"""),"") | BJ75: =IFERROR(__xludf.DUMMYFUNCTION("""COMPUTED_VALUE"""),"") | BO75: =IFERROR(__xludf.DUMMYFUNCTION("""COMPUTED_VALUE"""),"") | BT75: =IFERROR(__xludf.DUMMYFUNCTION("""COMPUTED_VALUE"""),"")
A76: =IFERROR(__xludf.DUMMYFUNCTION("""COMPUTED_VALUE"""),"Missile Amplifier") -> Missile Amplifier | B76: =IFERROR(__xludf.DUMMYFUNCTION("""COMPUTED_VALUE"""),0.0) -> 0 | D76: =IFERROR(__xludf.DUMMYFUNCTION("""COMPUTED_VALUE"""),25.0) -> 25 | BE76: =IFERROR(__xludf.DUMMYFUNCTION("""COMPUTED_VALUE"""),"") | BJ76: =IFERROR(__xludf.DUMMYFUNCTION("""COMPUTED_VALUE"""),"") | BO76: =IFERROR(__xludf.DUMMYFUNCTION("""COMPUTED_VALUE"""),"") | BT76: =IFERROR(__xludf.DUMMYFUNCTION("""COMPUTED_VALUE"""),"")
A77: =IFERROR(__xludf.DUMMYFUNCTION("""COMPUTED_VALUE"""),"Missile Barrage") -> Missile Barrage | B77: =IFERROR(__xludf.DUMMYFUNCTION("""COMPUTED_VALUE"""),0.0) -> 0 | D77: =IFERROR(__xludf.DUMMYFUNCTION("""COMPUTED_VALUE"""),1.0) -> 1 | BE77: =IFERROR(__xludf.DUMMYFUNCTION("""COMPUTED_VALUE"""),"") | BJ77: =IFERROR(__xludf.DUMMYFUNCTION("""COMPUTED_VALUE"""),"") | BO77: =IFERROR(__xludf.DUMMYFUNCTION("""COMPUTED_VALUE"""),"") | BT77: =IFERROR(__xludf.DUMMYFUNCTION("""COMPUTED_VALUE"""),"")
