Workbook
Name MOD_ARMOR_INCREASE_ARRAY: DVT_Modules!$D$21:$D$30
Name DVT_Mod_Generator_Substats: DVT_Modules!$W$3:$W$29
Name MOD_GENERATOR_INCREASE_ARRAY: DVT_Modules!$E$21:$E$30
Name DVT_Mod_Cannon_Substats: DVT_Modules!$U$3:$U$29
Name MOD_STEPS_INCREASE_NEXT: DVT_Modules!$B$22:$B$31
Name MOD_CANNONS_LIST: DVT_Modules!$N$4:$N$79
Name MOD_BASE_STAT_ARRAY: DVT_Modules!$B$3:$F$17
Name LABS_LabLevel_Array: DVT_Laboratory!$A$3:$A$102
Name MOD_GENERATORS_LIST: DVT_Modules!$P$4:$P$79
Name MOD_CORES_LIST: DVT_Modules!$Q$4:$Q$79
Name DVT_Mod_SubStat_Value_Array: DVT_Modules!$Z$2:$AM$77
Name DVT_Mod_Core_Substats: DVT_Modules!$X$3:$X$29
Name DVT_Mod_Stat_Rarity: DVT_Modules!$T$3:$T$9
Name MOD_STEPS_INCREASE: DVT_Modules!$B$21:$B$30
Name DVT_Mod_Armor_Substats: DVT_Modules!$V$3:$V$29
Name DVT_Mod_Assist_Level: DVT_Modules!$K$2:$K$1000
Name MOD_ARMORS_LIST: DVT_Modules!$O$4:$O$79
Name MOD_CANNON_INCREASE_ARRAY: DVT_Modules!$C$21:$C$30
Name LABS_LabName_Array: DVT_Laboratory!$B$1:$LO$1
Name DVT_Mod_Base_Rarity_Uniques: DVT_Modules!$S$3:$S$15
Name DVT_Mod_Base_Rarity: DVT_Modules!$R$3:$R$18
Name LABS_LabSearchStartPoint: DVT_Laboratory!$B$3
Name MOD_CORE_INCREASE_ARRAY: DVT_Modules!$F$21:$F$30
Name LABDURATION_SINGLE_ADJUSTED: LAMBDA(lab_name, lab_level, DVT_LAB_DURATION(lab_name, lab_level) / LAB_SPEED_TOTAL())
Name IDS_MOD_CORE_SUBSTATS: LAMBDA(name, IFERROR(OFFSET('_IDS'!$BQ$31, MATCH(name, '_IDS'!$BQ$27:$BQ, 0)-1, 0, 8, 4)))
Name IDS_MOD_CANNON_ASSIST_SUBSTAT_CAP: LAMBDA('_IDS'!$BC$5)
Name IDS_MOD_ARMOR_ASSIST_NAME: LAMBDA(preset, OFFSET('_IDS'!$BH$9, MATCH(preset, '_IDS'!$BG$7:$BG$23, 0)-1, 0, 1, 1))
Name IDS_CARD_MASTERY: LAMBDA(card_name, VLOOKUP(card_name,'_IDS'!$AE$2:$AG, 3, FALSE))
Name IDS_MOD_CORE_BONUS: LAMBDA(name, OFFSET('_IDS'!$BS$29, MATCH(name, '_IDS'!$BQ$27:$BQ, 0)-1, 0, 1, 1))
Name IDS_BOT_LEVEL: LAMBDA(bot_name, bot_property, LET( off, (MATCH(bot_name, '_IDS'!$AS$2:$AS$17, 0) - 1), VLOOKUP(bot_property, OFFSET('_IDS'!$AU$2, off, 0, 4, 3), 3, FALSE) ))
Name IDS_PS_FARMING_TIER: LAMBDA('_IDS'!$CE$4)
Name IDS_MOD_GENERATOR_BONUS: LAMBDA(name, OFFSET('_IDS'!$BN$29, MATCH(name, '_IDS'!$BL$27:$BL, 0)-1, 0, 1, 1))
Name IDS_MOD_CORE_ASSIST_NAME: LAMBDA(preset, OFFSET('_IDS'!$BR$9, MATCH(preset, '_IDS'!$BQ$7:$BQ$23, 0)-1, 0, 1, 1))
Name IDS_MOD_GENERATOR_ASSIST_LEVEL: LAMBDA('_IDS'!$BN$2)
Name IDS_MOD_ARMOR_ASSIST_SUBSTAT_CAP: LAMBDA('_IDS'!$BH$5)
Name IDS_MOD_CANNON_ASSIST_MULT_CAP: LAMBDA('_IDS'!$BC$4)
Name IDS_MOD_GENERATOR_RARITY: LAMBDA(name, IFERROR(OFFSET('_IDS'!$BL$29, MATCH(name, '_IDS'!$BL$27:$BL, 0)-1, 0, 1, 1)))
Name IDS_WS_LEVEL: LAMBDA(ws_name, MAX(IDS_WS_COIN_LEVEL(ws_name), IDS_WS_CASH_LEVEL(ws_name)))
Name IDS_WS_PRESET_LEVEL: LAMBDA(preset, ws_name, MAX(IDS_WS_PRESET_COIN_LEVEL(preset, ws_name), IDS_WS_PRESET_CASH_LEVEL(preset, ws_name)))
Name LABDURATION_SINGLE_BASE: LAMBDA(lab_name, lab_level, XLOOKUP(lab_level,LABS_LabLevel_Array,OFFSET(LABS_LabSearchStartPoint,0,MATCH(lab_name,LABS_LabName_Array,0)-1,100,1),"N/F",0,1))
Name IDS_LAB_LEVEL: LAMBDA(lab_name, IF('_IDS'!$C$1="✅", VLOOKUP(lab_name, '_IDS'!$A$2:$B, 2, FALSE), 0))
Name IDS_MOD_ARMOR_ASSIST_MULT_CAP: LAMBDA('_IDS'!$BH$4)
Name IDS_CARD_PRESET: LAMBDA(preset, OFFSET('_IDS'!$AH$3, 0, MATCH(preset, '_IDS'!$AH$2:$AL$2, 0)-1, 27, 1))
Name DVT_MODULE_COINS_COST_CUMMULATIVE: LAMBDA(level, IF(level <= 1, 0, SUM(ARRAYFORMULA(DVT_MODULE_COINS_COST(ROW(INDIRECT("1:"&level)))))))
Name IDS_MOD_CORE_NAME: LAMBDA(preset, OFFSET('_IDS'!$BR$8, MATCH(preset, '_IDS'!$BQ$7:$BQ$23, 0)-1, 0, 1, 1))
Name IDS_CARD_LEVEL: LAMBDA(card_name, IF(VLOOKUP(card_name,'_IDS'!$AE$2:$AG$31, 2, FALSE)="Locked", 1, VLOOKUP(card_name,'_IDS'!$AE$2:$AG, 2, FALSE)))
Name IDS_MOD_ARMOR_ASSIST_LEVEL: LAMBDA('_IDS'!$BI$2)
Name IDS_MOD_CANNON_ASSIST_LEVEL: LAMBDA('_IDS'!$BD$2)
Name IDS_MOD_GENERATOR_ASSIST_SUBSTAT_CAP: LAMBDA('_IDS'!$BM$5)
Name IDS_PS_TIER_PB: LAMBDA(tiername, VLOOKUP(TierName, '_IDS'!$BZ$3:$CA, 2))
Name IDS_RELIC_STAT: LAMBDA(relic_stat, IFERROR(IF('_IDS'!$AO$1="✅", VLOOKUP(relic_stat,'_IDS'!$AM$2:$AN,2,FALSE), 0), 0))
Name IDS_MOD_CANNON_LEVEL: LAMBDA(name, OFFSET('_IDS'!$BC$29, MATCH(name, '_IDS'!$BB$27:$BB, 0)-1, 0, 1, 1))
Name DVT_MODULE_SHARDS_COST_CUMMULATIVE: LAMBDA(level, IF(level <=1, 0, SUM(ARRAYFORMULA(DVT_MODULE_SHARDS_COST(ROW(INDIRECT("1:"&level)))))))
Name IDS_MOD_GENERATOR_NAME: LAMBDA(preset, OFFSET('_IDS'!$BM$8, MATCH(preset, '_IDS'!$BL$7:$BL$23, 0)-1, 0, 1, 1))
Name IDS_MOD_GENERATOR_LEVEL: LAMBDA(name, OFFSET('_IDS'!$BM$29, MATCH(name, '_IDS'!$BL$27:$BL, 0)-1, 0, 1, 1))
Name IDS_BOT_OWN: LAMBDA(bot_name, LET( off, (MATCH(bot_name, '_IDS'!$AS$2:$AS$17, 0) - 1), OFFSET('_IDS'!$AS$5, off, 0, 1, 1) ))
Name LAB_SPEED_TOTAL: LAMBDA((1+('Master Sheet'!$C$3*0.02))*(1+'Master Sheet'!$G$2))
Name RELIC_STAT: LAMBDA(relic_name, IF(RelicValidation="✅", VLOOKUP(relic_name,'_IDS'!$A$1:$B,2,FALSE), 0))
Name IDS_UW_VALUE: LAMBDA(uw_name, uw_stat, LET( off, (MATCH(uw_name, '_IDS'!$Z$2:$Z$37, 0) - 1), VLOOKUP(uw_stat, OFFSET('_IDS'!$AB$2, off, 0, 4, 2), 2, FALSE) ))
Name IDS_MOD_ARMOR_NAME: LAMBDA(preset, OFFSET('_IDS'!$BH$8, MATCH(preset, '_IDS'!$BG$7:$BG$23, 0)-1, 0, 1, 1))

Sheet Home Page
B2: Modules
B4: =HYPERLINK("https://docs.google.com/spreadsheets/d/1KCxnSAvhstAbFdBSYSO_3bKUPtCFX42Eb7Z13agPU9s/copy", "Modules Initial Link") -> Modules Initial Link | G4: Sheet Tab | H4: Creator | I4: Main Contributor | J4: Helpers
G6: IDS | H6: @Mattew | I6: @Mattew | J6: @Bisse
B7: Latest remote version : | G7: Master Sheet | H7: @Mattew | I7: @Mattew | J7: @TC Team
B8: =IFERROR(__xludf.DUMMYFUNCTION("IMPORTRANGE(""1KCxnSAvhstAbFdBSYSO_3bKUPtCFX42Eb7Z13agPU9s"", ""'Home Page'!B12:C13"")"),"v5.13") -> v5.13 | C8: =IFERROR(__xludf.DUMMYFUNCTION("""COMPUTED_VALUE"""),"feat: Shattered epic tracker (@ghostofthecommentsection)") -> feat: Shattered epic tracker (@ghostofthecommentsection) | G8: Inventory | H8: @Shiriru94 | I8: @Shiriru94, @Mattew
B9: =IFERROR(__xludf.DUMMYFUNCTION("""COMPUTED_VALUE"""),"v5.12.1") -> v5.12.1 | C9: =IFERROR(__xludf.DUMMYFUNCTION("""COMPUTED_VALUE"""),"feat: Enhanced OAL button") -> feat: Enhanced OAL button | G9: Presets | H9: @Shiriru94, @Mattew | I9: @Mattew | J9: @Shiriru94
G10: Tracker | H10: @Audacious, @gtsum | I10: @Shiriru94 | J10: @Meringue
B11: Version Change : | G11: Reroll Calculator V3 | H11: @Freeman0916
B12: v5.13 | C12: feat: Shattered epic tracker (@ghostofthecommentsection) | G12: Optimal Assist levels | H12: @Eyethberg | I12: @Eyethberg | J12: @avacede
B13: v5.12.1 | C13: feat: Enhanced OAL button | G13: Shard Path | H13: @QuietFanta
B14: v5.12 | C14: feat: Optimal Assist Levels "Apply" button | G14: Overview | H14: @GodzillasDaddy
B15: v5.11.1 | C15: fix: Optimal Assist Levels fix for Assist Level = 0 | G15: Substats | H15: @kosmirionepos | I15: @Mattew
B16: v5.11 | C16: feat: Added Spare OA and Spare RB
B17: v5.10 | C17: feat: Minimum levels for Optimal Assist & performance improvements | G17: Tab colors explanation
B18: v5.9 | C18: feat: New Module: Orbital Augment
B19: v5.8 | C19: fix: Any Other 2 Substat values are grabbed | G19: Home Page | H19: Input Tabs | I19: Local Tools | J19: Static Data
B20: v5.7 | C20: feat: New Module: Restorative Bonus
B21: v5.6.4 | C21: fix: Optimal assist current now mults properly | G21: Related tools
B22: v5.6.3 | C22: feat: Optimal Assist Levels Multi update | G22: =HYPERLINK(IF('_IDS'!AB1="✅",'_IDS'!AF1, "https://docs.google.com/spreadsheets/d/1wVLlvWfmcjHRkAnQJzAQu_YZo_eW1FXMVTfYYQnF7Xc")&"#gid=2001828042", "RPC Mastery") -> RPC Mastery | H22: Shows Shard earning prediction
B23: v5.6.2 | C23: Fix: Level cap for Common, Rare, Rare+
B24: v5.6.1 | C24: fix: Shard Path (@Gladiator)
B25: v5.6 | C25: Add: Shard Path (@QuietFanta)
B26: v5.5.5 | C26: fix: dropdown for spare modules | G26: Enjoying those sheets? You can support me by using my creator code for any in game or webstore purchases. My creator code is : SHEETLORD
B27: v5.5.4 | C27: fix: #ref! and data validations
B28: v5.5.3 | C28: fix: Max Assist Level #ref!
B29: v5.5.2 | C29: fix: 7th substat export for SR and AS
B30: v5.5.1 | C30: Tracker: Fodder text bar improvements
B31: v5.5 | C31: Add: Amplifying Strike | G31: Want to support someone else ? Here is the creator code list
B32: v5.4.4 | C32: fix: Export Completion
B33: v5.4.3 | C33: fix: OAL not showing optimal levels | G33: =IFERROR(__xludf.DUMMYFUNCTION("IMPORTRANGE(""1eCPPuQOE3Pyh8HhnApEMK3RFIutkUjWd61ppVImwWk8"", ""_Giveaway_summary!A1:A2"")"),"⚠️ 1 Giveaway(s) running - 22 Mar") -> ⚠️ 1 Giveaway(s) running - 22 Mar
B34: v5.4.2 | C34: fix: Tracker showing correct merge instructions now | G34: =IFERROR(__xludf.DUMMYFUNCTION("""COMPUTED_VALUE"""),"Giveaway Details") -> Giveaway Details
B35: v5.4.1 | C35: fix: Optimal Assist Levels referencing only Cannon level
B36: v5.4 | C36: Tracker: 6th Mod series included
B37: v5.3 | C37: Add: Primordial Collapse
B38: v5.2.1 | C38: Internal changes / Renames
B39: v5.2 | C39: Add: Modules Overview Sheet
B40: v5.1.1 | C40: fix: Optimal Assist Levels n/a's and other references
B41: v5.1 | C41: Add: Optimal Assist Levels
B42: v5.0 | C42: IDS 2.0 + V27
B43: v4.7 | C43: Added Modules Tracker (hidden Mods Obtained)
B44: v4.6.2 | C44: fix: 4.6 Import Updated
B45: v4.6.1 | C45: fix: 4.6 highest level was broken [Import not update yet]
B46: v4.6 | C46: fix: Spare modules | feat: Highest Level
... B52: v4.0 | C52: New Modules Presets UI

Sheet IDS
B2: The IDS System | I2: Looking for the Import script ? Just run it as you were doing it before, but from IDS Master. It will let you import every new versions at once!
B4: This Sheet ID is : | C4: 1rOoSY6TK918myJ6Mn6zO4rmUaFbPu6qJnGI17kc9DzQ
B6: IDS Master's ID ➡️ | C6: 1HOIkxWbbciTIAzVruaahEGADlM8rS0-w86uBXj4PwNQ | D6: =IFERROR(__xludf.DUMMYFUNCTION("IFERROR(C6.url, IFS(LEFT(C6,8)=""https://"", C6, LEN(C6)=44, ""https://docs.google.com/spreadsheets/d/"" & C6 & ""/edit"", TRUE, C6))"),"https://docs.google.com/spreadsheets/d/1HOIkxWbbciTIAzVruaahEGADlM8rS0-w86uBXj4PwNQ/edit") -> https://docs.google.com/spreadsheets/d/1HOIkxWbbciTIAzVruaahEGADlM8rS0-w86uBXj4PwNQ/edit | E6: =IFERROR(__xludf.DUMMYFUNCTION("IF(D6<>"""", IF(IMPORTRANGE(D6,""EXPORT!A1"") = F6, ""✅"", ""Wrong ID or Version""), """")"),"✅") -> ✅ | F6: v2
B7: =HYPERLINK("https://docs.google.com/spreadsheets/d/1osjoqKmMwtOWs7Up3e21-3ofN1RHOjsgKV6y3dc6rgE/copy", "1️⃣ Copy Me") -> 1️⃣ Copy Me | C7: =IFS( ISERROR(E6), "3️⃣ Click on #REF! and then AUTHORISE ↗", E6="", "2️⃣ Please input your IDS Master's ID here ⤴️", E6="✅", HYPERLINK(D6, "Go to my IDS Master Sheet"), TRUE, "") -> Go to my IDS Master Sheet | E7: ✅ | I7: Issues
I8: Mobile Users If you are on mobile, you will not be able to do STEP 3. There is a workaround you can do still : You need to edit the viewing permissions to "anyone with the link" of all your IDs sheets If you have any other trouble, let us know in the #effective-path Discord's channel. I say us, but don't ask Fanta. Fanta hates IDS.
B9: How to use
B10: STEP 1: Click on the Copy Me link and create your copy of the IDS Master. STEP 2: Copy the ID (you will find it in the IDS page) of your newly created sheet and paste it in the light gray area. STEP 3: Wait a little bit, the F5 cell will show "Loading...", and after few seconds it will display "#REF!". Click on the cell, and "Authorize" to let this sheet access the other one.
B19: And that's it! The IDS are setuped. You can now fill sub IDS in the IDS Master with sub IDS sheets (Laboratory, Workshop, ...) just like you did in here. Every time you will change a value (let's say, a lab level in Laboratory Sheet) the change will be propagated to every other sheet using the IDS Master automatically.

Sheet Master Sheet
B1: =IF('_IDS'!C1="✅", HYPERLINK('_IDS'!B1, "Go to my Laboratory Sheet"), "Labs") -> Go to my Laboratory Sheet | C1: Level | D1: Max | F1: =IF('_IDS'!AO1="✅", HYPERLINK('_IDS'!AN1, "Go to my Relic Sheet"), "Relic") -> Go to my Relic Sheet | G1: Bonus
A2: LABS | B2: Labs Coin Discount | C2: =IDS_LAB_LEVEL(B2) -> 68 | D2: 99 | E2: VAULT TREE | F2: Lab Speed | G2: =IDS_RELIC_STAT(F2) -> 0.395
B3: Labs Speed | C3: =IDS_LAB_LEVEL(B3) -> 91 | D3: 99
B4: Package After Boss | C4: =IDS_LAB_LEVEL(B4) -> 1 | D4: =COUNTA(OFFSET(DVT_Laboratory!$B$3, 0, MATCH(A2,DVT_Laboratory!$B$1:I$1, 0)-1, 100, 1)) -> 1 | F4: =IF('_IDS'!AF1="✅", HYPERLINK('_IDS'!AE1, "Go to my Vault Sheet"), "Vault Upgrade") -> Vault Upgrade | G4: Bonus
B5: Recovery Package Chance | C5: =IDS_LAB_LEVEL(B5) -> 20 | D5: 20 | F5: Discount Rerolls | G5: =IDS_VAULT_STAT(F5) -> 0
B6: Recovery Package Chance Mastery | C6: =IDS_LAB_LEVEL(B6) -> 3 | D6: 9
B7: Common Drop Chance | C7: =IDS_LAB_LEVEL(B7) -> 10 | D7: 10
B8: Daily Mission Shards | C8: =IDS_LAB_LEVEL(B8) -> 50 | D8: 50
B9: Module Shards Cost | C9: =IDS_LAB_LEVEL(B9) -> 30 | D9: 30
B10: Rare Drop Chance | C10: =IDS_LAB_LEVEL(B10) -> 10 | D10: 10
B11: Shatter Shards | C11: =IDS_LAB_LEVEL(B11) -> 5 | D11: 5
B12: Cannon Effect Bans | C12: =IDS_LAB_LEVEL(B12) -> 0 | D12: 4
B13: Armor Effect Bans | C13: =IDS_LAB_LEVEL(B13) -> 2 | D13: 4
B14: Generator Effect Bans | C14: =IDS_LAB_LEVEL(B14) -> 1 | D14: 3
B15: Core Effect Bans | C15: =IDS_LAB_LEVEL(B15) -> 4 | D15: 7
B16: Assist Module Bonus - Cannon | C16: =IDS_LAB_LEVEL(B16) -> 0 | D16: 30
B17: Assist Module Bonus - Armor | C17: =IDS_LAB_LEVEL(B17) -> 0 | D17: 30
... B19: Assist Module Bonus - Core | C19: =IDS_LAB_LEVEL(B19) -> 0 | D19: 30

Sheet Inventory
F1: Module Inventory
A3: 🔵 CANNON | F3: Astral Deliverance | K3: Being Annihilator | P3: Death Penalty | U3: Havoc Bringer | Z3: Shrink Ray | AE3: Amplifying Strike | AJ3: Any Other | AO3: Any Other 2
D4: Highest Level | F4: Rarity | G4: Level | H4: Stat | K4: Rarity | L4: Level | M4: Stat | P4: Rarity | Q4: Level | R4: Stat | U4: Rarity | V4: Level | W4: Stat | Z4: Rarity | AA4: Level | AB4: Stat | AE4: Rarity | AF4: Level | AG4: Stat | AJ4: Rarity | AK4: Level | AL4: Stat | AO4: Rarity | AP4: Level | AQ4: Stat
B5: Tower Damage | D5: 164 | F5: Mythic+ | G5: =CAP_MOD_LEVEL($D5,F5) -> 160 | H5: =IF(F5="None",1,MODSTAT_CANNON(F5,G5)) -> 8.19 | K5: Ancestral | L5: =CAP_MOD_LEVEL($D5,K5) -> 164 | M5: =IF(K5="None",1,MODSTAT_CANNON(K5,L5)) -> 9.04 | P5: Mythic+ | Q5: =CAP_MOD_LEVEL($D5,P5) -> 160 | R5: =IF(P5="None",1,MODSTAT_CANNON(P5,Q5)) -> 8.19 | U5: Ancestral | V5: =CAP_MOD_LEVEL($D5,U5) -> 164 | W5: =IF(U5="None",1,MODSTAT_CANNON(U5,V5)) -> 9.04 | Z5: Legendary | AA5: =CAP_MOD_LEVEL($D5,Z5) -> 100 | AB5: =IF(Z5="None",1,MODSTAT_CANNON(Z5,AA5)) -> 2.27 | AE5: Ancestral | AF5: =CAP_MOD_LEVEL($D5,AE5) -> 164 | AG5: =IF(AE5="None",1,MODSTAT_CANNON(AE5,AF5)) -> 9.04 | AJ5: Epic | AK5: =CAP_MOD_LEVEL($D5,AJ5) -> 60 | AL5: =IF(AJ5="None",1,MODSTAT_CANNON(AJ5,AK5)) -> 1.37 | AO5: Common | AP5: =CAP_MOD_LEVEL($D5,AO5) -> 20 | AQ5: =IF(AO5="None",1,MODSTAT_CANNON(AO5,AP5)) -> 1.05
D7: Assist Level | H7: =MOD_SUBSTAT_LOOKUP(F7,G7,1) | I7: =IF(ISBLANK(F7), "", MOD_SUBSTAT_LOOKUP(F7,G7,0)) | K7: Attack Speed | L7: Mythic | M7: =MOD_SUBSTAT_LOOKUP(K7,L7,1) -> +3 | N7: =IF(ISBLANK(K7), "", MOD_SUBSTAT_LOOKUP(K7,L7,0)) -> 3 | P7: MultiShot Chance | Q7: Mythic | R7: =MOD_SUBSTAT_LOOKUP(P7,Q7,1) -> +10% | S7: =IF(ISBLANK(P7), "", MOD_SUBSTAT_LOOKUP(P7,Q7,0)) -> 0.1 | W7: =MOD_SUBSTAT_LOOKUP(U7,V7,1) | X7: =IF(ISBLANK(U7), "", MOD_SUBSTAT_LOOKUP(U7,V7,0)) | AB7: =MOD_SUBSTAT_LOOKUP(Z7,AA7,1) | AC7: =IF(ISBLANK(Z7), "", MOD_SUBSTAT_LOOKUP(Z7,AA7,0)) | AE7: Bounce Shot Chance | AF7: Mythic | AG7: =MOD_SUBSTAT_LOOKUP(AE7,AF7,1) -> +9% | AH7: =IF(ISBLANK(AE7), "", MOD_SUBSTAT_LOOKUP(AE7,AF7,0)) -> 0.09 | AL7: =MOD_SUBSTAT_LOOKUP(AJ7,AK7,1) | AM7: =IF(ISBLANK(AJ7), "", MOD_SUBSTAT_LOOKUP(AJ7,AK7,0)) | AQ7: =MOD_SUBSTAT_LOOKUP(AO7,AP7,1) | AR7: =IF(ISBLANK(AO7), "", MOD_SUBSTAT_LOOKUP(AO7,AP7,0))
D8: 0 | H8: =MOD_SUBSTAT_LOOKUP(F8,G8,1) | I8: =IF(ISBLANK(F8), "", MOD_SUBSTAT_LOOKUP(F8,G8,0)) | K8: Multishot Targets | L8: Mythic | M8: =MOD_SUBSTAT_LOOKUP(K8,L8,1) -> +3 | N8: =IF(ISBLANK(K8), "", MOD_SUBSTAT_LOOKUP(K8,L8,0)) -> 3 | P8: Bounce Shot Chance | Q8: Mythic | R8: =MOD_SUBSTAT_LOOKUP(P8,Q8,1) -> +9% | S8: =IF(ISBLANK(P8), "", MOD_SUBSTAT_LOOKUP(P8,Q8,0)) -> 0.09 | W8: =MOD_SUBSTAT_LOOKUP(U8,V8,1) | X8: =IF(ISBLANK(U8), "", MOD_SUBSTAT_LOOKUP(U8,V8,0)) | AB8: =MOD_SUBSTAT_LOOKUP(Z8,AA8,1) | AC8: =IF(ISBLANK(Z8), "", MOD_SUBSTAT_LOOKUP(Z8,AA8,0)) | AE8: Attack Speed | AF8: Mythic | AG8: =MOD_SUBSTAT_LOOKUP(AE8,AF8,1) -> +3 | AH8: =IF(ISBLANK(AE8), "", MOD_SUBSTAT_LOOKUP(AE8,AF8,0)) -> 3 | AL8: =MOD_SUBSTAT_LOOKUP(AJ8,AK8,1) | AM8: =IF(ISBLANK(AJ8), "", MOD_SUBSTAT_LOOKUP(AJ8,AK8,0)) | AQ8: =MOD_SUBSTAT_LOOKUP(AO8,AP8,1) | AR8: =IF(ISBLANK(AO8), "", MOD_SUBSTAT_LOOKUP(AO8,AP8,0))
H9: =MOD_SUBSTAT_LOOKUP(F9,G9,1) | I9: =IF(ISBLANK(F9), "", MOD_SUBSTAT_LOOKUP(F9,G9,0)) | K9: Critical Factor | L9: Mythic | M9: =MOD_SUBSTAT_LOOKUP(K9,L9,1) -> +12x | N9: =IF(ISBLANK(K9), "", MOD_SUBSTAT_LOOKUP(K9,L9,0)) -> 12 | P9: Bounce Shot Targets | Q9: Mythic | R9: =MOD_SUBSTAT_LOOKUP(P9,Q9,1) -> +3 | S9: =IF(ISBLANK(P9), "", MOD_SUBSTAT_LOOKUP(P9,Q9,0)) -> 3 | W9: =MOD_SUBSTAT_LOOKUP(U9,V9,1) | X9: =IF(ISBLANK(U9), "", MOD_SUBSTAT_LOOKUP(U9,V9,0)) | AB9: =MOD_SUBSTAT_LOOKUP(Z9,AA9,1) | AC9: =IF(ISBLANK(Z9), "", MOD_SUBSTAT_LOOKUP(Z9,AA9,0)) | AE9: Multishot Targets | AF9: Ancestral | AG9: =MOD_SUBSTAT_LOOKUP(AE9,AF9,1) -> +4 | AH9: =IF(ISBLANK(AE9), "", MOD_SUBSTAT_LOOKUP(AE9,AF9,0)) -> 4 | AL9: =MOD_SUBSTAT_LOOKUP(AJ9,AK9,1) | AM9: =IF(ISBLANK(AJ9), "", MOD_SUBSTAT_LOOKUP(AJ9,AK9,0)) | AQ9: =MOD_SUBSTAT_LOOKUP(AO9,AP9,1) | AR9: =IF(ISBLANK(AO9), "", MOD_SUBSTAT_LOOKUP(AO9,AP9,0))
H10: =MOD_SUBSTAT_LOOKUP(F10,G10,1) | I10: =IF(ISBLANK(F10), "", MOD_SUBSTAT_LOOKUP(F10,G10,0)) | K10: Bounce Shot Chance | L10: Mythic | M10: =MOD_SUBSTAT_LOOKUP(K10,L10,1) -> +9% | N10: =IF(ISBLANK(K10), "", MOD_SUBSTAT_LOOKUP(K10,L10,0)) -> 0.09 | P10: Multishot Targets | Q10: Mythic | R10: =MOD_SUBSTAT_LOOKUP(P10,Q10,1) -> +3 | S10: =IF(ISBLANK(P10), "", MOD_SUBSTAT_LOOKUP(P10,Q10,0)) -> 3 | W10: =MOD_SUBSTAT_LOOKUP(U10,V10,1) | X10: =IF(ISBLANK(U10), "", MOD_SUBSTAT_LOOKUP(U10,V10,0)) | AB10: =MOD_SUBSTAT_LOOKUP(Z10,AA10,1) | AC10: =IF(ISBLANK(Z10), "", MOD_SUBSTAT_LOOKUP(Z10,AA10,0)) | AE10: Critical Factor | AF10: Ancestral | AG10: =MOD_SUBSTAT_LOOKUP(AE10,AF10,1) -> +15x | AH10: =IF(ISBLANK(AE10), "", MOD_SUBSTAT_LOOKUP(AE10,AF10,0)) -> 15 | AL10: =MOD_SUBSTAT_LOOKUP(AJ10,AK10,1) | AM10: =IF(ISBLANK(AJ10), "", MOD_SUBSTAT_LOOKUP(AJ10,AK10,0)) | AQ10: =MOD_SUBSTAT_LOOKUP(AO10,AP10,1) | AR10: =IF(ISBLANK(AO10), "", MOD_SUBSTAT_LOOKUP(AO10,AP10,0))
H11: =MOD_SUBSTAT_LOOKUP(F11,G11,1) | I11: =IF(ISBLANK(F11), "", MOD_SUBSTAT_LOOKUP(F11,G11,0)) | M11: =MOD_SUBSTAT_LOOKUP(K11,L11,1) | N11: =IF(ISBLANK(K11), "", MOD_SUBSTAT_LOOKUP(K11,L11,0)) | R11: =MOD_SUBSTAT_LOOKUP(P11,Q11,1) | S11: =IF(ISBLANK(P11), "", MOD_SUBSTAT_LOOKUP(P11,Q11,0)) | W11: =MOD_SUBSTAT_LOOKUP(U11,V11,1) | X11: =IF(ISBLANK(U11), "", MOD_SUBSTAT_LOOKUP(U11,V11,0)) | AB11: =MOD_SUBSTAT_LOOKUP(Z11,AA11,1) | AC11: =IF(ISBLANK(Z11), "", MOD_SUBSTAT_LOOKUP(Z11,AA11,0)) | AE11: Super Crit Multi | AF11: Mythic | AG11: =MOD_SUBSTAT_LOOKUP(AE11,AF11,1) -> +5x | AH11: =IF(ISBLANK(AE11), "", MOD_SUBSTAT_LOOKUP(AE11,AF11,0)) -> 5 | AL11: =MOD_SUBSTAT_LOOKUP(AJ11,AK11,1) | AM11: =IF(ISBLANK(AJ11), "", MOD_SUBSTAT_LOOKUP(AJ11,AK11,0)) | AQ11: =MOD_SUBSTAT_LOOKUP(AO11,AP11,1) | AR11: =IF(ISBLANK(AO11), "", MOD_SUBSTAT_LOOKUP(AO11,AP11,0))
H12: =MOD_SUBSTAT_LOOKUP(F12,G12,1) | I12: =IF(ISBLANK(F12), "", MOD_SUBSTAT_LOOKUP(F12,G12,0)) | M12: =MOD_SUBSTAT_LOOKUP(K12,L12,1) | N12: =IF(ISBLANK(K12), "", MOD_SUBSTAT_LOOKUP(K12,L12,0)) | R12: =MOD_SUBSTAT_LOOKUP(P12,Q12,1) | S12: =IF(ISBLANK(P12), "", MOD_SUBSTAT_LOOKUP(P12,Q12,0)) | W12: =MOD_SUBSTAT_LOOKUP(U12,V12,1) | X12: =IF(ISBLANK(U12), "", MOD_SUBSTAT_LOOKUP(U12,V12,0)) | AB12: =MOD_SUBSTAT_LOOKUP(Z12,AA12,1) | AC12: =IF(ISBLANK(Z12), "", MOD_SUBSTAT_LOOKUP(Z12,AA12,0)) | AG12: =MOD_SUBSTAT_LOOKUP(AE12,AF12,1) | AH12: =IF(ISBLANK(AE12), "", MOD_SUBSTAT_LOOKUP(AE12,AF12,0)) | AL12: =MOD_SUBSTAT_LOOKUP(AJ12,AK12,1) | AM12: =IF(ISBLANK(AJ12), "", MOD_SUBSTAT_LOOKUP(AJ12,AK12,0)) | AQ12: =MOD_SUBSTAT_LOOKUP(AO12,AP12,1) | AR12: =IF(ISBLANK(AO12), "", MOD_SUBSTAT_LOOKUP(AO12,AP12,0))
H13: =MOD_SUBSTAT_LOOKUP(F13,G13,1) | I13: =IF(ISBLANK(F13), "", MOD_SUBSTAT_LOOKUP(F13,G13,0)) | M13: =MOD_SUBSTAT_LOOKUP(K13,L13,1) | N13: =IF(ISBLANK(K13), "", MOD_SUBSTAT_LOOKUP(K13,L13,0)) | R13: =MOD_SUBSTAT_LOOKUP(P13,Q13,1) | S13: =IF(ISBLANK(P13), "", MOD_SUBSTAT_LOOKUP(P13,Q13,0)) | W13: =MOD_SUBSTAT_LOOKUP(U13,V13,1) | X13: =IF(ISBLANK(U13), "", MOD_SUBSTAT_LOOKUP(U13,V13,0)) | AB13: =MOD_SUBSTAT_LOOKUP(Z13,AA13,1) | AC13: =IF(ISBLANK(Z13), "", MOD_SUBSTAT_LOOKUP(Z13,AA13,0)) | AG13: =MOD_SUBSTAT_LOOKUP(AE13,AF13,1) | AH13: =IF(ISBLANK(AE13), "", MOD_SUBSTAT_LOOKUP(AE13,AF13,0)) | AL13: =MOD_SUBSTAT_LOOKUP(AJ13,AK13,1) | AM13: =IF(ISBLANK(AJ13), "", MOD_SUBSTAT_LOOKUP(AJ13,AK13,0)) | AQ13: =MOD_SUBSTAT_LOOKUP(AO13,AP13,1) | AR13: =IF(ISBLANK(AO13), "", MOD_SUBSTAT_LOOKUP(AO13,AP13,0))
H14: =MOD_SUBSTAT_LOOKUP(F14,G14,1) | I14: =IF(ISBLANK(F14), "", MOD_SUBSTAT_LOOKUP(F14,G14,0)) | M14: =MOD_SUBSTAT_LOOKUP(K14,L14,1) | N14: =IF(ISBLANK(K14), "", MOD_SUBSTAT_LOOKUP(K14,L14,0)) | R14: =MOD_SUBSTAT_LOOKUP(P14,Q14,1) | S14: =IF(ISBLANK(P14), "", MOD_SUBSTAT_LOOKUP(P14,Q14,0)) | W14: =MOD_SUBSTAT_LOOKUP(U14,V14,1) | X14: =IF(ISBLANK(U14), "", MOD_SUBSTAT_LOOKUP(U14,V14,0)) | AB14: =MOD_SUBSTAT_LOOKUP(Z14,AA14,1) | AC14: =IF(ISBLANK(Z14), "", MOD_SUBSTAT_LOOKUP(Z14,AA14,0)) | AG14: =MOD_SUBSTAT_LOOKUP(AE14,AF14,1) | AH14: =IF(ISBLANK(AE14), "", MOD_SUBSTAT_LOOKUP(AE14,AF14,0)) | AL14: =MOD_SUBSTAT_LOOKUP(AJ14,AK14,1) | AM14: =IF(ISBLANK(AJ14), "", MOD_SUBSTAT_LOOKUP(AJ14,AK14,0)) | AQ14: =MOD_SUBSTAT_LOOKUP(AO14,AP14,1) | AR14: =IF(ISBLANK(AO14), "", MOD_SUBSTAT_LOOKUP(AO14,AP14,0))
A16: 🟥 ARMOR | F16: Anti-Cube Portal | K16: Negative Mass Projector | P16: Space Displacer | U16: Wormhole Redirector | Z16: Sharp Fortitude | AE16: Orbital Augment | AJ16: Any Other | AO16: Any Other 2
D17: Highest Level | F17: Rarity | G17: Level | H17: Stat | K17: Rarity | L17: Level | M17: Stat | P17: Rarity | Q17: Level | R17: Stat | U17: Rarity | V17: Level | W17: Stat | Z17: Rarity | AA17: Level | AB17: Stat | AE17: Rarity | AF17: Level | AG17: Stat | AJ17: Rarity | AK17: Level | AL17: Stat | AO17: Rarity | AP17: Level | AQ17: Stat
B18: Tower Health | D18: 163 | F18: Mythic+ | G18: =CAP_MOD_LEVEL($D18,F18) -> 160 | H18: =IF(F18="None",1,MODSTAT_ARMOR(F18,G18)) -> 8.19 | K18: Legendary | L18: =CAP_MOD_LEVEL($D18,K18) -> 100 | M18: =IF(K18="None",1,MODSTAT_ARMOR(K18,L18)) -> 2.27 | P18: Ancestral 2* | Q18: =CAP_MOD_LEVEL($D18,P18) -> 163 | R18: =IF(P18="None",1,MODSTAT_ARMOR(P18,Q18)) -> 9.467 | U18: Mythic+ | V18: =CAP_MOD_LEVEL($D18,U18) -> 160 | W18: =IF(U18="None",1,MODSTAT_ARMOR(U18,V18)) -> 8.19 | Z18: Ancestral | AA18: =CAP_MOD_LEVEL($D18,Z18) -> 163 | AB18: =IF(Z18="None",1,MODSTAT_ARMOR(Z18,AA18)) -> 8.84 | AE18: Ancestral 1* | AF18: =CAP_MOD_LEVEL($D18,AE18) -> 163 | AG18: =IF(AE18="None",1,MODSTAT_ARMOR(AE18,AF18)) -> 9.154 | AJ18: Epic | AK18: =CAP_MOD_LEVEL($D18,AJ18) -> 60 | AL18: =IF(AJ18="None",1,MODSTAT_ARMOR(AJ18,AK18)) -> 1.37 | AO18: Common | AP18: =CAP_MOD_LEVEL($D18,AO18) -> 20 | AQ18: =IF(AO18="None",1,MODSTAT_ARMOR(AO18,AP18)) -> 1.05
D20: Assist Level | F20: Orb Speed | G20: Legendary | H20: =MOD_SUBSTAT_LOOKUP(F20,G20,1) -> +1.5 | I20: =IF(ISBLANK(F20), "", MOD_SUBSTAT_LOOKUP(F20,G20,0)) -> 1.5 | M20: =MOD_SUBSTAT_LOOKUP(K20,L20,1) | N20: =IF(ISBLANK(K20), "", MOD_SUBSTAT_LOOKUP(K20,L20,0)) | R20: =MOD_SUBSTAT_LOOKUP(P20,Q20,1) | S20: =IF(ISBLANK(P20), "", MOD_SUBSTAT_LOOKUP(P20,Q20,0)) | U20: Defense % | V20: Legendary | W20: =MOD_SUBSTAT_LOOKUP(U20,V20,1) -> +5% | X20: =IF(ISBLANK(U20), "", MOD_SUBSTAT_LOOKUP(U20,V20,0)) -> 0.05 | Z20: Health Regen | AA20: Ancestral | AB20: =MOD_SUBSTAT_LOOKUP(Z20,AA20,1) -> +400% | AC20: =IF(ISBLANK(Z20), "", MOD_SUBSTAT_LOOKUP(Z20,AA20,0)) -> 4 | AE20: Defense % | AF20: Ancestral | AG20: =MOD_SUBSTAT_LOOKUP(AE20,AF20,1) -> +8% | AH20: =IF(ISBLANK(AE20), "", MOD_SUBSTAT_LOOKUP(AE20,AF20,0)) -> 0.08 | AL20: =MOD_SUBSTAT_LOOKUP(AJ20,AK20,1) | AM20: =IF(ISBLANK(AJ20), "", MOD_SUBSTAT_LOOKUP(AJ20,AK20,0)) | AQ20: =MOD_SUBSTAT_LOOKUP(AO20,AP20,1) | AR20: =IF(ISBLANK(AO20), "", MOD_SUBSTAT_LOOKUP(AO20,AP20,0))
D21: 41 | F21: Shockwave Size | G21: Legendary | H21: =MOD_SUBSTAT_LOOKUP(F21,G21,1) -> +0.3 | I21: =IF(ISBLANK(F21), "", MOD_SUBSTAT_LOOKUP(F21,G21,0)) -> 0.3 | M21: =MOD_SUBSTAT_LOOKUP(K21,L21,1) | N21: =IF(ISBLANK(K21), "", MOD_SUBSTAT_LOOKUP(K21,L21,0)) | R21: =MOD_SUBSTAT_LOOKUP(P21,Q21,1) | S21: =IF(ISBLANK(P21), "", MOD_SUBSTAT_LOOKUP(P21,Q21,0)) | U21: Wall Health | V21: Legendary | W21: =MOD_SUBSTAT_LOOKUP(U21,V21,1) -> +40% | X21: =IF(ISBLANK(U21), "", MOD_SUBSTAT_LOOKUP(U21,V21,0)) -> 0.4 | Z21: Knockback Force | AA21: Mythic | AB21: =MOD_SUBSTAT_LOOKUP(Z21,AA21,1) -> +0.9 | AC21: =IF(ISBLANK(Z21), "", MOD_SUBSTAT_LOOKUP(Z21,AA21,0)) -> 0.9 | AE21: Health Regen | AF21: Ancestral | AG21: =MOD_SUBSTAT_LOOKUP(AE21,AF21,1) -> +400% | AH21: =IF(ISBLANK(AE21), "", MOD_SUBSTAT_LOOKUP(AE21,AF21,0)) -> 4 | AL21: =MOD_SUBSTAT_LOOKUP(AJ21,AK21,1) | AM21: =IF(ISBLANK(AJ21), "", MOD_SUBSTAT_LOOKUP(AJ21,AK21,0)) | AQ21: =MOD_SUBSTAT_LOOKUP(AO21,AP21,1) | AR21: =IF(ISBLANK(AO21), "", MOD_SUBSTAT_LOOKUP(AO21,AP21,0))
F22: Death Defy | G22: Legendary | H22: =MOD_SUBSTAT_LOOKUP(F22,G22,1) -> +1.5% | I22: =IF(ISBLANK(F22), "", MOD_SUBSTAT_LOOKUP(F22,G22,0)) -> 0.015 | M22: =MOD_SUBSTAT_LOOKUP(K22,L22,1) | N22: =IF(ISBLANK(K22), "", MOD_SUBSTAT_LOOKUP(K22,L22,0)) | R22: =MOD_SUBSTAT_LOOKUP(P22,Q22,1) | S22: =IF(ISBLANK(P22), "", MOD_SUBSTAT_LOOKUP(P22,Q22,0)) | U22: Health Regen | V22: Legendary | W22: =MOD_SUBSTAT_LOOKUP(U22,V22,1) -> +100% | X22: =IF(ISBLANK(U22), "", MOD_SUBSTAT_LOOKUP(U22,V22,0)) -> 1 | Z22: Defense % | AA22: Ancestral | AB22: =MOD_SUBSTAT_LOOKUP(Z22,AA22,1) -> +8% | AC22: =IF(ISBLANK(Z22), "", MOD_SUBSTAT_LOOKUP(Z22,AA22,0)) -> 0.08 | AE22: Wall Health | AF22: Ancestral | AG22: =MOD_SUBSTAT_LOOKUP(AE22,AF22,1) -> +120% | AH22: =IF(ISBLANK(AE22), "", MOD_SUBSTAT_LOOKUP(AE22,AF22,0)) -> 1.2 | AL22: =MOD_SUBSTAT_LOOKUP(AJ22,AK22,1) | AM22: =IF(ISBLANK(AJ22), "", MOD_SUBSTAT_LOOKUP(AJ22,AK22,0)) | AQ22: =MOD_SUBSTAT_LOOKUP(AO22,AP22,1) | AR22: =IF(ISBLANK(AO22), "", MOD_SUBSTAT_LOOKUP(AO22,AP22,0))
H23: =MOD_SUBSTAT_LOOKUP(F23,G23,1) | I23: =IF(ISBLANK(F23), "", MOD_SUBSTAT_LOOKUP(F23,G23,0)) | M23: =MOD_SUBSTAT_LOOKUP(K23,L23,1) | N23: =IF(ISBLANK(K23), "", MOD_SUBSTAT_LOOKUP(K23,L23,0)) | R23: =MOD_SUBSTAT_LOOKUP(P23,Q23,1) | S23: =IF(ISBLANK(P23), "", MOD_SUBSTAT_LOOKUP(P23,Q23,0)) | W23: =MOD_SUBSTAT_LOOKUP(U23,V23,1) | X23: =IF(ISBLANK(U23), "", MOD_SUBSTAT_LOOKUP(U23,V23,0)) | Z23: Wall Health | AA23: Ancestral | AB23: =MOD_SUBSTAT_LOOKUP(Z23,AA23,1) -> +120% | AC23: =IF(ISBLANK(Z23), "", MOD_SUBSTAT_LOOKUP(Z23,AA23,0)) -> 1.2 | AE23: Thorns Damage | AF23: Ancestral | AG23: =MOD_SUBSTAT_LOOKUP(AE23,AF23,1) -> +10% | AH23: =IF(ISBLANK(AE23), "", MOD_SUBSTAT_LOOKUP(AE23,AF23,0)) -> 0.1 | AL23: =MOD_SUBSTAT_LOOKUP(AJ23,AK23,1) | AM23: =IF(ISBLANK(AJ23), "", MOD_SUBSTAT_LOOKUP(AJ23,AK23,0)) | AQ23: =MOD_SUBSTAT_LOOKUP(AO23,AP23,1) | AR23: =IF(ISBLANK(AO23), "", MOD_SUBSTAT_LOOKUP(AO23,AP23,0))
H24: =MOD_SUBSTAT_LOOKUP(F24,G24,1) | I24: =IF(ISBLANK(F24), "", MOD_SUBSTAT_LOOKUP(F24,G24,0)) | M24: =MOD_SUBSTAT_LOOKUP(K24,L24,1) | N24: =IF(ISBLANK(K24), "", MOD_SUBSTAT_LOOKUP(K24,L24,0)) | R24: =MOD_SUBSTAT_LOOKUP(P24,Q24,1) | S24: =IF(ISBLANK(P24), "", MOD_SUBSTAT_LOOKUP(P24,Q24,0)) | W24: =MOD_SUBSTAT_LOOKUP(U24,V24,1) | X24: =IF(ISBLANK(U24), "", MOD_SUBSTAT_LOOKUP(U24,V24,0)) | Z24: Thorns Damage | AA24: Ancestral | AB24: =MOD_SUBSTAT_LOOKUP(Z24,AA24,1) -> +10% | AC24: =IF(ISBLANK(Z24), "", MOD_SUBSTAT_LOOKUP(Z24,AA24,0)) -> 0.1 | AG24: =MOD_SUBSTAT_LOOKUP(AE24,AF24,1) | AH24: =IF(ISBLANK(AE24), "", MOD_SUBSTAT_LOOKUP(AE24,AF24,0)) | AL24: =MOD_SUBSTAT_LOOKUP(AJ24,AK24,1) | AM24: =IF(ISBLANK(AJ24), "", MOD_SUBSTAT_LOOKUP(AJ24,AK24,0)) | AQ24: =MOD_SUBSTAT_LOOKUP(AO24,AP24,1) | AR24: =IF(ISBLANK(AO24), "", MOD_SUBSTAT_LOOKUP(AO24,AP24,0))
H25: =MOD_SUBSTAT_LOOKUP(F25,G25,1) | I25: =IF(ISBLANK(F25), "", MOD_SUBSTAT_LOOKUP(F25,G25,0)) | M25: =MOD_SUBSTAT_LOOKUP(K25,L25,1) | N25: =IF(ISBLANK(K25), "", MOD_SUBSTAT_LOOKUP(K25,L25,0)) | R25: =MOD_SUBSTAT_LOOKUP(P25,Q25,1) | S25: =IF(ISBLANK(P25), "", MOD_SUBSTAT_LOOKUP(P25,Q25,0)) | W25: =MOD_SUBSTAT_LOOKUP(U25,V25,1) | X25: =IF(ISBLANK(U25), "", MOD_SUBSTAT_LOOKUP(U25,V25,0)) | Z25: Orb Speed | AA25: Epic | AB25: =MOD_SUBSTAT_LOOKUP(Z25,AA25,1) -> +1 | AC25: =IF(ISBLANK(Z25), "", MOD_SUBSTAT_LOOKUP(Z25,AA25,0)) -> 1 | AG25: =MOD_SUBSTAT_LOOKUP(AE25,AF25,1) | AH25: =IF(ISBLANK(AE25), "", MOD_SUBSTAT_LOOKUP(AE25,AF25,0)) | AL25: =MOD_SUBSTAT_LOOKUP(AJ25,AK25,1) | AM25: =IF(ISBLANK(AJ25), "", MOD_SUBSTAT_LOOKUP(AJ25,AK25,0)) | AQ25: =MOD_SUBSTAT_LOOKUP(AO25,AP25,1) | AR25: =IF(ISBLANK(AO25), "", MOD_SUBSTAT_LOOKUP(AO25,AP25,0))
H26: =MOD_SUBSTAT_LOOKUP(F26,G26,1) | I26: =IF(ISBLANK(F26), "", MOD_SUBSTAT_LOOKUP(F26,G26,0)) | M26: =MOD_SUBSTAT_LOOKUP(K26,L26,1) | N26: =IF(ISBLANK(K26), "", MOD_SUBSTAT_LOOKUP(K26,L26,0)) | R26: =MOD_SUBSTAT_LOOKUP(P26,Q26,1) | S26: =IF(ISBLANK(P26), "", MOD_SUBSTAT_LOOKUP(P26,Q26,0)) | W26: =MOD_SUBSTAT_LOOKUP(U26,V26,1) | X26: =IF(ISBLANK(U26), "", MOD_SUBSTAT_LOOKUP(U26,V26,0)) | AB26: =MOD_SUBSTAT_LOOKUP(Z26,AA26,1) | AC26: =IF(ISBLANK(Z26), "", MOD_SUBSTAT_LOOKUP(Z26,AA26,0)) | AG26: =MOD_SUBSTAT_LOOKUP(AE26,AF26,1) | AH26: =IF(ISBLANK(AE26), "", MOD_SUBSTAT_LOOKUP(AE26,AF26,0)) | AL26: =MOD_SUBSTAT_LOOKUP(AJ26,AK26,1) | AM26: =IF(ISBLANK(AJ26), "", MOD_SUBSTAT_LOOKUP(AJ26,AK26,0)) | AQ26: =MOD_SUBSTAT_LOOKUP(AO26,AP26,1) | AR26: =IF(ISBLANK(AO26), "", MOD_SUBSTAT_LOOKUP(AO26,AP26,0))
H27: =MOD_SUBSTAT_LOOKUP(F27,G27,1) | I27: =IF(ISBLANK(F27), "", MOD_SUBSTAT_LOOKUP(F27,G27,0)) | M27: =MOD_SUBSTAT_LOOKUP(K27,L27,1) | N27: =IF(ISBLANK(K27), "", MOD_SUBSTAT_LOOKUP(K27,L27,0)) | R27: =MOD_SUBSTAT_LOOKUP(P27,Q27,1) | S27: =IF(ISBLANK(P27), "", MOD_SUBSTAT_LOOKUP(P27,Q27,0)) | W27: =MOD_SUBSTAT_LOOKUP(U27,V27,1) | X27: =IF(ISBLANK(U27), "", MOD_SUBSTAT_LOOKUP(U27,V27,0)) | AB27: =MOD_SUBSTAT_LOOKUP(Z27,AA27,1) | AC27: =IF(ISBLANK(Z27), "", MOD_SUBSTAT_LOOKUP(Z27,AA27,0)) | AG27: =MOD_SUBSTAT_LOOKUP(AE27,AF27,1) | AH27: =IF(ISBLANK(AE27), "", MOD_SUBSTAT_LOOKUP(AE27,AF27,0)) | AL27: =MOD_SUBSTAT_LOOKUP(AJ27,AK27,1) | AM27: =IF(ISBLANK(AJ27), "", MOD_SUBSTAT_LOOKUP(AJ27,AK27,0)) | AQ27: =MOD_SUBSTAT_LOOKUP(AO27,AP27,1) | AR27: =IF(ISBLANK(AO27), "", MOD_SUBSTAT_LOOKUP(AO27,AP27,0))
A29: ▲ GENERATOR | F29: Black Hole Digestor | K29: Galaxy Compressor | P29: Singularity Harness | U29: Pulsar Harvester | Z29: Project Funding | AE29: Restorative Bonus | AJ29: Any Other | AO29: Any Other 2
D30: Highest Level | F30: Rarity | G30: Level | H30: Stat | K30: Rarity | L30: Level | M30: Stat | P30: Rarity | Q30: Level | R30: Stat | U30: Rarity | V30: Level | W30: Stat | Z30: Rarity | AA30: Level | AB30: Stat | AE30: Rarity | AF30: Level | AG30: Stat | AJ30: Rarity | AK30: Level | AL30: Stat | AO30: Rarity | AP30: Level | AQ30: Stat
B31: Coin Bonus | D31: 161 | F31: Legendary | G31: =CAP_MOD_LEVEL($D31,F31) -> 100 | H31: =IF(F31="None",1,MODSTAT_GENERATOR(F31,G31)) -> 1.275 | K31: Mythic+ | L31: =CAP_MOD_LEVEL($D31,K31) -> 160 | M31: =IF(K31="None",1,MODSTAT_GENERATOR(K31,L31)) -> 1.665 | P31: Ancestral | Q31: =CAP_MOD_LEVEL($D31,P31) -> 161 | R31: =IF(P31="None",1,MODSTAT_GENERATOR(P31,Q31)) -> 1.68 | U31: Ancestral 1* | V31: =CAP_MOD_LEVEL($D31,U31) -> 161 | W31: =IF(U31="None",1,MODSTAT_GENERATOR(U31,V31)) -> 1.707 | Z31: Mythic+ | AA31: =CAP_MOD_LEVEL($D31,Z31) -> 160 | AB31: =IF(Z31="None",1,MODSTAT_GENERATOR(Z31,AA31)) -> 1.665 | AE31: Mythic+ | AF31: =CAP_MOD_LEVEL($D31,AE31) -> 160 | AG31: =IF(AE31="None",1,MODSTAT_GENERATOR(AE31,AF31)) -> 1.665 | AJ31: Legendary | AK31: =CAP_MOD_LEVEL($D31,AJ31) -> 100 | AL31: =IF(AJ31="None",1,MODSTAT_GENERATOR(AJ31,AK31)) -> 1.275 | AO31: Common | AP31: =CAP_MOD_LEVEL($D31,AO31) -> 20 | AQ31: =IF(AO31="None",1,MODSTAT_GENERATOR(AO31,AP31)) -> 1.03
D33: Assist Level | F33: Coins / Kill Bonus | G33: Legendary | H33: =MOD_SUBSTAT_LOOKUP(F33,G33,1) -> +0.4x | I33: =IF(ISBLANK(F33), "", MOD_SUBSTAT_LOOKUP(F33,G33,0)) -> 0.4 | K33: Package Chance | L33: Legendary | M33: =MOD_SUBSTAT_LOOKUP(K33,L33,1) -> +8% | N33: =IF(ISBLANK(K33), "", MOD_SUBSTAT_LOOKUP(K33,L33,0)) -> 0.08 | P33: Free Utility Upgrade | Q33: Mythic | R33: =MOD_SUBSTAT_LOOKUP(P33,Q33,1) -> +10% | S33: =IF(ISBLANK(P33), "", MOD_SUBSTAT_LOOKUP(P33,Q33,0)) -> 0.1 | U33: Free Utility Upgrade | V33: Ancestral | W33: =MOD_SUBSTAT_LOOKUP(U33,V33,1) -> +12% | X33: =IF(ISBLANK(U33), "", MOD_SUBSTAT_LOOKUP(U33,V33,0)) -> 0.12 | Z33: Enemy Attack Level Skip | AA33: Mythic | AB33: =MOD_SUBSTAT_LOOKUP(Z33,AA33,1) -> +6% | AC33: =IF(ISBLANK(Z33), "", MOD_SUBSTAT_LOOKUP(Z33,AA33,0)) -> 0.06 | AE33: Enemy Health Level Skip | AF33: Mythic | AG33: =MOD_SUBSTAT_LOOKUP(AE33,AF33,1) -> +6% | AH33: =IF(ISBLANK(AE33), "", MOD_SUBSTAT_LOOKUP(AE33,AF33,0)) -> 0.06 | AJ33: Enemy Attack Level Skip | AK33: Legendary | AL33: =MOD_SUBSTAT_LOOKUP(AJ33,AK33,1) -> +4% | AM33: =IF(ISBLANK(AJ33), "", MOD_SUBSTAT_LOOKUP(AJ33,AK33,0)) -> 0.04 | AQ33: =MOD_SUBSTAT_LOOKUP(AO33,AP33,1) | AR33: =IF(ISBLANK(AO33), "", MOD_SUBSTAT_LOOKUP(AO33,AP33,0))
D34: 97 | F34: Enemy Attack Level Skip | G34: Legendary | H34: =MOD_SUBSTAT_LOOKUP(F34,G34,1) -> +4% | I34: =IF(ISBLANK(F34), "", MOD_SUBSTAT_LOOKUP(F34,G34,0)) -> 0.04 | K34: Enemy Attack Level Skip | L34: Legendary | M34: =MOD_SUBSTAT_LOOKUP(K34,L34,1) -> +4% | N34: =IF(ISBLANK(K34), "", MOD_SUBSTAT_LOOKUP(K34,L34,0)) -> 0.04 | P34: Coins / Kill Bonus | Q34: Mythic | R34: =MOD_SUBSTAT_LOOKUP(P34,Q34,1) -> +0.5x | S34: =IF(ISBLANK(P34), "", MOD_SUBSTAT_LOOKUP(P34,Q34,0)) -> 0.5 | U34: Enemy Attack Level Skip | V34: Ancestral | W34: =MOD_SUBSTAT_LOOKUP(U34,V34,1) -> +8% | X34: =IF(ISBLANK(U34), "", MOD_SUBSTAT_LOOKUP(U34,V34,0)) -> 0.08 | Z34: Enemy Health Level Skip | AA34: Mythic | AB34: =MOD_SUBSTAT_LOOKUP(Z34,AA34,1) -> +6% | AC34: =IF(ISBLANK(Z34), "", MOD_SUBSTAT_LOOKUP(Z34,AA34,0)) -> 0.06 | AE34: Enemy Attack Level Skip | AF34: Mythic | AG34: =MOD_SUBSTAT_LOOKUP(AE34,AF34,1) -> +6% | AH34: =IF(ISBLANK(AE34), "", MOD_SUBSTAT_LOOKUP(AE34,AF34,0)) -> 0.06 | AJ34: Coins / Kill Bonus | AK34: Epic | AL34: =MOD_SUBSTAT_LOOKUP(AJ34,AK34,1) -> +0.3x | AM34: =IF(ISBLANK(AJ34), "", MOD_SUBSTAT_LOOKUP(AJ34,AK34,0)) -> 0.3 | AQ34: =MOD_SUBSTAT_LOOKUP(AO34,AP34,1) | AR34: =IF(ISBLANK(AO34), "", MOD_SUBSTAT_LOOKUP(AO34,AP34,0))
F35: Free Utility Upgrade | G35: Legendary | H35: =MOD_SUBSTAT_LOOKUP(F35,G35,1) -> +8% | I35: =IF(ISBLANK(F35), "", MOD_SUBSTAT_LOOKUP(F35,G35,0)) -> 0.08 | K35: Free Utility Upgrade | L35: Legendary | M35: =MOD_SUBSTAT_LOOKUP(K35,L35,1) -> +8% | N35: =IF(ISBLANK(K35), "", MOD_SUBSTAT_LOOKUP(K35,L35,0)) -> 0.08 | P35: Enemy Health Level Skip | Q35: Mythic | R35: =MOD_SUBSTAT_LOOKUP(P35,Q35,1) -> +6% | S35: =IF(ISBLANK(P35), "", MOD_SUBSTAT_LOOKUP(P35,Q35,0)) -> 0.06 | U35: Coins / Kill Bonus | V35: Ancestral | W35: =MOD_SUBSTAT_LOOKUP(U35,V35,1) -> +0.6x | X35: =IF(ISBLANK(U35), "", MOD_SUBSTAT_LOOKUP(U35,V35,0)) -> 0.6 | Z35: Free Utility Upgrade | AA35: Mythic | AB35: =MOD_SUBSTAT_LOOKUP(Z35,AA35,1) -> +10% | AC35: =IF(ISBLANK(Z35), "", MOD_SUBSTAT_LOOKUP(Z35,AA35,0)) -> 0.1 | AE35: Free Utility Upgrade | AF35: Legendary | AG35: =MOD_SUBSTAT_LOOKUP(AE35,AF35,1) -> +8% | AH35: =IF(ISBLANK(AE35), "", MOD_SUBSTAT_LOOKUP(AE35,AF35,0)) -> 0.08 | AJ35: Free Utility Upgrade | AK35: Legendary | AL35: =MOD_SUBSTAT_LOOKUP(AJ35,AK35,1) -> +8% | AM35: =IF(ISBLANK(AJ35), "", MOD_SUBSTAT_LOOKUP(AJ35,AK35,0)) -> 0.08 | AQ35: =MOD_SUBSTAT_LOOKUP(AO35,AP35,1) | AR35: =IF(ISBLANK(AO35), "", MOD_SUBSTAT_LOOKUP(AO35,AP35,0))
H36: =MOD_SUBSTAT_LOOKUP(F36,G36,1) | I36: =IF(ISBLANK(F36), "", MOD_SUBSTAT_LOOKUP(F36,G36,0)) | M36: =MOD_SUBSTAT_LOOKUP(K36,L36,1) | N36: =IF(ISBLANK(K36), "", MOD_SUBSTAT_LOOKUP(K36,L36,0)) | P36: Enemy Attack Level Skip | Q36: Ancestral | R36: =MOD_SUBSTAT_LOOKUP(P36,Q36,1) -> +8% | S36: =IF(ISBLANK(P36), "", MOD_SUBSTAT_LOOKUP(P36,Q36,0)) -> 0.08 | U36: Enemy Health Level Skip | V36: Ancestral | W36: =MOD_SUBSTAT_LOOKUP(U36,V36,1) -> +8% | X36: =IF(ISBLANK(U36), "", MOD_SUBSTAT_LOOKUP(U36,V36,0)) -> 0.08 | Z36: Free Defense Upgrade | AA36: Epic | AB36: =MOD_SUBSTAT_LOOKUP(Z36,AA36,1) -> +6% | AC36: =IF(ISBLANK(Z36), "", MOD_SUBSTAT_LOOKUP(Z36,AA36,0)) -> 0.06 | AE36: Package Chance | AF36: Mythic | AG36: =MOD_SUBSTAT_LOOKUP(AE36,AF36,1) -> +11% | AH36: =IF(ISBLANK(AE36), "", MOD_SUBSTAT_LOOKUP(AE36,AF36,0)) -> 0.11 | AJ36: Free Attack Upgrade | AK36: Legendary | AL36: =MOD_SUBSTAT_LOOKUP(AJ36,AK36,1) -> +8% | AM36: =IF(ISBLANK(AJ36), "", MOD_SUBSTAT_LOOKUP(AJ36,AK36,0)) -> 0.08 | AQ36: =MOD_SUBSTAT_LOOKUP(AO36,AP36,1) | AR36: =IF(ISBLANK(AO36), "", MOD_SUBSTAT_LOOKUP(AO36,AP36,0))
H37: =MOD_SUBSTAT_LOOKUP(F37,G37,1) | I37: =IF(ISBLANK(F37), "", MOD_SUBSTAT_LOOKUP(F37,G37,0)) | M37: =MOD_SUBSTAT_LOOKUP(K37,L37,1) | N37: =IF(ISBLANK(K37), "", MOD_SUBSTAT_LOOKUP(K37,L37,0)) | P37: Package Chance | Q37: Mythic | R37: =MOD_SUBSTAT_LOOKUP(P37,Q37,1) -> +11% | S37: =IF(ISBLANK(P37), "", MOD_SUBSTAT_LOOKUP(P37,Q37,0)) -> 0.11 | U37: Package Chance | V37: Epic | W37: =MOD_SUBSTAT_LOOKUP(U37,V37,1) -> +5% | X37: =IF(ISBLANK(U37), "", MOD_SUBSTAT_LOOKUP(U37,V37,0)) -> 0.05 | Z37: Package Chance | AA37: Mythic | AB37: =MOD_SUBSTAT_LOOKUP(Z37,AA37,1) -> +11% | AC37: =IF(ISBLANK(Z37), "", MOD_SUBSTAT_LOOKUP(Z37,AA37,0)) -> 0.11 | AG37: =MOD_SUBSTAT_LOOKUP(AE37,AF37,1) | AH37: =IF(ISBLANK(AE37), "", MOD_SUBSTAT_LOOKUP(AE37,AF37,0)) | AL37: =MOD_SUBSTAT_LOOKUP(AJ37,AK37,1) | AM37: =IF(ISBLANK(AJ37), "", MOD_SUBSTAT_LOOKUP(AJ37,AK37,0)) | AQ37: =MOD_SUBSTAT_LOOKUP(AO37,AP37,1) | AR37: =IF(ISBLANK(AO37), "", MOD_SUBSTAT_LOOKUP(AO37,AP37,0))
H38: =MOD_SUBSTAT_LOOKUP(F38,G38,1) | I38: =IF(ISBLANK(F38), "", MOD_SUBSTAT_LOOKUP(F38,G38,0)) | M38: =MOD_SUBSTAT_LOOKUP(K38,L38,1) | N38: =IF(ISBLANK(K38), "", MOD_SUBSTAT_LOOKUP(K38,L38,0)) | R38: =MOD_SUBSTAT_LOOKUP(P38,Q38,1) | S38: =IF(ISBLANK(P38), "", MOD_SUBSTAT_LOOKUP(P38,Q38,0)) | W38: =MOD_SUBSTAT_LOOKUP(U38,V38,1) | X38: =IF(ISBLANK(U38), "", MOD_SUBSTAT_LOOKUP(U38,V38,0)) | AB38: =MOD_SUBSTAT_LOOKUP(Z38,AA38,1) | AC38: =IF(ISBLANK(Z38), "", MOD_SUBSTAT_LOOKUP(Z38,AA38,0)) | AG38: =MOD_SUBSTAT_LOOKUP(AE38,AF38,1) | AH38: =IF(ISBLANK(AE38), "", MOD_SUBSTAT_LOOKUP(AE38,AF38,0)) | AL38: =MOD_SUBSTAT_LOOKUP(AJ38,AK38,1) | AM38: =IF(ISBLANK(AJ38), "", MOD_SUBSTAT_LOOKUP(AJ38,AK38,0)) | AQ38: =MOD_SUBSTAT_LOOKUP(AO38,AP38,1) | AR38: =IF(ISBLANK(AO38), "", MOD_SUBSTAT_LOOKUP(AO38,AP38,0))
H39: =MOD_SUBSTAT_LOOKUP(F39,G39,1) | I39: =IF(ISBLANK(F39), "", MOD_SUBSTAT_LOOKUP(F39,G39,0)) | M39: =MOD_SUBSTAT_LOOKUP(K39,L39,1) | N39: =IF(ISBLANK(K39), "", MOD_SUBSTAT_LOOKUP(K39,L39,0)) | R39: =MOD_SUBSTAT_LOOKUP(P39,Q39,1) | S39: =IF(ISBLANK(P39), "", MOD_SUBSTAT_LOOKUP(P39,Q39,0)) | W39: =MOD_SUBSTAT_LOOKUP(U39,V39,1) | X39: =IF(ISBLANK(U39), "", MOD_SUBSTAT_LOOKUP(U39,V39,0)) | AB39: =MOD_SUBSTAT_LOOKUP(Z39,AA39,1) | AC39: =IF(ISBLANK(Z39), "", MOD_SUBSTAT_LOOKUP(Z39,AA39,0)) | AG39: =MOD_SUBSTAT_LOOKUP(AE39,AF39,1) | AH39: =IF(ISBLANK(AE39), "", MOD_SUBSTAT_LOOKUP(AE39,AF39,0)) | AL39: =MOD_SUBSTAT_LOOKUP(AJ39,AK39,1) | AM39: =IF(ISBLANK(AJ39), "", MOD_SUBSTAT_LOOKUP(AJ39,AK39,0)) | AQ39: =MOD_SUBSTAT_LOOKUP(AO39,AP39,1) | AR39: =IF(ISBLANK(AO39), "", MOD_SUBSTAT_LOOKUP(AO39,AP39,0))
H40: =MOD_SUBSTAT_LOOKUP(F40,G40,1) | I40: =IF(ISBLANK(F40), "", MOD_SUBSTAT_LOOKUP(F40,G40,0)) | M40: =MOD_SUBSTAT_LOOKUP(K40,L40,1) | N40: =IF(ISBLANK(K40), "", MOD_SUBSTAT_LOOKUP(K40,L40,0)) | R40: =MOD_SUBSTAT_LOOKUP(P40,Q40,1) | S40: =IF(ISBLANK(P40), "", MOD_SUBSTAT_LOOKUP(P40,Q40,0)) | W40: =MOD_SUBSTAT_LOOKUP(U40,V40,1) | X40: =IF(ISBLANK(U40), "", MOD_SUBSTAT_LOOKUP(U40,V40,0)) | AB40: =MOD_SUBSTAT_LOOKUP(Z40,AA40,1) | AC40: =IF(ISBLANK(Z40), "", MOD_SUBSTAT_LOOKUP(Z40,AA40,0)) | AG40: =MOD_SUBSTAT_LOOKUP(AE40,AF40,1) | AH40: =IF(ISBLANK(AE40), "", MOD_SUBSTAT_LOOKUP(AE40,AF40,0)) | AL40: =MOD_SUBSTAT_LOOKUP(AJ40,AK40,1) | AM40: =IF(ISBLANK(AJ40), "", MOD_SUBSTAT_LOOKUP(AJ40,AK40,0)) | AQ40: =MOD_SUBSTAT_LOOKUP(AO40,AP40,1) | AR40: =IF(ISBLANK(AO40), "", MOD_SUBSTAT_LOOKUP(AO40,AP40,0))
A42: 🔶 CORE | F42: Multiverse Nexus | K42: Dimension Core | P42: Harmony Conductor | U42: Om Chip | Z42: Magnetic Hook | AE42: Primordial Collapse | AJ42: Any Other | AO42: Any Other 2
D43: Highest Level | F43: Rarity | G43: Level | H43: Stat | K43: Rarity | L43: Level | M43: Stat | P43: Rarity | Q43: Level | R43: Stat | U43: Rarity | V43: Level | W43: Stat | Z43: Rarity | AA43: Level | AB43: Stat | AE43: Rarity | AF43: Level | AG43: Stat | AJ43: Rarity | AK43: Level | AL43: Stat | AO43: Rarity | AP43: Level | AQ43: Stat
B44: UW Damage | D44: 159 | F44: Ancestral 2* | G44: =CAP_MOD_LEVEL($D44,F44) -> 159 | H44: =IF(F44="None",1,MODSTAT_CORE(F44,G44)) -> 11.692 | K44: Ancestral | L44: =CAP_MOD_LEVEL($D44,K44) -> 159 | M44: =IF(K44="None",1,MODSTAT_CORE(K44,L44)) -> 10.9 | P44: Ancestral 5* | Q44: =CAP_MOD_LEVEL($D44,P44) -> 159 | R44: =IF(P44="None",1,MODSTAT_CORE(P44,Q44)) -> 12.88 | U44: Ancestral | V44: =CAP_MOD_LEVEL($D44,U44) -> 159 | W44: =IF(U44="None",1,MODSTAT_CORE(U44,V44)) -> 10.9 | Z44: Ancestral | AA44: =CAP_MOD_LEVEL($D44,Z44) -> 159 | AB44: =IF(Z44="None",1,MODSTAT_CORE(Z44,AA44)) -> 10.9 | AE44: Ancestral 2* | AF44: =CAP_MOD_LEVEL($D44,AE44) -> 159 | AG44: =IF(AE44="None",1,MODSTAT_CORE(AE44,AF44)) -> 11.692 | AJ44: Epic | AK44: =CAP_MOD_LEVEL($D44,AJ44) -> 60 | AL44: =IF(AJ44="None",1,MODSTAT_CORE(AJ44,AK44)) -> 2.17 | AO44: Common | AP44: =CAP_MOD_LEVEL($D44,AO44) -> 20 | AQ44: =IF(AO44="None",1,MODSTAT_CORE(AO44,AP44)) -> 1.23
D46: Assist Level | F46: Death Wave - Quantity | G46: Legendary | H46: =MOD_SUBSTAT_LOOKUP(F46,G46,1) -> +1 | I46: =IF(ISBLANK(F46), "", MOD_SUBSTAT_LOOKUP(F46,G46,0)) -> 1 | K46: Chain Lightning - Chance | L46: Mythic | M46: =MOD_SUBSTAT_LOOKUP(K46,L46,1) -> +12% | N46: =IF(ISBLANK(K46), "", MOD_SUBSTAT_LOOKUP(K46,L46,0)) -> 0.12 | R46: =MOD_SUBSTAT_LOOKUP(P46,Q46,1) | S46: =IF(ISBLANK(P46), "", MOD_SUBSTAT_LOOKUP(P46,Q46,0)) | U46: Chrono Field - Duration | V46: Mythic | W46: =MOD_SUBSTAT_LOOKUP(U46,V46,1) -> +7s | X46: =IF(ISBLANK(U46), "", MOD_SUBSTAT_LOOKUP(U46,V46,0)) -> 7 | AB46: =MOD_SUBSTAT_LOOKUP(Z46,AA46,1) | AC46: =IF(ISBLANK(Z46), "", MOD_SUBSTAT_LOOKUP(Z46,AA46,0)) | AE46: Black Hole - Duration | AF46: Ancestral | AG46: =MOD_SUBSTAT_LOOKUP(AE46,AF46,1) -> +4s | AH46: =IF(ISBLANK(AE46), "", MOD_SUBSTAT_LOOKUP(AE46,AF46,0)) -> 4 | AL46: =MOD_SUBSTAT_LOOKUP(AJ46,AK46,1) | AM46: =IF(ISBLANK(AJ46), "", MOD_SUBSTAT_LOOKUP(AJ46,AK46,0)) | AQ46: =MOD_SUBSTAT_LOOKUP(AO46,AP46,1) | AR46: =IF(ISBLANK(AO46), "", MOD_SUBSTAT_LOOKUP(AO46,AP46,0))
D47: 101 | F47: Golden Tower - Bonus | G47: Legendary | H47: =MOD_SUBSTAT_LOOKUP(F47,G47,1) -> +2x | I47: =IF(ISBLANK(F47), "", MOD_SUBSTAT_LOOKUP(F47,G47,0)) -> 2 | K47: Spotlight - Angle | L47: Mythic | M47: =MOD_SUBSTAT_LOOKUP(K47,L47,1) -> +11° | N47: =IF(ISBLANK(K47), "", MOD_SUBSTAT_LOOKUP(K47,L47,0)) -> 11 | R47: =MOD_SUBSTAT_LOOKUP(P47,Q47,1) | S47: =IF(ISBLANK(P47), "", MOD_SUBSTAT_LOOKUP(P47,Q47,0)) | U47: Spotlight - Bonus | V47: Mythic | W47: =MOD_SUBSTAT_LOOKUP(U47,V47,1) -> +15x | X47: =IF(ISBLANK(U47), "", MOD_SUBSTAT_LOOKUP(U47,V47,0)) -> 15 | AB47: =MOD_SUBSTAT_LOOKUP(Z47,AA47,1) | AC47: =IF(ISBLANK(Z47), "", MOD_SUBSTAT_LOOKUP(Z47,AA47,0)) | AE47: Black Hole - Cooldown | AF47: Ancestral | AG47: =MOD_SUBSTAT_LOOKUP(AE47,AF47,1) -> -4s | AH47: =IF(ISBLANK(AE47), "", MOD_SUBSTAT_LOOKUP(AE47,AF47,0)) -> -4 | AL47: =MOD_SUBSTAT_LOOKUP(AJ47,AK47,1) | AM47: =IF(ISBLANK(AJ47), "", MOD_SUBSTAT_LOOKUP(AJ47,AK47,0)) | AQ47: =MOD_SUBSTAT_LOOKUP(AO47,AP47,1) | AR47: =IF(ISBLANK(AO47), "", MOD_SUBSTAT_LOOKUP(AO47,AP47,0))
F48: Black Hole - Size | G48: Legendary | H48: =MOD_SUBSTAT_LOOKUP(F48,G48,1) -> +8.00m | I48: =IF(ISBLANK(F48), "", MOD_SUBSTAT_LOOKUP(F48,G48,0)) -> 8 | K48: Spotlight - Bonus | L48: Mythic | M48: =MOD_SUBSTAT_LOOKUP(K48,L48,1) -> +15x | N48: =IF(ISBLANK(K48), "", MOD_SUBSTAT_LOOKUP(K48,L48,0)) -> 15 | R48: =MOD_SUBSTAT_LOOKUP(P48,Q48,1) | S48: =IF(ISBLANK(P48), "", MOD_SUBSTAT_LOOKUP(P48,Q48,0)) | U48: Spotlight - Angle | V48: Epic | W48: =MOD_SUBSTAT_LOOKUP(U48,V48,1) -> +3° | X48: =IF(ISBLANK(U48), "", MOD_SUBSTAT_LOOKUP(U48,V48,0)) -> 3 | AB48: =MOD_SUBSTAT_LOOKUP(Z48,AA48,1) | AC48: =IF(ISBLANK(Z48), "", MOD_SUBSTAT_LOOKUP(Z48,AA48,0)) | AE48: Death Wave - Quantity | AF48: Mythic | AG48: =MOD_SUBSTAT_LOOKUP(AE48,AF48,1) -> +2 | AH48: =IF(ISBLANK(AE48), "", MOD_SUBSTAT_LOOKUP(AE48,AF48,0)) -> 2 | AL48: =MOD_SUBSTAT_LOOKUP(AJ48,AK48,1) | AM48: =IF(ISBLANK(AJ48), "", MOD_SUBSTAT_LOOKUP(AJ48,AK48,0)) | AQ48: =MOD_SUBSTAT_LOOKUP(AO48,AP48,1) | AR48: =IF(ISBLANK(AO48), "", MOD_SUBSTAT_LOOKUP(AO48,AP48,0))
F49: Spotlight - Angle | H49: =MOD_SUBSTAT_LOOKUP(F49,G49,1) | I49: =IF(ISBLANK(F49), "", MOD_SUBSTAT_LOOKUP(F49,G49,0)) | K49: Chain Lightning - Quantity | L49: Mythic | M49: =MOD_SUBSTAT_LOOKUP(K49,L49,1) -> +3 | N49: =IF(ISBLANK(K49), "", MOD_SUBSTAT_LOOKUP(K49,L49,0)) -> 3 | R49: =MOD_SUBSTAT_LOOKUP(P49,Q49,1) | S49: =IF(ISBLANK(P49), "", MOD_SUBSTAT_LOOKUP(P49,Q49,0)) | U49: Chain Lightning - Chance | V49: Rare | W49: =MOD_SUBSTAT_LOOKUP(U49,V49,1) -> +4% | X49: =IF(ISBLANK(U49), "", MOD_SUBSTAT_LOOKUP(U49,V49,0)) -> 0.04 | AB49: =MOD_SUBSTAT_LOOKUP(Z49,AA49,1) | AC49: =IF(ISBLANK(Z49), "", MOD_SUBSTAT_LOOKUP(Z49,AA49,0)) | AE49: Spotlight - Angle | AF49: Ancestral | AG49: =MOD_SUBSTAT_LOOKUP(AE49,AF49,1) -> +15° | AH49: =IF(ISBLANK(AE49), "", MOD_SUBSTAT_LOOKUP(AE49,AF49,0)) -> 15 | AL49: =MOD_SUBSTAT_LOOKUP(AJ49,AK49,1) | AM49: =IF(ISBLANK(AJ49), "", MOD_SUBSTAT_LOOKUP(AJ49,AK49,0)) | AQ49: =MOD_SUBSTAT_LOOKUP(AO49,AP49,1) | AR49: =IF(ISBLANK(AO49), "", MOD_SUBSTAT_LOOKUP(AO49,AP49,0))
F50: Death Wave - Quantity | H50: =MOD_SUBSTAT_LOOKUP(F50,G50,1) | I50: =IF(ISBLANK(F50), "", MOD_SUBSTAT_LOOKUP(F50,G50,0)) | K50: Chain Lightning - Damage | L50: Legendary | M50: =MOD_SUBSTAT_LOOKUP(K50,L50,1) -> +50x | N50: =IF(ISBLANK(K50), "", MOD_SUBSTAT_LOOKUP(K50,L50,0)) -> 50 | R50: =MOD_SUBSTAT_LOOKUP(P50,Q50,1) | S50: =IF(ISBLANK(P50), "", MOD_SUBSTAT_LOOKUP(P50,Q50,0)) | W50: =MOD_SUBSTAT_LOOKUP(U50,V50,1) | X50: =IF(ISBLANK(U50), "", MOD_SUBSTAT_LOOKUP(U50,V50,0)) | AB50: =MOD_SUBSTAT_LOOKUP(Z50,AA50,1) | AC50: =IF(ISBLANK(Z50), "", MOD_SUBSTAT_LOOKUP(Z50,AA50,0)) | AG50: =MOD_SUBSTAT_LOOKUP(AE50,AF50,1) | AH50: =IF(ISBLANK(AE50), "", MOD_SUBSTAT_LOOKUP(AE50,AF50,0)) | AL50: =MOD_SUBSTAT_LOOKUP(AJ50,AK50,1) | AM50: =IF(ISBLANK(AJ50), "", MOD_SUBSTAT_LOOKUP(AJ50,AK50,0)) | AQ50: =MOD_SUBSTAT_LOOKUP(AO50,AP50,1) | AR50: =IF(ISBLANK(AO50), "", MOD_SUBSTAT_LOOKUP(AO50,AP50,0))
F51: Death Wave - Cooldown | H51: =MOD_SUBSTAT_LOOKUP(F51,G51,1) | I51: =IF(ISBLANK(F51), "", MOD_SUBSTAT_LOOKUP(F51,G51,0)) | K51: Chrono Field - Cooldown | M51: =MOD_SUBSTAT_LOOKUP(K51,L51,1) | N51: =IF(ISBLANK(K51), "", MOD_SUBSTAT_LOOKUP(K51,L51,0)) | R51: =MOD_SUBSTAT_LOOKUP(P51,Q51,1) | S51: =IF(ISBLANK(P51), "", MOD_SUBSTAT_LOOKUP(P51,Q51,0)) | W51: =MOD_SUBSTAT_LOOKUP(U51,V51,1) | X51: =IF(ISBLANK(U51), "", MOD_SUBSTAT_LOOKUP(U51,V51,0)) | AB51: =MOD_SUBSTAT_LOOKUP(Z51,AA51,1) | AC51: =IF(ISBLANK(Z51), "", MOD_SUBSTAT_LOOKUP(Z51,AA51,0)) | AG51: =MOD_SUBSTAT_LOOKUP(AE51,AF51,1) | AH51: =IF(ISBLANK(AE51), "", MOD_SUBSTAT_LOOKUP(AE51,AF51,0)) | AL51: =MOD_SUBSTAT_LOOKUP(AJ51,AK51,1) | AM51: =IF(ISBLANK(AJ51), "", MOD_SUBSTAT_LOOKUP(AJ51,AK51,0)) | AQ51: =MOD_SUBSTAT_LOOKUP(AO51,AP51,1) | AR51: =IF(ISBLANK(AO51), "", MOD_SUBSTAT_LOOKUP(AO51,AP51,0))
F52: Golden Tower - Bonus | H52: =MOD_SUBSTAT_LOOKUP(F52,G52,1) | I52: =IF(ISBLANK(F52), "", MOD_SUBSTAT_LOOKUP(F52,G52,0)) | K52: Chrono Field - Speed Reduction | M52: =MOD_SUBSTAT_LOOKUP(K52,L52,1) | N52: =IF(ISBLANK(K52), "", MOD_SUBSTAT_LOOKUP(K52,L52,0)) | R52: =MOD_SUBSTAT_LOOKUP(P52,Q52,1) | S52: =IF(ISBLANK(P52), "", MOD_SUBSTAT_LOOKUP(P52,Q52,0)) | W52: =MOD_SUBSTAT_LOOKUP(U52,V52,1) | X52: =IF(ISBLANK(U52), "", MOD_SUBSTAT_LOOKUP(U52,V52,0)) | AB52: =MOD_SUBSTAT_LOOKUP(Z52,AA52,1) | AC52: =IF(ISBLANK(Z52), "", MOD_SUBSTAT_LOOKUP(Z52,AA52,0)) | AG52: =MOD_SUBSTAT_LOOKUP(AE52,AF52,1) | AH52: =IF(ISBLANK(AE52), "", MOD_SUBSTAT_LOOKUP(AE52,AF52,0)) | AL52: =MOD_SUBSTAT_LOOKUP(AJ52,AK52,1) | AM52: =IF(ISBLANK(AJ52), "", MOD_SUBSTAT_LOOKUP(AJ52,AK52,0)) | AQ52: =MOD_SUBSTAT_LOOKUP(AO52,AP52,1) | AR52: =IF(ISBLANK(AO52), "", MOD_SUBSTAT_LOOKUP(AO52,AP52,0))
F53: Death Wave - Damage | G53: Common | H53: =MOD_SUBSTAT_LOOKUP(F53,G53,1) -> +8x | I53: =IF(ISBLANK(F53), "", MOD_SUBSTAT_LOOKUP(F53,G53,0)) -> 8 | M53: =MOD_SUBSTAT_LOOKUP(K53,L53,1) | N53: =IF(ISBLANK(K53), "", MOD_SUBSTAT_LOOKUP(K53,L53,0)) | R53: =MOD_SUBSTAT_LOOKUP(P53,Q53,1) | S53: =IF(ISBLANK(P53), "", MOD_SUBSTAT_LOOKUP(P53,Q53,0)) | W53: =MOD_SUBSTAT_LOOKUP(U53,V53,1) | X53: =IF(ISBLANK(U53), "", MOD_SUBSTAT_LOOKUP(U53,V53,0)) | AB53: =MOD_SUBSTAT_LOOKUP(Z53,AA53,1) | AC53: =IF(ISBLANK(Z53), "", MOD_SUBSTAT_LOOKUP(Z53,AA53,0)) | AG53: =MOD_SUBSTAT_LOOKUP(AE53,AF53,1) | AH53: =IF(ISBLANK(AE53), "", MOD_SUBSTAT_LOOKUP(AE53,AF53,0)) | AL53: =MOD_SUBSTAT_LOOKUP(AJ53,AK53,1) | AM53: =IF(ISBLANK(AJ53), "", MOD_SUBSTAT_LOOKUP(AJ53,AK53,0)) | AQ53: =MOD_SUBSTAT_LOOKUP(AO53,AP53,1) | AR53: =IF(ISBLANK(AO53), "", MOD_SUBSTAT_LOOKUP(AO53,AP53,0))

Sheet _IDS
A1: =IFERROR(__xludf.DUMMYFUNCTION("IMPORTRANGE(IF(IDS!E6=""✅"", IDS!D6, ""1osjoqKmMwtOWs7Up3e21-3ofN1RHOjsgKV6y3dc6rgE""), ""_IDS!A1:BY212"")"),"Labs") -> Labs | B1: =IFERROR(__xludf.DUMMYFUNCTION("""COMPUTED_VALUE"""),"https://docs.google.com/spreadsheets/d/1jojOg_XIJCzm1LCYWu2F4KCtErjUIdKuFL1PiKzA0OE/edit") -> https://docs.google.com/spreadsheets/d/1jojOg_XIJCzm1LCYWu2F4KCtErjUIdKuFL1PiKzA0OE/edit | C1: =IFERROR(__xludf.DUMMYFUNCTION("""COMPUTED_VALUE"""),"✅") -> ✅ | D1: =IFERROR(__xludf.DUMMYFUNCTION("""COMPUTED_VALUE"""),"v2.5.7") -> v2.5.7 | E1: =IFERROR(__xludf.DUMMYFUNCTION("""COMPUTED_VALUE"""),"WS") -> WS | F1: =IFERROR(__xludf.DUMMYFUNCTION("""COMPUTED_VALUE"""),"https://docs.google.com/spreadsheets/d/1huHJMcyg1uRJEeRYqAgWzMc5TodPPplVZEFhwBiIeEs/edit") -> https://docs.google.com/spreadsheets/d/1huHJMcyg1uRJEeRYqAgWzMc5TodPPplVZEFhwBiIeEs/edit | G1: =IFERROR(__xludf.DUMMYFUNCTION("""COMPUTED_VALUE"""),"✅") -> ✅ | H1: =IFERROR(__xludf.DUMMYFUNCTION("""COMPUTED_VALUE"""),"v2.3.1") -> v2.3.1 | R1: =IFERROR(__xludf.DUMMYFUNCTION("""COMPUTED_VALUE"""),"WS+") -> WS+ | Z1: =IFERROR(__xludf.DUMMYFUNCTION("""COMPUTED_VALUE"""),"UWs") -> UWs | AA1: =IFERROR(__xludf.DUMMYFUNCTION("""COMPUTED_VALUE"""),"https://docs.google.com/spreadsheets/d/1VTRhVyt28cxrjCRcgVkQr2R_u4g9irfJTHy1cfftlIE/edit") -> https://docs.google.com/spreadsheets/d/1VTRhVyt28cxrjCRcgVkQr2R_u4g9irfJTHy1cfftlIE/edit | AB1: =IFERROR(__xludf.DUMMYFUNCTION("""COMPUTED_VALUE"""),"✅") -> ✅ | AC1: =IFERROR(__xludf.DUMMYFUNCTION("""COMPUTED_VALUE"""),"v2.1.3") -> v2.1.3 | AE1: =IFERROR(__xludf.DUMMYFUNCTION("""COMPUTED_VALUE"""),"Cards") -> Cards | AF1: =IFERROR(__xludf.DUMMYFUNCTION("""COMPUTED_VALUE"""),"https://docs.google.com/spreadsheets/d/1HMQwNLTvcw7aXmjjL7cXmZSdjAF_62ehWpwDIdjqEGs/edit") -> https://docs.google.com/spreadsheets/d/1HMQwNLTvcw7aXmjjL7cXmZSdjAF_62ehWpwDIdjqEGs/edit | AG1: =IFERROR(__xludf.DUMMYFUNCTION("""COMPUTED_VALUE"""),"✅") -> ✅ | AH1: =IFERROR(__xludf.DUMMYFUNCTION("""COMPUTED_VALUE"""),"Cards Presets") -> Cards Presets | AI1: =IFERROR(__xludf.DUMMYFUNCTION("""COMPUTED_VALUE"""),"v2.2.3") -> v2.2.3 | AJ1: =IFERROR(__xludf.DUMMYFUNCTION("""COMPUTED_VALUE"""),17.0) -> 17 | AM1: =IFERROR(__xludf.DUMMYFUNCTION("""COMPUTED_VALUE"""),"Relics") -> Relics | AN1: =IFERROR(__xludf.DUMMYFUNCTION("""COMPUTED_VALUE"""),"https://docs.google.com/spreadsheets/d/1Dll0IofJTWYkzhzhRWx1aA-_xtO3i_1iD65nAP6R_Ec/edit") -> https://docs.google.com/spreadsheets/d/1Dll0IofJTWYkzhzhRWx1aA-_xtO3i_1iD65nAP6R_Ec/edit | AO1: =IFERROR(__xludf.DUMMYFUNCTION("""COMPUTED_VALUE"""),"✅") -> ✅ | AP1: =IFERROR(__xludf.DUMMYFUNCTION("""COMPUTED_VALUE"""),"Vault") -> Vault | AR1: =IFERROR(__xludf.DUMMYFUNCTION("""COMPUTED_VALUE"""),"") | AS1: =IFERROR(__xludf.DUMMYFUNCTION("""COMPUTED_VALUE"""),"Bots") -> Bots | AT1: =IFERROR(__xludf.DUMMYFUNCTION("""COMPUTED_VALUE"""),"https://docs.google.com/spreadsheets/d/1H3PYvtIH7kId6WswEeMmrx7u5_g1GlkNPJtJhkASrbs/edit") -> https://docs.google.com/spreadsheets/d/1H3PYvtIH7kId6WswEeMmrx7u5_g1GlkNPJtJhkASrbs/edit | AU1: =IFERROR(__xludf.DUMMYFUNCTION("""COMPUTED_VALUE"""),"✅") -> ✅ | AV1: =IFERROR(__xludf.DUMMYFUNCTION("""COMPUTED_VALUE"""),"v2.2.1") -> v2.2.1 | AY1: =IFERROR(__xludf.DUMMYFUNCTION("""COMPUTED_VALUE"""),"Themes & Songs") -> Themes & Songs | AZ1: =IFERROR(__xludf.DUMMYFUNCTION("""COMPUTED_VALUE"""),"https://docs.google.com/spreadsheets/d/19KliigQhAeXztRPa9cSGZ7n9Q-REp4dyqMNI9d-UB0k/edit") -> https://docs.google.com/spreadsheets/d/19KliigQhAeXztRPa9cSGZ7n9Q-REp4dyqMNI9d-UB0k/edit | BA1: =IFERROR(__xludf.DUMMYFUNCTION("""COMPUTED_VALUE"""),"✅") -> ✅ | BB1: =IFERROR(__xludf.DUMMYFUNCTION("""COMPUTED_VALUE"""),"Modules") -> Modules | BC1: =IFERROR(__xludf.DUMMYFUNCTION("""COMPUTED_VALUE"""),"https://docs.google.com/spreadsheets/d/1rOoSY6TK918myJ6Mn6zO4rmUaFbPu6qJnGI17kc9DzQ/edit") -> https://docs.google.com/spreadsheets/d/1rOoSY6TK918myJ6Mn6zO4rmUaFbPu6qJnGI17kc9DzQ/edit | BD1: =IFERROR(__xludf.DUMMYFUNCTION("""COMPUTED_VALUE"""),"✅") -> ✅ | BE1: =IFERROR(__xludf.DUMMYFUNCTION("""COMPUTED_VALUE"""),"v5.13") -> v5.13 | BU1: =IFERROR(__xludf.DUMMYFUNCTION("""COMPUTED_VALUE"""),"Guardians") -> Guardians | BV1: =IFERROR(__xludf.DUMMYFUNCTION("""COMPUTED_VALUE"""),"https://docs.google.com/spreadsheets/d/1J4UPKzR9MLY_zzM7u7SzmyclgTEYX_PUvBcua4EbsSU/edit") -> https://docs.google.com/spreadsheets/d/1J4UPKzR9MLY_zzM7u7SzmyclgTEYX_PUvBcua4EbsSU/edit | BW1: =IFERROR(__xludf.DUMMYFUNCTION("""COMPUTED_VALUE"""),"✅") -> ✅ | BX1: =IFERROR(__xludf.DUMMYFUNCTION("""COMPUTED_VALUE"""),"v2.3.6") -> v2.3.6
A2: =IFERROR(__xludf.DUMMYFUNCTION("""COMPUTED_VALUE"""),"Game Speed") -> Game Speed | B2: =IFERROR(__xludf.DUMMYFUNCTION("""COMPUTED_VALUE"""),7.0) -> 7 | C2: =IFERROR(__xludf.DUMMYFUNCTION("""COMPUTED_VALUE"""),7.0) -> 7 | D2: =IFERROR(__xludf.DUMMYFUNCTION("""COMPUTED_VALUE"""),7.0) -> 7 | E2: =IFERROR(__xludf.DUMMYFUNCTION("""COMPUTED_VALUE"""),"U") -> U | F2: =IFERROR(__xludf.DUMMYFUNCTION("""COMPUTED_VALUE"""),"Workshop Upgrade") -> Workshop Upgrade | G2: =IFERROR(__xludf.DUMMYFUNCTION("""COMPUTED_VALUE"""),"Farming") -> Farming | I2: =IFERROR(__xludf.DUMMYFUNCTION("""COMPUTED_VALUE"""),"Tourney") -> Tourney | K2: =IFERROR(__xludf.DUMMYFUNCTION("""COMPUTED_VALUE"""),"Preset 3") -> Preset 3 | M2: =IFERROR(__xludf.DUMMYFUNCTION("""COMPUTED_VALUE"""),"Preset 4") -> Preset 4 | O2: =IFERROR(__xludf.DUMMYFUNCTION("""COMPUTED_VALUE"""),"Preset 5") -> Preset 5 | R2: =IFERROR(__xludf.DUMMYFUNCTION("""COMPUTED_VALUE"""),"Workshop Enhancement") -> Workshop Enhancement | T2: =IFERROR(__xludf.DUMMYFUNCTION("""COMPUTED_VALUE"""),"Farming") -> Farming | U2: =IFERROR(__xludf.DUMMYFUNCTION("""COMPUTED_VALUE"""),"Tourney") -> Tourney | V2: =IFERROR(__xludf.DUMMYFUNCTION("""COMPUTED_VALUE"""),"Preset 3") -> Preset 3 | W2: =IFERROR(__xludf.DUMMYFUNCTION("""COMPUTED_VALUE"""),"Preset 4") -> Preset 4 | X2: =IFERROR(__xludf.DUMMYFUNCTION("""COMPUTED_VALUE"""),"Preset 5") -> Preset 5 | Y2: =IFERROR(__xludf.DUMMYFUNCTION("""COMPUTED_VALUE"""),"7 q") -> 7 q | Z2: =IFERROR(__xludf.DUMMYFUNCTION("""COMPUTED_VALUE"""),"Chain Lightning") -> Chain Lightning | AB2: =IFERROR(__xludf.DUMMYFUNCTION("""COMPUTED_VALUE"""),"Damage") -> Damage | AC2: =IFERROR(__xludf.DUMMYFUNCTION("""COMPUTED_VALUE"""),898.0) -> 898 | AD2: =IFERROR(__xludf.DUMMYFUNCTION("""COMPUTED_VALUE"""),"19 | x898 | Cost 302 ⧌ | Next 362 ⧌") -> 19 | x898 | Cost 302 ⧌ | Next 362 ⧌ | AE2: =IFERROR(__xludf.DUMMYFUNCTION("""COMPUTED_VALUE"""),"Damage") -> Damage | AF2: =IFERROR(__xludf.DUMMYFUNCTION("""COMPUTED_VALUE"""),7.0) -> 7 | AG2: =IFERROR(__xludf.DUMMYFUNCTION("""COMPUTED_VALUE"""),FALSE) -> FALSE | AH2: =IFERROR(__xludf.DUMMYFUNCTION("""COMPUTED_VALUE"""),"Farming") -> Farming | AI2: =IFERROR(__xludf.DUMMYFUNCTION("""COMPUTED_VALUE"""),"Tourney") -> Tourney | AJ2: =IFERROR(__xludf.DUMMYFUNCTION("""COMPUTED_VALUE"""),"Preset 3") -> Preset 3 | AK2: =IFERROR(__xludf.DUMMYFUNCTION("""COMPUTED_VALUE"""),"Preset 4") -> Preset 4 | AL2: =IFERROR(__xludf.DUMMYFUNCTION("""COMPUTED_VALUE"""),"Preset 5") -> Preset 5 | AM2: =IFERROR(__xludf.DUMMYFUNCTION("""COMPUTED_VALUE"""),"Relics") -> Relics | AN2: =IFERROR(__xludf.DUMMYFUNCTION("""COMPUTED_VALUE"""),"Owned") -> Owned | AO2: =IFERROR(__xludf.DUMMYFUNCTION("""COMPUTED_VALUE"""),"v2.3.7") -> v2.3.7 | AP2: =IFERROR(__xludf.DUMMYFUNCTION("""COMPUTED_VALUE"""),"Keys spent") -> Keys spent | AQ2: =IFERROR(__xludf.DUMMYFUNCTION("""COMPUTED_VALUE"""),0.0) -> 0 | AS2: =IFERROR(__xludf.DUMMYFUNCTION("""COMPUTED_VALUE"""),"Flame Bot") -> Flame Bot | AU2: =IFERROR(__xludf.DUMMYFUNCTION("""COMPUTED_VALUE"""),"Damage R.") -> Damage R. | AV2: =IFERROR(__xludf.DUMMYFUNCTION("""COMPUTED_VALUE"""),0.3500000000000001) -> 0.35 | AW2: =IFERROR(__xludf.DUMMYFUNCTION("""COMPUTED_VALUE"""),"05 | 35% | Cost 260 ⧓ | Next 300 ⧓") -> 05 | 35% | Cost 260 ⧓ | Next 300 ⧓ | AY2: =IFERROR(__xludf.DUMMYFUNCTION("""COMPUTED_VALUE"""),1.682) -> 1.682 | BA2: =IFERROR(__xludf.DUMMYFUNCTION("""COMPUTED_VALUE"""),"v2.2.3") -> v2.2.3 | BB2: =IFERROR(__xludf.DUMMYFUNCTION("""COMPUTED_VALUE"""),"Assist Slot") -> Assist Slot | BC2: =IFERROR(__xludf.DUMMYFUNCTION("""COMPUTED_VALUE"""),FALSE) -> FALSE | BD2: =IFERROR(__xludf.DUMMYFUNCTION("""COMPUTED_VALUE"""),0.0) -> 0 | BG2: =IFERROR(__xludf.DUMMYFUNCTION("""COMPUTED_VALUE"""),"Assist Slot") -> Assist Slot | BH2: =IFERROR(__xludf.DUMMYFUNCTION("""COMPUTED_VALUE"""),TRUE) -> TRUE | BI2: =IFERROR(__xludf.DUMMYFUNCTION("""COMPUTED_VALUE"""),41.0) -> 41 | BL2: =IFERROR(__xludf.DUMMYFUNCTION("""COMPUTED_VALUE"""),"Assist Slot") -> Assist Slot | BM2: =IFERROR(__xludf.DUMMYFUNCTION("""COMPUTED_VALUE"""),TRUE) -> TRUE | BN2: =IFERROR(__xludf.DUMMYFUNCTION("""COMPUTED_VALUE"""),97.0) -> 97 | BQ2: =IFERROR(__xludf.DUMMYFUNCTION("""COMPUTED_VALUE"""),"Assist Slot") -> Assist Slot | BR2: =IFERROR(__xludf.DUMMYFUNCTION("""COMPUTED_VALUE"""),TRUE) -> TRUE | BS2: =IFERROR(__xludf.DUMMYFUNCTION("""COMPUTED_VALUE"""),101.0) -> 101 | BU2: =IFERROR(__xludf.DUMMYFUNCTION("""COMPUTED_VALUE"""),"Attack") -> Attack | BW2: =IFERROR(__xludf.DUMMYFUNCTION("""COMPUTED_VALUE"""),"Percentage") -> Percentage | BX2: =IFERROR(__xludf.DUMMYFUNCTION("""COMPUTED_VALUE"""),0.01) -> 0.01 | BY2: =IFERROR(__xludf.DUMMYFUNCTION("""COMPUTED_VALUE"""),"00 | 1% | Cost 0 ⧈ | Next 25 ⧈") -> 00 | 1% | Cost 0 ⧈ | Next 25 ⧈
A3: =IFERROR(__xludf.DUMMYFUNCTION("""COMPUTED_VALUE"""),"Starting Cash") -> Starting Cash | B3: =IFERROR(__xludf.DUMMYFUNCTION("""COMPUTED_VALUE"""),6.0) -> 6 | D3: =IFERROR(__xludf.DUMMYFUNCTION("""COMPUTED_VALUE"""),99.0) -> 99 | G3: =IFERROR(__xludf.DUMMYFUNCTION("""COMPUTED_VALUE"""),"¢ Level") -> ¢ Level | H3: =IFERROR(__xludf.DUMMYFUNCTION("""COMPUTED_VALUE"""),"$ Level") -> $ Level | I3: =IFERROR(__xludf.DUMMYFUNCTION("""COMPUTED_VALUE"""),"¢ Level") -> ¢ Level | J3: =IFERROR(__xludf.DUMMYFUNCTION("""COMPUTED_VALUE"""),"$ Level") -> $ Level | K3: =IFERROR(__xludf.DUMMYFUNCTION("""COMPUTED_VALUE"""),"¢ Level") -> ¢ Level | L3: =IFERROR(__xludf.DUMMYFUNCTION("""COMPUTED_VALUE"""),"$ Level") -> $ Level | M3: =IFERROR(__xludf.DUMMYFUNCTION("""COMPUTED_VALUE"""),"¢ Level") -> ¢ Level | N3: =IFERROR(__xludf.DUMMYFUNCTION("""COMPUTED_VALUE"""),"$ Level") -> $ Level | O3: =IFERROR(__xludf.DUMMYFUNCTION("""COMPUTED_VALUE"""),"¢ Level") -> ¢ Level | P3: =IFERROR(__xludf.DUMMYFUNCTION("""COMPUTED_VALUE"""),"$ Level") -> $ Level | Q3: =IFERROR(__xludf.DUMMYFUNCTION("""COMPUTED_VALUE"""),"Max") -> Max | T3: =IFERROR(__xludf.DUMMYFUNCTION("""COMPUTED_VALUE"""),"WS+") -> WS+ | U3: =IFERROR(__xludf.DUMMYFUNCTION("""COMPUTED_VALUE"""),"WS+") -> WS+ | V3: =IFERROR(__xludf.DUMMYFUNCTION("""COMPUTED_VALUE"""),"WS+") -> WS+ | W3: =IFERROR(__xludf.DUMMYFUNCTION("""COMPUTED_VALUE"""),"WS+") -> WS+ | X3: =IFERROR(__xludf.DUMMYFUNCTION("""COMPUTED_VALUE"""),"WS+") -> WS+ | Y3: =IFERROR(__xludf.DUMMYFUNCTION("""COMPUTED_VALUE"""),"Max") -> Max | AB3: =IFERROR(__xludf.DUMMYFUNCTION("""COMPUTED_VALUE"""),"Quantity") -> Quantity | AC3: =IFERROR(__xludf.DUMMYFUNCTION("""COMPUTED_VALUE"""),4.0) -> 4 | AD3: =IFERROR(__xludf.DUMMYFUNCTION("""COMPUTED_VALUE"""),"03 | #4 | Cost 150 ⧌ | Next 400 ⧌") -> 03 | #4 | Cost 150 ⧌ | Next 400 ⧌ | AE3: =IFERROR(__xludf.DUMMYFUNCTION("""COMPUTED_VALUE"""),"Attack Speed") -> Attack Speed | AF3: =IFERROR(__xludf.DUMMYFUNCTION("""COMPUTED_VALUE"""),7.0) -> 7 | AG3: =IFERROR(__xludf.DUMMYFUNCTION("""COMPUTED_VALUE"""),FALSE) -> FALSE | AH3: =IFERROR(__xludf.DUMMYFUNCTION("""COMPUTED_VALUE"""),"Enemy Balance") -> Enemy Balance | AI3: =IFERROR(__xludf.DUMMYFUNCTION("""COMPUTED_VALUE"""),"Attack Speed") -> Attack Speed | AM3: =IFERROR(__xludf.DUMMYFUNCTION("""COMPUTED_VALUE"""),"Event Relics") -> Event Relics | AN3: =IFERROR(__xludf.DUMMYFUNCTION("""COMPUTED_VALUE"""),112.0) -> 112 | AU3: =IFERROR(__xludf.DUMMYFUNCTION("""COMPUTED_VALUE"""),"Cooldown") -> Cooldown | AV3: =IFERROR(__xludf.DUMMYFUNCTION("""COMPUTED_VALUE"""),51.0) -> 51 | AW3: =IFERROR(__xludf.DUMMYFUNCTION("""COMPUTED_VALUE"""),"08 | 51s | Cost 380 ⧓ | Next 420 ⧓") -> 08 | 51s | Cost 380 ⧓ | Next 420 ⧓ | BB3: =IFERROR(__xludf.DUMMYFUNCTION("""COMPUTED_VALUE"""),"Rarity Cap") -> Rarity Cap | BC3: =IFERROR(__xludf.DUMMYFUNCTION("""COMPUTED_VALUE"""),"Epic") -> Epic | BG3: =IFERROR(__xludf.DUMMYFUNCTION("""COMPUTED_VALUE"""),"Rarity Cap") -> Rarity Cap | BH3: =IFERROR(__xludf.DUMMYFUNCTION("""COMPUTED_VALUE"""),"Epic") -> Epic | BL3: =IFERROR(__xludf.DUMMYFUNCTION("""COMPUTED_VALUE"""),"Rarity Cap") -> Rarity Cap | BM3: =IFERROR(__xludf.DUMMYFUNCTION("""COMPUTED_VALUE"""),"Epic") -> Epic | BQ3: =IFERROR(__xludf.DUMMYFUNCTION("""COMPUTED_VALUE"""),"Rarity Cap") -> Rarity Cap | BR3: =IFERROR(__xludf.DUMMYFUNCTION("""COMPUTED_VALUE"""),"Epic") -> Epic | BW3: =IFERROR(__xludf.DUMMYFUNCTION("""COMPUTED_VALUE"""),"Cooldown") -> Cooldown | BX3: =IFERROR(__xludf.DUMMYFUNCTION("""COMPUTED_VALUE"""),120.0) -> 120 | BY3: =IFERROR(__xludf.DUMMYFUNCTION("""COMPUTED_VALUE"""),"00 | 120s | Cost 0 ⧈ | Next 1 ⧈") -> 00 | 120s | Cost 0 ⧈ | Next 1 ⧈
A4: =IFERROR(__xludf.DUMMYFUNCTION("""COMPUTED_VALUE"""),"Workshop Attack Discount") -> Workshop Attack Discount | B4: =IFERROR(__xludf.DUMMYFUNCTION("""COMPUTED_VALUE"""),27.0) -> 27 | D4: =IFERROR(__xludf.DUMMYFUNCTION("""COMPUTED_VALUE"""),99.0) -> 99 | F4: =IFERROR(__xludf.DUMMYFUNCTION("""COMPUTED_VALUE"""),"Damage") -> Damage | G4: =IFERROR(__xludf.DUMMYFUNCTION("""COMPUTED_VALUE"""),5750.0) -> 5750 | H4: =IFERROR(__xludf.DUMMYFUNCTION("""COMPUTED_VALUE"""),6000.0) -> 6000 | I4: =IFERROR(__xludf.DUMMYFUNCTION("""COMPUTED_VALUE"""),5750.0) -> 5750 | J4: =IFERROR(__xludf.DUMMYFUNCTION("""COMPUTED_VALUE"""),6000.0) -> 6000 | Q4: =IFERROR(__xludf.DUMMYFUNCTION("""COMPUTED_VALUE"""),6000.0) -> 6000 | R4: =IFERROR(__xludf.DUMMYFUNCTION("""COMPUTED_VALUE"""),"Damage +") -> Damage + | S4: =IFERROR(__xludf.DUMMYFUNCTION("""COMPUTED_VALUE"""),1.56) -> 1.56 | T4: =IFERROR(__xludf.DUMMYFUNCTION("""COMPUTED_VALUE"""),56.0) -> 56 | U4: =IFERROR(__xludf.DUMMYFUNCTION("""COMPUTED_VALUE"""),56.0) -> 56 | Y4: =IFERROR(__xludf.DUMMYFUNCTION("""COMPUTED_VALUE"""),400.0) -> 400 | Z4: =IFERROR(__xludf.DUMMYFUNCTION("""COMPUTED_VALUE"""),TRUE) -> TRUE | AA4: =IFERROR(__xludf.DUMMYFUNCTION("""COMPUTED_VALUE"""),"UW Unlocked") -> UW Unlocked | AB4: =IFERROR(__xludf.DUMMYFUNCTION("""COMPUTED_VALUE"""),"Chance") -> Chance | AC4: =IFERROR(__xludf.DUMMYFUNCTION("""COMPUTED_VALUE"""),0.17) -> 0.17 | AD4: =IFERROR(__xludf.DUMMYFUNCTION("""COMPUTED_VALUE"""),"08 | 17.0% | Cost 134 ⧌ | Next 152 ⧌") -> 08 | 17.0% | Cost 134 ⧌ | Next 152 ⧌ | AE4: =IFERROR(__xludf.DUMMYFUNCTION("""COMPUTED_VALUE"""),"Health") -> Health | AF4: =IFERROR(__xludf.DUMMYFUNCTION("""COMPUTED_VALUE"""),7.0) -> 7 | AG4: =IFERROR(__xludf.DUMMYFUNCTION("""COMPUTED_VALUE"""),FALSE) -> FALSE | AH4: =IFERROR(__xludf.DUMMYFUNCTION("""COMPUTED_VALUE"""),"Extra Defense") -> Extra Defense | AI4: =IFERROR(__xludf.DUMMYFUNCTION("""COMPUTED_VALUE"""),"Damage") -> Damage | AM4: =IFERROR(__xludf.DUMMYFUNCTION("""COMPUTED_VALUE"""),"Guild Relics") -> Guild Relics | AN4: =IFERROR(__xludf.DUMMYFUNCTION("""COMPUTED_VALUE"""),13.0) -> 13 | AP4: =IFERROR(__xludf.DUMMYFUNCTION("""COMPUTED_VALUE"""),"Total Bonuses") -> Total Bonuses | AQ4: =IFERROR(__xludf.DUMMYFUNCTION("""COMPUTED_VALUE"""),"Active") -> Active | AU4: =IFERROR(__xludf.DUMMYFUNCTION("""COMPUTED_VALUE"""),"Damage") -> Damage | AV4: =IFERROR(__xludf.DUMMYFUNCTION("""COMPUTED_VALUE"""),50.0) -> 50 | AW4: =IFERROR(__xludf.DUMMYFUNCTION("""COMPUTED_VALUE"""),"00 | x50 | Cost 0 ⧓ | Next 100 ⧓") -> 00 | x50 | Cost 0 ⧓ | Next 100 ⧓ | BB4: =IFERROR(__xludf.DUMMYFUNCTION("""COMPUTED_VALUE"""),"Multiplier Cap") -> Multiplier Cap | BC4: =IFERROR(__xludf.DUMMYFUNCTION("""COMPUTED_VALUE"""),0.01) -> 0.01 | BD4: =IFERROR(__xludf.DUMMYFUNCTION("""COMPUTED_VALUE"""),"00 | 1% | Cost 0 ⧌ | Next 15 ⧌") -> 00 | 1% | Cost 0 ⧌ | Next 15 ⧌ | BG4: =IFERROR(__xludf.DUMMYFUNCTION("""COMPUTED_VALUE"""),"Multiplier Cap") -> Multiplier Cap | BH4: =IFERROR(__xludf.DUMMYFUNCTION("""COMPUTED_VALUE"""),0.01) -> 0.01 | BI4: =IFERROR(__xludf.DUMMYFUNCTION("""COMPUTED_VALUE"""),"00 | 1% | Cost 0 ⧌ | Next 15 ⧌") -> 00 | 1% | Cost 0 ⧌ | Next 15 ⧌ | BL4: =IFERROR(__xludf.DUMMYFUNCTION("""COMPUTED_VALUE"""),"Multiplier Cap") -> Multiplier Cap | BM4: =IFERROR(__xludf.DUMMYFUNCTION("""COMPUTED_VALUE"""),0.1) -> 0.1 | BN4: =IFERROR(__xludf.DUMMYFUNCTION("""COMPUTED_VALUE"""),"09 | 10% | Cost 39 ⧌ | Next 42 ⧌") -> 09 | 10% | Cost 39 ⧌ | Next 42 ⧌ | BQ4: =IFERROR(__xludf.DUMMYFUNCTION("""COMPUTED_VALUE"""),"Multiplier Cap") -> Multiplier Cap | BR4: =IFERROR(__xludf.DUMMYFUNCTION("""COMPUTED_VALUE"""),0.1) -> 0.1 | BS4: =IFERROR(__xludf.DUMMYFUNCTION("""COMPUTED_VALUE"""),"09 | 10% | Cost 39 ⧌ | Next 42 ⧌") -> 09 | 10% | Cost 39 ⧌ | Next 42 ⧌ | BU4: =IFERROR(__xludf.DUMMYFUNCTION("""COMPUTED_VALUE"""),TRUE) -> TRUE | BV4: =IFERROR(__xludf.DUMMYFUNCTION("""COMPUTED_VALUE"""),"Unlocked") -> Unlocked | BW4: =IFERROR(__xludf.DUMMYFUNCTION("""COMPUTED_VALUE"""),"Targets") -> Targets | BX4: =IFERROR(__xludf.DUMMYFUNCTION("""COMPUTED_VALUE"""),1.0) -> 1 | BY4: =IFERROR(__xludf.DUMMYFUNCTION("""COMPUTED_VALUE"""),"00 | 1 | Cost 0 ⧈ | Next 100 ⧈") -> 00 | 1 | Cost 0 ⧈ | Next 100 ⧈
A5: =IFERROR(__xludf.DUMMYFUNCTION("""COMPUTED_VALUE"""),"Workshop Defense Discount") -> Workshop Defense Discount | B5: =IFERROR(__xludf.DUMMYFUNCTION("""COMPUTED_VALUE"""),28.0) -> 28 | D5: =IFERROR(__xludf.DUMMYFUNCTION("""COMPUTED_VALUE"""),99.0) -> 99 | F5: =IFERROR(__xludf.DUMMYFUNCTION("""COMPUTED_VALUE"""),"Attack Speed") -> Attack Speed | G5: =IFERROR(__xludf.DUMMYFUNCTION("""COMPUTED_VALUE"""),99.0) -> 99 | H5: =IFERROR(__xludf.DUMMYFUNCTION("""COMPUTED_VALUE"""),99.0) -> 99 | I5: =IFERROR(__xludf.DUMMYFUNCTION("""COMPUTED_VALUE"""),99.0) -> 99 | J5: =IFERROR(__xludf.DUMMYFUNCTION("""COMPUTED_VALUE"""),99.0) -> 99 | Q5: =IFERROR(__xludf.DUMMYFUNCTION("""COMPUTED_VALUE"""),99.0) -> 99 | R5: =IFERROR(__xludf.DUMMYFUNCTION("""COMPUTED_VALUE"""),"Rend Armor Mult +") -> Rend Armor Mult + | S5: =IFERROR(__xludf.DUMMYFUNCTION("""COMPUTED_VALUE"""),1.21) -> 1.21 | T5: =IFERROR(__xludf.DUMMYFUNCTION("""COMPUTED_VALUE"""),21.0) -> 21 | U5: =IFERROR(__xludf.DUMMYFUNCTION("""COMPUTED_VALUE"""),21.0) -> 21 | Y5: =IFERROR(__xludf.DUMMYFUNCTION("""COMPUTED_VALUE"""),400.0) -> 400 | Z5: =IFERROR(__xludf.DUMMYFUNCTION("""COMPUTED_VALUE"""),"UW+") -> UW+ | AB5: =IFERROR(__xludf.DUMMYFUNCTION("""COMPUTED_VALUE"""),"Smite") -> Smite | AC5: =IFERROR(__xludf.DUMMYFUNCTION("""COMPUTED_VALUE"""),"Locked") -> Locked | AD5: =IFERROR(__xludf.DUMMYFUNCTION("""COMPUTED_VALUE"""),"Lo | Locked") -> Lo | Locked | AE5: =IFERROR(__xludf.DUMMYFUNCTION("""COMPUTED_VALUE"""),"Health Regen") -> Health Regen | AF5: =IFERROR(__xludf.DUMMYFUNCTION("""COMPUTED_VALUE"""),7.0) -> 7 | AG5: =IFERROR(__xludf.DUMMYFUNCTION("""COMPUTED_VALUE"""),FALSE) -> FALSE | AH5: =IFERROR(__xludf.DUMMYFUNCTION("""COMPUTED_VALUE"""),"Health") -> Health | AI5: =IFERROR(__xludf.DUMMYFUNCTION("""COMPUTED_VALUE"""),"Berserker") -> Berserker | AM5: =IFERROR(__xludf.DUMMYFUNCTION("""COMPUTED_VALUE"""),"Other Relics") -> Other Relics | AN5: =IFERROR(__xludf.DUMMYFUNCTION("""COMPUTED_VALUE"""),22.0) -> 22 | AP5: =IFERROR(__xludf.DUMMYFUNCTION("""COMPUTED_VALUE"""),"Misc.") -> Misc. | AS5: =IFERROR(__xludf.DUMMYFUNCTION("""COMPUTED_VALUE"""),TRUE) -> TRUE | AT5: =IFERROR(__xludf.DUMMYFUNCTION("""COMPUTED_VALUE"""),"Unlocked") -> Unlocked | AU5: =IFERROR(__xludf.DUMMYFUNCTION("""COMPUTED_VALUE"""),"Range") -> Range | AV5: =IFERROR(__xludf.DUMMYFUNCTION("""COMPUTED_VALUE"""),46.0) -> 46 | AW5: =IFERROR(__xludf.DUMMYFUNCTION("""COMPUTED_VALUE"""),"04 | 46m | Cost 220 ⧓ | Next 260 ⧓") -> 04 | 46m | Cost 220 ⧓ | Next 260 ⧓ | BB5: =IFERROR(__xludf.DUMMYFUNCTION("""COMPUTED_VALUE"""),"Substat Cap") -> Substat Cap | BC5: =IFERROR(__xludf.DUMMYFUNCTION("""COMPUTED_VALUE"""),0.01) -> 0.01 | BD5: =IFERROR(__xludf.DUMMYFUNCTION("""COMPUTED_VALUE"""),"00 | 1% | Cost 0 ⧌ | Next 15 ⧌") -> 00 | 1% | Cost 0 ⧌ | Next 15 ⧌ | BG5: =IFERROR(__xludf.DUMMYFUNCTION("""COMPUTED_VALUE"""),"Substat Cap") -> Substat Cap | BH5: =IFERROR(__xludf.DUMMYFUNCTION("""COMPUTED_VALUE"""),0.1) -> 0.1 | BI5: =IFERROR(__xludf.DUMMYFUNCTION("""COMPUTED_VALUE"""),"09 | 10% | Cost 39 ⧌ | Next 42 ⧌") -> 09 | 10% | Cost 39 ⧌ | Next 42 ⧌ | BL5: =IFERROR(__xludf.DUMMYFUNCTION("""COMPUTED_VALUE"""),"Substat Cap") -> Substat Cap | BM5: =IFERROR(__xludf.DUMMYFUNCTION("""COMPUTED_VALUE"""),0.1) -> 0.1 | BN5: =IFERROR(__xludf.DUMMYFUNCTION("""COMPUTED_VALUE"""),"09 | 10% | Cost 39 ⧌ | Next 42 ⧌") -> 09 | 10% | Cost 39 ⧌ | Next 42 ⧌ | BQ5: =IFERROR(__xludf.DUMMYFUNCTION("""COMPUTED_VALUE"""),"Substat Cap") -> Substat Cap | BR5: =IFERROR(__xludf.DUMMYFUNCTION("""COMPUTED_VALUE"""),0.1) -> 0.1 | BS5: =IFERROR(__xludf.DUMMYFUNCTION("""COMPUTED_VALUE"""),"09 | 10% | Cost 39 ⧌ | Next 42 ⧌") -> 09 | 10% | Cost 39 ⧌ | Next 42 ⧌ | BU5: =IFERROR(__xludf.DUMMYFUNCTION("""COMPUTED_VALUE"""),"Ally") -> Ally | BW5: =IFERROR(__xludf.DUMMYFUNCTION("""COMPUTED_VALUE"""),"Recovery Amount") -> Recovery Amount | BX5: =IFERROR(__xludf.DUMMYFUNCTION("""COMPUTED_VALUE"""),0.01) -> 0.01 | BY5: =IFERROR(__xludf.DUMMYFUNCTION("""COMPUTED_VALUE"""),"00 | 1% | Cost 0 ⧈ | Next 10 ⧈") -> 00 | 1% | Cost 0 ⧈ | Next 10 ⧈
A6: =IFERROR(__xludf.DUMMYFUNCTION("""COMPUTED_VALUE"""),"Workshop Utility Discount") -> Workshop Utility Discount | B6: =IFERROR(__xludf.DUMMYFUNCTION("""COMPUTED_VALUE"""),41.0) -> 41 | D6: =IFERROR(__xludf.DUMMYFUNCTION("""COMPUTED_VALUE"""),99.0) -> 99 | F6: =IFERROR(__xludf.DUMMYFUNCTION("""COMPUTED_VALUE"""),"Critical Chance") -> Critical Chance | G6: =IFERROR(__xludf.DUMMYFUNCTION("""COMPUTED_VALUE"""),79.0) -> 79 | H6: =IFERROR(__xludf.DUMMYFUNCTION("""COMPUTED_VALUE"""),79.0) -> 79 | I6: =IFERROR(__xludf.DUMMYFUNCTION("""COMPUTED_VALUE"""),79.0) -> 79 | J6: =IFERROR(__xludf.DUMMYFUNCTION("""COMPUTED_VALUE"""),79.0) -> 79 | Q6: =IFERROR(__xludf.DUMMYFUNCTION("""COMPUTED_VALUE"""),79.0) -> 79 | R6: =IFERROR(__xludf.DUMMYFUNCTION("""COMPUTED_VALUE"""),"Critical Factor +") -> Critical Factor + | S6: =IFERROR(__xludf.DUMMYFUNCTION("""COMPUTED_VALUE"""),1.6) -> 1.6 | T6: =IFERROR(__xludf.DUMMYFUNCTION("""COMPUTED_VALUE"""),60.0) -> 60 | U6: =IFERROR(__xludf.DUMMYFUNCTION("""COMPUTED_VALUE"""),60.0) -> 60 | Y6: =IFERROR(__xludf.DUMMYFUNCTION("""COMPUTED_VALUE"""),400.0) -> 400 | Z6: =IFERROR(__xludf.DUMMYFUNCTION("""COMPUTED_VALUE"""),"Smart Missiles") -> Smart Missiles | AB6: =IFERROR(__xludf.DUMMYFUNCTION("""COMPUTED_VALUE"""),"Damage") -> Damage | AC6: =IFERROR(__xludf.DUMMYFUNCTION("""COMPUTED_VALUE"""),10.0) -> 10 | AD6: =IFERROR(__xludf.DUMMYFUNCTION("""COMPUTED_VALUE"""),"00 | x10 | Cost 0 ⧌ | Next 5 ⧌") -> 00 | x10 | Cost 0 ⧌ | Next 5 ⧌ | AE6: =IFERROR(__xludf.DUMMYFUNCTION("""COMPUTED_VALUE"""),"Range") -> Range | AF6: =IFERROR(__xludf.DUMMYFUNCTION("""COMPUTED_VALUE"""),7.0) -> 7 | AG6: =IFERROR(__xludf.DUMMYFUNCTION("""COMPUTED_VALUE"""),FALSE) -> FALSE | AH6: =IFERROR(__xludf.DUMMYFUNCTION("""COMPUTED_VALUE"""),"Coins") -> Coins | AI6: =IFERROR(__xludf.DUMMYFUNCTION("""COMPUTED_VALUE"""),"Critical Chance") -> Critical Chance | AM6: =IFERROR(__xludf.DUMMYFUNCTION("""COMPUTED_VALUE"""),"Total Relics") -> Total Relics | AN6: =IFERROR(__xludf.DUMMYFUNCTION("""COMPUTED_VALUE"""),147.0) -> 147 | AP6: =IFERROR(__xludf.DUMMYFUNCTION("""COMPUTED_VALUE"""),"Bot Range") -> Bot Range | AQ6: =IFERROR(__xludf.DUMMYFUNCTION("""COMPUTED_VALUE"""),0.0) -> 0 | AS6: =IFERROR(__xludf.DUMMYFUNCTION("""COMPUTED_VALUE"""),"Thunder Bot") -> Thunder Bot | AU6: =IFERROR(__xludf.DUMMYFUNCTION("""COMPUTED_VALUE"""),"Duration") -> Duration | AV6: =IFERROR(__xludf.DUMMYFUNCTION("""COMPUTED_VALUE"""),5.0) -> 5 | AW6: =IFERROR(__xludf.DUMMYFUNCTION("""COMPUTED_VALUE"""),"00 | 5.0s | Cost 0 ⧓ | Next 100 ⧓") -> 00 | 5.0s | Cost 0 ⧓ | Next 100 ⧓ | BE6: =IFERROR(__xludf.DUMMYFUNCTION("""COMPUTED_VALUE"""),0.4444444444444444) -> 0.44444444 | BW6: =IFERROR(__xludf.DUMMYFUNCTION("""COMPUTED_VALUE"""),"Max Recovery") -> Max Recovery | BX6: =IFERROR(__xludf.DUMMYFUNCTION("""COMPUTED_VALUE"""),1.1) -> 1.1 | BY6: =IFERROR(__xludf.DUMMYFUNCTION("""COMPUTED_VALUE"""),"00 | 1.1x | Cost 0 ⧈ | Next 1 ⧈") -> 00 | 1.1x | Cost 0 ⧈ | Next 1 ⧈
A7: =IFERROR(__xludf.DUMMYFUNCTION("""COMPUTED_VALUE"""),"Labs Coin Discount") -> Labs Coin Discount | B7: =IFERROR(__xludf.DUMMYFUNCTION("""COMPUTED_VALUE"""),68.0) -> 68 | D7: =IFERROR(__xludf.DUMMYFUNCTION("""COMPUTED_VALUE"""),99.0) -> 99 | F7: =IFERROR(__xludf.DUMMYFUNCTION("""COMPUTED_VALUE"""),"Critical Factor") -> Critical Factor | G7: =IFERROR(__xludf.DUMMYFUNCTION("""COMPUTED_VALUE"""),150.0) -> 150 | H7: =IFERROR(__xludf.DUMMYFUNCTION("""COMPUTED_VALUE"""),150.0) -> 150 | I7: =IFERROR(__xludf.DUMMYFUNCTION("""COMPUTED_VALUE"""),150.0) -> 150 | J7: =IFERROR(__xludf.DUMMYFUNCTION("""COMPUTED_VALUE"""),150.0) -> 150 | Q7: =IFERROR(__xludf.DUMMYFUNCTION("""COMPUTED_VALUE"""),150.0) -> 150 | R7: =IFERROR(__xludf.DUMMYFUNCTION("""COMPUTED_VALUE"""),"Damage / Meter +") -> Damage / Meter + | S7: =IFERROR(__xludf.DUMMYFUNCTION("""COMPUTED_VALUE"""),1.17) -> 1.17 | T7: =IFERROR(__xludf.DUMMYFUNCTION("""COMPUTED_VALUE"""),17.0) -> 17 | U7: =IFERROR(__xludf.DUMMYFUNCTION("""COMPUTED_VALUE"""),17.0) -> 17 | Y7: =IFERROR(__xludf.DUMMYFUNCTION("""COMPUTED_VALUE"""),400.0) -> 400 | AB7: =IFERROR(__xludf.DUMMYFUNCTION("""COMPUTED_VALUE"""),"Quantity") -> Quantity | AC7: =IFERROR(__xludf.DUMMYFUNCTION("""COMPUTED_VALUE"""),5.0) -> 5 | AD7: =IFERROR(__xludf.DUMMYFUNCTION("""COMPUTED_VALUE"""),"00 | #5 | Cost 0 ⧌ | Next 4 ⧌") -> 00 | #5 | Cost 0 ⧌ | Next 4 ⧌ | AE7: =IFERROR(__xludf.DUMMYFUNCTION("""COMPUTED_VALUE"""),"Cash") -> Cash | AF7: =IFERROR(__xludf.DUMMYFUNCTION("""COMPUTED_VALUE"""),7.0) -> 7 | AG7: =IFERROR(__xludf.DUMMYFUNCTION("""COMPUTED_VALUE"""),TRUE) -> TRUE | AH7: =IFERROR(__xludf.DUMMYFUNCTION("""COMPUTED_VALUE"""),"Plasma Cannon") -> Plasma Cannon | AI7: =IFERROR(__xludf.DUMMYFUNCTION("""COMPUTED_VALUE"""),"Health") -> Health | AP7: =IFERROR(__xludf.DUMMYFUNCTION("""COMPUTED_VALUE"""),"Discount Enhancements") -> Discount Enhancements | AQ7: =IFERROR(__xludf.DUMMYFUNCTION("""COMPUTED_VALUE"""),0.0) -> 0 | AU7: =IFERROR(__xludf.DUMMYFUNCTION("""COMPUTED_VALUE"""),"Cooldown") -> Cooldown | AV7: =IFERROR(__xludf.DUMMYFUNCTION("""COMPUTED_VALUE"""),120.0) -> 120 | AW7: =IFERROR(__xludf.DUMMYFUNCTION("""COMPUTED_VALUE"""),"00 | 120s | Cost 0 ⧓ | Next 100 ⧓") -> 00 | 120s | Cost 0 ⧓ | Next 100 ⧓ | BB7: =IFERROR(__xludf.DUMMYFUNCTION("""COMPUTED_VALUE"""),"Farming") -> Farming | BG7: =IFERROR(__xludf.DUMMYFUNCTION("""COMPUTED_VALUE"""),"Farming") -> Farming | BL7: =IFERROR(__xludf.DUMMYFUNCTION("""COMPUTED_VALUE"""),"Farming") -> Farming | BQ7: =IFERROR(__xludf.DUMMYFUNCTION("""COMPUTED_VALUE"""),"Farming") -> Farming | BU7: =IFERROR(__xludf.DUMMYFUNCTION("""COMPUTED_VALUE"""),TRUE) -> TRUE | BV7: =IFERROR(__xludf.DUMMYFUNCTION("""COMPUTED_VALUE"""),"Unlocked") -> Unlocked | BW7: =IFERROR(__xludf.DUMMYFUNCTION("""COMPUTED_VALUE"""),"Cooldown") -> Cooldown | BX7: =IFERROR(__xludf.DUMMYFUNCTION("""COMPUTED_VALUE"""),120.0) -> 120 | BY7: =IFERROR(__xludf.DUMMYFUNCTION("""COMPUTED_VALUE"""),"00 | 120s | Cost 0 ⧈ | Next 1 ⧈") -> 00 | 120s | Cost 0 ⧈ | Next 1 ⧈
A8: =IFERROR(__xludf.DUMMYFUNCTION("""COMPUTED_VALUE"""),"Labs Speed") -> Labs Speed | B8: =IFERROR(__xludf.DUMMYFUNCTION("""COMPUTED_VALUE"""),91.0) -> 91 | D8: =IFERROR(__xludf.DUMMYFUNCTION("""COMPUTED_VALUE"""),99.0) -> 99 | E8: =IFERROR(__xludf.DUMMYFUNCTION("""COMPUTED_VALUE"""),TRUE) -> TRUE | F8: =IFERROR(__xludf.DUMMYFUNCTION("""COMPUTED_VALUE"""),"Range") -> Range | G8: =IFERROR(__xludf.DUMMYFUNCTION("""COMPUTED_VALUE"""),79.0) -> 79 | H8: =IFERROR(__xludf.DUMMYFUNCTION("""COMPUTED_VALUE"""),79.0) -> 79 | I8: =IFERROR(__xludf.DUMMYFUNCTION("""COMPUTED_VALUE"""),79.0) -> 79 | J8: =IFERROR(__xludf.DUMMYFUNCTION("""COMPUTED_VALUE"""),79.0) -> 79 | Q8: =IFERROR(__xludf.DUMMYFUNCTION("""COMPUTED_VALUE"""),79.0) -> 79 | R8: =IFERROR(__xludf.DUMMYFUNCTION("""COMPUTED_VALUE"""),"Super Crit Multi +") -> Super Crit Multi + | S8: =IFERROR(__xludf.DUMMYFUNCTION("""COMPUTED_VALUE"""),1.57) -> 1.57 | T8: =IFERROR(__xludf.DUMMYFUNCTION("""COMPUTED_VALUE"""),57.0) -> 57 | U8: =IFERROR(__xludf.DUMMYFUNCTION("""COMPUTED_VALUE"""),57.0) -> 57 | Y8: =IFERROR(__xludf.DUMMYFUNCTION("""COMPUTED_VALUE"""),400.0) -> 400 | Z8: =IFERROR(__xludf.DUMMYFUNCTION("""COMPUTED_VALUE"""),FALSE) -> FALSE | AA8: =IFERROR(__xludf.DUMMYFUNCTION("""COMPUTED_VALUE"""),"UW Locked") -> UW Locked | AB8: =IFERROR(__xludf.DUMMYFUNCTION("""COMPUTED_VALUE"""),"Cooldown") -> Cooldown | AC8: =IFERROR(__xludf.DUMMYFUNCTION("""COMPUTED_VALUE"""),180.0) -> 180 | AD8: =IFERROR(__xludf.DUMMYFUNCTION("""COMPUTED_VALUE"""),"00 | 180s | Cost 0 ⧌ | Next 8 ⧌") -> 00 | 180s | Cost 0 ⧌ | Next 8 ⧌ | AE8: =IFERROR(__xludf.DUMMYFUNCTION("""COMPUTED_VALUE"""),"Coins") -> Coins | AF8: =IFERROR(__xludf.DUMMYFUNCTION("""COMPUTED_VALUE"""),7.0) -> 7 | AG8: =IFERROR(__xludf.DUMMYFUNCTION("""COMPUTED_VALUE"""),FALSE) -> FALSE | AH8: =IFERROR(__xludf.DUMMYFUNCTION("""COMPUTED_VALUE"""),"Attack Speed") -> Attack Speed | AI8: =IFERROR(__xludf.DUMMYFUNCTION("""COMPUTED_VALUE"""),"Health Regen") -> Health Regen | AM8: =IFERROR(__xludf.DUMMYFUNCTION("""COMPUTED_VALUE"""),"Total Bonuses") -> Total Bonuses | AN8: =IFERROR(__xludf.DUMMYFUNCTION("""COMPUTED_VALUE"""),"Active") -> Active | AP8: =IFERROR(__xludf.DUMMYFUNCTION("""COMPUTED_VALUE"""),"Discount Rerolls") -> Discount Rerolls | AQ8: =IFERROR(__xludf.DUMMYFUNCTION("""COMPUTED_VALUE"""),0.0) -> 0 | AU8: =IFERROR(__xludf.DUMMYFUNCTION("""COMPUTED_VALUE"""),"Linger") -> Linger | AV8: =IFERROR(__xludf.DUMMYFUNCTION("""COMPUTED_VALUE"""),0.2) -> 0.2 | AW8: =IFERROR(__xludf.DUMMYFUNCTION("""COMPUTED_VALUE"""),"00 | 20% | Cost 0 ⧓ | Next 100 ⧓") -> 00 | 20% | Cost 0 ⧓ | Next 100 ⧓ | BB8: =IFERROR(__xludf.DUMMYFUNCTION("""COMPUTED_VALUE"""),"Primary Slot") -> Primary Slot | BC8: =IFERROR(__xludf.DUMMYFUNCTION("""COMPUTED_VALUE"""),"Amplifying Strike") -> Amplifying Strike | BG8: =IFERROR(__xludf.DUMMYFUNCTION("""COMPUTED_VALUE"""),"Primary Slot") -> Primary Slot | BH8: =IFERROR(__xludf.DUMMYFUNCTION("""COMPUTED_VALUE"""),"Sharp Fortitude") -> Sharp Fortitude | BL8: =IFERROR(__xludf.DUMMYFUNCTION("""COMPUTED_VALUE"""),"Primary Slot") -> Primary Slot | BM8: =IFERROR(__xludf.DUMMYFUNCTION("""COMPUTED_VALUE"""),"Singularity Harness") -> Singularity Harness | BQ8: =IFERROR(__xludf.DUMMYFUNCTION("""COMPUTED_VALUE"""),"Primary Slot") -> Primary Slot | BR8: =IFERROR(__xludf.DUMMYFUNCTION("""COMPUTED_VALUE"""),"Primordial Collapse") -> Primordial Collapse | BU8: =IFERROR(__xludf.DUMMYFUNCTION("""COMPUTED_VALUE"""),"Bounty") -> Bounty | BW8: =IFERROR(__xludf.DUMMYFUNCTION("""COMPUTED_VALUE"""),"Multiplier") -> Multiplier | BX8: =IFERROR(__xludf.DUMMYFUNCTION("""COMPUTED_VALUE"""),0.01) -> 0.01 | BY8: =IFERROR(__xludf.DUMMYFUNCTION("""COMPUTED_VALUE"""),"00 | 0.01x | Cost 0 ⧈ | Next 1 ⧈") -> 00 | 0.01x | Cost 0 ⧈ | Next 1 ⧈
A9: =IFERROR(__xludf.DUMMYFUNCTION("""COMPUTED_VALUE"""),"Buy Multiplier") -> Buy Multiplier | B9: =IFERROR(__xludf.DUMMYFUNCTION("""COMPUTED_VALUE"""),4.0) -> 4 | D9: =IFERROR(__xludf.DUMMYFUNCTION("""COMPUTED_VALUE"""),4.0) -> 4 | F9: =IFERROR(__xludf.DUMMYFUNCTION("""COMPUTED_VALUE"""),"Damage / Meter") -> Damage / Meter | G9: =IFERROR(__xludf.DUMMYFUNCTION("""COMPUTED_VALUE"""),180.0) -> 180 | H9: =IFERROR(__xludf.DUMMYFUNCTION("""COMPUTED_VALUE"""),200.0) -> 200 | I9: =IFERROR(__xludf.DUMMYFUNCTION("""COMPUTED_VALUE"""),180.0) -> 180 | J9: =IFERROR(__xludf.DUMMYFUNCTION("""COMPUTED_VALUE"""),200.0) -> 200 | Q9: =IFERROR(__xludf.DUMMYFUNCTION("""COMPUTED_VALUE"""),200.0) -> 200 | R9: =IFERROR(__xludf.DUMMYFUNCTION("""COMPUTED_VALUE"""),"Attack Speed +") -> Attack Speed + | S9: =IFERROR(__xludf.DUMMYFUNCTION("""COMPUTED_VALUE"""),1.13) -> 1.13 | T9: =IFERROR(__xludf.DUMMYFUNCTION("""COMPUTED_VALUE"""),13.0) -> 13 | U9: =IFERROR(__xludf.DUMMYFUNCTION("""COMPUTED_VALUE"""),13.0) -> 13 | Y9: =IFERROR(__xludf.DUMMYFUNCTION("""COMPUTED_VALUE"""),75.0) -> 75 | Z9: =IFERROR(__xludf.DUMMYFUNCTION("""COMPUTED_VALUE"""),"UW+") -> UW+ | AB9: =IFERROR(__xludf.DUMMYFUNCTION("""COMPUTED_VALUE"""),"Cover Fire") -> Cover Fire | AC9: =IFERROR(__xludf.DUMMYFUNCTION("""COMPUTED_VALUE"""),"Locked") -> Locked | AD9: =IFERROR(__xludf.DUMMYFUNCTION("""COMPUTED_VALUE"""),"Lo | Locked") -> Lo | Locked | AE9: =IFERROR(__xludf.DUMMYFUNCTION("""COMPUTED_VALUE"""),"Slow Aura") -> Slow Aura | AF9: =IFERROR(__xludf.DUMMYFUNCTION("""COMPUTED_VALUE"""),7.0) -> 7 | AG9: =IFERROR(__xludf.DUMMYFUNCTION("""COMPUTED_VALUE"""),FALSE) -> FALSE | AH9: =IFERROR(__xludf.DUMMYFUNCTION("""COMPUTED_VALUE"""),"Wave Skip") -> Wave Skip | AI9: =IFERROR(__xludf.DUMMYFUNCTION("""COMPUTED_VALUE"""),"Plasma Cannon") -> Plasma Cannon | AM9: =IFERROR(__xludf.DUMMYFUNCTION("""COMPUTED_VALUE"""),"Misc.") -> Misc. | AP9: =IFERROR(__xludf.DUMMYFUNCTION("""COMPUTED_VALUE"""),"Additional Card Slot") -> Additional Card Slot | AQ9: =IFERROR(__xludf.DUMMYFUNCTION("""COMPUTED_VALUE"""),0.0) -> 0 | AS9: =IFERROR(__xludf.DUMMYFUNCTION("""COMPUTED_VALUE"""),FALSE) -> FALSE | AT9: =IFERROR(__xludf.DUMMYFUNCTION("""COMPUTED_VALUE"""),"Locked") -> Locked | AU9: =IFERROR(__xludf.DUMMYFUNCTION("""COMPUTED_VALUE"""),"Range") -> Range | AV9: =IFERROR(__xludf.DUMMYFUNCTION("""COMPUTED_VALUE"""),25.0) -> 25 | AW9: =IFERROR(__xludf.DUMMYFUNCTION("""COMPUTED_VALUE"""),"00 | 25m | Cost 0 ⧓ | Next 100 ⧓") -> 00 | 25m | Cost 0 ⧓ | Next 100 ⧓ | BB9: =IFERROR(__xludf.DUMMYFUNCTION("""COMPUTED_VALUE"""),"Assist Slot") -> Assist Slot | BG9: =IFERROR(__xludf.DUMMYFUNCTION("""COMPUTED_VALUE"""),"Assist Slot") -> Assist Slot | BH9: =IFERROR(__xludf.DUMMYFUNCTION("""COMPUTED_VALUE"""),"Orbital Augment") -> Orbital Augment | BL9: =IFERROR(__xludf.DUMMYFUNCTION("""COMPUTED_VALUE"""),"Assist Slot") -> Assist Slot | BM9: =IFERROR(__xludf.DUMMYFUNCTION("""COMPUTED_VALUE"""),"Pulsar Harvester") -> Pulsar Harvester | BQ9: =IFERROR(__xludf.DUMMYFUNCTION("""COMPUTED_VALUE"""),"Assist Slot") -> Assist Slot | BR9: =IFERROR(__xludf.DUMMYFUNCTION("""COMPUTED_VALUE"""),"Dimension Core") -> Dimension Core | BW9: =IFERROR(__xludf.DUMMYFUNCTION("""COMPUTED_VALUE"""),"Cooldown") -> Cooldown | BX9: =IFERROR(__xludf.DUMMYFUNCTION("""COMPUTED_VALUE"""),120.0) -> 120 | BY9: =IFERROR(__xludf.DUMMYFUNCTION("""COMPUTED_VALUE"""),"00 | 120s | Cost 0 ⧈ | Next 2 ⧈") -> 00 | 120s | Cost 0 ⧈ | Next 2 ⧈
A10: =IFERROR(__xludf.DUMMYFUNCTION("""COMPUTED_VALUE"""),"More Round Stats") -> More Round Stats | B10: =IFERROR(__xludf.DUMMYFUNCTION("""COMPUTED_VALUE"""),1.0) -> 1 | D10: =IFERROR(__xludf.DUMMYFUNCTION("""COMPUTED_VALUE"""),1.0) -> 1 | E10: =IFERROR(__xludf.DUMMYFUNCTION("""COMPUTED_VALUE"""),TRUE) -> TRUE | F10: =IFERROR(__xludf.DUMMYFUNCTION("""COMPUTED_VALUE"""),"Multishot Chance") -> Multishot Chance | G10: =IFERROR(__xludf.DUMMYFUNCTION("""COMPUTED_VALUE"""),99.0) -> 99 | H10: =IFERROR(__xludf.DUMMYFUNCTION("""COMPUTED_VALUE"""),99.0) -> 99 | I10: =IFERROR(__xludf.DUMMYFUNCTION("""COMPUTED_VALUE"""),99.0) -> 99 | J10: =IFERROR(__xludf.DUMMYFUNCTION("""COMPUTED_VALUE"""),99.0) -> 99 | Q10: =IFERROR(__xludf.DUMMYFUNCTION("""COMPUTED_VALUE"""),99.0) -> 99 | R10: =IFERROR(__xludf.DUMMYFUNCTION("""COMPUTED_VALUE"""),"Health +") -> Health + | S10: =IFERROR(__xludf.DUMMYFUNCTION("""COMPUTED_VALUE"""),1.62) -> 1.62 | T10: =IFERROR(__xludf.DUMMYFUNCTION("""COMPUTED_VALUE"""),62.0) -> 62 | U10: =IFERROR(__xludf.DUMMYFUNCTION("""COMPUTED_VALUE"""),62.0) -> 62 | Y10: =IFERROR(__xludf.DUMMYFUNCTION("""COMPUTED_VALUE"""),400.0) -> 400 | Z10: =IFERROR(__xludf.DUMMYFUNCTION("""COMPUTED_VALUE"""),"Death Wave") -> Death Wave | AB10: =IFERROR(__xludf.DUMMYFUNCTION("""COMPUTED_VALUE"""),"Damage") -> Damage | AC10: =IFERROR(__xludf.DUMMYFUNCTION("""COMPUTED_VALUE"""),63.0) -> 63 | AD10: =IFERROR(__xludf.DUMMYFUNCTION("""COMPUTED_VALUE"""),"08 | x63 | Cost 47 ⧌ | Next 53 ⧌") -> 08 | x63 | Cost 47 ⧌ | Next 53 ⧌ | AE10: =IFERROR(__xludf.DUMMYFUNCTION("""COMPUTED_VALUE"""),"Critical Chance") -> Critical Chance | AF10: =IFERROR(__xludf.DUMMYFUNCTION("""COMPUTED_VALUE"""),7.0) -> 7 | AG10: =IFERROR(__xludf.DUMMYFUNCTION("""COMPUTED_VALUE"""),FALSE) -> FALSE | AH10: =IFERROR(__xludf.DUMMYFUNCTION("""COMPUTED_VALUE"""),"Health Regen") -> Health Regen | AI10: =IFERROR(__xludf.DUMMYFUNCTION("""COMPUTED_VALUE"""),"Wave Skip") -> Wave Skip | AM10: =IFERROR(__xludf.DUMMYFUNCTION("""COMPUTED_VALUE"""),"Lab Speed") -> Lab Speed | AN10: =IFERROR(__xludf.DUMMYFUNCTION("""COMPUTED_VALUE"""),0.395) -> 0.395 | AP10: =IFERROR(__xludf.DUMMYFUNCTION("""COMPUTED_VALUE"""),"Workshop Respec Discount") -> Workshop Respec Discount | AQ10: =IFERROR(__xludf.DUMMYFUNCTION("""COMPUTED_VALUE"""),0.0) -> 0 | AS10: =IFERROR(__xludf.DUMMYFUNCTION("""COMPUTED_VALUE"""),"Golden Bot") -> Golden Bot | AU10: =IFERROR(__xludf.DUMMYFUNCTION("""COMPUTED_VALUE"""),"Duration") -> Duration | AV10: =IFERROR(__xludf.DUMMYFUNCTION("""COMPUTED_VALUE"""),26.0) -> 26 | AW10: =IFERROR(__xludf.DUMMYFUNCTION("""COMPUTED_VALUE"""),"12 | 26.0s | Cost 540 ⧓ | Next 580 ⧓") -> 12 | 26.0s | Cost 540 ⧓ | Next 580 ⧓ | BU10: =IFERROR(__xludf.DUMMYFUNCTION("""COMPUTED_VALUE"""),FALSE) -> FALSE | BV10: =IFERROR(__xludf.DUMMYFUNCTION("""COMPUTED_VALUE"""),"Locked") -> Locked | BW10: =IFERROR(__xludf.DUMMYFUNCTION("""COMPUTED_VALUE"""),"Targets") -> Targets | BX10: =IFERROR(__xludf.DUMMYFUNCTION("""COMPUTED_VALUE"""),1.0) -> 1 | BY10: =IFERROR(__xludf.DUMMYFUNCTION("""COMPUTED_VALUE"""),"00 | 1 | Cost 0 ⧈ | Next 100 ⧈") -> 00 | 1 | Cost 0 ⧈ | Next 100 ⧈
A11: =IFERROR(__xludf.DUMMYFUNCTION("""COMPUTED_VALUE"""),"Target Priority") -> Target Priority | B11: =IFERROR(__xludf.DUMMYFUNCTION("""COMPUTED_VALUE"""),2.0) -> 2 | D11: =IFERROR(__xludf.DUMMYFUNCTION("""COMPUTED_VALUE"""),2.0) -> 2 | F11: =IFERROR(__xludf.DUMMYFUNCTION("""COMPUTED_VALUE"""),"Multishot Targets") -> Multishot Targets | G11: =IFERROR(__xludf.DUMMYFUNCTION("""COMPUTED_VALUE"""),7.0) -> 7 | H11: =IFERROR(__xludf.DUMMYFUNCTION("""COMPUTED_VALUE"""),7.0) -> 7 | I11: =IFERROR(__xludf.DUMMYFUNCTION("""COMPUTED_VALUE"""),7.0) -> 7 | J11: =IFERROR(__xludf.DUMMYFUNCTION("""COMPUTED_VALUE"""),7.0) -> 7 | Q11: =IFERROR(__xludf.DUMMYFUNCTION("""COMPUTED_VALUE"""),7.0) -> 7 | R11: =IFERROR(__xludf.DUMMYFUNCTION("""COMPUTED_VALUE"""),"Health Regen +") -> Health Regen + | S11: =IFERROR(__xludf.DUMMYFUNCTION("""COMPUTED_VALUE"""),1.6) -> 1.6 | T11: =IFERROR(__xludf.DUMMYFUNCTION("""COMPUTED_VALUE"""),60.0) -> 60 | U11: =IFERROR(__xludf.DUMMYFUNCTION("""COMPUTED_VALUE"""),60.0) -> 60 | Y11: =IFERROR(__xludf.DUMMYFUNCTION("""COMPUTED_VALUE"""),400.0) -> 400 | AB11: =IFERROR(__xludf.DUMMYFUNCTION("""COMPUTED_VALUE"""),"Quantity") -> Quantity | AC11: =IFERROR(__xludf.DUMMYFUNCTION("""COMPUTED_VALUE"""),3.0) -> 3 | AD11: =IFERROR(__xludf.DUMMYFUNCTION("""COMPUTED_VALUE"""),"02 | #3 | Cost 500 ⧌ | Next 850 ⧌") -> 02 | #3 | Cost 500 ⧌ | Next 850 ⧌ | AE11: =IFERROR(__xludf.DUMMYFUNCTION("""COMPUTED_VALUE"""),"Enemy Balance") -> Enemy Balance | AF11: =IFERROR(__xludf.DUMMYFUNCTION("""COMPUTED_VALUE"""),7.0) -> 7 | AG11: =IFERROR(__xludf.DUMMYFUNCTION("""COMPUTED_VALUE"""),FALSE) -> FALSE | AH11: =IFERROR(__xludf.DUMMYFUNCTION("""COMPUTED_VALUE"""),"Wave Accelerator") -> Wave Accelerator | AI11: =IFERROR(__xludf.DUMMYFUNCTION("""COMPUTED_VALUE"""),"Energy Shield") -> Energy Shield | AM11: =IFERROR(__xludf.DUMMYFUNCTION("""COMPUTED_VALUE"""),"Bot Range") -> Bot Range | AN11: =IFERROR(__xludf.DUMMYFUNCTION("""COMPUTED_VALUE"""),9.0) -> 9 | AP11: =IFERROR(__xludf.DUMMYFUNCTION("""COMPUTED_VALUE"""),"Bot Respec Discount") -> Bot Respec Discount | AQ11: =IFERROR(__xludf.DUMMYFUNCTION("""COMPUTED_VALUE"""),0.0) -> 0 | AU11: =IFERROR(__xludf.DUMMYFUNCTION("""COMPUTED_VALUE"""),"Cooldown") -> Cooldown | AV11: =IFERROR(__xludf.DUMMYFUNCTION("""COMPUTED_VALUE"""),111.0) -> 111 | AW11: =IFERROR(__xludf.DUMMYFUNCTION("""COMPUTED_VALUE"""),"03 | 111s | Cost 180 ⧓ | Next 220 ⧓") -> 03 | 111s | Cost 180 ⧓ | Next 220 ⧓ | BB11: =IFERROR(__xludf.DUMMYFUNCTION("""COMPUTED_VALUE"""),"Tourney") -> Tourney | BG11: =IFERROR(__xludf.DUMMYFUNCTION("""COMPUTED_VALUE"""),"Tourney") -> Tourney | BL11: =IFERROR(__xludf.DUMMYFUNCTION("""COMPUTED_VALUE"""),"Tourney") -> Tourney | BQ11: =IFERROR(__xludf.DUMMYFUNCTION("""COMPUTED_VALUE"""),"Tourney") -> Tourney | BU11: =IFERROR(__xludf.DUMMYFUNCTION("""COMPUTED_VALUE"""),"Fetch") -> Fetch | BW11: =IFERROR(__xludf.DUMMYFUNCTION("""COMPUTED_VALUE"""),"Cooldown") -> Cooldown | BX11: =IFERROR(__xludf.DUMMYFUNCTION("""COMPUTED_VALUE"""),88.0) -> 88 | BY11: =IFERROR(__xludf.DUMMYFUNCTION("""COMPUTED_VALUE"""),"32 | 88.0s | Cost 64 ⧈ | Next 66 ⧈") -> 32 | 88.0s | Cost 64 ⧈ | Next 66 ⧈
A12: =IFERROR(__xludf.DUMMYFUNCTION("""COMPUTED_VALUE"""),"Card Presets") -> Card Presets | B12: =IFERROR(__xludf.DUMMYFUNCTION("""COMPUTED_VALUE"""),1.0) -> 1 | D12: =IFERROR(__xludf.DUMMYFUNCTION("""COMPUTED_VALUE"""),1.0) -> 1 | E12: =IFERROR(__xludf.DUMMYFUNCTION("""COMPUTED_VALUE"""),TRUE) -> TRUE | F12: =IFERROR(__xludf.DUMMYFUNCTION("""COMPUTED_VALUE"""),"Rapid Fire Chance") -> Rapid Fire Chance | G12: =IFERROR(__xludf.DUMMYFUNCTION("""COMPUTED_VALUE"""),85.0) -> 85 | H12: =IFERROR(__xludf.DUMMYFUNCTION("""COMPUTED_VALUE"""),85.0) -> 85 | I12: =IFERROR(__xludf.DUMMYFUNCTION("""COMPUTED_VALUE"""),85.0) -> 85 | J12: =IFERROR(__xludf.DUMMYFUNCTION("""COMPUTED_VALUE"""),85.0) -> 85 | Q12: =IFERROR(__xludf.DUMMYFUNCTION("""COMPUTED_VALUE"""),85.0) -> 85 | R12: =IFERROR(__xludf.DUMMYFUNCTION("""COMPUTED_VALUE"""),"Defense Absolute +") -> Defense Absolute + | S12: =IFERROR(__xludf.DUMMYFUNCTION("""COMPUTED_VALUE"""),1.0) -> 1 | T12: =IFERROR(__xludf.DUMMYFUNCTION("""COMPUTED_VALUE"""),0.0) -> 0 | U12: =IFERROR(__xludf.DUMMYFUNCTION("""COMPUTED_VALUE"""),0.0) -> 0 | Y12: =IFERROR(__xludf.DUMMYFUNCTION("""COMPUTED_VALUE"""),400.0) -> 400 | Z12: =IFERROR(__xludf.DUMMYFUNCTION("""COMPUTED_VALUE"""),TRUE) -> TRUE | AA12: =IFERROR(__xludf.DUMMYFUNCTION("""COMPUTED_VALUE"""),"UW Unlocked") -> UW Unlocked | AB12: =IFERROR(__xludf.DUMMYFUNCTION("""COMPUTED_VALUE"""),"Cooldown") -> Cooldown | AC12: =IFERROR(__xludf.DUMMYFUNCTION("""COMPUTED_VALUE"""),180.0) -> 180 | AD12: =IFERROR(__xludf.DUMMYFUNCTION("""COMPUTED_VALUE"""),"12 | 180s | Cost 184 ⧌ | Next 200 ⧌") -> 12 | 180s | Cost 184 ⧌ | Next 200 ⧌ | AE12: =IFERROR(__xludf.DUMMYFUNCTION("""COMPUTED_VALUE"""),"Extra Defense") -> Extra Defense | AF12: =IFERROR(__xludf.DUMMYFUNCTION("""COMPUTED_VALUE"""),7.0) -> 7 | AG12: =IFERROR(__xludf.DUMMYFUNCTION("""COMPUTED_VALUE"""),FALSE) -> FALSE | AH12: =IFERROR(__xludf.DUMMYFUNCTION("""COMPUTED_VALUE"""),"Critical Coin") -> Critical Coin | AI12: =IFERROR(__xludf.DUMMYFUNCTION("""COMPUTED_VALUE"""),"Ultimate Crit") -> Ultimate Crit | AM12: =IFERROR(__xludf.DUMMYFUNCTION("""COMPUTED_VALUE"""),"Damage‎ ") -> Damage‎ | AP12: =IFERROR(__xludf.DUMMYFUNCTION("""COMPUTED_VALUE"""),"Ad Gems Stack") -> Ad Gems Stack | AQ12: =IFERROR(__xludf.DUMMYFUNCTION("""COMPUTED_VALUE"""),1.0) -> 1 | AU12: =IFERROR(__xludf.DUMMYFUNCTION("""COMPUTED_VALUE"""),"Bonus") -> Bonus | AV12: =IFERROR(__xludf.DUMMYFUNCTION("""COMPUTED_VALUE"""),6.200000000000004) -> 6.2 | AW12: =IFERROR(__xludf.DUMMYFUNCTION("""COMPUTED_VALUE"""),"21 | x6.2 | Cost 900 ⧓ | Next 940 ⧓") -> 21 | x6.2 | Cost 900 ⧓ | Next 940 ⧓ | BB12: =IFERROR(__xludf.DUMMYFUNCTION("""COMPUTED_VALUE"""),"Primary Slot") -> Primary Slot | BC12: =IFERROR(__xludf.DUMMYFUNCTION("""COMPUTED_VALUE"""),"Amplifying Strike") -> Amplifying Strike | BG12: =IFERROR(__xludf.DUMMYFUNCTION("""COMPUTED_VALUE"""),"Primary Slot") -> Primary Slot | BH12: =IFERROR(__xludf.DUMMYFUNCTION("""COMPUTED_VALUE"""),"Sharp Fortitude") -> Sharp Fortitude | BL12: =IFERROR(__xludf.DUMMYFUNCTION("""COMPUTED_VALUE"""),"Primary Slot") -> Primary Slot | BM12: =IFERROR(__xludf.DUMMYFUNCTION("""COMPUTED_VALUE"""),"Project Funding") -> Project Funding | BQ12: =IFERROR(__xludf.DUMMYFUNCTION("""COMPUTED_VALUE"""),"Primary Slot") -> Primary Slot | BR12: =IFERROR(__xludf.DUMMYFUNCTION("""COMPUTED_VALUE"""),"Primordial Collapse") -> Primordial Collapse | BW12: =IFERROR(__xludf.DUMMYFUNCTION("""COMPUTED_VALUE"""),"Find Chance") -> Find Chance | BX12: =IFERROR(__xludf.DUMMYFUNCTION("""COMPUTED_VALUE"""),0.3700000000000002) -> 0.37 | BY12: =IFERROR(__xludf.DUMMYFUNCTION("""COMPUTED_VALUE"""),"27 | 37% | Cost 150 ⧈ | Next 155 ⧈") -> 27 | 37% | Cost 150 ⧈ | Next 155 ⧈
A13: =IFERROR(__xludf.DUMMYFUNCTION("""COMPUTED_VALUE"""),"Workshop Respec") -> Workshop Respec | B13: =IFERROR(__xludf.DUMMYFUNCTION("""COMPUTED_VALUE"""),1.0) -> 1 | D13: =IFERROR(__xludf.DUMMYFUNCTION("""COMPUTED_VALUE"""),1.0) -> 1 | F13: =IFERROR(__xludf.DUMMYFUNCTION("""COMPUTED_VALUE"""),"Rapid Fire Duration") -> Rapid Fire Duration | G13: =IFERROR(__xludf.DUMMYFUNCTION("""COMPUTED_VALUE"""),99.0) -> 99 | H13: =IFERROR(__xludf.DUMMYFUNCTION("""COMPUTED_VALUE"""),99.0) -> 99 | I13: =IFERROR(__xludf.DUMMYFUNCTION("""COMPUTED_VALUE"""),99.0) -> 99 | J13: =IFERROR(__xludf.DUMMYFUNCTION("""COMPUTED_VALUE"""),99.0) -> 99 | Q13: =IFERROR(__xludf.DUMMYFUNCTION("""COMPUTED_VALUE"""),99.0) -> 99 | R13: =IFERROR(__xludf.DUMMYFUNCTION("""COMPUTED_VALUE"""),"Land Mine Damage +") -> Land Mine Damage + | S13: =IFERROR(__xludf.DUMMYFUNCTION("""COMPUTED_VALUE"""),2.08) -> 2.08 | T13: =IFERROR(__xludf.DUMMYFUNCTION("""COMPUTED_VALUE"""),18.0) -> 18 | U13: =IFERROR(__xludf.DUMMYFUNCTION("""COMPUTED_VALUE"""),18.0) -> 18 | Y13: =IFERROR(__xludf.DUMMYFUNCTION("""COMPUTED_VALUE"""),400.0) -> 400 | Z13: =IFERROR(__xludf.DUMMYFUNCTION("""COMPUTED_VALUE"""),"UW+") -> UW+ | AB13: =IFERROR(__xludf.DUMMYFUNCTION("""COMPUTED_VALUE"""),"Kill Wall") -> Kill Wall | AC13: =IFERROR(__xludf.DUMMYFUNCTION("""COMPUTED_VALUE"""),"Locked") -> Locked | AD13: =IFERROR(__xludf.DUMMYFUNCTION("""COMPUTED_VALUE"""),"Lo | Locked") -> Lo | Locked | AE13: =IFERROR(__xludf.DUMMYFUNCTION("""COMPUTED_VALUE"""),"Fortress") -> Fortress | AF13: =IFERROR(__xludf.DUMMYFUNCTION("""COMPUTED_VALUE"""),7.0) -> 7 | AG13: =IFERROR(__xludf.DUMMYFUNCTION("""COMPUTED_VALUE"""),FALSE) -> FALSE | AH13: =IFERROR(__xludf.DUMMYFUNCTION("""COMPUTED_VALUE"""),"Second Wind") -> Second Wind | AI13: =IFERROR(__xludf.DUMMYFUNCTION("""COMPUTED_VALUE"""),"Extra Orb") -> Extra Orb | AM13: =IFERROR(__xludf.DUMMYFUNCTION("""COMPUTED_VALUE"""),"Damage") -> Damage | AN13: =IFERROR(__xludf.DUMMYFUNCTION("""COMPUTED_VALUE"""),0.5399999999999999) -> 0.54 | AP13: =IFERROR(__xludf.DUMMYFUNCTION("""COMPUTED_VALUE"""),"Attack") -> Attack | AS13: =IFERROR(__xludf.DUMMYFUNCTION("""COMPUTED_VALUE"""),TRUE) -> TRUE | AT13: =IFERROR(__xludf.DUMMYFUNCTION("""COMPUTED_VALUE"""),"Unlocked") -> Unlocked | AU13: =IFERROR(__xludf.DUMMYFUNCTION("""COMPUTED_VALUE"""),"Range") -> Range | AV13: =IFERROR(__xludf.DUMMYFUNCTION("""COMPUTED_VALUE"""),50.0) -> 50 | AW13: =IFERROR(__xludf.DUMMYFUNCTION("""COMPUTED_VALUE"""),"15 | 50m | Cost 660 ⧓ | Maxed") -> 15 | 50m | Cost 660 ⧓ | Maxed | BB13: =IFERROR(__xludf.DUMMYFUNCTION("""COMPUTED_VALUE"""),"Assist Slot") -> Assist Slot | BG13: =IFERROR(__xludf.DUMMYFUNCTION("""COMPUTED_VALUE"""),"Assist Slot") -> Assist Slot | BH13: =IFERROR(__xludf.DUMMYFUNCTION("""COMPUTED_VALUE"""),"Anti-Cube Portal") -> Anti-Cube Portal | BL13: =IFERROR(__xludf.DUMMYFUNCTION("""COMPUTED_VALUE"""),"Assist Slot") -> Assist Slot | BM13: =IFERROR(__xludf.DUMMYFUNCTION("""COMPUTED_VALUE"""),"Galaxy Compressor") -> Galaxy Compressor | BQ13: =IFERROR(__xludf.DUMMYFUNCTION("""COMPUTED_VALUE"""),"Assist Slot") -> Assist Slot | BR13: =IFERROR(__xludf.DUMMYFUNCTION("""COMPUTED_VALUE"""),"Dimension Core") -> Dimension Core | BU13: =IFERROR(__xludf.DUMMYFUNCTION("""COMPUTED_VALUE"""),TRUE) -> TRUE | BV13: =IFERROR(__xludf.DUMMYFUNCTION("""COMPUTED_VALUE"""),"Unlocked") -> Unlocked | BW13: =IFERROR(__xludf.DUMMYFUNCTION("""COMPUTED_VALUE"""),"Double Find Chance") -> Double Find Chance | BX13: =IFERROR(__xludf.DUMMYFUNCTION("""COMPUTED_VALUE"""),0.10999999999999999) -> 0.11 | BY13: =IFERROR(__xludf.DUMMYFUNCTION("""COMPUTED_VALUE"""),"09 | 11% | Cost 50 ⧈ | Next 55 ⧈") -> 09 | 11% | Cost 50 ⧈ | Next 55 ⧈
A14: =IFERROR(__xludf.DUMMYFUNCTION("""COMPUTED_VALUE"""),"Reroll Daily Mission") -> Reroll Daily Mission | B14: =IFERROR(__xludf.DUMMYFUNCTION("""COMPUTED_VALUE"""),1.0) -> 1 | D14: =IFERROR(__xludf.DUMMYFUNCTION("""COMPUTED_VALUE"""),1.0) -> 1 | E14: =IFERROR(__xludf.DUMMYFUNCTION("""COMPUTED_VALUE"""),TRUE) -> TRUE | F14: =IFERROR(__xludf.DUMMYFUNCTION("""COMPUTED_VALUE"""),"Bounce Shot Chance") -> Bounce Shot Chance | G14: =IFERROR(__xludf.DUMMYFUNCTION("""COMPUTED_VALUE"""),85.0) -> 85 | H14: =IFERROR(__xludf.DUMMYFUNCTION("""COMPUTED_VALUE"""),85.0) -> 85 | I14: =IFERROR(__xludf.DUMMYFUNCTION("""COMPUTED_VALUE"""),85.0) -> 85 | J14: =IFERROR(__xludf.DUMMYFUNCTION("""COMPUTED_VALUE"""),85.0) -> 85 | Q14: =IFERROR(__xludf.DUMMYFUNCTION("""COMPUTED_VALUE"""),85.0) -> 85 | R14: =IFERROR(__xludf.DUMMYFUNCTION("""COMPUTED_VALUE"""),"Wall Health +") -> Wall Health + | S14: =IFERROR(__xludf.DUMMYFUNCTION("""COMPUTED_VALUE"""),1.5899999999999999) -> 1.59 | T14: =IFERROR(__xludf.DUMMYFUNCTION("""COMPUTED_VALUE"""),59.0) -> 59 | U14: =IFERROR(__xludf.DUMMYFUNCTION("""COMPUTED_VALUE"""),59.0) -> 59 | Y14: =IFERROR(__xludf.DUMMYFUNCTION("""COMPUTED_VALUE"""),400.0) -> 400 | Z14: =IFERROR(__xludf.DUMMYFUNCTION("""COMPUTED_VALUE"""),"Chrono Field") -> Chrono Field | AB14: =IFERROR(__xludf.DUMMYFUNCTION("""COMPUTED_VALUE"""),"Duration") -> Duration | AC14: =IFERROR(__xludf.DUMMYFUNCTION("""COMPUTED_VALUE"""),20.0) -> 20 | AD14: =IFERROR(__xludf.DUMMYFUNCTION("""COMPUTED_VALUE"""),"15 | 20s | Cost 131 ⧌ | Next 140 ⧌") -> 15 | 20s | Cost 131 ⧌ | Next 140 ⧌ | AE14: =IFERROR(__xludf.DUMMYFUNCTION("""COMPUTED_VALUE"""),"Free Upgrades") -> Free Upgrades | AF14: =IFERROR(__xludf.DUMMYFUNCTION("""COMPUTED_VALUE"""),7.0) -> 7 | AG14: =IFERROR(__xludf.DUMMYFUNCTION("""COMPUTED_VALUE"""),FALSE) -> FALSE | AH14: =IFERROR(__xludf.DUMMYFUNCTION("""COMPUTED_VALUE"""),"Energy Shield") -> Energy Shield | AI14: =IFERROR(__xludf.DUMMYFUNCTION("""COMPUTED_VALUE"""),"Recovery Package Chance") -> Recovery Package Chance | AM14: =IFERROR(__xludf.DUMMYFUNCTION("""COMPUTED_VALUE"""),"Ultimate Damage") -> Ultimate Damage | AN14: =IFERROR(__xludf.DUMMYFUNCTION("""COMPUTED_VALUE"""),0.22000000000000003) -> 0.22 | AP14: =IFERROR(__xludf.DUMMYFUNCTION("""COMPUTED_VALUE"""),"Damage") -> Damage | AQ14: =IFERROR(__xludf.DUMMYFUNCTION("""COMPUTED_VALUE"""),0.0) -> 0 | AS14: =IFERROR(__xludf.DUMMYFUNCTION("""COMPUTED_VALUE"""),"Amplify Bot") -> Amplify Bot | AU14: =IFERROR(__xludf.DUMMYFUNCTION("""COMPUTED_VALUE"""),"Duration") -> Duration | AV14: =IFERROR(__xludf.DUMMYFUNCTION("""COMPUTED_VALUE"""),20.0) -> 20 | AW14: =IFERROR(__xludf.DUMMYFUNCTION("""COMPUTED_VALUE"""),"00 | 20.0s | Cost 0 ⧓ | Next 100 ⧓") -> 00 | 20.0s | Cost 0 ⧓ | Next 100 ⧓ | BU14: =IFERROR(__xludf.DUMMYFUNCTION("""COMPUTED_VALUE"""),"Summon") -> Summon | BW14: =IFERROR(__xludf.DUMMYFUNCTION("""COMPUTED_VALUE"""),"Cooldown") -> Cooldown | BX14: =IFERROR(__xludf.DUMMYFUNCTION("""COMPUTED_VALUE"""),90.0) -> 90 | BY14: =IFERROR(__xludf.DUMMYFUNCTION("""COMPUTED_VALUE"""),"50 | 90s | Cost 99 ⧈ | Next 101 ⧈") -> 50 | 90s | Cost 99 ⧈ | Next 101 ⧈
A15: =IFERROR(__xludf.DUMMYFUNCTION("""COMPUTED_VALUE"""),"Workshop Enhancements") -> Workshop Enhancements | B15: =IFERROR(__xludf.DUMMYFUNCTION("""COMPUTED_VALUE"""),1.0) -> 1 | D15: =IFERROR(__xludf.DUMMYFUNCTION("""COMPUTED_VALUE"""),1.0) -> 1 | F15: =IFERROR(__xludf.DUMMYFUNCTION("""COMPUTED_VALUE"""),"Bounce Shot Targets") -> Bounce Shot Targets | G15: =IFERROR(__xludf.DUMMYFUNCTION("""COMPUTED_VALUE"""),5.0) -> 5 | H15: =IFERROR(__xludf.DUMMYFUNCTION("""COMPUTED_VALUE"""),7.0) -> 7 | I15: =IFERROR(__xludf.DUMMYFUNCTION("""COMPUTED_VALUE"""),5.0) -> 5 | J15: =IFERROR(__xludf.DUMMYFUNCTION("""COMPUTED_VALUE"""),7.0) -> 7 | Q15: =IFERROR(__xludf.DUMMYFUNCTION("""COMPUTED_VALUE"""),7.0) -> 7 | R15: =IFERROR(__xludf.DUMMYFUNCTION("""COMPUTED_VALUE"""),"Orb Size +") -> Orb Size + | S15: =IFERROR(__xludf.DUMMYFUNCTION("""COMPUTED_VALUE"""),1.2) -> 1.2 | T15: =IFERROR(__xludf.DUMMYFUNCTION("""COMPUTED_VALUE"""),20.0) -> 20 | U15: =IFERROR(__xludf.DUMMYFUNCTION("""COMPUTED_VALUE"""),20.0) -> 20 | Y15: =IFERROR(__xludf.DUMMYFUNCTION("""COMPUTED_VALUE"""),200.0) -> 200 | AB15: =IFERROR(__xludf.DUMMYFUNCTION("""COMPUTED_VALUE"""),"Speed Reduction") -> Speed Reduction | AC15: =IFERROR(__xludf.DUMMYFUNCTION("""COMPUTED_VALUE"""),0.5) -> 0.5 | AD15: =IFERROR(__xludf.DUMMYFUNCTION("""COMPUTED_VALUE"""),"06 | 50% | Cost 150 ⧌ | Next 200 ⧌") -> 06 | 50% | Cost 150 ⧌ | Next 200 ⧌ | AE15: =IFERROR(__xludf.DUMMYFUNCTION("""COMPUTED_VALUE"""),"Extra Orb") -> Extra Orb | AF15: =IFERROR(__xludf.DUMMYFUNCTION("""COMPUTED_VALUE"""),7.0) -> 7 | AG15: =IFERROR(__xludf.DUMMYFUNCTION("""COMPUTED_VALUE"""),FALSE) -> FALSE | AH15: =IFERROR(__xludf.DUMMYFUNCTION("""COMPUTED_VALUE"""),"Recovery Package Chance") -> Recovery Package Chance | AI15: =IFERROR(__xludf.DUMMYFUNCTION("""COMPUTED_VALUE"""),"Extra Defense") -> Extra Defense | AM15: =IFERROR(__xludf.DUMMYFUNCTION("""COMPUTED_VALUE"""),"Attack Speed") -> Attack Speed | AN15: =IFERROR(__xludf.DUMMYFUNCTION("""COMPUTED_VALUE"""),0.05) -> 0.05 | AP15: =IFERROR(__xludf.DUMMYFUNCTION("""COMPUTED_VALUE"""),"Ultimate Weapon Damage") -> Ultimate Weapon Damage | AQ15: =IFERROR(__xludf.DUMMYFUNCTION("""COMPUTED_VALUE"""),0.0) -> 0 | AU15: =IFERROR(__xludf.DUMMYFUNCTION("""COMPUTED_VALUE"""),"Cooldown") -> Cooldown | AV15: =IFERROR(__xludf.DUMMYFUNCTION("""COMPUTED_VALUE"""),120.0) -> 120 | AW15: =IFERROR(__xludf.DUMMYFUNCTION("""COMPUTED_VALUE"""),"00 | 120s | Cost 0 ⧓ | Next 100 ⧓") -> 00 | 120s | Cost 0 ⧓ | Next 100 ⧓ | BB15: =IFERROR(__xludf.DUMMYFUNCTION("""COMPUTED_VALUE"""),"Testing") -> Testing | BG15: =IFERROR(__xludf.DUMMYFUNCTION("""COMPUTED_VALUE"""),"Testing") -> Testing | BL15: =IFERROR(__xludf.DUMMYFUNCTION("""COMPUTED_VALUE"""),"Testing") -> Testing | BQ15: =IFERROR(__xludf.DUMMYFUNCTION("""COMPUTED_VALUE"""),"Testing") -> Testing | BW15: =IFERROR(__xludf.DUMMYFUNCTION("""COMPUTED_VALUE"""),"Duration") -> Duration | BX15: =IFERROR(__xludf.DUMMYFUNCTION("""COMPUTED_VALUE"""),24.0) -> 24 | BY15: =IFERROR(__xludf.DUMMYFUNCTION("""COMPUTED_VALUE"""),"19 | 24s| Cost 195 ⧈ | Next 205 ⧈") -> 19 | 24s| Cost 195 ⧈ | Next 205 ⧈
A16: =IFERROR(__xludf.DUMMYFUNCTION("""COMPUTED_VALUE"""),"Enhancement Attack - Coin Discount") -> Enhancement Attack - Coin Discount | B16: =IFERROR(__xludf.DUMMYFUNCTION("""COMPUTED_VALUE"""),0.0) -> 0 | D16: =IFERROR(__xludf.DUMMYFUNCTION("""COMPUTED_VALUE"""),100.0) -> 100 | F16: =IFERROR(__xludf.DUMMYFUNCTION("""COMPUTED_VALUE"""),"Bounce Shot Range") -> Bounce Shot Range | G16: =IFERROR(__xludf.DUMMYFUNCTION("""COMPUTED_VALUE"""),60.0) -> 60 | H16: =IFERROR(__xludf.DUMMYFUNCTION("""COMPUTED_VALUE"""),60.0) -> 60 | I16: =IFERROR(__xludf.DUMMYFUNCTION("""COMPUTED_VALUE"""),60.0) -> 60 | J16: =IFERROR(__xludf.DUMMYFUNCTION("""COMPUTED_VALUE"""),60.0) -> 60 | Q16: =IFERROR(__xludf.DUMMYFUNCTION("""COMPUTED_VALUE"""),60.0) -> 60 | R16: =IFERROR(__xludf.DUMMYFUNCTION("""COMPUTED_VALUE"""),"Cash Bonus +") -> Cash Bonus + | S16: =IFERROR(__xludf.DUMMYFUNCTION("""COMPUTED_VALUE"""),1.44) -> 1.44 | T16: =IFERROR(__xludf.DUMMYFUNCTION("""COMPUTED_VALUE"""),44.0) -> 44 | U16: =IFERROR(__xludf.DUMMYFUNCTION("""COMPUTED_VALUE"""),44.0) -> 44 | Y16: =IFERROR(__xludf.DUMMYFUNCTION("""COMPUTED_VALUE"""),400.0) -> 400 | Z16: =IFERROR(__xludf.DUMMYFUNCTION("""COMPUTED_VALUE"""),TRUE) -> TRUE | AA16: =IFERROR(__xludf.DUMMYFUNCTION("""COMPUTED_VALUE"""),"UW Unlocked") -> UW Unlocked | AB16: =IFERROR(__xludf.DUMMYFUNCTION("""COMPUTED_VALUE"""),"Cooldown") -> Cooldown | AC16: =IFERROR(__xludf.DUMMYFUNCTION("""COMPUTED_VALUE"""),60.0) -> 60 | AD16: =IFERROR(__xludf.DUMMYFUNCTION("""COMPUTED_VALUE"""),"12 | 60s | Cost 241 ⧌ | Maxed") -> 12 | 60s | Cost 241 ⧌ | Maxed | AE16: =IFERROR(__xludf.DUMMYFUNCTION("""COMPUTED_VALUE"""),"Plasma Cannon") -> Plasma Cannon | AF16: =IFERROR(__xludf.DUMMYFUNCTION("""COMPUTED_VALUE"""),7.0) -> 7 | AG16: =IFERROR(__xludf.DUMMYFUNCTION("""COMPUTED_VALUE"""),FALSE) -> FALSE | AH16: =IFERROR(__xludf.DUMMYFUNCTION("""COMPUTED_VALUE"""),"Intro Sprint") -> Intro Sprint | AI16: =IFERROR(__xludf.DUMMYFUNCTION("""COMPUTED_VALUE"""),"Slow Aura") -> Slow Aura | AM16: =IFERROR(__xludf.DUMMYFUNCTION("""COMPUTED_VALUE"""),"Crit Chance") -> Crit Chance | AN16: =IFERROR(__xludf.DUMMYFUNCTION("""COMPUTED_VALUE"""),0.06) -> 0.06 | AP16: =IFERROR(__xludf.DUMMYFUNCTION("""COMPUTED_VALUE"""),"Attack Speed") -> Attack Speed | AQ16: =IFERROR(__xludf.DUMMYFUNCTION("""COMPUTED_VALUE"""),0.0) -> 0 | AU16: =IFERROR(__xludf.DUMMYFUNCTION("""COMPUTED_VALUE"""),"Bonus") -> Bonus | AV16: =IFERROR(__xludf.DUMMYFUNCTION("""COMPUTED_VALUE"""),3.5) -> 3.5 | AW16: =IFERROR(__xludf.DUMMYFUNCTION("""COMPUTED_VALUE"""),"00 | x3.5 | Cost 0 ⧓ | Next 100 ⧓") -> 00 | x3.5 | Cost 0 ⧓ | Next 100 ⧓ | BB16: =IFERROR(__xludf.DUMMYFUNCTION("""COMPUTED_VALUE"""),"Primary Slot") -> Primary Slot | BC16: =IFERROR(__xludf.DUMMYFUNCTION("""COMPUTED_VALUE"""),"Being Annihilator") -> Being Annihilator | BG16: =IFERROR(__xludf.DUMMYFUNCTION("""COMPUTED_VALUE"""),"Primary Slot") -> Primary Slot | BH16: =IFERROR(__xludf.DUMMYFUNCTION("""COMPUTED_VALUE"""),"Sharp Fortitude") -> Sharp Fortitude | BL16: =IFERROR(__xludf.DUMMYFUNCTION("""COMPUTED_VALUE"""),"Primary Slot") -> Primary Slot | BM16: =IFERROR(__xludf.DUMMYFUNCTION("""COMPUTED_VALUE"""),"Galaxy Compressor") -> Galaxy Compressor | BQ16: =IFERROR(__xludf.DUMMYFUNCTION("""COMPUTED_VALUE"""),"Primary Slot") -> Primary Slot | BR16: =IFERROR(__xludf.DUMMYFUNCTION("""COMPUTED_VALUE"""),"Dimension Core") -> Dimension Core | BU16: =IFERROR(__xludf.DUMMYFUNCTION("""COMPUTED_VALUE"""),TRUE) -> TRUE | BV16: =IFERROR(__xludf.DUMMYFUNCTION("""COMPUTED_VALUE"""),"Unlocked") -> Unlocked | BW16: =IFERROR(__xludf.DUMMYFUNCTION("""COMPUTED_VALUE"""),"Cash Bonus") -> Cash Bonus | BX16: =IFERROR(__xludf.DUMMYFUNCTION("""COMPUTED_VALUE"""),1.0) -> 1 | BY16: =IFERROR(__xludf.DUMMYFUNCTION("""COMPUTED_VALUE"""),"00 | 1.0x | Cost 0 ⧈ | Next 100 ⧈") -> 00 | 1.0x | Cost 0 ⧈ | Next 100 ⧈
A17: =IFERROR(__xludf.DUMMYFUNCTION("""COMPUTED_VALUE"""),"Enhancement Defense - Coin Discount") -> Enhancement Defense - Coin Discount | B17: =IFERROR(__xludf.DUMMYFUNCTION("""COMPUTED_VALUE"""),0.0) -> 0 | D17: =IFERROR(__xludf.DUMMYFUNCTION("""COMPUTED_VALUE"""),100.0) -> 100 | E17: =IFERROR(__xludf.DUMMYFUNCTION("""COMPUTED_VALUE"""),TRUE) -> TRUE | F17: =IFERROR(__xludf.DUMMYFUNCTION("""COMPUTED_VALUE"""),"Super Critical Chance") -> Super Critical Chance | G17: =IFERROR(__xludf.DUMMYFUNCTION("""COMPUTED_VALUE"""),100.0) -> 100 | H17: =IFERROR(__xludf.DUMMYFUNCTION("""COMPUTED_VALUE"""),100.0) -> 100 | I17: =IFERROR(__xludf.DUMMYFUNCTION("""COMPUTED_VALUE"""),100.0) -> 100 | J17: =IFERROR(__xludf.DUMMYFUNCTION("""COMPUTED_VALUE"""),100.0) -> 100 | Q17: =IFERROR(__xludf.DUMMYFUNCTION("""COMPUTED_VALUE"""),100.0) -> 100 | R17: =IFERROR(__xludf.DUMMYFUNCTION("""COMPUTED_VALUE"""),"Coin Bonus +") -> Coin Bonus + | S17: =IFERROR(__xludf.DUMMYFUNCTION("""COMPUTED_VALUE"""),1.33) -> 1.33 | T17: =IFERROR(__xludf.DUMMYFUNCTION("""COMPUTED_VALUE"""),33.0) -> 33 | U17: =IFERROR(__xludf.DUMMYFUNCTION("""COMPUTED_VALUE"""),33.0) -> 33 | Y17: =IFERROR(__xludf.DUMMYFUNCTION("""COMPUTED_VALUE"""),200.0) -> 200 | Z17: =IFERROR(__xludf.DUMMYFUNCTION("""COMPUTED_VALUE"""),"UW+") -> UW+ | AB17: =IFERROR(__xludf.DUMMYFUNCTION("""COMPUTED_VALUE"""),"Chrono Loop") -> Chrono Loop | AC17: =IFERROR(__xludf.DUMMYFUNCTION("""COMPUTED_VALUE"""),"Locked") -> Locked | AD17: =IFERROR(__xludf.DUMMYFUNCTION("""COMPUTED_VALUE"""),"Lo | Locked") -> Lo | Locked | AE17: =IFERROR(__xludf.DUMMYFUNCTION("""COMPUTED_VALUE"""),"Critical Coin") -> Critical Coin | AF17: =IFERROR(__xludf.DUMMYFUNCTION("""COMPUTED_VALUE"""),7.0) -> 7 | AG17: =IFERROR(__xludf.DUMMYFUNCTION("""COMPUTED_VALUE"""),FALSE) -> FALSE | AH17: =IFERROR(__xludf.DUMMYFUNCTION("""COMPUTED_VALUE"""),"Extra Orb") -> Extra Orb | AI17: =IFERROR(__xludf.DUMMYFUNCTION("""COMPUTED_VALUE"""),"Energy Net") -> Energy Net | AM17: =IFERROR(__xludf.DUMMYFUNCTION("""COMPUTED_VALUE"""),"Crit Factor") -> Crit Factor | AN17: =IFERROR(__xludf.DUMMYFUNCTION("""COMPUTED_VALUE"""),0.5) -> 0.5 | AP17: =IFERROR(__xludf.DUMMYFUNCTION("""COMPUTED_VALUE"""),"Critical Chance") -> Critical Chance | AQ17: =IFERROR(__xludf.DUMMYFUNCTION("""COMPUTED_VALUE"""),0.0) -> 0 | AS17: =IFERROR(__xludf.DUMMYFUNCTION("""COMPUTED_VALUE"""),FALSE) -> FALSE | AT17: =IFERROR(__xludf.DUMMYFUNCTION("""COMPUTED_VALUE"""),"Locked") -> Locked | AU17: =IFERROR(__xludf.DUMMYFUNCTION("""COMPUTED_VALUE"""),"Range") -> Range | AV17: =IFERROR(__xludf.DUMMYFUNCTION("""COMPUTED_VALUE"""),25.0) -> 25 | AW17: =IFERROR(__xludf.DUMMYFUNCTION("""COMPUTED_VALUE"""),"00 | 25m | Cost 0 ⧓ | Next 100 ⧓") -> 00 | 25m | Cost 0 ⧓ | Next 100 ⧓ | BB17: =IFERROR(__xludf.DUMMYFUNCTION("""COMPUTED_VALUE"""),"Assist Slot") -> Assist Slot | BG17: =IFERROR(__xludf.DUMMYFUNCTION("""COMPUTED_VALUE"""),"Assist Slot") -> Assist Slot | BL17: =IFERROR(__xludf.DUMMYFUNCTION("""COMPUTED_VALUE"""),"Assist Slot") -> Assist Slot | BM17: =IFERROR(__xludf.DUMMYFUNCTION("""COMPUTED_VALUE"""),"Restorative Bonus") -> Restorative Bonus | BQ17: =IFERROR(__xludf.DUMMYFUNCTION("""COMPUTED_VALUE"""),"Assist Slot") -> Assist Slot | BR17: =IFERROR(__xludf.DUMMYFUNCTION("""COMPUTED_VALUE"""),"Om Chip") -> Om Chip | BU17: =IFERROR(__xludf.DUMMYFUNCTION("""COMPUTED_VALUE"""),"Scout") -> Scout | BW17: =IFERROR(__xludf.DUMMYFUNCTION("""COMPUTED_VALUE"""),"Cooldown") -> Cooldown | BX17: =IFERROR(__xludf.DUMMYFUNCTION("""COMPUTED_VALUE"""),105.0) -> 105 | BY17: =IFERROR(__xludf.DUMMYFUNCTION("""COMPUTED_VALUE"""),"00 | 105s | Cost 0 ⧈ | Next 1 ⧈") -> 00 | 105s | Cost 0 ⧈ | Next 1 ⧈
A18: =IFERROR(__xludf.DUMMYFUNCTION("""COMPUTED_VALUE"""),"Enhancement Utility - Coin Discount") -> Enhancement Utility - Coin Discount | B18: =IFERROR(__xludf.DUMMYFUNCTION("""COMPUTED_VALUE"""),0.0) -> 0 | D18: =IFERROR(__xludf.DUMMYFUNCTION("""COMPUTED_VALUE"""),100.0) -> 100 | F18: =IFERROR(__xludf.DUMMYFUNCTION("""COMPUTED_VALUE"""),"Super Critical Mult") -> Super Critical Mult | G18: =IFERROR(__xludf.DUMMYFUNCTION("""COMPUTED_VALUE"""),100.0) -> 100 | H18: =IFERROR(__xludf.DUMMYFUNCTION("""COMPUTED_VALUE"""),120.0) -> 120 | I18: =IFERROR(__xludf.DUMMYFUNCTION("""COMPUTED_VALUE"""),100.0) -> 100 | J18: =IFERROR(__xludf.DUMMYFUNCTION("""COMPUTED_VALUE"""),120.0) -> 120 | Q18: =IFERROR(__xludf.DUMMYFUNCTION("""COMPUTED_VALUE"""),120.0) -> 120 | R18: =IFERROR(__xludf.DUMMYFUNCTION("""COMPUTED_VALUE"""),"Cells / Kill Bonus +") -> Cells / Kill Bonus + | S18: =IFERROR(__xludf.DUMMYFUNCTION("""COMPUTED_VALUE"""),1.25) -> 1.25 | T18: =IFERROR(__xludf.DUMMYFUNCTION("""COMPUTED_VALUE"""),25.0) -> 25 | U18: =IFERROR(__xludf.DUMMYFUNCTION("""COMPUTED_VALUE"""),25.0) -> 25 | Y18: =IFERROR(__xludf.DUMMYFUNCTION("""COMPUTED_VALUE"""),200.0) -> 200 | Z18: =IFERROR(__xludf.DUMMYFUNCTION("""COMPUTED_VALUE"""),"Inner Land Mines") -> Inner Land Mines | AB18: =IFERROR(__xludf.DUMMYFUNCTION("""COMPUTED_VALUE"""),"Damage") -> Damage | AC18: =IFERROR(__xludf.DUMMYFUNCTION("""COMPUTED_VALUE"""),10.0) -> 10 | AD18: =IFERROR(__xludf.DUMMYFUNCTION("""COMPUTED_VALUE"""),"00 | x10 | Cost 0 ⧌ | Next 5 ⧌") -> 00 | x10 | Cost 0 ⧌ | Next 5 ⧌ | AE18: =IFERROR(__xludf.DUMMYFUNCTION("""COMPUTED_VALUE"""),"Wave Skip") -> Wave Skip | AF18: =IFERROR(__xludf.DUMMYFUNCTION("""COMPUTED_VALUE"""),7.0) -> 7 | AG18: =IFERROR(__xludf.DUMMYFUNCTION("""COMPUTED_VALUE"""),FALSE) -> FALSE | AH18: =IFERROR(__xludf.DUMMYFUNCTION("""COMPUTED_VALUE"""),"Cash") -> Cash | AI18: =IFERROR(__xludf.DUMMYFUNCTION("""COMPUTED_VALUE"""),"Land Mine Stun") -> Land Mine Stun | AM18: =IFERROR(__xludf.DUMMYFUNCTION("""COMPUTED_VALUE"""),"Damage / Meter") -> Damage / Meter | AN18: =IFERROR(__xludf.DUMMYFUNCTION("""COMPUTED_VALUE"""),0.42999999999999994) -> 0.43 | AP18: =IFERROR(__xludf.DUMMYFUNCTION("""COMPUTED_VALUE"""),"Critical Factor") -> Critical Factor | AQ18: =IFERROR(__xludf.DUMMYFUNCTION("""COMPUTED_VALUE"""),0.0) -> 0 | BW18: =IFERROR(__xludf.DUMMYFUNCTION("""COMPUTED_VALUE"""),"Range Bonus") -> Range Bonus | BX18: =IFERROR(__xludf.DUMMYFUNCTION("""COMPUTED_VALUE"""),2.0) -> 2 | BY18: =IFERROR(__xludf.DUMMYFUNCTION("""COMPUTED_VALUE"""),"00 | 2.0x | Cost 0 ⧈ | Next 10 ⧈") -> 00 | 2.0x | Cost 0 ⧈ | Next 10 ⧈
A19: =IFERROR(__xludf.DUMMYFUNCTION("""COMPUTED_VALUE"""),"Damage") -> Damage | B19: =IFERROR(__xludf.DUMMYFUNCTION("""COMPUTED_VALUE"""),69.0) -> 69 | D19: =IFERROR(__xludf.DUMMYFUNCTION("""COMPUTED_VALUE"""),100.0) -> 100 | E19: =IFERROR(__xludf.DUMMYFUNCTION("""COMPUTED_VALUE"""),TRUE) -> TRUE | F19: =IFERROR(__xludf.DUMMYFUNCTION("""COMPUTED_VALUE"""),"Rend Armor Chance") -> Rend Armor Chance | G19: =IFERROR(__xludf.DUMMYFUNCTION("""COMPUTED_VALUE"""),80.0) -> 80 | H19: =IFERROR(__xludf.DUMMYFUNCTION("""COMPUTED_VALUE"""),299.0) -> 299 | I19: =IFERROR(__xludf.DUMMYFUNCTION("""COMPUTED_VALUE"""),80.0) -> 80 | J19: =IFERROR(__xludf.DUMMYFUNCTION("""COMPUTED_VALUE"""),299.0) -> 299 | Q19: =IFERROR(__xludf.DUMMYFUNCTION("""COMPUTED_VALUE"""),299.0) -> 299 | R19: =IFERROR(__xludf.DUMMYFUNCTION("""COMPUTED_VALUE"""),"Free Upgrades +") -> Free Upgrades + | S19: =IFERROR(__xludf.DUMMYFUNCTION("""COMPUTED_VALUE"""),1.12) -> 1.12 | T19: =IFERROR(__xludf.DUMMYFUNCTION("""COMPUTED_VALUE"""),12.0) -> 12 | U19: =IFERROR(__xludf.DUMMYFUNCTION("""COMPUTED_VALUE"""),12.0) -> 12 | Y19: =IFERROR(__xludf.DUMMYFUNCTION("""COMPUTED_VALUE"""),100.0) -> 100 | AB19: =IFERROR(__xludf.DUMMYFUNCTION("""COMPUTED_VALUE"""),"Quantity") -> Quantity | AC19: =IFERROR(__xludf.DUMMYFUNCTION("""COMPUTED_VALUE"""),3.0) -> 3 | AD19: =IFERROR(__xludf.DUMMYFUNCTION("""COMPUTED_VALUE"""),"00 | #3 | Cost 0 ⧌ | Next 50 ⧌") -> 00 | #3 | Cost 0 ⧌ | Next 50 ⧌ | AE19: =IFERROR(__xludf.DUMMYFUNCTION("""COMPUTED_VALUE"""),"Intro Sprint") -> Intro Sprint | AF19: =IFERROR(__xludf.DUMMYFUNCTION("""COMPUTED_VALUE"""),7.0) -> 7 | AG19: =IFERROR(__xludf.DUMMYFUNCTION("""COMPUTED_VALUE"""),TRUE) -> TRUE | AH19: =IFERROR(__xludf.DUMMYFUNCTION("""COMPUTED_VALUE"""),"Free Upgrades") -> Free Upgrades | AI19: =IFERROR(__xludf.DUMMYFUNCTION("""COMPUTED_VALUE"""),"Second Wind") -> Second Wind | AM19: =IFERROR(__xludf.DUMMYFUNCTION("""COMPUTED_VALUE"""),"Super Critical Chance") -> Super Critical Chance | AN19: =IFERROR(__xludf.DUMMYFUNCTION("""COMPUTED_VALUE"""),0.04) -> 0.04 | AP19: =IFERROR(__xludf.DUMMYFUNCTION("""COMPUTED_VALUE"""),"Damage / Meter") -> Damage / Meter | AQ19: =IFERROR(__xludf.DUMMYFUNCTION("""COMPUTED_VALUE"""),0.0) -> 0 | BB19: =IFERROR(__xludf.DUMMYFUNCTION("""COMPUTED_VALUE"""),"Placeholder 4th preset") -> Placeholder 4th preset | BG19: =IFERROR(__xludf.DUMMYFUNCTION("""COMPUTED_VALUE"""),"Placeholder 4th preset") -> Placeholder 4th preset | BL19: =IFERROR(__xludf.DUMMYFUNCTION("""COMPUTED_VALUE"""),"Placeholder 4th preset") -> Placeholder 4th preset | BQ19: =IFERROR(__xludf.DUMMYFUNCTION("""COMPUTED_VALUE"""),"Placeholder 4th preset") -> Placeholder 4th preset | BU19: =IFERROR(__xludf.DUMMYFUNCTION("""COMPUTED_VALUE"""),FALSE) -> FALSE | BV19: =IFERROR(__xludf.DUMMYFUNCTION("""COMPUTED_VALUE"""),"Locked") -> Locked | BW19: =IFERROR(__xludf.DUMMYFUNCTION("""COMPUTED_VALUE"""),"Duration") -> Duration | BX19: =IFERROR(__xludf.DUMMYFUNCTION("""COMPUTED_VALUE"""),5.0) -> 5 | BY19: =IFERROR(__xludf.DUMMYFUNCTION("""COMPUTED_VALUE"""),"00 | 5s | Cost 0 ⧈ | Next 10 ⧈") -> 00 | 5s | Cost 0 ⧈ | Next 10 ⧈
A20: =IFERROR(__xludf.DUMMYFUNCTION("""COMPUTED_VALUE"""),"Attack Speed") -> Attack Speed | B20: =IFERROR(__xludf.DUMMYFUNCTION("""COMPUTED_VALUE"""),75.0) -> 75 | D20: =IFERROR(__xludf.DUMMYFUNCTION("""COMPUTED_VALUE"""),99.0) -> 99 | F20: =IFERROR(__xludf.DUMMYFUNCTION("""COMPUTED_VALUE"""),"Rend Armor Mult") -> Rend Armor Mult | G20: =IFERROR(__xludf.DUMMYFUNCTION("""COMPUTED_VALUE"""),70.0) -> 70 | H20: =IFERROR(__xludf.DUMMYFUNCTION("""COMPUTED_VALUE"""),299.0) -> 299 | I20: =IFERROR(__xludf.DUMMYFUNCTION("""COMPUTED_VALUE"""),70.0) -> 70 | J20: =IFERROR(__xludf.DUMMYFUNCTION("""COMPUTED_VALUE"""),299.0) -> 299 | Q20: =IFERROR(__xludf.DUMMYFUNCTION("""COMPUTED_VALUE"""),299.0) -> 299 | R20: =IFERROR(__xludf.DUMMYFUNCTION("""COMPUTED_VALUE"""),"Recovery Package +") -> Recovery Package + | S20: =IFERROR(__xludf.DUMMYFUNCTION("""COMPUTED_VALUE"""),1.42) -> 1.42 | T20: =IFERROR(__xludf.DUMMYFUNCTION("""COMPUTED_VALUE"""),42.0) -> 42 | U20: =IFERROR(__xludf.DUMMYFUNCTION("""COMPUTED_VALUE"""),42.0) -> 42 | Y20: =IFERROR(__xludf.DUMMYFUNCTION("""COMPUTED_VALUE"""),300.0) -> 300 | Z20: =IFERROR(__xludf.DUMMYFUNCTION("""COMPUTED_VALUE"""),FALSE) -> FALSE | AA20: =IFERROR(__xludf.DUMMYFUNCTION("""COMPUTED_VALUE"""),"UW Locked") -> UW Locked | AB20: =IFERROR(__xludf.DUMMYFUNCTION("""COMPUTED_VALUE"""),"Cooldown") -> Cooldown | AC20: =IFERROR(__xludf.DUMMYFUNCTION("""COMPUTED_VALUE"""),200.0) -> 200 | AD20: =IFERROR(__xludf.DUMMYFUNCTION("""COMPUTED_VALUE"""),"00 | 200s | Cost 0 ⧌ | Next 8 ⧌") -> 00 | 200s | Cost 0 ⧌ | Next 8 ⧌ | AE20: =IFERROR(__xludf.DUMMYFUNCTION("""COMPUTED_VALUE"""),"Land Mine Stun") -> Land Mine Stun | AF20: =IFERROR(__xludf.DUMMYFUNCTION("""COMPUTED_VALUE"""),7.0) -> 7 | AG20: =IFERROR(__xludf.DUMMYFUNCTION("""COMPUTED_VALUE"""),FALSE) -> FALSE | AM20: =IFERROR(__xludf.DUMMYFUNCTION("""COMPUTED_VALUE"""),"Super Critical Mult") -> Super Critical Mult | AN20: =IFERROR(__xludf.DUMMYFUNCTION("""COMPUTED_VALUE"""),0.05) -> 0.05 | AP20: =IFERROR(__xludf.DUMMYFUNCTION("""COMPUTED_VALUE"""),"Multishot Chance") -> Multishot Chance | AQ20: =IFERROR(__xludf.DUMMYFUNCTION("""COMPUTED_VALUE"""),0.0) -> 0
A21: =IFERROR(__xludf.DUMMYFUNCTION("""COMPUTED_VALUE"""),"Critical Factor") -> Critical Factor | B21: =IFERROR(__xludf.DUMMYFUNCTION("""COMPUTED_VALUE"""),83.0) -> 83 | D21: =IFERROR(__xludf.DUMMYFUNCTION("""COMPUTED_VALUE"""),99.0) -> 99 | E21: =IFERROR(__xludf.DUMMYFUNCTION("""COMPUTED_VALUE""")," ") | F21: =IFERROR(__xludf.DUMMYFUNCTION("""COMPUTED_VALUE"""),"Health") -> Health | G21: =IFERROR(__xludf.DUMMYFUNCTION("""COMPUTED_VALUE"""),5700.0) -> 5700 | H21: =IFERROR(__xludf.DUMMYFUNCTION("""COMPUTED_VALUE"""),6000.0) -> 6000 | I21: =IFERROR(__xludf.DUMMYFUNCTION("""COMPUTED_VALUE"""),5700.0) -> 5700 | J21: =IFERROR(__xludf.DUMMYFUNCTION("""COMPUTED_VALUE"""),6000.0) -> 6000 | Q21: =IFERROR(__xludf.DUMMYFUNCTION("""COMPUTED_VALUE"""),6000.0) -> 6000 | R21: =IFERROR(__xludf.DUMMYFUNCTION("""COMPUTED_VALUE"""),"Enemy Level Skips +") -> Enemy Level Skips + | S21: =IFERROR(__xludf.DUMMYFUNCTION("""COMPUTED_VALUE"""),1.15) -> 1.15 | T21: =IFERROR(__xludf.DUMMYFUNCTION("""COMPUTED_VALUE"""),15.0) -> 15 | U21: =IFERROR(__xludf.DUMMYFUNCTION("""COMPUTED_VALUE"""),15.0) -> 15 | Y21: =IFERROR(__xludf.DUMMYFUNCTION("""COMPUTED_VALUE"""),60.0) -> 60 | Z21: =IFERROR(__xludf.DUMMYFUNCTION("""COMPUTED_VALUE"""),"UW+") -> UW+ | AB21: =IFERROR(__xludf.DUMMYFUNCTION("""COMPUTED_VALUE"""),"Charged Mines") -> Charged Mines | AC21: =IFERROR(__xludf.DUMMYFUNCTION("""COMPUTED_VALUE"""),"Locked") -> Locked | AD21: =IFERROR(__xludf.DUMMYFUNCTION("""COMPUTED_VALUE"""),"Lo | Locked") -> Lo | Locked | AE21: =IFERROR(__xludf.DUMMYFUNCTION("""COMPUTED_VALUE"""),"Recovery Package Chance") -> Recovery Package Chance | AF21: =IFERROR(__xludf.DUMMYFUNCTION("""COMPUTED_VALUE"""),7.0) -> 7 | AG21: =IFERROR(__xludf.DUMMYFUNCTION("""COMPUTED_VALUE"""),TRUE) -> TRUE | AM21: =IFERROR(__xludf.DUMMYFUNCTION("""COMPUTED_VALUE"""),"Rend Armor Mult") -> Rend Armor Mult | AN21: =IFERROR(__xludf.DUMMYFUNCTION("""COMPUTED_VALUE"""),0.0) -> 0 | AP21: =IFERROR(__xludf.DUMMYFUNCTION("""COMPUTED_VALUE"""),"Rapid Fire Chance") -> Rapid Fire Chance | AQ21: =IFERROR(__xludf.DUMMYFUNCTION("""COMPUTED_VALUE"""),0.0) -> 0
A22: =IFERROR(__xludf.DUMMYFUNCTION("""COMPUTED_VALUE"""),"Range") -> Range | B22: =IFERROR(__xludf.DUMMYFUNCTION("""COMPUTED_VALUE"""),33.0) -> 33 | D22: =IFERROR(__xludf.DUMMYFUNCTION("""COMPUTED_VALUE"""),80.0) -> 80 | F22: =IFERROR(__xludf.DUMMYFUNCTION("""COMPUTED_VALUE"""),"Health Regen") -> Health Regen | G22: =IFERROR(__xludf.DUMMYFUNCTION("""COMPUTED_VALUE"""),6000.0) -> 6000 | H22: =IFERROR(__xludf.DUMMYFUNCTION("""COMPUTED_VALUE"""),6000.0) -> 6000 | I22: =IFERROR(__xludf.DUMMYFUNCTION("""COMPUTED_VALUE"""),6000.0) -> 6000 | J22: =IFERROR(__xludf.DUMMYFUNCTION("""COMPUTED_VALUE"""),6000.0) -> 6000 | Q22: =IFERROR(__xludf.DUMMYFUNCTION("""COMPUTED_VALUE"""),6000.0) -> 6000 | Z22: =IFERROR(__xludf.DUMMYFUNCTION("""COMPUTED_VALUE"""),"Golden Tower") -> Golden Tower | AB22: =IFERROR(__xludf.DUMMYFUNCTION("""COMPUTED_VALUE"""),"Multiplier") -> Multiplier | AC22: =IFERROR(__xludf.DUMMYFUNCTION("""COMPUTED_VALUE"""),14.600000000000005) -> 14.6 | AD22: =IFERROR(__xludf.DUMMYFUNCTION("""COMPUTED_VALUE"""),"12 | x14.6 | Cost 162 ⧌ | Next 250 ⧌") -> 12 | x14.6 | Cost 162 ⧌ | Next 250 ⧌ | AE22: =IFERROR(__xludf.DUMMYFUNCTION("""COMPUTED_VALUE"""),"Death Ray") -> Death Ray | AF22: =IFERROR(__xludf.DUMMYFUNCTION("""COMPUTED_VALUE"""),7.0) -> 7 | AG22: =IFERROR(__xludf.DUMMYFUNCTION("""COMPUTED_VALUE"""),FALSE) -> FALSE | AM22: =IFERROR(__xludf.DUMMYFUNCTION("""COMPUTED_VALUE"""),"Defense") -> Defense | AP22: =IFERROR(__xludf.DUMMYFUNCTION("""COMPUTED_VALUE"""),"Bounce Shot Chance") -> Bounce Shot Chance | AQ22: =IFERROR(__xludf.DUMMYFUNCTION("""COMPUTED_VALUE"""),0.0) -> 0
A23: =IFERROR(__xludf.DUMMYFUNCTION("""COMPUTED_VALUE"""),"Damage / Meter") -> Damage / Meter | B23: =IFERROR(__xludf.DUMMYFUNCTION("""COMPUTED_VALUE"""),16.0) -> 16 | D23: =IFERROR(__xludf.DUMMYFUNCTION("""COMPUTED_VALUE"""),99.0) -> 99 | E23: =IFERROR(__xludf.DUMMYFUNCTION("""COMPUTED_VALUE"""),TRUE) -> TRUE | F23: =IFERROR(__xludf.DUMMYFUNCTION("""COMPUTED_VALUE"""),"Defense %") -> Defense % | G23: =IFERROR(__xludf.DUMMYFUNCTION("""COMPUTED_VALUE"""),99.0) -> 99 | H23: =IFERROR(__xludf.DUMMYFUNCTION("""COMPUTED_VALUE"""),99.0) -> 99 | I23: =IFERROR(__xludf.DUMMYFUNCTION("""COMPUTED_VALUE"""),99.0) -> 99 | J23: =IFERROR(__xludf.DUMMYFUNCTION("""COMPUTED_VALUE"""),99.0) -> 99 | Q23: =IFERROR(__xludf.DUMMYFUNCTION("""COMPUTED_VALUE"""),99.0) -> 99 | AB23: =IFERROR(__xludf.DUMMYFUNCTION("""COMPUTED_VALUE"""),"Duration") -> Duration | AC23: =IFERROR(__xludf.DUMMYFUNCTION("""COMPUTED_VALUE"""),22.0) -> 22 | AD23: =IFERROR(__xludf.DUMMYFUNCTION("""COMPUTED_VALUE"""),"07 | 22s | Cost 59 ⧌ | Next 68 ⧌") -> 07 | 22s | Cost 59 ⧌ | Next 68 ⧌ | AE23: =IFERROR(__xludf.DUMMYFUNCTION("""COMPUTED_VALUE"""),"Energy Net") -> Energy Net | AF23: =IFERROR(__xludf.DUMMYFUNCTION("""COMPUTED_VALUE"""),7.0) -> 7 | AG23: =IFERROR(__xludf.DUMMYFUNCTION("""COMPUTED_VALUE"""),FALSE) -> FALSE | AM23: =IFERROR(__xludf.DUMMYFUNCTION("""COMPUTED_VALUE"""),"Health") -> Health | AN23: =IFERROR(__xludf.DUMMYFUNCTION("""COMPUTED_VALUE"""),0.51) -> 0.51 | AP23: =IFERROR(__xludf.DUMMYFUNCTION("""COMPUTED_VALUE"""),"Super Crit Chance") -> Super Crit Chance | AQ23: =IFERROR(__xludf.DUMMYFUNCTION("""COMPUTED_VALUE"""),0.0) -> 0 | BB23: =IFERROR(__xludf.DUMMYFUNCTION("""COMPUTED_VALUE"""),"Placeholder 5th preset") -> Placeholder 5th preset | BG23: =IFERROR(__xludf.DUMMYFUNCTION("""COMPUTED_VALUE"""),"Placeholder 5th preset") -> Placeholder 5th preset | BL23: =IFERROR(__xludf.DUMMYFUNCTION("""COMPUTED_VALUE"""),"Placeholder 5th preset") -> Placeholder 5th preset | BQ23: =IFERROR(__xludf.DUMMYFUNCTION("""COMPUTED_VALUE"""),"Placeholder 5th preset") -> Placeholder 5th preset
A24: =IFERROR(__xludf.DUMMYFUNCTION("""COMPUTED_VALUE"""),"Super Crit Chance") -> Super Crit Chance | B24: =IFERROR(__xludf.DUMMYFUNCTION("""COMPUTED_VALUE"""),9.0) -> 9 | D24: =IFERROR(__xludf.DUMMYFUNCTION("""COMPUTED_VALUE"""),50.0) -> 50 | F24: =IFERROR(__xludf.DUMMYFUNCTION("""COMPUTED_VALUE"""),"Defense Absolute") -> Defense Absolute | G24: =IFERROR(__xludf.DUMMYFUNCTION("""COMPUTED_VALUE"""),5000.0) -> 5000 | H24: =IFERROR(__xludf.DUMMYFUNCTION("""COMPUTED_VALUE"""),5000.0) -> 5000 | I24: =IFERROR(__xludf.DUMMYFUNCTION("""COMPUTED_VALUE"""),5000.0) -> 5000 | J24: =IFERROR(__xludf.DUMMYFUNCTION("""COMPUTED_VALUE"""),5000.0) -> 5000 | Q24: =IFERROR(__xludf.DUMMYFUNCTION("""COMPUTED_VALUE"""),5000.0) -> 5000 | Z24: =IFERROR(__xludf.DUMMYFUNCTION("""COMPUTED_VALUE"""),TRUE) -> TRUE | AA24: =IFERROR(__xludf.DUMMYFUNCTION("""COMPUTED_VALUE"""),"UW Unlocked") -> UW Unlocked | AB24: =IFERROR(__xludf.DUMMYFUNCTION("""COMPUTED_VALUE"""),"Cooldown") -> Cooldown | AC24: =IFERROR(__xludf.DUMMYFUNCTION("""COMPUTED_VALUE"""),180.0) -> 180 | AD24: =IFERROR(__xludf.DUMMYFUNCTION("""COMPUTED_VALUE"""),"12 | 180s | Cost 208 ⧌ | Next 226 ⧌") -> 12 | 180s | Cost 208 ⧌ | Next 226 ⧌ | AE24: =IFERROR(__xludf.DUMMYFUNCTION("""COMPUTED_VALUE"""),"Super Tower") -> Super Tower | AF24: =IFERROR(__xludf.DUMMYFUNCTION("""COMPUTED_VALUE"""),7.0) -> 7 | AG24: =IFERROR(__xludf.DUMMYFUNCTION("""COMPUTED_VALUE"""),FALSE) -> FALSE | AM24: =IFERROR(__xludf.DUMMYFUNCTION("""COMPUTED_VALUE"""),"Health Regen") -> Health Regen | AN24: =IFERROR(__xludf.DUMMYFUNCTION("""COMPUTED_VALUE"""),0.22999999999999998) -> 0.23 | AP24: =IFERROR(__xludf.DUMMYFUNCTION("""COMPUTED_VALUE"""),"Super Crit Mult") -> Super Crit Mult | AQ24: =IFERROR(__xludf.DUMMYFUNCTION("""COMPUTED_VALUE"""),0.0) -> 0
A25: =IFERROR(__xludf.DUMMYFUNCTION("""COMPUTED_VALUE"""),"Super Crit Multi") -> Super Crit Multi | B25: =IFERROR(__xludf.DUMMYFUNCTION("""COMPUTED_VALUE"""),13.0) -> 13 | D25: =IFERROR(__xludf.DUMMYFUNCTION("""COMPUTED_VALUE"""),40.0) -> 40 | E25: =IFERROR(__xludf.DUMMYFUNCTION("""COMPUTED_VALUE"""),TRUE) -> TRUE | F25: =IFERROR(__xludf.DUMMYFUNCTION("""COMPUTED_VALUE"""),"Thorn Damage") -> Thorn Damage | G25: =IFERROR(__xludf.DUMMYFUNCTION("""COMPUTED_VALUE"""),99.0) -> 99 | H25: =IFERROR(__xludf.DUMMYFUNCTION("""COMPUTED_VALUE"""),99.0) -> 99 | I25: =IFERROR(__xludf.DUMMYFUNCTION("""COMPUTED_VALUE"""),99.0) -> 99 | J25: =IFERROR(__xludf.DUMMYFUNCTION("""COMPUTED_VALUE"""),99.0) -> 99 | Q25: =IFERROR(__xludf.DUMMYFUNCTION("""COMPUTED_VALUE"""),99.0) -> 99 | Z25: =IFERROR(__xludf.DUMMYFUNCTION("""COMPUTED_VALUE"""),"UW+") -> UW+ | AB25: =IFERROR(__xludf.DUMMYFUNCTION("""COMPUTED_VALUE"""),"Golden Combo") -> Golden Combo | AC25: =IFERROR(__xludf.DUMMYFUNCTION("""COMPUTED_VALUE"""),"Locked") -> Locked | AD25: =IFERROR(__xludf.DUMMYFUNCTION("""COMPUTED_VALUE"""),"Lo | Locked") -> Lo | Locked | AE25: =IFERROR(__xludf.DUMMYFUNCTION("""COMPUTED_VALUE"""),"Second Wind") -> Second Wind | AF25: =IFERROR(__xludf.DUMMYFUNCTION("""COMPUTED_VALUE"""),7.0) -> 7 | AG25: =IFERROR(__xludf.DUMMYFUNCTION("""COMPUTED_VALUE"""),FALSE) -> FALSE | AM25: =IFERROR(__xludf.DUMMYFUNCTION("""COMPUTED_VALUE"""),"Defense %") -> Defense % | AN25: =IFERROR(__xludf.DUMMYFUNCTION("""COMPUTED_VALUE"""),0.04) -> 0.04 | AP25: =IFERROR(__xludf.DUMMYFUNCTION("""COMPUTED_VALUE"""),"Rend Armor Chance") -> Rend Armor Chance | AQ25: =IFERROR(__xludf.DUMMYFUNCTION("""COMPUTED_VALUE"""),0.0) -> 0
A26: =IFERROR(__xludf.DUMMYFUNCTION("""COMPUTED_VALUE"""),"Max Rend Armor Multiplier") -> Max Rend Armor Multiplier | B26: =IFERROR(__xludf.DUMMYFUNCTION("""COMPUTED_VALUE"""),0.0) -> 0 | D26: =IFERROR(__xludf.DUMMYFUNCTION("""COMPUTED_VALUE"""),30.0) -> 30 | E26: =IFERROR(__xludf.DUMMYFUNCTION("""COMPUTED_VALUE"""),TRUE) -> TRUE | F26: =IFERROR(__xludf.DUMMYFUNCTION("""COMPUTED_VALUE"""),"Lifesteal") -> Lifesteal | G26: =IFERROR(__xludf.DUMMYFUNCTION("""COMPUTED_VALUE"""),80.0) -> 80 | H26: =IFERROR(__xludf.DUMMYFUNCTION("""COMPUTED_VALUE"""),80.0) -> 80 | I26: =IFERROR(__xludf.DUMMYFUNCTION("""COMPUTED_VALUE"""),80.0) -> 80 | J26: =IFERROR(__xludf.DUMMYFUNCTION("""COMPUTED_VALUE"""),80.0) -> 80 | Q26: =IFERROR(__xludf.DUMMYFUNCTION("""COMPUTED_VALUE"""),80.0) -> 80 | Z26: =IFERROR(__xludf.DUMMYFUNCTION("""COMPUTED_VALUE"""),"Poison Swamp") -> Poison Swamp | AB26: =IFERROR(__xludf.DUMMYFUNCTION("""COMPUTED_VALUE"""),"Damage") -> Damage | AC26: =IFERROR(__xludf.DUMMYFUNCTION("""COMPUTED_VALUE"""),10.0) -> 10 | AD26: =IFERROR(__xludf.DUMMYFUNCTION("""COMPUTED_VALUE"""),"00 | x10 | Cost 0 ⧌ | Next 5 ⧌") -> 00 | x10 | Cost 0 ⧌ | Next 5 ⧌ | AE26: =IFERROR(__xludf.DUMMYFUNCTION("""COMPUTED_VALUE"""),"Demon Mode") -> Demon Mode | AF26: =IFERROR(__xludf.DUMMYFUNCTION("""COMPUTED_VALUE"""),7.0) -> 7 | AG26: =IFERROR(__xludf.DUMMYFUNCTION("""COMPUTED_VALUE"""),FALSE) -> FALSE | AM26: =IFERROR(__xludf.DUMMYFUNCTION("""COMPUTED_VALUE"""),"Defense Absolute") -> Defense Absolute | AN26: =IFERROR(__xludf.DUMMYFUNCTION("""COMPUTED_VALUE"""),0.28) -> 0.28 | AP26: =IFERROR(__xludf.DUMMYFUNCTION("""COMPUTED_VALUE"""),"Rend Armor Mult") -> Rend Armor Mult | AQ26: =IFERROR(__xludf.DUMMYFUNCTION("""COMPUTED_VALUE"""),0.0) -> 0
A27: =IFERROR(__xludf.DUMMYFUNCTION("""COMPUTED_VALUE"""),"Light Speed Shots") -> Light Speed Shots | B27: =IFERROR(__xludf.DUMMYFUNCTION("""COMPUTED_VALUE"""),1.0) -> 1 | D27: =IFERROR(__xludf.DUMMYFUNCTION("""COMPUTED_VALUE"""),1.0) -> 1 | E27: =IFERROR(__xludf.DUMMYFUNCTION("""COMPUTED_VALUE"""),TRUE) -> TRUE | F27: =IFERROR(__xludf.DUMMYFUNCTION("""COMPUTED_VALUE"""),"Knockback Chance") -> Knockback Chance | G27: =IFERROR(__xludf.DUMMYFUNCTION("""COMPUTED_VALUE"""),80.0) -> 80 | H27: =IFERROR(__xludf.DUMMYFUNCTION("""COMPUTED_VALUE"""),80.0) -> 80 | I27: =IFERROR(__xludf.DUMMYFUNCTION("""COMPUTED_VALUE"""),80.0) -> 80 | J27: =IFERROR(__xludf.DUMMYFUNCTION("""COMPUTED_VALUE"""),80.0) -> 80 | Q27: =IFERROR(__xludf.DUMMYFUNCTION("""COMPUTED_VALUE"""),80.0) -> 80 | AB27: =IFERROR(__xludf.DUMMYFUNCTION("""COMPUTED_VALUE"""),"Duration") -> Duration | AC27: =IFERROR(__xludf.DUMMYFUNCTION("""COMPUTED_VALUE"""),30.0) -> 30 | AD27: =IFERROR(__xludf.DUMMYFUNCTION("""COMPUTED_VALUE"""),"00 | 30s | Cost 0 ⧌ | Next 10 ⧌") -> 00 | 30s | Cost 0 ⧌ | Next 10 ⧌ | AE27: =IFERROR(__xludf.DUMMYFUNCTION("""COMPUTED_VALUE"""),"Energy Shield") -> Energy Shield | AF27: =IFERROR(__xludf.DUMMYFUNCTION("""COMPUTED_VALUE"""),7.0) -> 7 | AG27: =IFERROR(__xludf.DUMMYFUNCTION("""COMPUTED_VALUE"""),FALSE) -> FALSE | AM27: =IFERROR(__xludf.DUMMYFUNCTION("""COMPUTED_VALUE"""),"Thorns") -> Thorns | AN27: =IFERROR(__xludf.DUMMYFUNCTION("""COMPUTED_VALUE"""),0.09000000000000001) -> 0.09 | AP27: =IFERROR(__xludf.DUMMYFUNCTION("""COMPUTED_VALUE"""),"Defense") -> Defense | BB27: =IFERROR(__xludf.DUMMYFUNCTION("""COMPUTED_VALUE"""),"Astral Deliverance") -> Astral Deliverance | BG27: =IFERROR(__xludf.DUMMYFUNCTION("""COMPUTED_VALUE"""),"Anti-Cube Portal") -> Anti-Cube Portal | BL27: =IFERROR(__xludf.DUMMYFUNCTION("""COMPUTED_VALUE"""),"Black Hole Digestor") -> Black Hole Digestor | BQ27: =IFERROR(__xludf.DUMMYFUNCTION("""COMPUTED_VALUE"""),"Multiverse Nexus") -> Multiverse Nexus
A28: =IFERROR(__xludf.DUMMYFUNCTION("""COMPUTED_VALUE"""),"Health") -> Health | B28: =IFERROR(__xludf.DUMMYFUNCTION("""COMPUTED_VALUE"""),68.0) -> 68 | D28: =IFERROR(__xludf.DUMMYFUNCTION("""COMPUTED_VALUE"""),100.0) -> 100 | F28: =IFERROR(__xludf.DUMMYFUNCTION("""COMPUTED_VALUE"""),"Knockback Force") -> Knockback Force | G28: =IFERROR(__xludf.DUMMYFUNCTION("""COMPUTED_VALUE"""),40.0) -> 40 | H28: =IFERROR(__xludf.DUMMYFUNCTION("""COMPUTED_VALUE"""),40.0) -> 40 | I28: =IFERROR(__xludf.DUMMYFUNCTION("""COMPUTED_VALUE"""),40.0) -> 40 | J28: =IFERROR(__xludf.DUMMYFUNCTION("""COMPUTED_VALUE"""),40.0) -> 40 | Q28: =IFERROR(__xludf.DUMMYFUNCTION("""COMPUTED_VALUE"""),40.0) -> 40 | Z28: =IFERROR(__xludf.DUMMYFUNCTION("""COMPUTED_VALUE"""),FALSE) -> FALSE | AA28: =IFERROR(__xludf.DUMMYFUNCTION("""COMPUTED_VALUE"""),"UW Locked") -> UW Locked | AB28: =IFERROR(__xludf.DUMMYFUNCTION("""COMPUTED_VALUE"""),"Cooldown") -> Cooldown | AC28: =IFERROR(__xludf.DUMMYFUNCTION("""COMPUTED_VALUE"""),125.0) -> 125 | AD28: =IFERROR(__xludf.DUMMYFUNCTION("""COMPUTED_VALUE"""),"00 | 125s | Cost 0 ⧌ | Next 8 ⧌") -> 00 | 125s | Cost 0 ⧌ | Next 8 ⧌ | AE28: =IFERROR(__xludf.DUMMYFUNCTION("""COMPUTED_VALUE"""),"Wave Accelerator") -> Wave Accelerator | AF28: =IFERROR(__xludf.DUMMYFUNCTION("""COMPUTED_VALUE"""),7.0) -> 7 | AG28: =IFERROR(__xludf.DUMMYFUNCTION("""COMPUTED_VALUE"""),FALSE) -> FALSE | AM28: =IFERROR(__xludf.DUMMYFUNCTION("""COMPUTED_VALUE"""),"Knockback Force") -> Knockback Force | AN28: =IFERROR(__xludf.DUMMYFUNCTION("""COMPUTED_VALUE"""),0.24) -> 0.24 | AP28: =IFERROR(__xludf.DUMMYFUNCTION("""COMPUTED_VALUE"""),"Health") -> Health | AQ28: =IFERROR(__xludf.DUMMYFUNCTION("""COMPUTED_VALUE"""),0.0) -> 0 | BB28: =IFERROR(__xludf.DUMMYFUNCTION("""COMPUTED_VALUE"""),"Rarity") -> Rarity | BC28: =IFERROR(__xludf.DUMMYFUNCTION("""COMPUTED_VALUE"""),"Level") -> Level | BD28: =IFERROR(__xludf.DUMMYFUNCTION("""COMPUTED_VALUE"""),"Stat") -> Stat | BG28: =IFERROR(__xludf.DUMMYFUNCTION("""COMPUTED_VALUE"""),"Rarity") -> Rarity | BH28: =IFERROR(__xludf.DUMMYFUNCTION("""COMPUTED_VALUE"""),"Level") -> Level | BI28: =IFERROR(__xludf.DUMMYFUNCTION("""COMPUTED_VALUE"""),"Stat") -> Stat | BL28: =IFERROR(__xludf.DUMMYFUNCTION("""COMPUTED_VALUE"""),"Rarity") -> Rarity | BM28: =IFERROR(__xludf.DUMMYFUNCTION("""COMPUTED_VALUE"""),"Level") -> Level | BN28: =IFERROR(__xludf.DUMMYFUNCTION("""COMPUTED_VALUE"""),"Stat") -> Stat | BQ28: =IFERROR(__xludf.DUMMYFUNCTION("""COMPUTED_VALUE"""),"Rarity") -> Rarity | BR28: =IFERROR(__xludf.DUMMYFUNCTION("""COMPUTED_VALUE"""),"Level") -> Level | BS28: =IFERROR(__xludf.DUMMYFUNCTION("""COMPUTED_VALUE"""),"Stat") -> Stat
A29: =IFERROR(__xludf.DUMMYFUNCTION("""COMPUTED_VALUE"""),"Health Regen") -> Health Regen | B29: =IFERROR(__xludf.DUMMYFUNCTION("""COMPUTED_VALUE"""),68.0) -> 68 | D29: =IFERROR(__xludf.DUMMYFUNCTION("""COMPUTED_VALUE"""),100.0) -> 100 | E29: =IFERROR(__xludf.DUMMYFUNCTION("""COMPUTED_VALUE"""),TRUE) -> TRUE | F29: =IFERROR(__xludf.DUMMYFUNCTION("""COMPUTED_VALUE"""),"Orb Speed") -> Orb Speed | G29: =IFERROR(__xludf.DUMMYFUNCTION("""COMPUTED_VALUE"""),38.0) -> 38 | H29: =IFERROR(__xludf.DUMMYFUNCTION("""COMPUTED_VALUE"""),38.0) -> 38 | I29: =IFERROR(__xludf.DUMMYFUNCTION("""COMPUTED_VALUE"""),38.0) -> 38 | J29: =IFERROR(__xludf.DUMMYFUNCTION("""COMPUTED_VALUE"""),38.0) -> 38 | Q29: =IFERROR(__xludf.DUMMYFUNCTION("""COMPUTED_VALUE"""),38.0) -> 38 | Z29: =IFERROR(__xludf.DUMMYFUNCTION("""COMPUTED_VALUE"""),"UW+") -> UW+ | AB29: =IFERROR(__xludf.DUMMYFUNCTION("""COMPUTED_VALUE"""),"Death Creep") -> Death Creep | AC29: =IFERROR(__xludf.DUMMYFUNCTION("""COMPUTED_VALUE"""),"Locked") -> Locked | AD29: =IFERROR(__xludf.DUMMYFUNCTION("""COMPUTED_VALUE"""),"Lo | Locked") -> Lo | Locked | AE29: =IFERROR(__xludf.DUMMYFUNCTION("""COMPUTED_VALUE"""),"Berserker") -> Berserker | AF29: =IFERROR(__xludf.DUMMYFUNCTION("""COMPUTED_VALUE"""),7.0) -> 7 | AG29: =IFERROR(__xludf.DUMMYFUNCTION("""COMPUTED_VALUE"""),FALSE) -> FALSE | AM29: =IFERROR(__xludf.DUMMYFUNCTION("""COMPUTED_VALUE"""),"Orb Speed") -> Orb Speed | AN29: =IFERROR(__xludf.DUMMYFUNCTION("""COMPUTED_VALUE"""),0.12000000000000001) -> 0.12 | AP29: =IFERROR(__xludf.DUMMYFUNCTION("""COMPUTED_VALUE"""),"Health Regen") -> Health Regen | AQ29: =IFERROR(__xludf.DUMMYFUNCTION("""COMPUTED_VALUE"""),0.0) -> 0 | BB29: =IFERROR(__xludf.DUMMYFUNCTION("""COMPUTED_VALUE"""),"Mythic+") -> Mythic+ | BC29: =IFERROR(__xludf.DUMMYFUNCTION("""COMPUTED_VALUE"""),160.0) -> 160 | BD29: =IFERROR(__xludf.DUMMYFUNCTION("""COMPUTED_VALUE"""),8.19) -> 8.19 | BG29: =IFERROR(__xludf.DUMMYFUNCTION("""COMPUTED_VALUE"""),"Mythic+") -> Mythic+ | BH29: =IFERROR(__xludf.DUMMYFUNCTION("""COMPUTED_VALUE"""),160.0) -> 160 | BI29: =IFERROR(__xludf.DUMMYFUNCTION("""COMPUTED_VALUE"""),8.19) -> 8.19 | BL29: =IFERROR(__xludf.DUMMYFUNCTION("""COMPUTED_VALUE"""),"Legendary") -> Legendary | BM29: =IFERROR(__xludf.DUMMYFUNCTION("""COMPUTED_VALUE"""),100.0) -> 100 | BN29: =IFERROR(__xludf.DUMMYFUNCTION("""COMPUTED_VALUE"""),1.275) -> 1.275 | BQ29: =IFERROR(__xludf.DUMMYFUNCTION("""COMPUTED_VALUE"""),"Ancestral 2*") -> Ancestral 2* | BR29: =IFERROR(__xludf.DUMMYFUNCTION("""COMPUTED_VALUE"""),159.0) -> 159 | BS29: =IFERROR(__xludf.DUMMYFUNCTION("""COMPUTED_VALUE"""),11.692) -> 11.692
A30: =IFERROR(__xludf.DUMMYFUNCTION("""COMPUTED_VALUE"""),"Defense Absolute") -> Defense Absolute | B30: =IFERROR(__xludf.DUMMYFUNCTION("""COMPUTED_VALUE"""),14.0) -> 14 | C30: =IFERROR(__xludf.DUMMYFUNCTION("""COMPUTED_VALUE"""),14.0) -> 14 | D30: =IFERROR(__xludf.DUMMYFUNCTION("""COMPUTED_VALUE"""),100.0) -> 100 | F30: =IFERROR(__xludf.DUMMYFUNCTION("""COMPUTED_VALUE"""),"Orbs") -> Orbs | G30: =IFERROR(__xludf.DUMMYFUNCTION("""COMPUTED_VALUE"""),4.0) -> 4 | H30: =IFERROR(__xludf.DUMMYFUNCTION("""COMPUTED_VALUE"""),4.0) -> 4 | I30: =IFERROR(__xludf.DUMMYFUNCTION("""COMPUTED_VALUE"""),4.0) -> 4 | J30: =IFERROR(__xludf.DUMMYFUNCTION("""COMPUTED_VALUE"""),4.0) -> 4 | Q30: =IFERROR(__xludf.DUMMYFUNCTION("""COMPUTED_VALUE"""),4.0) -> 4 | Z30: =IFERROR(__xludf.DUMMYFUNCTION("""COMPUTED_VALUE"""),"Black Hole") -> Black Hole | AB30: =IFERROR(__xludf.DUMMYFUNCTION("""COMPUTED_VALUE"""),"Size") -> Size | AC30: =IFERROR(__xludf.DUMMYFUNCTION("""COMPUTED_VALUE"""),48.0) -> 48 | AD30: =IFERROR(__xludf.DUMMYFUNCTION("""COMPUTED_VALUE"""),"09 | 48m | Cost 76 ⧌ | Next 89 ⧌") -> 09 | 48m | Cost 76 ⧌ | Next 89 ⧌ | AE30: =IFERROR(__xludf.DUMMYFUNCTION("""COMPUTED_VALUE"""),"Ultimate Crit") -> Ultimate Crit | AF30: =IFERROR(__xludf.DUMMYFUNCTION("""COMPUTED_VALUE"""),7.0) -> 7 | AG30: =IFERROR(__xludf.DUMMYFUNCTION("""COMPUTED_VALUE"""),FALSE) -> FALSE | AM30: =IFERROR(__xludf.DUMMYFUNCTION("""COMPUTED_VALUE"""),"Wall Rebuild") -> Wall Rebuild | AN30: =IFERROR(__xludf.DUMMYFUNCTION("""COMPUTED_VALUE"""),2.0) -> 2 | AP30: =IFERROR(__xludf.DUMMYFUNCTION("""COMPUTED_VALUE"""),"Defense %") -> Defense % | AQ30: =IFERROR(__xludf.DUMMYFUNCTION("""COMPUTED_VALUE"""),0.0) -> 0
A31: =IFERROR(__xludf.DUMMYFUNCTION("""COMPUTED_VALUE"""),"Defense %") -> Defense % | B31: =IFERROR(__xludf.DUMMYFUNCTION("""COMPUTED_VALUE"""),28.0) -> 28 | C31: =IFERROR(__xludf.DUMMYFUNCTION("""COMPUTED_VALUE"""),28.0) -> 28 | D31: =IFERROR(__xludf.DUMMYFUNCTION("""COMPUTED_VALUE"""),50.0) -> 50 | E31: =IFERROR(__xludf.DUMMYFUNCTION("""COMPUTED_VALUE"""),TRUE) -> TRUE | F31: =IFERROR(__xludf.DUMMYFUNCTION("""COMPUTED_VALUE"""),"Shockwave Size") -> Shockwave Size | G31: =IFERROR(__xludf.DUMMYFUNCTION("""COMPUTED_VALUE"""),35.0) -> 35 | H31: =IFERROR(__xludf.DUMMYFUNCTION("""COMPUTED_VALUE"""),35.0) -> 35 | I31: =IFERROR(__xludf.DUMMYFUNCTION("""COMPUTED_VALUE"""),35.0) -> 35 | J31: =IFERROR(__xludf.DUMMYFUNCTION("""COMPUTED_VALUE"""),35.0) -> 35 | Q31: =IFERROR(__xludf.DUMMYFUNCTION("""COMPUTED_VALUE"""),35.0) -> 35 | AB31: =IFERROR(__xludf.DUMMYFUNCTION("""COMPUTED_VALUE"""),"Duration") -> Duration | AC31: =IFERROR(__xludf.DUMMYFUNCTION("""COMPUTED_VALUE"""),32.0) -> 32 | AD31: =IFERROR(__xludf.DUMMYFUNCTION("""COMPUTED_VALUE"""),"17 | 32s | Cost 224 ⧌ | Next 308 ⧌") -> 17 | 32s | Cost 224 ⧌ | Next 308 ⧌ | AE31: =IFERROR(__xludf.DUMMYFUNCTION("""COMPUTED_VALUE"""),"Nuke") -> Nuke | AF31: =IFERROR(__xludf.DUMMYFUNCTION("""COMPUTED_VALUE"""),7.0) -> 7 | AG31: =IFERROR(__xludf.DUMMYFUNCTION("""COMPUTED_VALUE"""),FALSE) -> FALSE | AM31: =IFERROR(__xludf.DUMMYFUNCTION("""COMPUTED_VALUE"""),"Utility") -> Utility | AP31: =IFERROR(__xludf.DUMMYFUNCTION("""COMPUTED_VALUE"""),"Defense Absolute") -> Defense Absolute | AQ31: =IFERROR(__xludf.DUMMYFUNCTION("""COMPUTED_VALUE"""),0.0) -> 0 | BE31: =IFERROR(__xludf.DUMMYFUNCTION("""COMPUTED_VALUE"""),"") | BG31: =IFERROR(__xludf.DUMMYFUNCTION("""COMPUTED_VALUE"""),"Orb Speed") -> Orb Speed | BH31: =IFERROR(__xludf.DUMMYFUNCTION("""COMPUTED_VALUE"""),"Legendary") -> Legendary | BI31: =IFERROR(__xludf.DUMMYFUNCTION("""COMPUTED_VALUE"""),"+1.5") -> +1.5 | BJ31: =IFERROR(__xludf.DUMMYFUNCTION("""COMPUTED_VALUE"""),1.5) -> 1.5 | BL31: =IFERROR(__xludf.DUMMYFUNCTION("""COMPUTED_VALUE"""),"Coins / Kill Bonus") -> Coins / Kill Bonus | BM31: =IFERROR(__xludf.DUMMYFUNCTION("""COMPUTED_VALUE"""),"Legendary") -> Legendary | BN31: =IFERROR(__xludf.DUMMYFUNCTION("""COMPUTED_VALUE"""),"+0.4x") -> +0.4x | BO31: =IFERROR(__xludf.DUMMYFUNCTION("""COMPUTED_VALUE"""),0.4) -> 0.4 | BQ31: =IFERROR(__xludf.DUMMYFUNCTION("""COMPUTED_VALUE"""),"Death Wave - Quantity") -> Death Wave - Quantity | BR31: =IFERROR(__xludf.DUMMYFUNCTION("""COMPUTED_VALUE"""),"Legendary") -> Legendary | BS31: =IFERROR(__xludf.DUMMYFUNCTION("""COMPUTED_VALUE"""),"+1") -> +1 | BT31: =IFERROR(__xludf.DUMMYFUNCTION("""COMPUTED_VALUE"""),1.0) -> 1
A32: =IFERROR(__xludf.DUMMYFUNCTION("""COMPUTED_VALUE"""),"Orbs Speed") -> Orbs Speed | B32: =IFERROR(__xludf.DUMMYFUNCTION("""COMPUTED_VALUE"""),20.0) -> 20 | D32: =IFERROR(__xludf.DUMMYFUNCTION("""COMPUTED_VALUE"""),20.0) -> 20 | F32: =IFERROR(__xludf.DUMMYFUNCTION("""COMPUTED_VALUE"""),"Shockwave Frequency") -> Shockwave Frequency | G32: =IFERROR(__xludf.DUMMYFUNCTION("""COMPUTED_VALUE"""),40.0) -> 40 | H32: =IFERROR(__xludf.DUMMYFUNCTION("""COMPUTED_VALUE"""),40.0) -> 40 | I32: =IFERROR(__xludf.DUMMYFUNCTION("""COMPUTED_VALUE"""),40.0) -> 40 | J32: =IFERROR(__xludf.DUMMYFUNCTION("""COMPUTED_VALUE"""),40.0) -> 40 | Q32: =IFERROR(__xludf.DUMMYFUNCTION("""COMPUTED_VALUE"""),40.0) -> 40 | Z32: =IFERROR(__xludf.DUMMYFUNCTION("""COMPUTED_VALUE"""),TRUE) -> TRUE | AA32: =IFERROR(__xludf.DUMMYFUNCTION("""COMPUTED_VALUE"""),"UW Unlocked") -> UW Unlocked | AB32: =IFERROR(__xludf.DUMMYFUNCTION("""COMPUTED_VALUE"""),"Cooldown") -> Cooldown | AC32: =IFERROR(__xludf.DUMMYFUNCTION("""COMPUTED_VALUE"""),50.0) -> 50 | AD32: =IFERROR(__xludf.DUMMYFUNCTION("""COMPUTED_VALUE"""),"15 | 50s | Cost 262 ⧌ | Maxed") -> 15 | 50s | Cost 262 ⧌ | Maxed | AE32: =IFERROR(__xludf.DUMMYFUNCTION("""COMPUTED_VALUE"""),"Area of Effect") -> Area of Effect | AF32: =IFERROR(__xludf.DUMMYFUNCTION("""COMPUTED_VALUE"""),"Locked") -> Locked | AG32: =IFERROR(__xludf.DUMMYFUNCTION("""COMPUTED_VALUE"""),FALSE) -> FALSE | AM32: =IFERROR(__xludf.DUMMYFUNCTION("""COMPUTED_VALUE"""),"Cash") -> Cash | AN32: =IFERROR(__xludf.DUMMYFUNCTION("""COMPUTED_VALUE"""),0.06) -> 0.06 | AP32: =IFERROR(__xludf.DUMMYFUNCTION("""COMPUTED_VALUE"""),"Thorn Damage") -> Thorn Damage | AQ32: =IFERROR(__xludf.DUMMYFUNCTION("""COMPUTED_VALUE"""),0.0) -> 0 | BE32: =IFERROR(__xludf.DUMMYFUNCTION("""COMPUTED_VALUE"""),"") | BG32: =IFERROR(__xludf.DUMMYFUNCTION("""COMPUTED_VALUE"""),"Shockwave Size") -> Shockwave Size | BH32: =IFERROR(__xludf.DUMMYFUNCTION("""COMPUTED_VALUE"""),"Legendary") -> Legendary | BI32: =IFERROR(__xludf.DUMMYFUNCTION("""COMPUTED_VALUE"""),"+0.3") -> +0.3 | BJ32: =IFERROR(__xludf.DUMMYFUNCTION("""COMPUTED_VALUE"""),0.3) -> 0.3 | BL32: =IFERROR(__xludf.DUMMYFUNCTION("""COMPUTED_VALUE"""),"Enemy Attack Level Skip") -> Enemy Attack Level Skip | BM32: =IFERROR(__xludf.DUMMYFUNCTION("""COMPUTED_VALUE"""),"Legendary") -> Legendary | BN32: =IFERROR(__xludf.DUMMYFUNCTION("""COMPUTED_VALUE"""),"+4%") -> +4% | BO32: =IFERROR(__xludf.DUMMYFUNCTION("""COMPUTED_VALUE"""),0.04) -> 0.04 | BQ32: =IFERROR(__xludf.DUMMYFUNCTION("""COMPUTED_VALUE"""),"Golden Tower - Bonus") -> Golden Tower - Bonus | BR32: =IFERROR(__xludf.DUMMYFUNCTION("""COMPUTED_VALUE"""),"Legendary") -> Legendary | BS32: =IFERROR(__xludf.DUMMYFUNCTION("""COMPUTED_VALUE"""),"+2x") -> +2x | BT32: =IFERROR(__xludf.DUMMYFUNCTION("""COMPUTED_VALUE"""),2.0) -> 2
A33: =IFERROR(__xludf.DUMMYFUNCTION("""COMPUTED_VALUE"""),"Land Mine Damage") -> Land Mine Damage | B33: =IFERROR(__xludf.DUMMYFUNCTION("""COMPUTED_VALUE"""),0.0) -> 0 | D33: =IFERROR(__xludf.DUMMYFUNCTION("""COMPUTED_VALUE"""),20.0) -> 20 | E33: =IFERROR(__xludf.DUMMYFUNCTION("""COMPUTED_VALUE"""),TRUE) -> TRUE | F33: =IFERROR(__xludf.DUMMYFUNCTION("""COMPUTED_VALUE"""),"Land Mine Chance") -> Land Mine Chance | G33: =IFERROR(__xludf.DUMMYFUNCTION("""COMPUTED_VALUE"""),50.0) -> 50 | H33: =IFERROR(__xludf.DUMMYFUNCTION("""COMPUTED_VALUE"""),50.0) -> 50 | I33: =IFERROR(__xludf.DUMMYFUNCTION("""COMPUTED_VALUE"""),50.0) -> 50 | J33: =IFERROR(__xludf.DUMMYFUNCTION("""COMPUTED_VALUE"""),50.0) -> 50 | Q33: =IFERROR(__xludf.DUMMYFUNCTION("""COMPUTED_VALUE"""),50.0) -> 50 | Z33: =IFERROR(__xludf.DUMMYFUNCTION("""COMPUTED_VALUE"""),"UW+") -> UW+ | AB33: =IFERROR(__xludf.DUMMYFUNCTION("""COMPUTED_VALUE"""),"Consume") -> Consume | AC33: =IFERROR(__xludf.DUMMYFUNCTION("""COMPUTED_VALUE"""),"Locked") -> Locked | AD33: =IFERROR(__xludf.DUMMYFUNCTION("""COMPUTED_VALUE"""),"Lo | Locked") -> Lo | Locked | AM33: =IFERROR(__xludf.DUMMYFUNCTION("""COMPUTED_VALUE"""),"Coins") -> Coins | AN33: =IFERROR(__xludf.DUMMYFUNCTION("""COMPUTED_VALUE"""),0.48) -> 0.48 | AP33: =IFERROR(__xludf.DUMMYFUNCTION("""COMPUTED_VALUE"""),"Knockback Chance") -> Knockback Chance | AQ33: =IFERROR(__xludf.DUMMYFUNCTION("""COMPUTED_VALUE"""),0.0) -> 0 | BE33: =IFERROR(__xludf.DUMMYFUNCTION("""COMPUTED_VALUE"""),"") | BG33: =IFERROR(__xludf.DUMMYFUNCTION("""COMPUTED_VALUE"""),"Death Defy") -> Death Defy | BH33: =IFERROR(__xludf.DUMMYFUNCTION("""COMPUTED_VALUE"""),"Legendary") -> Legendary | BI33: =IFERROR(__xludf.DUMMYFUNCTION("""COMPUTED_VALUE"""),"+1.5%") -> +1.5% | BJ33: =IFERROR(__xludf.DUMMYFUNCTION("""COMPUTED_VALUE"""),0.015) -> 0.015 | BL33: =IFERROR(__xludf.DUMMYFUNCTION("""COMPUTED_VALUE"""),"Free Utility Upgrade") -> Free Utility Upgrade | BM33: =IFERROR(__xludf.DUMMYFUNCTION("""COMPUTED_VALUE"""),"Legendary") -> Legendary | BN33: =IFERROR(__xludf.DUMMYFUNCTION("""COMPUTED_VALUE"""),"+8%") -> +8% | BO33: =IFERROR(__xludf.DUMMYFUNCTION("""COMPUTED_VALUE"""),0.08) -> 0.08 | BQ33: =IFERROR(__xludf.DUMMYFUNCTION("""COMPUTED_VALUE"""),"Black Hole - Size") -> Black Hole - Size | BR33: =IFERROR(__xludf.DUMMYFUNCTION("""COMPUTED_VALUE"""),"Legendary") -> Legendary | BS33: =IFERROR(__xludf.DUMMYFUNCTION("""COMPUTED_VALUE"""),"+8.00m") -> +8.00m | BT33: =IFERROR(__xludf.DUMMYFUNCTION("""COMPUTED_VALUE"""),8.0) -> 8
A34: =IFERROR(__xludf.DUMMYFUNCTION("""COMPUTED_VALUE"""),"Land Mine Decay") -> Land Mine Decay | B34: =IFERROR(__xludf.DUMMYFUNCTION("""COMPUTED_VALUE"""),13.0) -> 13 | D34: =IFERROR(__xludf.DUMMYFUNCTION("""COMPUTED_VALUE"""),35.0) -> 35 | F34: =IFERROR(__xludf.DUMMYFUNCTION("""COMPUTED_VALUE"""),"Land Mine Damage") -> Land Mine Damage | G34: =IFERROR(__xludf.DUMMYFUNCTION("""COMPUTED_VALUE"""),160.0) -> 160 | H34: =IFERROR(__xludf.DUMMYFUNCTION("""COMPUTED_VALUE"""),200.0) -> 200 | I34: =IFERROR(__xludf.DUMMYFUNCTION("""COMPUTED_VALUE"""),160.0) -> 160 | J34: =IFERROR(__xludf.DUMMYFUNCTION("""COMPUTED_VALUE"""),200.0) -> 200 | Q34: =IFERROR(__xludf.DUMMYFUNCTION("""COMPUTED_VALUE"""),200.0) -> 200 | Z34: =IFERROR(__xludf.DUMMYFUNCTION("""COMPUTED_VALUE"""),"Spotlight") -> Spotlight | AB34: =IFERROR(__xludf.DUMMYFUNCTION("""COMPUTED_VALUE"""),"Multiplier") -> Multiplier | AC34: =IFERROR(__xludf.DUMMYFUNCTION("""COMPUTED_VALUE"""),20.599999999999998) -> 20.6 | AD34: =IFERROR(__xludf.DUMMYFUNCTION("""COMPUTED_VALUE"""),"09 | x20.6 | Cost 95 ⧌ | Next 112 ⧌") -> 09 | x20.6 | Cost 95 ⧌ | Next 112 ⧌ | AM34: =IFERROR(__xludf.DUMMYFUNCTION("""COMPUTED_VALUE"""),"Free Attack Upgrade") -> Free Attack Upgrade | AN34: =IFERROR(__xludf.DUMMYFUNCTION("""COMPUTED_VALUE"""),0.060000000000000005) -> 0.06 | AP34: =IFERROR(__xludf.DUMMYFUNCTION("""COMPUTED_VALUE"""),"Knockback Force") -> Knockback Force | AQ34: =IFERROR(__xludf.DUMMYFUNCTION("""COMPUTED_VALUE"""),0.0) -> 0 | BE34: =IFERROR(__xludf.DUMMYFUNCTION("""COMPUTED_VALUE"""),"") | BJ34: =IFERROR(__xludf.DUMMYFUNCTION("""COMPUTED_VALUE"""),"") | BO34: =IFERROR(__xludf.DUMMYFUNCTION("""COMPUTED_VALUE"""),"") | BQ34: =IFERROR(__xludf.DUMMYFUNCTION("""COMPUTED_VALUE"""),"Spotlight - Angle") -> Spotlight - Angle
A35: =IFERROR(__xludf.DUMMYFUNCTION("""COMPUTED_VALUE"""),"Shockwave Size") -> Shockwave Size | B35: =IFERROR(__xludf.DUMMYFUNCTION("""COMPUTED_VALUE"""),10.0) -> 10 | D35: =IFERROR(__xludf.DUMMYFUNCTION("""COMPUTED_VALUE"""),20.0) -> 20 | F35: =IFERROR(__xludf.DUMMYFUNCTION("""COMPUTED_VALUE"""),"Land Mine Radius") -> Land Mine Radius | G35: =IFERROR(__xludf.DUMMYFUNCTION("""COMPUTED_VALUE"""),50.0) -> 50 | H35: =IFERROR(__xludf.DUMMYFUNCTION("""COMPUTED_VALUE"""),50.0) -> 50 | I35: =IFERROR(__xludf.DUMMYFUNCTION("""COMPUTED_VALUE"""),50.0) -> 50 | J35: =IFERROR(__xludf.DUMMYFUNCTION("""COMPUTED_VALUE"""),50.0) -> 50 | Q35: =IFERROR(__xludf.DUMMYFUNCTION("""COMPUTED_VALUE"""),50.0) -> 50 | AB35: =IFERROR(__xludf.DUMMYFUNCTION("""COMPUTED_VALUE"""),"Angle") -> Angle | AC35: =IFERROR(__xludf.DUMMYFUNCTION("""COMPUTED_VALUE"""),39.0) -> 39 | AD35: =IFERROR(__xludf.DUMMYFUNCTION("""COMPUTED_VALUE"""),"09 | 39° | Cost 93 ⧌ | Next 104 ⧌") -> 09 | 39° | Cost 93 ⧌ | Next 104 ⧌ | AM35: =IFERROR(__xludf.DUMMYFUNCTION("""COMPUTED_VALUE"""),"Free Defense Upgrade") -> Free Defense Upgrade | AN35: =IFERROR(__xludf.DUMMYFUNCTION("""COMPUTED_VALUE"""),0.03) -> 0.03 | AP35: =IFERROR(__xludf.DUMMYFUNCTION("""COMPUTED_VALUE"""),"Orb Speed") -> Orb Speed | AQ35: =IFERROR(__xludf.DUMMYFUNCTION("""COMPUTED_VALUE"""),0.0) -> 0 | BE35: =IFERROR(__xludf.DUMMYFUNCTION("""COMPUTED_VALUE"""),"") | BJ35: =IFERROR(__xludf.DUMMYFUNCTION("""COMPUTED_VALUE"""),"") | BO35: =IFERROR(__xludf.DUMMYFUNCTION("""COMPUTED_VALUE"""),"") | BQ35: =IFERROR(__xludf.DUMMYFUNCTION("""COMPUTED_VALUE"""),"Death Wave - Quantity") -> Death Wave - Quantity
A36: =IFERROR(__xludf.DUMMYFUNCTION("""COMPUTED_VALUE"""),"Orb Boss Hit") -> Orb Boss Hit | B36: =IFERROR(__xludf.DUMMYFUNCTION("""COMPUTED_VALUE"""),10.0) -> 10 | D36: =IFERROR(__xludf.DUMMYFUNCTION("""COMPUTED_VALUE"""),10.0) -> 10 | E36: =IFERROR(__xludf.DUMMYFUNCTION("""COMPUTED_VALUE"""),TRUE) -> TRUE | F36: =IFERROR(__xludf.DUMMYFUNCTION("""COMPUTED_VALUE"""),"Death Defy") -> Death Defy | G36: =IFERROR(__xludf.DUMMYFUNCTION("""COMPUTED_VALUE"""),75.0) -> 75 | H36: =IFERROR(__xludf.DUMMYFUNCTION("""COMPUTED_VALUE"""),75.0) -> 75 | I36: =IFERROR(__xludf.DUMMYFUNCTION("""COMPUTED_VALUE"""),75.0) -> 75 | J36: =IFERROR(__xludf.DUMMYFUNCTION("""COMPUTED_VALUE"""),75.0) -> 75 | Q36: =IFERROR(__xludf.DUMMYFUNCTION("""COMPUTED_VALUE"""),75.0) -> 75 | Z36: =IFERROR(__xludf.DUMMYFUNCTION("""COMPUTED_VALUE"""),TRUE) -> TRUE | AA36: =IFERROR(__xludf.DUMMYFUNCTION("""COMPUTED_VALUE"""),"UW Unlocked") -> UW Unlocked | AB36: =IFERROR(__xludf.DUMMYFUNCTION("""COMPUTED_VALUE"""),"Quantity") -> Quantity | AC36: =IFERROR(__xludf.DUMMYFUNCTION("""COMPUTED_VALUE"""),3.0) -> 3 | AD36: =IFERROR(__xludf.DUMMYFUNCTION("""COMPUTED_VALUE"""),"02 | #3 | Cost 850 ⧌ | Next 2500 ⧌") -> 02 | #3 | Cost 850 ⧌ | Next 2500 ⧌ | AM36: =IFERROR(__xludf.DUMMYFUNCTION("""COMPUTED_VALUE"""),"Free Utility Upgrade") -> Free Utility Upgrade | AN36: =IFERROR(__xludf.DUMMYFUNCTION("""COMPUTED_VALUE"""),0.04) -> 0.04 | AP36: =IFERROR(__xludf.DUMMYFUNCTION("""COMPUTED_VALUE"""),"Orbs") -> Orbs | AQ36: =IFERROR(__xludf.DUMMYFUNCTION("""COMPUTED_VALUE"""),0.0) -> 0 | BE36: =IFERROR(__xludf.DUMMYFUNCTION("""COMPUTED_VALUE"""),"") | BJ36: =IFERROR(__xludf.DUMMYFUNCTION("""COMPUTED_VALUE"""),"") | BO36: =IFERROR(__xludf.DUMMYFUNCTION("""COMPUTED_VALUE"""),"") | BQ36: =IFERROR(__xludf.DUMMYFUNCTION("""COMPUTED_VALUE"""),"Death Wave - Cooldown") -> Death Wave - Cooldown
A37: =IFERROR(__xludf.DUMMYFUNCTION("""COMPUTED_VALUE"""),"Wall Health") -> Wall Health | B37: =IFERROR(__xludf.DUMMYFUNCTION("""COMPUTED_VALUE"""),50.0) -> 50 | D37: =IFERROR(__xludf.DUMMYFUNCTION("""COMPUTED_VALUE"""),50.0) -> 50 | E37: =IFERROR(__xludf.DUMMYFUNCTION("""COMPUTED_VALUE"""),TRUE) -> TRUE | F37: =IFERROR(__xludf.DUMMYFUNCTION("""COMPUTED_VALUE"""),"Wall Health") -> Wall Health | G37: =IFERROR(__xludf.DUMMYFUNCTION("""COMPUTED_VALUE"""),1340.0) -> 1340 | H37: =IFERROR(__xludf.DUMMYFUNCTION("""COMPUTED_VALUE"""),1800.0) -> 1800 | I37: =IFERROR(__xludf.DUMMYFUNCTION("""COMPUTED_VALUE"""),1340.0) -> 1340 | J37: =IFERROR(__xludf.DUMMYFUNCTION("""COMPUTED_VALUE"""),1800.0) -> 1800 | Q37: =IFERROR(__xludf.DUMMYFUNCTION("""COMPUTED_VALUE"""),1800.0) -> 1800 | Z37: =IFERROR(__xludf.DUMMYFUNCTION("""COMPUTED_VALUE"""),"UW+") -> UW+ | AB37: =IFERROR(__xludf.DUMMYFUNCTION("""COMPUTED_VALUE"""),"Light Range") -> Light Range | AC37: =IFERROR(__xludf.DUMMYFUNCTION("""COMPUTED_VALUE"""),"Locked") -> Locked | AD37: =IFERROR(__xludf.DUMMYFUNCTION("""COMPUTED_VALUE"""),"Lo | Locked") -> Lo | Locked | AM37: =IFERROR(__xludf.DUMMYFUNCTION("""COMPUTED_VALUE"""),"Recovery Amount") -> Recovery Amount | AN37: =IFERROR(__xludf.DUMMYFUNCTION("""COMPUTED_VALUE"""),0.11) -> 0.11 | AP37: =IFERROR(__xludf.DUMMYFUNCTION("""COMPUTED_VALUE"""),"Shockwave Frequency") -> Shockwave Frequency | AQ37: =IFERROR(__xludf.DUMMYFUNCTION("""COMPUTED_VALUE"""),0.0) -> 0 | BE37: =IFERROR(__xludf.DUMMYFUNCTION("""COMPUTED_VALUE"""),"") | BJ37: =IFERROR(__xludf.DUMMYFUNCTION("""COMPUTED_VALUE"""),"") | BO37: =IFERROR(__xludf.DUMMYFUNCTION("""COMPUTED_VALUE"""),"") | BQ37: =IFERROR(__xludf.DUMMYFUNCTION("""COMPUTED_VALUE"""),"Golden Tower - Bonus") -> Golden Tower - Bonus
A38: =IFERROR(__xludf.DUMMYFUNCTION("""COMPUTED_VALUE"""),"Wall Rebuild") -> Wall Rebuild | B38: =IFERROR(__xludf.DUMMYFUNCTION("""COMPUTED_VALUE"""),9.0) -> 9 | D38: =IFERROR(__xludf.DUMMYFUNCTION("""COMPUTED_VALUE"""),20.0) -> 20 | F38: =IFERROR(__xludf.DUMMYFUNCTION("""COMPUTED_VALUE"""),"Wall Rebuild") -> Wall Rebuild | G38: =IFERROR(__xludf.DUMMYFUNCTION("""COMPUTED_VALUE"""),250.0) -> 250 | H38: =IFERROR(__xludf.DUMMYFUNCTION("""COMPUTED_VALUE"""),300.0) -> 300 | I38: =IFERROR(__xludf.DUMMYFUNCTION("""COMPUTED_VALUE"""),250.0) -> 250 | J38: =IFERROR(__xludf.DUMMYFUNCTION("""COMPUTED_VALUE"""),300.0) -> 300 | Q38: =IFERROR(__xludf.DUMMYFUNCTION("""COMPUTED_VALUE"""),300.0) -> 300 | AM38: =IFERROR(__xludf.DUMMYFUNCTION("""COMPUTED_VALUE"""),"Enemy Attack Level Skip") -> Enemy Attack Level Skip | AN38: =IFERROR(__xludf.DUMMYFUNCTION("""COMPUTED_VALUE"""),0.02) -> 0.02 | AP38: =IFERROR(__xludf.DUMMYFUNCTION("""COMPUTED_VALUE"""),"Death Defy") -> Death Defy | AQ38: =IFERROR(__xludf.DUMMYFUNCTION("""COMPUTED_VALUE"""),0.0) -> 0 | BE38: =IFERROR(__xludf.DUMMYFUNCTION("""COMPUTED_VALUE"""),"") | BJ38: =IFERROR(__xludf.DUMMYFUNCTION("""COMPUTED_VALUE"""),"") | BO38: =IFERROR(__xludf.DUMMYFUNCTION("""COMPUTED_VALUE"""),"") | BQ38: =IFERROR(__xludf.DUMMYFUNCTION("""COMPUTED_VALUE"""),"Death Wave - Damage") -> Death Wave - Damage | BR38: =IFERROR(__xludf.DUMMYFUNCTION("""COMPUTED_VALUE"""),"Common") -> Common | BS38: =IFERROR(__xludf.DUMMYFUNCTION("""COMPUTED_VALUE"""),"+8x") -> +8x | BT38: =IFERROR(__xludf.DUMMYFUNCTION("""COMPUTED_VALUE"""),8.0) -> 8
A39: =IFERROR(__xludf.DUMMYFUNCTION("""COMPUTED_VALUE"""),"Wall Regen") -> Wall Regen | B39: =IFERROR(__xludf.DUMMYFUNCTION("""COMPUTED_VALUE"""),21.0) -> 21 | D39: =IFERROR(__xludf.DUMMYFUNCTION("""COMPUTED_VALUE"""),30.0) -> 30 | E39: =IFERROR(__xludf.DUMMYFUNCTION("""COMPUTED_VALUE"""),TRUE) -> TRUE | F39: =IFERROR(__xludf.DUMMYFUNCTION("""COMPUTED_VALUE"""),"Cash Bonus") -> Cash Bonus | G39: =IFERROR(__xludf.DUMMYFUNCTION("""COMPUTED_VALUE"""),149.0) -> 149 | H39: =IFERROR(__xludf.DUMMYFUNCTION("""COMPUTED_VALUE"""),149.0) -> 149 | I39: =IFERROR(__xludf.DUMMYFUNCTION("""COMPUTED_VALUE"""),149.0) -> 149 | J39: =IFERROR(__xludf.DUMMYFUNCTION("""COMPUTED_VALUE"""),149.0) -> 149 | Q39: =IFERROR(__xludf.DUMMYFUNCTION("""COMPUTED_VALUE"""),149.0) -> 149 | AM39: =IFERROR(__xludf.DUMMYFUNCTION("""COMPUTED_VALUE"""),"Enemy Health Level Skip") -> Enemy Health Level Skip | AN39: =IFERROR(__xludf.DUMMYFUNCTION("""COMPUTED_VALUE"""),0.02) -> 0.02 | AP39: =IFERROR(__xludf.DUMMYFUNCTION("""COMPUTED_VALUE"""),"Wall Rebuild") -> Wall Rebuild | AQ39: =IFERROR(__xludf.DUMMYFUNCTION("""COMPUTED_VALUE"""),0.0) -> 0
A40: =IFERROR(__xludf.DUMMYFUNCTION("""COMPUTED_VALUE"""),"Wall Thorns") -> Wall Thorns | B40: =IFERROR(__xludf.DUMMYFUNCTION("""COMPUTED_VALUE"""),15.0) -> 15 | D40: =IFERROR(__xludf.DUMMYFUNCTION("""COMPUTED_VALUE"""),20.0) -> 20 | F40: =IFERROR(__xludf.DUMMYFUNCTION("""COMPUTED_VALUE"""),"Cash / Wave") -> Cash / Wave | G40: =IFERROR(__xludf.DUMMYFUNCTION("""COMPUTED_VALUE"""),149.0) -> 149 | H40: =IFERROR(__xludf.DUMMYFUNCTION("""COMPUTED_VALUE"""),149.0) -> 149 | I40: =IFERROR(__xludf.DUMMYFUNCTION("""COMPUTED_VALUE"""),149.0) -> 149 | J40: =IFERROR(__xludf.DUMMYFUNCTION("""COMPUTED_VALUE"""),149.0) -> 149 | Q40: =IFERROR(__xludf.DUMMYFUNCTION("""COMPUTED_VALUE"""),149.0) -> 149 | AP40: =IFERROR(__xludf.DUMMYFUNCTION("""COMPUTED_VALUE"""),"Utility") -> Utility | BB40: =IFERROR(__xludf.DUMMYFUNCTION("""COMPUTED_VALUE"""),"Being Annihilator") -> Being Annihilator | BG40: =IFERROR(__xludf.DUMMYFUNCTION("""COMPUTED_VALUE"""),"Negative Mass Projector") -> Negative Mass Projector | BL40: =IFERROR(__xludf.DUMMYFUNCTION("""COMPUTED_VALUE"""),"Galaxy Compressor") -> Galaxy Compressor | BQ40: =IFERROR(__xludf.DUMMYFUNCTION("""COMPUTED_VALUE"""),"Dimension Core") -> Dimension Core
A41: =IFERROR(__xludf.DUMMYFUNCTION("""COMPUTED_VALUE"""),"Wall Invincibility") -> Wall Invincibility | B41: =IFERROR(__xludf.DUMMYFUNCTION("""COMPUTED_VALUE"""),0.0) -> 0 | D41: =IFERROR(__xludf.DUMMYFUNCTION("""COMPUTED_VALUE"""),10.0) -> 10 | E41: =IFERROR(__xludf.DUMMYFUNCTION("""COMPUTED_VALUE"""),TRUE) -> TRUE | F41: =IFERROR(__xludf.DUMMYFUNCTION("""COMPUTED_VALUE"""),"Coin / Kill Bonus") -> Coin / Kill Bonus | G41: =IFERROR(__xludf.DUMMYFUNCTION("""COMPUTED_VALUE"""),149.0) -> 149 | H41: =IFERROR(__xludf.DUMMYFUNCTION("""COMPUTED_VALUE"""),149.0) -> 149 | I41: =IFERROR(__xludf.DUMMYFUNCTION("""COMPUTED_VALUE"""),149.0) -> 149 | J41: =IFERROR(__xludf.DUMMYFUNCTION("""COMPUTED_VALUE"""),149.0) -> 149 | Q41: =IFERROR(__xludf.DUMMYFUNCTION("""COMPUTED_VALUE"""),149.0) -> 149 | AP41: =IFERROR(__xludf.DUMMYFUNCTION("""COMPUTED_VALUE"""),"Cash") -> Cash | AQ41: =IFERROR(__xludf.DUMMYFUNCTION("""COMPUTED_VALUE"""),0.0) -> 0 | BB41: =IFERROR(__xludf.DUMMYFUNCTION("""COMPUTED_VALUE"""),"Rarity") -> Rarity | BC41: =IFERROR(__xludf.DUMMYFUNCTION("""COMPUTED_VALUE"""),"Level") -> Level | BD41: =IFERROR(__xludf.DUMMYFUNCTION("""COMPUTED_VALUE"""),"Stat") -> Stat | BG41: =IFERROR(__xludf.DUMMYFUNCTION("""COMPUTED_VALUE"""),"Rarity") -> Rarity | BH41: =IFERROR(__xludf.DUMMYFUNCTION("""COMPUTED_VALUE"""),"Level") -> Level | BI41: =IFERROR(__xludf.DUMMYFUNCTION("""COMPUTED_VALUE"""),"Stat") -> Stat | BL41: =IFERROR(__xludf.DUMMYFUNCTION("""COMPUTED_VALUE"""),"Rarity") -> Rarity | BM41: =IFERROR(__xludf.DUMMYFUNCTION("""COMPUTED_VALUE"""),"Level") -> Level | BN41: =IFERROR(__xludf.DUMMYFUNCTION("""COMPUTED_VALUE"""),"Stat") -> Stat | BQ41: =IFERROR(__xludf.DUMMYFUNCTION("""COMPUTED_VALUE"""),"Rarity") -> Rarity | BR41: =IFERROR(__xludf.DUMMYFUNCTION("""COMPUTED_VALUE"""),"Level") -> Level | BS41: =IFERROR(__xludf.DUMMYFUNCTION("""COMPUTED_VALUE"""),"Stat") -> Stat
A42: =IFERROR(__xludf.DUMMYFUNCTION("""COMPUTED_VALUE"""),"Wall Fortification") -> Wall Fortification | B42: =IFERROR(__xludf.DUMMYFUNCTION("""COMPUTED_VALUE"""),47.0) -> 47 | D42: =IFERROR(__xludf.DUMMYFUNCTION("""COMPUTED_VALUE"""),60.0) -> 60 | F42: =IFERROR(__xludf.DUMMYFUNCTION("""COMPUTED_VALUE"""),"Coin / Wave") -> Coin / Wave | G42: =IFERROR(__xludf.DUMMYFUNCTION("""COMPUTED_VALUE"""),149.0) -> 149 | H42: =IFERROR(__xludf.DUMMYFUNCTION("""COMPUTED_VALUE"""),149.0) -> 149 | I42: =IFERROR(__xludf.DUMMYFUNCTION("""COMPUTED_VALUE"""),149.0) -> 149 | J42: =IFERROR(__xludf.DUMMYFUNCTION("""COMPUTED_VALUE"""),149.0) -> 149 | Q42: =IFERROR(__xludf.DUMMYFUNCTION("""COMPUTED_VALUE"""),149.0) -> 149 | AP42: =IFERROR(__xludf.DUMMYFUNCTION("""COMPUTED_VALUE"""),"Cash / Wave") -> Cash / Wave | AQ42: =IFERROR(__xludf.DUMMYFUNCTION("""COMPUTED_VALUE"""),0.0) -> 0 | BB42: =IFERROR(__xludf.DUMMYFUNCTION("""COMPUTED_VALUE"""),"Ancestral") -> Ancestral | BC42: =IFERROR(__xludf.DUMMYFUNCTION("""COMPUTED_VALUE"""),164.0) -> 164 | BD42: =IFERROR(__xludf.DUMMYFUNCTION("""COMPUTED_VALUE"""),9.04) -> 9.04 | BG42: =IFERROR(__xludf.DUMMYFUNCTION("""COMPUTED_VALUE"""),"Legendary") -> Legendary | BH42: =IFERROR(__xludf.DUMMYFUNCTION("""COMPUTED_VALUE"""),100.0) -> 100 | BI42: =IFERROR(__xludf.DUMMYFUNCTION("""COMPUTED_VALUE"""),2.27) -> 2.27 | BL42: =IFERROR(__xludf.DUMMYFUNCTION("""COMPUTED_VALUE"""),"Mythic+") -> Mythic+ | BM42: =IFERROR(__xludf.DUMMYFUNCTION("""COMPUTED_VALUE"""),160.0) -> 160 | BN42: =IFERROR(__xludf.DUMMYFUNCTION("""COMPUTED_VALUE"""),1.665) -> 1.665 | BQ42: =IFERROR(__xludf.DUMMYFUNCTION("""COMPUTED_VALUE"""),"Ancestral") -> Ancestral | BR42: =IFERROR(__xludf.DUMMYFUNCTION("""COMPUTED_VALUE"""),159.0) -> 159 | BS42: =IFERROR(__xludf.DUMMYFUNCTION("""COMPUTED_VALUE"""),10.9) -> 10.9
A43: =IFERROR(__xludf.DUMMYFUNCTION("""COMPUTED_VALUE"""),"Garlic Thorns") -> Garlic Thorns | B43: =IFERROR(__xludf.DUMMYFUNCTION("""COMPUTED_VALUE"""),10.0) -> 10 | D43: =IFERROR(__xludf.DUMMYFUNCTION("""COMPUTED_VALUE"""),10.0) -> 10 | E43: =IFERROR(__xludf.DUMMYFUNCTION("""COMPUTED_VALUE"""),TRUE) -> TRUE | F43: =IFERROR(__xludf.DUMMYFUNCTION("""COMPUTED_VALUE"""),"Free Attack Upgrade") -> Free Attack Upgrade | G43: =IFERROR(__xludf.DUMMYFUNCTION("""COMPUTED_VALUE"""),99.0) -> 99 | H43: =IFERROR(__xludf.DUMMYFUNCTION("""COMPUTED_VALUE"""),99.0) -> 99 | I43: =IFERROR(__xludf.DUMMYFUNCTION("""COMPUTED_VALUE"""),99.0) -> 99 | J43: =IFERROR(__xludf.DUMMYFUNCTION("""COMPUTED_VALUE"""),99.0) -> 99 | Q43: =IFERROR(__xludf.DUMMYFUNCTION("""COMPUTED_VALUE"""),99.0) -> 99 | AP43: =IFERROR(__xludf.DUMMYFUNCTION("""COMPUTED_VALUE"""),"Coins / Kill") -> Coins / Kill | AQ43: =IFERROR(__xludf.DUMMYFUNCTION("""COMPUTED_VALUE"""),0.0) -> 0
A44: =IFERROR(__xludf.DUMMYFUNCTION("""COMPUTED_VALUE"""),"Cash Bonus") -> Cash Bonus | B44: =IFERROR(__xludf.DUMMYFUNCTION("""COMPUTED_VALUE"""),33.0) -> 33 | D44: =IFERROR(__xludf.DUMMYFUNCTION("""COMPUTED_VALUE"""),99.0) -> 99 | F44: =IFERROR(__xludf.DUMMYFUNCTION("""COMPUTED_VALUE"""),"Free Defense Upgrade") -> Free Defense Upgrade | G44: =IFERROR(__xludf.DUMMYFUNCTION("""COMPUTED_VALUE"""),99.0) -> 99 | H44: =IFERROR(__xludf.DUMMYFUNCTION("""COMPUTED_VALUE"""),99.0) -> 99 | I44: =IFERROR(__xludf.DUMMYFUNCTION("""COMPUTED_VALUE"""),99.0) -> 99 | J44: =IFERROR(__xludf.DUMMYFUNCTION("""COMPUTED_VALUE"""),99.0) -> 99 | Q44: =IFERROR(__xludf.DUMMYFUNCTION("""COMPUTED_VALUE"""),99.0) -> 99 | AP44: =IFERROR(__xludf.DUMMYFUNCTION("""COMPUTED_VALUE"""),"Coins / Wave") -> Coins / Wave | AQ44: =IFERROR(__xludf.DUMMYFUNCTION("""COMPUTED_VALUE"""),0.0) -> 0 | BB44: =IFERROR(__xludf.DUMMYFUNCTION("""COMPUTED_VALUE"""),"Attack Speed") -> Attack Speed | BC44: =IFERROR(__xludf.DUMMYFUNCTION("""COMPUTED_VALUE"""),"Mythic") -> Mythic | BD44: =IFERROR(__xludf.DUMMYFUNCTION("""COMPUTED_VALUE"""),"+3") -> +3 | BE44: =IFERROR(__xludf.DUMMYFUNCTION("""COMPUTED_VALUE"""),3.0) -> 3 | BJ44: =IFERROR(__xludf.DUMMYFUNCTION("""COMPUTED_VALUE"""),"") | BL44: =IFERROR(__xludf.DUMMYFUNCTION("""COMPUTED_VALUE"""),"Package Chance") -> Package Chance | BM44: =IFERROR(__xludf.DUMMYFUNCTION("""COMPUTED_VALUE"""),"Legendary") -> Legendary | BN44: =IFERROR(__xludf.DUMMYFUNCTION("""COMPUTED_VALUE"""),"+8%") -> +8% | BO44: =IFERROR(__xludf.DUMMYFUNCTION("""COMPUTED_VALUE"""),0.08) -> 0.08 | BQ44: =IFERROR(__xludf.DUMMYFUNCTION("""COMPUTED_VALUE"""),"Chain Lightning - Chance") -> Chain Lightning - Chance | BR44: =IFERROR(__xludf.DUMMYFUNCTION("""COMPUTED_VALUE"""),"Mythic") -> Mythic | BS44: =IFERROR(__xludf.DUMMYFUNCTION("""COMPUTED_VALUE"""),"+12%") -> +12% | BT44: =IFERROR(__xludf.DUMMYFUNCTION("""COMPUTED_VALUE"""),0.12) -> 0.12
A45: =IFERROR(__xludf.DUMMYFUNCTION("""COMPUTED_VALUE"""),"Cash / Wave") -> Cash / Wave | B45: =IFERROR(__xludf.DUMMYFUNCTION("""COMPUTED_VALUE"""),8.0) -> 8 | D45: =IFERROR(__xludf.DUMMYFUNCTION("""COMPUTED_VALUE"""),99.0) -> 99 | F45: =IFERROR(__xludf.DUMMYFUNCTION("""COMPUTED_VALUE"""),"Free Utility Upgrade") -> Free Utility Upgrade | G45: =IFERROR(__xludf.DUMMYFUNCTION("""COMPUTED_VALUE"""),99.0) -> 99 | H45: =IFERROR(__xludf.DUMMYFUNCTION("""COMPUTED_VALUE"""),99.0) -> 99 | I45: =IFERROR(__xludf.DUMMYFUNCTION("""COMPUTED_VALUE"""),99.0) -> 99 | J45: =IFERROR(__xludf.DUMMYFUNCTION("""COMPUTED_VALUE"""),99.0) -> 99 | Q45: =IFERROR(__xludf.DUMMYFUNCTION("""COMPUTED_VALUE"""),99.0) -> 99 | AP45: =IFERROR(__xludf.DUMMYFUNCTION("""COMPUTED_VALUE"""),"Free Attack Upgrade") -> Free Attack Upgrade | AQ45: =IFERROR(__xludf.DUMMYFUNCTION("""COMPUTED_VALUE"""),0.0) -> 0 | BB45: =IFERROR(__xludf.DUMMYFUNCTION("""COMPUTED_VALUE"""),"Multishot Targets") -> Multishot Targets | BC45: =IFERROR(__xludf.DUMMYFUNCTION("""COMPUTED_VALUE"""),"Mythic") -> Mythic | BD45: =IFERROR(__xludf.DUMMYFUNCTION("""COMPUTED_VALUE"""),"+3") -> +3 | BE45: =IFERROR(__xludf.DUMMYFUNCTION("""COMPUTED_VALUE"""),3.0) -> 3 | BJ45: =IFERROR(__xludf.DUMMYFUNCTION("""COMPUTED_VALUE"""),"") | BL45: =IFERROR(__xludf.DUMMYFUNCTION("""COMPUTED_VALUE"""),"Enemy Attack Level Skip") -> Enemy Attack Level Skip | BM45: =IFERROR(__xludf.DUMMYFUNCTION("""COMPUTED_VALUE"""),"Legendary") -> Legendary | BN45: =IFERROR(__xludf.DUMMYFUNCTION("""COMPUTED_VALUE"""),"+4%") -> +4% | BO45: =IFERROR(__xludf.DUMMYFUNCTION("""COMPUTED_VALUE"""),0.04) -> 0.04 | BQ45: =IFERROR(__xludf.DUMMYFUNCTION("""COMPUTED_VALUE"""),"Spotlight - Angle") -> Spotlight - Angle | BR45: =IFERROR(__xludf.DUMMYFUNCTION("""COMPUTED_VALUE"""),"Mythic") -> Mythic | BS45: =IFERROR(__xludf.DUMMYFUNCTION("""COMPUTED_VALUE"""),"+11°") -> +11° | BT45: =IFERROR(__xludf.DUMMYFUNCTION("""COMPUTED_VALUE"""),11.0) -> 11
A46: =IFERROR(__xludf.DUMMYFUNCTION("""COMPUTED_VALUE"""),"Coins / Kill Bonus") -> Coins / Kill Bonus | B46: =IFERROR(__xludf.DUMMYFUNCTION("""COMPUTED_VALUE"""),87.0) -> 87 | D46: =IFERROR(__xludf.DUMMYFUNCTION("""COMPUTED_VALUE"""),99.0) -> 99 | E46: =IFERROR(__xludf.DUMMYFUNCTION("""COMPUTED_VALUE"""),TRUE) -> TRUE | F46: =IFERROR(__xludf.DUMMYFUNCTION("""COMPUTED_VALUE"""),"Interest / Wave") -> Interest / Wave | G46: =IFERROR(__xludf.DUMMYFUNCTION("""COMPUTED_VALUE"""),99.0) -> 99 | H46: =IFERROR(__xludf.DUMMYFUNCTION("""COMPUTED_VALUE"""),99.0) -> 99 | I46: =IFERROR(__xludf.DUMMYFUNCTION("""COMPUTED_VALUE"""),99.0) -> 99 | J46: =IFERROR(__xludf.DUMMYFUNCTION("""COMPUTED_VALUE"""),99.0) -> 99 | Q46: =IFERROR(__xludf.DUMMYFUNCTION("""COMPUTED_VALUE"""),99.0) -> 99 | AP46: =IFERROR(__xludf.DUMMYFUNCTION("""COMPUTED_VALUE"""),"Free Defense Upgrade") -> Free Defense Upgrade | AQ46: =IFERROR(__xludf.DUMMYFUNCTION("""COMPUTED_VALUE"""),0.0) -> 0 | BB46: =IFERROR(__xludf.DUMMYFUNCTION("""COMPUTED_VALUE"""),"Critical Factor") -> Critical Factor | BC46: =IFERROR(__xludf.DUMMYFUNCTION("""COMPUTED_VALUE"""),"Mythic") -> Mythic | BD46: =IFERROR(__xludf.DUMMYFUNCTION("""COMPUTED_VALUE"""),"+12x") -> +12x | BE46: =IFERROR(__xludf.DUMMYFUNCTION("""COMPUTED_VALUE"""),12.0) -> 12 | BJ46: =IFERROR(__xludf.DUMMYFUNCTION("""COMPUTED_VALUE"""),"") | BL46: =IFERROR(__xludf.DUMMYFUNCTION("""COMPUTED_VALUE"""),"Free Utility Upgrade") -> Free Utility Upgrade | BM46: =IFERROR(__xludf.DUMMYFUNCTION("""COMPUTED_VALUE"""),"Legendary") -> Legendary | BN46: =IFERROR(__xludf.DUMMYFUNCTION("""COMPUTED_VALUE"""),"+8%") -> +8% | BO46: =IFERROR(__xludf.DUMMYFUNCTION("""COMPUTED_VALUE"""),0.08) -> 0.08 | BQ46: =IFERROR(__xludf.DUMMYFUNCTION("""COMPUTED_VALUE"""),"Spotlight - Bonus") -> Spotlight - Bonus | BR46: =IFERROR(__xludf.DUMMYFUNCTION("""COMPUTED_VALUE"""),"Mythic") -> Mythic | BS46: =IFERROR(__xludf.DUMMYFUNCTION("""COMPUTED_VALUE"""),"+15x") -> +15x | BT46: =IFERROR(__xludf.DUMMYFUNCTION("""COMPUTED_VALUE"""),15.0) -> 15
A47: =IFERROR(__xludf.DUMMYFUNCTION("""COMPUTED_VALUE"""),"Coins / Wave") -> Coins / Wave | B47: =IFERROR(__xludf.DUMMYFUNCTION("""COMPUTED_VALUE"""),6.0) -> 6 | D47: =IFERROR(__xludf.DUMMYFUNCTION("""COMPUTED_VALUE"""),99.0) -> 99 | E47: =IFERROR(__xludf.DUMMYFUNCTION("""COMPUTED_VALUE"""),TRUE) -> TRUE | F47: =IFERROR(__xludf.DUMMYFUNCTION("""COMPUTED_VALUE"""),"Recovery Amount") -> Recovery Amount | G47: =IFERROR(__xludf.DUMMYFUNCTION("""COMPUTED_VALUE"""),300.0) -> 300 | H47: =IFERROR(__xludf.DUMMYFUNCTION("""COMPUTED_VALUE"""),300.0) -> 300 | I47: =IFERROR(__xludf.DUMMYFUNCTION("""COMPUTED_VALUE"""),300.0) -> 300 | J47: =IFERROR(__xludf.DUMMYFUNCTION("""COMPUTED_VALUE"""),300.0) -> 300 | Q47: =IFERROR(__xludf.DUMMYFUNCTION("""COMPUTED_VALUE"""),300.0) -> 300 | AP47: =IFERROR(__xludf.DUMMYFUNCTION("""COMPUTED_VALUE"""),"Free Utility Upgrade") -> Free Utility Upgrade | AQ47: =IFERROR(__xludf.DUMMYFUNCTION("""COMPUTED_VALUE"""),0.0) -> 0 | BB47: =IFERROR(__xludf.DUMMYFUNCTION("""COMPUTED_VALUE"""),"Bounce Shot Chance") -> Bounce Shot Chance | BC47: =IFERROR(__xludf.DUMMYFUNCTION("""COMPUTED_VALUE"""),"Mythic") -> Mythic | BD47: =IFERROR(__xludf.DUMMYFUNCTION("""COMPUTED_VALUE"""),"+9%") -> +9% | BE47: =IFERROR(__xludf.DUMMYFUNCTION("""COMPUTED_VALUE"""),0.09) -> 0.09 | BJ47: =IFERROR(__xludf.DUMMYFUNCTION("""COMPUTED_VALUE"""),"") | BO47: =IFERROR(__xludf.DUMMYFUNCTION("""COMPUTED_VALUE"""),"") | BQ47: =IFERROR(__xludf.DUMMYFUNCTION("""COMPUTED_VALUE"""),"Chain Lightning - Quantity") -> Chain Lightning - Quantity | BR47: =IFERROR(__xludf.DUMMYFUNCTION("""COMPUTED_VALUE"""),"Mythic") -> Mythic | BS47: =IFERROR(__xludf.DUMMYFUNCTION("""COMPUTED_VALUE"""),"+3") -> +3 | BT47: =IFERROR(__xludf.DUMMYFUNCTION("""COMPUTED_VALUE"""),3.0) -> 3
A48: =IFERROR(__xludf.DUMMYFUNCTION("""COMPUTED_VALUE"""),"Interest") -> Interest | B48: =IFERROR(__xludf.DUMMYFUNCTION("""COMPUTED_VALUE"""),11.0) -> 11 | D48: =IFERROR(__xludf.DUMMYFUNCTION("""COMPUTED_VALUE"""),99.0) -> 99 | F48: =IFERROR(__xludf.DUMMYFUNCTION("""COMPUTED_VALUE"""),"Max Amount") -> Max Amount | G48: =IFERROR(__xludf.DUMMYFUNCTION("""COMPUTED_VALUE"""),300.0) -> 300 | H48: =IFERROR(__xludf.DUMMYFUNCTION("""COMPUTED_VALUE"""),500.0) -> 500 | I48: =IFERROR(__xludf.DUMMYFUNCTION("""COMPUTED_VALUE"""),300.0) -> 300 | J48: =IFERROR(__xludf.DUMMYFUNCTION("""COMPUTED_VALUE"""),500.0) -> 500 | Q48: =IFERROR(__xludf.DUMMYFUNCTION("""COMPUTED_VALUE"""),500.0) -> 500 | AP48: =IFERROR(__xludf.DUMMYFUNCTION("""COMPUTED_VALUE"""),"Interest / Wave") -> Interest / Wave | AQ48: =IFERROR(__xludf.DUMMYFUNCTION("""COMPUTED_VALUE"""),0.0) -> 0 | BE48: =IFERROR(__xludf.DUMMYFUNCTION("""COMPUTED_VALUE"""),"") | BJ48: =IFERROR(__xludf.DUMMYFUNCTION("""COMPUTED_VALUE"""),"") | BO48: =IFERROR(__xludf.DUMMYFUNCTION("""COMPUTED_VALUE"""),"") | BQ48: =IFERROR(__xludf.DUMMYFUNCTION("""COMPUTED_VALUE"""),"Chain Lightning - Damage") -> Chain Lightning - Damage | BR48: =IFERROR(__xludf.DUMMYFUNCTION("""COMPUTED_VALUE"""),"Legendary") -> Legendary | BS48: =IFERROR(__xludf.DUMMYFUNCTION("""COMPUTED_VALUE"""),"+50x") -> +50x | BT48: =IFERROR(__xludf.DUMMYFUNCTION("""COMPUTED_VALUE"""),50.0) -> 50
A49: =IFERROR(__xludf.DUMMYFUNCTION("""COMPUTED_VALUE"""),"Max Interest") -> Max Interest | B49: =IFERROR(__xludf.DUMMYFUNCTION("""COMPUTED_VALUE"""),8.0) -> 8 | D49: =IFERROR(__xludf.DUMMYFUNCTION("""COMPUTED_VALUE"""),15.0) -> 15 | F49: =IFERROR(__xludf.DUMMYFUNCTION("""COMPUTED_VALUE"""),"Package Chance") -> Package Chance | G49: =IFERROR(__xludf.DUMMYFUNCTION("""COMPUTED_VALUE"""),60.0) -> 60 | H49: =IFERROR(__xludf.DUMMYFUNCTION("""COMPUTED_VALUE"""),60.0) -> 60 | I49: =IFERROR(__xludf.DUMMYFUNCTION("""COMPUTED_VALUE"""),60.0) -> 60 | J49: =IFERROR(__xludf.DUMMYFUNCTION("""COMPUTED_VALUE"""),60.0) -> 60 | Q49: =IFERROR(__xludf.DUMMYFUNCTION("""COMPUTED_VALUE"""),60.0) -> 60 | AP49: =IFERROR(__xludf.DUMMYFUNCTION("""COMPUTED_VALUE"""),"Recovery Amount") -> Recovery Amount | AQ49: =IFERROR(__xludf.DUMMYFUNCTION("""COMPUTED_VALUE"""),0.0) -> 0 | BE49: =IFERROR(__xludf.DUMMYFUNCTION("""COMPUTED_VALUE"""),"") | BJ49: =IFERROR(__xludf.DUMMYFUNCTION("""COMPUTED_VALUE"""),"") | BO49: =IFERROR(__xludf.DUMMYFUNCTION("""COMPUTED_VALUE"""),"") | BQ49: =IFERROR(__xludf.DUMMYFUNCTION("""COMPUTED_VALUE"""),"Chrono Field - Cooldown") -> Chrono Field - Cooldown
A50: =IFERROR(__xludf.DUMMYFUNCTION("""COMPUTED_VALUE"""),"Package After Boss") -> Package After Boss | B50: =IFERROR(__xludf.DUMMYFUNCTION("""COMPUTED_VALUE"""),1.0) -> 1 | D50: =IFERROR(__xludf.DUMMYFUNCTION("""COMPUTED_VALUE"""),1.0) -> 1 | E50: =IFERROR(__xludf.DUMMYFUNCTION("""COMPUTED_VALUE"""),TRUE) -> TRUE | F50: =IFERROR(__xludf.DUMMYFUNCTION("""COMPUTED_VALUE"""),"Enemy Attack Level Skip") -> Enemy Attack Level Skip | G50: =IFERROR(__xludf.DUMMYFUNCTION("""COMPUTED_VALUE"""),330.0) -> 330 | H50: =IFERROR(__xludf.DUMMYFUNCTION("""COMPUTED_VALUE"""),699.0) -> 699 | I50: =IFERROR(__xludf.DUMMYFUNCTION("""COMPUTED_VALUE"""),330.0) -> 330 | J50: =IFERROR(__xludf.DUMMYFUNCTION("""COMPUTED_VALUE"""),699.0) -> 699 | Q50: =IFERROR(__xludf.DUMMYFUNCTION("""COMPUTED_VALUE"""),699.0) -> 699 | AP50: =IFERROR(__xludf.DUMMYFUNCTION("""COMPUTED_VALUE"""),"Max Recovery") -> Max Recovery | AQ50: =IFERROR(__xludf.DUMMYFUNCTION("""COMPUTED_VALUE"""),0.0) -> 0 | BE50: =IFERROR(__xludf.DUMMYFUNCTION("""COMPUTED_VALUE"""),"") | BJ50: =IFERROR(__xludf.DUMMYFUNCTION("""COMPUTED_VALUE"""),"") | BO50: =IFERROR(__xludf.DUMMYFUNCTION("""COMPUTED_VALUE"""),"") | BQ50: =IFERROR(__xludf.DUMMYFUNCTION("""COMPUTED_VALUE"""),"Chrono Field - Speed Reduction") -> Chrono Field - Speed Reduction
A51: =IFERROR(__xludf.DUMMYFUNCTION("""COMPUTED_VALUE"""),"Recovery Package Amount") -> Recovery Package Amount | B51: =IFERROR(__xludf.DUMMYFUNCTION("""COMPUTED_VALUE"""),0.0) -> 0 | D51: =IFERROR(__xludf.DUMMYFUNCTION("""COMPUTED_VALUE"""),20.0) -> 20 | F51: =IFERROR(__xludf.DUMMYFUNCTION("""COMPUTED_VALUE"""),"Enemy Health Level Skip") -> Enemy Health Level Skip | G51: =IFERROR(__xludf.DUMMYFUNCTION("""COMPUTED_VALUE"""),320.0) -> 320 | H51: =IFERROR(__xludf.DUMMYFUNCTION("""COMPUTED_VALUE"""),699.0) -> 699 | I51: =IFERROR(__xludf.DUMMYFUNCTION("""COMPUTED_VALUE"""),320.0) -> 320 | J51: =IFERROR(__xludf.DUMMYFUNCTION("""COMPUTED_VALUE"""),699.0) -> 699 | Q51: =IFERROR(__xludf.DUMMYFUNCTION("""COMPUTED_VALUE"""),699.0) -> 699 | AP51: =IFERROR(__xludf.DUMMYFUNCTION("""COMPUTED_VALUE"""),"Enemy Attack Skip") -> Enemy Attack Skip | AQ51: =IFERROR(__xludf.DUMMYFUNCTION("""COMPUTED_VALUE"""),0.0) -> 0 | BE51: =IFERROR(__xludf.DUMMYFUNCTION("""COMPUTED_VALUE"""),"") | BJ51: =IFERROR(__xludf.DUMMYFUNCTION("""COMPUTED_VALUE"""),"") | BO51: =IFERROR(__xludf.DUMMYFUNCTION("""COMPUTED_VALUE"""),"") | BT51: =IFERROR(__xludf.DUMMYFUNCTION("""COMPUTED_VALUE"""),"")
A52: =IFERROR(__xludf.DUMMYFUNCTION("""COMPUTED_VALUE"""),"Recovery Package Max") -> Recovery Package Max | B52: =IFERROR(__xludf.DUMMYFUNCTION("""COMPUTED_VALUE"""),0.0) -> 0 | D52: =IFERROR(__xludf.DUMMYFUNCTION("""COMPUTED_VALUE"""),20.0) -> 20 | AP52: =IFERROR(__xludf.DUMMYFUNCTION("""COMPUTED_VALUE"""),"Enemy Health Skip") -> Enemy Health Skip | AQ52: =IFERROR(__xludf.DUMMYFUNCTION("""COMPUTED_VALUE"""),0.0) -> 0
A53: =IFERROR(__xludf.DUMMYFUNCTION("""COMPUTED_VALUE"""),"Recovery Package Chance") -> Recovery Package Chance | B53: =IFERROR(__xludf.DUMMYFUNCTION("""COMPUTED_VALUE"""),20.0) -> 20 | D53: =IFERROR(__xludf.DUMMYFUNCTION("""COMPUTED_VALUE"""),20.0) -> 20 | AP53: =IFERROR(__xludf.DUMMYFUNCTION("""COMPUTED_VALUE"""),"Unlocks") -> Unlocks | BB53: =IFERROR(__xludf.DUMMYFUNCTION("""COMPUTED_VALUE"""),"Death Penalty") -> Death Penalty | BG53: =IFERROR(__xludf.DUMMYFUNCTION("""COMPUTED_VALUE"""),"Space Displacer") -> Space Displacer | BL53: =IFERROR(__xludf.DUMMYFUNCTION("""COMPUTED_VALUE"""),"Singularity Harness") -> Singularity Harness | BQ53: =IFERROR(__xludf.DUMMYFUNCTION("""COMPUTED_VALUE"""),"Harmony Conductor") -> Harmony Conductor
A54: =IFERROR(__xludf.DUMMYFUNCTION("""COMPUTED_VALUE"""),"Enemy Attack Level Skip") -> Enemy Attack Level Skip | B54: =IFERROR(__xludf.DUMMYFUNCTION("""COMPUTED_VALUE"""),20.0) -> 20 | D54: =IFERROR(__xludf.DUMMYFUNCTION("""COMPUTED_VALUE"""),20.0) -> 20 | AP54: =IFERROR(__xludf.DUMMYFUNCTION("""COMPUTED_VALUE"""),"Demon Mode Automation") -> Demon Mode Automation | AQ54: =IFERROR(__xludf.DUMMYFUNCTION("""COMPUTED_VALUE"""),FALSE) -> FALSE | BB54: =IFERROR(__xludf.DUMMYFUNCTION("""COMPUTED_VALUE"""),"Rarity") -> Rarity | BC54: =IFERROR(__xludf.DUMMYFUNCTION("""COMPUTED_VALUE"""),"Level") -> Level | BD54: =IFERROR(__xludf.DUMMYFUNCTION("""COMPUTED_VALUE"""),"Stat") -> Stat | BG54: =IFERROR(__xludf.DUMMYFUNCTION("""COMPUTED_VALUE"""),"Rarity") -> Rarity | BH54: =IFERROR(__xludf.DUMMYFUNCTION("""COMPUTED_VALUE"""),"Level") -> Level | BI54: =IFERROR(__xludf.DUMMYFUNCTION("""COMPUTED_VALUE"""),"Stat") -> Stat | BL54: =IFERROR(__xludf.DUMMYFUNCTION("""COMPUTED_VALUE"""),"Rarity") -> Rarity | BM54: =IFERROR(__xludf.DUMMYFUNCTION("""COMPUTED_VALUE"""),"Level") -> Level | BN54: =IFERROR(__xludf.DUMMYFUNCTION("""COMPUTED_VALUE"""),"Stat") -> Stat | BQ54: =IFERROR(__xludf.DUMMYFUNCTION("""COMPUTED_VALUE"""),"Rarity") -> Rarity | BR54: =IFERROR(__xludf.DUMMYFUNCTION("""COMPUTED_VALUE"""),"Level") -> Level | BS54: =IFERROR(__xludf.DUMMYFUNCTION("""COMPUTED_VALUE"""),"Stat") -> Stat
A55: =IFERROR(__xludf.DUMMYFUNCTION("""COMPUTED_VALUE"""),"Enemy Health Level Skip") -> Enemy Health Level Skip | B55: =IFERROR(__xludf.DUMMYFUNCTION("""COMPUTED_VALUE"""),20.0) -> 20 | D55: =IFERROR(__xludf.DUMMYFUNCTION("""COMPUTED_VALUE"""),20.0) -> 20 | AP55: =IFERROR(__xludf.DUMMYFUNCTION("""COMPUTED_VALUE"""),"Smart Demon Mode Automation") -> Smart Demon Mode Automation | AQ55: =IFERROR(__xludf.DUMMYFUNCTION("""COMPUTED_VALUE"""),FALSE) -> FALSE | BB55: =IFERROR(__xludf.DUMMYFUNCTION("""COMPUTED_VALUE"""),"Mythic+") -> Mythic+ | BC55: =IFERROR(__xludf.DUMMYFUNCTION("""COMPUTED_VALUE"""),160.0) -> 160 | BD55: =IFERROR(__xludf.DUMMYFUNCTION("""COMPUTED_VALUE"""),8.19) -> 8.19 | BG55: =IFERROR(__xludf.DUMMYFUNCTION("""COMPUTED_VALUE"""),"Ancestral 2*") -> Ancestral 2* | BH55: =IFERROR(__xludf.DUMMYFUNCTION("""COMPUTED_VALUE"""),163.0) -> 163 | BI55: =IFERROR(__xludf.DUMMYFUNCTION("""COMPUTED_VALUE"""),9.467) -> 9.467 | BL55: =IFERROR(__xludf.DUMMYFUNCTION("""COMPUTED_VALUE"""),"Ancestral") -> Ancestral | BM55: =IFERROR(__xludf.DUMMYFUNCTION("""COMPUTED_VALUE"""),161.0) -> 161 | BN55: =IFERROR(__xludf.DUMMYFUNCTION("""COMPUTED_VALUE"""),1.68) -> 1.68 | BQ55: =IFERROR(__xludf.DUMMYFUNCTION("""COMPUTED_VALUE"""),"Ancestral 5*") -> Ancestral 5* | BR55: =IFERROR(__xludf.DUMMYFUNCTION("""COMPUTED_VALUE"""),159.0) -> 159 | BS55: =IFERROR(__xludf.DUMMYFUNCTION("""COMPUTED_VALUE"""),12.88) -> 12.88
A56: =IFERROR(__xludf.DUMMYFUNCTION("""COMPUTED_VALUE"""),"Missile Despawn Time") -> Missile Despawn Time | B56: =IFERROR(__xludf.DUMMYFUNCTION("""COMPUTED_VALUE"""),0.0) -> 0 | D56: =IFERROR(__xludf.DUMMYFUNCTION("""COMPUTED_VALUE"""),20.0) -> 20 | AP56: =IFERROR(__xludf.DUMMYFUNCTION("""COMPUTED_VALUE"""),"Free Mission Reroll") -> Free Mission Reroll | AQ56: =IFERROR(__xludf.DUMMYFUNCTION("""COMPUTED_VALUE"""),FALSE) -> FALSE
A57: =IFERROR(__xludf.DUMMYFUNCTION("""COMPUTED_VALUE"""),"Missiles Explosion") -> Missiles Explosion | B57: =IFERROR(__xludf.DUMMYFUNCTION("""COMPUTED_VALUE"""),0.0) -> 0 | D57: =IFERROR(__xludf.DUMMYFUNCTION("""COMPUTED_VALUE"""),1.0) -> 1 | AP57: =IFERROR(__xludf.DUMMYFUNCTION("""COMPUTED_VALUE"""),"Nuke Automation") -> Nuke Automation | AQ57: =IFERROR(__xludf.DUMMYFUNCTION("""COMPUTED_VALUE"""),FALSE) -> FALSE | BB57: =IFERROR(__xludf.DUMMYFUNCTION("""COMPUTED_VALUE"""),"MultiShot Chance") -> MultiShot Chance | BC57: =IFERROR(__xludf.DUMMYFUNCTION("""COMPUTED_VALUE"""),"Mythic") -> Mythic | BD57: =IFERROR(__xludf.DUMMYFUNCTION("""COMPUTED_VALUE"""),"+10%") -> +10% | BE57: =IFERROR(__xludf.DUMMYFUNCTION("""COMPUTED_VALUE"""),0.1) -> 0.1 | BJ57: =IFERROR(__xludf.DUMMYFUNCTION("""COMPUTED_VALUE"""),"") | BL57: =IFERROR(__xludf.DUMMYFUNCTION("""COMPUTED_VALUE"""),"Free Utility Upgrade") -> Free Utility Upgrade | BM57: =IFERROR(__xludf.DUMMYFUNCTION("""COMPUTED_VALUE"""),"Mythic") -> Mythic | BN57: =IFERROR(__xludf.DUMMYFUNCTION("""COMPUTED_VALUE"""),"+10%") -> +10% | BO57: =IFERROR(__xludf.DUMMYFUNCTION("""COMPUTED_VALUE"""),0.1) -> 0.1 | BT57: =IFERROR(__xludf.DUMMYFUNCTION("""COMPUTED_VALUE"""),"")
A58: =IFERROR(__xludf.DUMMYFUNCTION("""COMPUTED_VALUE"""),"Missile Radius") -> Missile Radius | B58: =IFERROR(__xludf.DUMMYFUNCTION("""COMPUTED_VALUE"""),0.0) -> 0 | D58: =IFERROR(__xludf.DUMMYFUNCTION("""COMPUTED_VALUE"""),20.0) -> 20 | AP58: =IFERROR(__xludf.DUMMYFUNCTION("""COMPUTED_VALUE"""),"Smart Nuke Automation") -> Smart Nuke Automation | AQ58: =IFERROR(__xludf.DUMMYFUNCTION("""COMPUTED_VALUE"""),FALSE) -> FALSE | BB58: =IFERROR(__xludf.DUMMYFUNCTION("""COMPUTED_VALUE"""),"Bounce Shot Chance") -> Bounce Shot Chance | BC58: =IFERROR(__xludf.DUMMYFUNCTION("""COMPUTED_VALUE"""),"Mythic") -> Mythic | BD58: =IFERROR(__xludf.DUMMYFUNCTION("""COMPUTED_VALUE"""),"+9%") -> +9% | BE58: =IFERROR(__xludf.DUMMYFUNCTION("""COMPUTED_VALUE"""),0.09) -> 0.09 | BJ58: =IFERROR(__xludf.DUMMYFUNCTION("""COMPUTED_VALUE"""),"") | BL58: =IFERROR(__xludf.DUMMYFUNCTION("""COMPUTED_VALUE"""),"Coins / Kill Bonus") -> Coins / Kill Bonus | BM58: =IFERROR(__xludf.DUMMYFUNCTION("""COMPUTED_VALUE"""),"Mythic") -> Mythic | BN58: =IFERROR(__xludf.DUMMYFUNCTION("""COMPUTED_VALUE"""),"+0.5x") -> +0.5x | BO58: =IFERROR(__xludf.DUMMYFUNCTION("""COMPUTED_VALUE"""),0.5) -> 0.5 | BT58: =IFERROR(__xludf.DUMMYFUNCTION("""COMPUTED_VALUE"""),"")
A59: =IFERROR(__xludf.DUMMYFUNCTION("""COMPUTED_VALUE"""),"Chrono Field Duration") -> Chrono Field Duration | B59: =IFERROR(__xludf.DUMMYFUNCTION("""COMPUTED_VALUE"""),30.0) -> 30 | D59: =IFERROR(__xludf.DUMMYFUNCTION("""COMPUTED_VALUE"""),30.0) -> 30 | AP59: =IFERROR(__xludf.DUMMYFUNCTION("""COMPUTED_VALUE"""),"Workshop Presets") -> Workshop Presets | AQ59: =IFERROR(__xludf.DUMMYFUNCTION("""COMPUTED_VALUE"""),FALSE) -> FALSE | BB59: =IFERROR(__xludf.DUMMYFUNCTION("""COMPUTED_VALUE"""),"Bounce Shot Targets") -> Bounce Shot Targets | BC59: =IFERROR(__xludf.DUMMYFUNCTION("""COMPUTED_VALUE"""),"Mythic") -> Mythic | BD59: =IFERROR(__xludf.DUMMYFUNCTION("""COMPUTED_VALUE"""),"+3") -> +3 | BE59: =IFERROR(__xludf.DUMMYFUNCTION("""COMPUTED_VALUE"""),3.0) -> 3 | BJ59: =IFERROR(__xludf.DUMMYFUNCTION("""COMPUTED_VALUE"""),"") | BL59: =IFERROR(__xludf.DUMMYFUNCTION("""COMPUTED_VALUE"""),"Enemy Health Level Skip") -> Enemy Health Level Skip | BM59: =IFERROR(__xludf.DUMMYFUNCTION("""COMPUTED_VALUE"""),"Mythic") -> Mythic | BN59: =IFERROR(__xludf.DUMMYFUNCTION("""COMPUTED_VALUE"""),"+6%") -> +6% | BO59: =IFERROR(__xludf.DUMMYFUNCTION("""COMPUTED_VALUE"""),0.06) -> 0.06 | BT59: =IFERROR(__xludf.DUMMYFUNCTION("""COMPUTED_VALUE"""),"")
A60: =IFERROR(__xludf.DUMMYFUNCTION("""COMPUTED_VALUE"""),"Chrono Field Damage Reduction") -> Chrono Field Damage Reduction | B60: =IFERROR(__xludf.DUMMYFUNCTION("""COMPUTED_VALUE"""),1.0) -> 1 | D60: =IFERROR(__xludf.DUMMYFUNCTION("""COMPUTED_VALUE"""),1.0) -> 1 | AP60: =IFERROR(__xludf.DUMMYFUNCTION("""COMPUTED_VALUE"""),"Missile Barrage Automation") -> Missile Barrage Automation | AQ60: =IFERROR(__xludf.DUMMYFUNCTION("""COMPUTED_VALUE"""),FALSE) -> FALSE | BB60: =IFERROR(__xludf.DUMMYFUNCTION("""COMPUTED_VALUE"""),"Multishot Targets") -> Multishot Targets | BC60: =IFERROR(__xludf.DUMMYFUNCTION("""COMPUTED_VALUE"""),"Mythic") -> Mythic | BD60: =IFERROR(__xludf.DUMMYFUNCTION("""COMPUTED_VALUE"""),"+3") -> +3 | BE60: =IFERROR(__xludf.DUMMYFUNCTION("""COMPUTED_VALUE"""),3.0) -> 3 | BJ60: =IFERROR(__xludf.DUMMYFUNCTION("""COMPUTED_VALUE"""),"") | BL60: =IFERROR(__xludf.DUMMYFUNCTION("""COMPUTED_VALUE"""),"Enemy Attack Level Skip") -> Enemy Attack Level Skip | BM60: =IFERROR(__xludf.DUMMYFUNCTION("""COMPUTED_VALUE"""),"Ancestral") -> Ancestral | BN60: =IFERROR(__xludf.DUMMYFUNCTION("""COMPUTED_VALUE"""),"+8%") -> +8% | BO60: =IFERROR(__xludf.DUMMYFUNCTION("""COMPUTED_VALUE"""),0.08) -> 0.08 | BT60: =IFERROR(__xludf.DUMMYFUNCTION("""COMPUTED_VALUE"""),"")
A61: =IFERROR(__xludf.DUMMYFUNCTION("""COMPUTED_VALUE"""),"Chrono Field Reduction %") -> Chrono Field Reduction % | B61: =IFERROR(__xludf.DUMMYFUNCTION("""COMPUTED_VALUE"""),20.0) -> 20 | D61: =IFERROR(__xludf.DUMMYFUNCTION("""COMPUTED_VALUE"""),30.0) -> 30 | AP61: =IFERROR(__xludf.DUMMYFUNCTION("""COMPUTED_VALUE"""),"Smart Missile Barrage Automation") -> Smart Missile Barrage Automation | AQ61: =IFERROR(__xludf.DUMMYFUNCTION("""COMPUTED_VALUE"""),FALSE) -> FALSE | BE61: =IFERROR(__xludf.DUMMYFUNCTION("""COMPUTED_VALUE"""),"") | BJ61: =IFERROR(__xludf.DUMMYFUNCTION("""COMPUTED_VALUE"""),"") | BL61: =IFERROR(__xludf.DUMMYFUNCTION("""COMPUTED_VALUE"""),"Package Chance") -> Package Chance | BM61: =IFERROR(__xludf.DUMMYFUNCTION("""COMPUTED_VALUE"""),"Mythic") -> Mythic | BN61: =IFERROR(__xludf.DUMMYFUNCTION("""COMPUTED_VALUE"""),"+11%") -> +11% | BO61: =IFERROR(__xludf.DUMMYFUNCTION("""COMPUTED_VALUE"""),0.11) -> 0.11 | BT61: =IFERROR(__xludf.DUMMYFUNCTION("""COMPUTED_VALUE"""),"")
A62: =IFERROR(__xludf.DUMMYFUNCTION("""COMPUTED_VALUE"""),"Swamp Radius") -> Swamp Radius | B62: =IFERROR(__xludf.DUMMYFUNCTION("""COMPUTED_VALUE"""),0.0) -> 0 | D62: =IFERROR(__xludf.DUMMYFUNCTION("""COMPUTED_VALUE"""),30.0) -> 30 | AP62: =IFERROR(__xludf.DUMMYFUNCTION("""COMPUTED_VALUE"""),"Daily Mission - Set Shard Type") -> Daily Mission - Set Shard Type | AQ62: =IFERROR(__xludf.DUMMYFUNCTION("""COMPUTED_VALUE"""),FALSE) -> FALSE | BE62: =IFERROR(__xludf.DUMMYFUNCTION("""COMPUTED_VALUE"""),"") | BJ62: =IFERROR(__xludf.DUMMYFUNCTION("""COMPUTED_VALUE"""),"") | BO62: =IFERROR(__xludf.DUMMYFUNCTION("""COMPUTED_VALUE"""),"") | BT62: =IFERROR(__xludf.DUMMYFUNCTION("""COMPUTED_VALUE"""),"")
A63: =IFERROR(__xludf.DUMMYFUNCTION("""COMPUTED_VALUE"""),"Swamp Stun") -> Swamp Stun | B63: =IFERROR(__xludf.DUMMYFUNCTION("""COMPUTED_VALUE"""),0.0) -> 0 | D63: =IFERROR(__xludf.DUMMYFUNCTION("""COMPUTED_VALUE"""),1.0) -> 1 | AP63: =IFERROR(__xludf.DUMMYFUNCTION("""COMPUTED_VALUE"""),"Auto Shatter Rare Modules") -> Auto Shatter Rare Modules | AQ63: =IFERROR(__xludf.DUMMYFUNCTION("""COMPUTED_VALUE"""),FALSE) -> FALSE | BE63: =IFERROR(__xludf.DUMMYFUNCTION("""COMPUTED_VALUE"""),"") | BJ63: =IFERROR(__xludf.DUMMYFUNCTION("""COMPUTED_VALUE"""),"") | BO63: =IFERROR(__xludf.DUMMYFUNCTION("""COMPUTED_VALUE"""),"") | BT63: =IFERROR(__xludf.DUMMYFUNCTION("""COMPUTED_VALUE"""),"")
A64: =IFERROR(__xludf.DUMMYFUNCTION("""COMPUTED_VALUE"""),"Swamp Stun Chance") -> Swamp Stun Chance | B64: =IFERROR(__xludf.DUMMYFUNCTION("""COMPUTED_VALUE"""),0.0) -> 0 | D64: =IFERROR(__xludf.DUMMYFUNCTION("""COMPUTED_VALUE"""),30.0) -> 30 | AP64: =IFERROR(__xludf.DUMMYFUNCTION("""COMPUTED_VALUE"""),"Auto Restart Run") -> Auto Restart Run | AQ64: =IFERROR(__xludf.DUMMYFUNCTION("""COMPUTED_VALUE"""),FALSE) -> FALSE | BE64: =IFERROR(__xludf.DUMMYFUNCTION("""COMPUTED_VALUE"""),"") | BJ64: =IFERROR(__xludf.DUMMYFUNCTION("""COMPUTED_VALUE"""),"") | BO64: =IFERROR(__xludf.DUMMYFUNCTION("""COMPUTED_VALUE"""),"") | BT64: =IFERROR(__xludf.DUMMYFUNCTION("""COMPUTED_VALUE"""),"")
A65: =IFERROR(__xludf.DUMMYFUNCTION("""COMPUTED_VALUE"""),"Swamp Stun Time") -> Swamp Stun Time | B65: =IFERROR(__xludf.DUMMYFUNCTION("""COMPUTED_VALUE"""),0.0) -> 0 | D65: =IFERROR(__xludf.DUMMYFUNCTION("""COMPUTED_VALUE"""),30.0) -> 30 | AP65: =IFERROR(__xludf.DUMMYFUNCTION("""COMPUTED_VALUE"""),"Auto Charge Berzerker") -> Auto Charge Berzerker | AQ65: =IFERROR(__xludf.DUMMYFUNCTION("""COMPUTED_VALUE"""),FALSE) -> FALSE
A66: =IFERROR(__xludf.DUMMYFUNCTION("""COMPUTED_VALUE"""),"Golden Tower Bonus") -> Golden Tower Bonus | B66: =IFERROR(__xludf.DUMMYFUNCTION("""COMPUTED_VALUE"""),22.0) -> 22 | D66: =IFERROR(__xludf.DUMMYFUNCTION("""COMPUTED_VALUE"""),25.0) -> 25 | AP66: =IFERROR(__xludf.DUMMYFUNCTION("""COMPUTED_VALUE"""),"Damage Cap Slider") -> Damage Cap Slider | AQ66: =IFERROR(__xludf.DUMMYFUNCTION("""COMPUTED_VALUE"""),FALSE) -> FALSE | BB66: =IFERROR(__xludf.DUMMYFUNCTION("""COMPUTED_VALUE"""),"Havoc Bringer") -> Havoc Bringer | BG66: =IFERROR(__xludf.DUMMYFUNCTION("""COMPUTED_VALUE"""),"Wormhole Redirector") -> Wormhole Redirector | BL66: =IFERROR(__xludf.DUMMYFUNCTION("""COMPUTED_VALUE"""),"Pulsar Harvester") -> Pulsar Harvester | BQ66: =IFERROR(__xludf.DUMMYFUNCTION("""COMPUTED_VALUE"""),"Om Chip") -> Om Chip
A67: =IFERROR(__xludf.DUMMYFUNCTION("""COMPUTED_VALUE"""),"Golden Tower Duration") -> Golden Tower Duration | B67: =IFERROR(__xludf.DUMMYFUNCTION("""COMPUTED_VALUE"""),19.0) -> 19 | D67: =IFERROR(__xludf.DUMMYFUNCTION("""COMPUTED_VALUE"""),20.0) -> 20 | AP67: =IFERROR(__xludf.DUMMYFUNCTION("""COMPUTED_VALUE"""),"Bot Presets") -> Bot Presets | AQ67: =IFERROR(__xludf.DUMMYFUNCTION("""COMPUTED_VALUE"""),FALSE) -> FALSE | BB67: =IFERROR(__xludf.DUMMYFUNCTION("""COMPUTED_VALUE"""),"Rarity") -> Rarity | BC67: =IFERROR(__xludf.DUMMYFUNCTION("""COMPUTED_VALUE"""),"Level") -> Level | BD67: =IFERROR(__xludf.DUMMYFUNCTION("""COMPUTED_VALUE"""),"Stat") -> Stat | BG67: =IFERROR(__xludf.DUMMYFUNCTION("""COMPUTED_VALUE"""),"Rarity") -> Rarity | BH67: =IFERROR(__xludf.DUMMYFUNCTION("""COMPUTED_VALUE"""),"Level") -> Level | BI67: =IFERROR(__xludf.DUMMYFUNCTION("""COMPUTED_VALUE"""),"Stat") -> Stat | BL67: =IFERROR(__xludf.DUMMYFUNCTION("""COMPUTED_VALUE"""),"Rarity") -> Rarity | BM67: =IFERROR(__xludf.DUMMYFUNCTION("""COMPUTED_VALUE"""),"Level") -> Level | BN67: =IFERROR(__xludf.DUMMYFUNCTION("""COMPUTED_VALUE"""),"Stat") -> Stat | BQ67: =IFERROR(__xludf.DUMMYFUNCTION("""COMPUTED_VALUE"""),"Rarity") -> Rarity | BR67: =IFERROR(__xludf.DUMMYFUNCTION("""COMPUTED_VALUE"""),"Level") -> Level | BS67: =IFERROR(__xludf.DUMMYFUNCTION("""COMPUTED_VALUE"""),"Stat") -> Stat
A68: =IFERROR(__xludf.DUMMYFUNCTION("""COMPUTED_VALUE"""),"Chain Lightning Shock") -> Chain Lightning Shock | B68: =IFERROR(__xludf.DUMMYFUNCTION("""COMPUTED_VALUE"""),1.0) -> 1 | D68: =IFERROR(__xludf.DUMMYFUNCTION("""COMPUTED_VALUE"""),1.0) -> 1 | AP68: =IFERROR(__xludf.DUMMYFUNCTION("""COMPUTED_VALUE"""),"Workshop Orb Adjuster") -> Workshop Orb Adjuster | AQ68: =IFERROR(__xludf.DUMMYFUNCTION("""COMPUTED_VALUE"""),FALSE) -> FALSE | BB68: =IFERROR(__xludf.DUMMYFUNCTION("""COMPUTED_VALUE"""),"Ancestral") -> Ancestral | BC68: =IFERROR(__xludf.DUMMYFUNCTION("""COMPUTED_VALUE"""),164.0) -> 164 | BD68: =IFERROR(__xludf.DUMMYFUNCTION("""COMPUTED_VALUE"""),9.04) -> 9.04 | BG68: =IFERROR(__xludf.DUMMYFUNCTION("""COMPUTED_VALUE"""),"Mythic+") -> Mythic+ | BH68: =IFERROR(__xludf.DUMMYFUNCTION("""COMPUTED_VALUE"""),160.0) -> 160 | BI68: =IFERROR(__xludf.DUMMYFUNCTION("""COMPUTED_VALUE"""),8.19) -> 8.19 | BL68: =IFERROR(__xludf.DUMMYFUNCTION("""COMPUTED_VALUE"""),"Ancestral 1*") -> Ancestral 1* | BM68: =IFERROR(__xludf.DUMMYFUNCTION("""COMPUTED_VALUE"""),161.0) -> 161 | BN68: =IFERROR(__xludf.DUMMYFUNCTION("""COMPUTED_VALUE"""),1.707) -> 1.707 | BQ68: =IFERROR(__xludf.DUMMYFUNCTION("""COMPUTED_VALUE"""),"Ancestral") -> Ancestral | BR68: =IFERROR(__xludf.DUMMYFUNCTION("""COMPUTED_VALUE"""),159.0) -> 159 | BS68: =IFERROR(__xludf.DUMMYFUNCTION("""COMPUTED_VALUE"""),10.9) -> 10.9
A69: =IFERROR(__xludf.DUMMYFUNCTION("""COMPUTED_VALUE"""),"Shock Chance") -> Shock Chance | B69: =IFERROR(__xludf.DUMMYFUNCTION("""COMPUTED_VALUE"""),14.0) -> 14 | D69: =IFERROR(__xludf.DUMMYFUNCTION("""COMPUTED_VALUE"""),30.0) -> 30 | AP69: =IFERROR(__xludf.DUMMYFUNCTION("""COMPUTED_VALUE"""),"Bot Cooldown Sliders") -> Bot Cooldown Sliders | AQ69: =IFERROR(__xludf.DUMMYFUNCTION("""COMPUTED_VALUE"""),FALSE) -> FALSE
A70: =IFERROR(__xludf.DUMMYFUNCTION("""COMPUTED_VALUE"""),"Shock Multiplier") -> Shock Multiplier | B70: =IFERROR(__xludf.DUMMYFUNCTION("""COMPUTED_VALUE"""),14.0) -> 14 | D70: =IFERROR(__xludf.DUMMYFUNCTION("""COMPUTED_VALUE"""),14.0) -> 14 | BE70: =IFERROR(__xludf.DUMMYFUNCTION("""COMPUTED_VALUE"""),"") | BG70: =IFERROR(__xludf.DUMMYFUNCTION("""COMPUTED_VALUE"""),"Defense %") -> Defense % | BH70: =IFERROR(__xludf.DUMMYFUNCTION("""COMPUTED_VALUE"""),"Legendary") -> Legendary | BI70: =IFERROR(__xludf.DUMMYFUNCTION("""COMPUTED_VALUE"""),"+5%") -> +5% | BJ70: =IFERROR(__xludf.DUMMYFUNCTION("""COMPUTED_VALUE"""),0.05) -> 0.05 | BL70: =IFERROR(__xludf.DUMMYFUNCTION("""COMPUTED_VALUE"""),"Free Utility Upgrade") -> Free Utility Upgrade | BM70: =IFERROR(__xludf.DUMMYFUNCTION("""COMPUTED_VALUE"""),"Ancestral") -> Ancestral | BN70: =IFERROR(__xludf.DUMMYFUNCTION("""COMPUTED_VALUE"""),"+12%") -> +12% | BO70: =IFERROR(__xludf.DUMMYFUNCTION("""COMPUTED_VALUE"""),0.12) -> 0.12 | BQ70: =IFERROR(__xludf.DUMMYFUNCTION("""COMPUTED_VALUE"""),"Chrono Field - Duration") -> Chrono Field - Duration | BR70: =IFERROR(__xludf.DUMMYFUNCTION("""COMPUTED_VALUE"""),"Mythic") -> Mythic | BS70: =IFERROR(__xludf.DUMMYFUNCTION("""COMPUTED_VALUE"""),"+7s") -> +7s | BT70: =IFERROR(__xludf.DUMMYFUNCTION("""COMPUTED_VALUE"""),7.0) -> 7
A71: =IFERROR(__xludf.DUMMYFUNCTION("""COMPUTED_VALUE"""),"Death Wave Health") -> Death Wave Health | B71: =IFERROR(__xludf.DUMMYFUNCTION("""COMPUTED_VALUE"""),30.0) -> 30 | D71: =IFERROR(__xludf.DUMMYFUNCTION("""COMPUTED_VALUE"""),30.0) -> 30 | BE71: =IFERROR(__xludf.DUMMYFUNCTION("""COMPUTED_VALUE"""),"") | BG71: =IFERROR(__xludf.DUMMYFUNCTION("""COMPUTED_VALUE"""),"Wall Health") -> Wall Health | BH71: =IFERROR(__xludf.DUMMYFUNCTION("""COMPUTED_VALUE"""),"Legendary") -> Legendary | BI71: =IFERROR(__xludf.DUMMYFUNCTION("""COMPUTED_VALUE"""),"+40%") -> +40% | BJ71: =IFERROR(__xludf.DUMMYFUNCTION("""COMPUTED_VALUE"""),0.4) -> 0.4 | BL71: =IFERROR(__xludf.DUMMYFUNCTION("""COMPUTED_VALUE"""),"Enemy Attack Level Skip") -> Enemy Attack Level Skip | BM71: =IFERROR(__xludf.DUMMYFUNCTION("""COMPUTED_VALUE"""),"Ancestral") -> Ancestral | BN71: =IFERROR(__xludf.DUMMYFUNCTION("""COMPUTED_VALUE"""),"+8%") -> +8% | BO71: =IFERROR(__xludf.DUMMYFUNCTION("""COMPUTED_VALUE"""),0.08) -> 0.08 | BQ71: =IFERROR(__xludf.DUMMYFUNCTION("""COMPUTED_VALUE"""),"Spotlight - Bonus") -> Spotlight - Bonus | BR71: =IFERROR(__xludf.DUMMYFUNCTION("""COMPUTED_VALUE"""),"Mythic") -> Mythic | BS71: =IFERROR(__xludf.DUMMYFUNCTION("""COMPUTED_VALUE"""),"+15x") -> +15x | BT71: =IFERROR(__xludf.DUMMYFUNCTION("""COMPUTED_VALUE"""),15.0) -> 15
A72: =IFERROR(__xludf.DUMMYFUNCTION("""COMPUTED_VALUE"""),"Death Wave Coin Bonus") -> Death Wave Coin Bonus | B72: =IFERROR(__xludf.DUMMYFUNCTION("""COMPUTED_VALUE"""),20.0) -> 20 | D72: =IFERROR(__xludf.DUMMYFUNCTION("""COMPUTED_VALUE"""),20.0) -> 20 | BE72: =IFERROR(__xludf.DUMMYFUNCTION("""COMPUTED_VALUE"""),"") | BG72: =IFERROR(__xludf.DUMMYFUNCTION("""COMPUTED_VALUE"""),"Health Regen") -> Health Regen | BH72: =IFERROR(__xludf.DUMMYFUNCTION("""COMPUTED_VALUE"""),"Legendary") -> Legendary | BI72: =IFERROR(__xludf.DUMMYFUNCTION("""COMPUTED_VALUE"""),"+100%") -> +100% | BJ72: =IFERROR(__xludf.DUMMYFUNCTION("""COMPUTED_VALUE"""),1.0) -> 1 | BL72: =IFERROR(__xludf.DUMMYFUNCTION("""COMPUTED_VALUE"""),"Coins / Kill Bonus") -> Coins / Kill Bonus | BM72: =IFERROR(__xludf.DUMMYFUNCTION("""COMPUTED_VALUE"""),"Ancestral") -> Ancestral | BN72: =IFERROR(__xludf.DUMMYFUNCTION("""COMPUTED_VALUE"""),"+0.6x") -> +0.6x | BO72: =IFERROR(__xludf.DUMMYFUNCTION("""COMPUTED_VALUE"""),0.6) -> 0.6 | BQ72: =IFERROR(__xludf.DUMMYFUNCTION("""COMPUTED_VALUE"""),"Spotlight - Angle") -> Spotlight - Angle | BR72: =IFERROR(__xludf.DUMMYFUNCTION("""COMPUTED_VALUE"""),"Epic") -> Epic | BS72: =IFERROR(__xludf.DUMMYFUNCTION("""COMPUTED_VALUE"""),"+3°") -> +3° | BT72: =IFERROR(__xludf.DUMMYFUNCTION("""COMPUTED_VALUE"""),3.0) -> 3
A73: =IFERROR(__xludf.DUMMYFUNCTION("""COMPUTED_VALUE"""),"Inner Mine Blast Radius") -> Inner Mine Blast Radius | B73: =IFERROR(__xludf.DUMMYFUNCTION("""COMPUTED_VALUE"""),0.0) -> 0 | D73: =IFERROR(__xludf.DUMMYFUNCTION("""COMPUTED_VALUE"""),20.0) -> 20 | BE73: =IFERROR(__xludf.DUMMYFUNCTION("""COMPUTED_VALUE"""),"") | BJ73: =IFERROR(__xludf.DUMMYFUNCTION("""COMPUTED_VALUE"""),"") | BL73: =IFERROR(__xludf.DUMMYFUNCTION("""COMPUTED_VALUE"""),"Enemy Health Level Skip") -> Enemy Health Level Skip | BM73: =IFERROR(__xludf.DUMMYFUNCTION("""COMPUTED_VALUE"""),"Ancestral") -> Ancestral | BN73: =IFERROR(__xludf.DUMMYFUNCTION("""COMPUTED_VALUE"""),"+8%") -> +8% | BO73: =IFERROR(__xludf.DUMMYFUNCTION("""COMPUTED_VALUE"""),0.08) -> 0.08 | BQ73: =IFERROR(__xludf.DUMMYFUNCTION("""COMPUTED_VALUE"""),"Chain Lightning - Chance") -> Chain Lightning - Chance | BR73: =IFERROR(__xludf.DUMMYFUNCTION("""COMPUTED_VALUE"""),"Rare") -> Rare | BS73: =IFERROR(__xludf.DUMMYFUNCTION("""COMPUTED_VALUE"""),"+4%") -> +4% | BT73: =IFERROR(__xludf.DUMMYFUNCTION("""COMPUTED_VALUE"""),0.04) -> 0.04
A74: =IFERROR(__xludf.DUMMYFUNCTION("""COMPUTED_VALUE"""),"Inner Mine Rotation Speed") -> Inner Mine Rotation Speed | B74: =IFERROR(__xludf.DUMMYFUNCTION("""COMPUTED_VALUE"""),0.0) -> 0 | D74: =IFERROR(__xludf.DUMMYFUNCTION("""COMPUTED_VALUE"""),20.0) -> 20 | BE74: =IFERROR(__xludf.DUMMYFUNCTION("""COMPUTED_VALUE"""),"") | BJ74: =IFERROR(__xludf.DUMMYFUNCTION("""COMPUTED_VALUE"""),"") | BL74: =IFERROR(__xludf.DUMMYFUNCTION("""COMPUTED_VALUE"""),"Package Chance") -> Package Chance | BM74: =IFERROR(__xludf.DUMMYFUNCTION("""COMPUTED_VALUE"""),"Epic") -> Epic | BN74: =IFERROR(__xludf.DUMMYFUNCTION("""COMPUTED_VALUE"""),"+5%") -> +5% | BO74: =IFERROR(__xludf.DUMMYFUNCTION("""COMPUTED_VALUE"""),0.05) -> 0.05 | BT74: =IFERROR(__xludf.DUMMYFUNCTION("""COMPUTED_VALUE"""),"")
A75: =IFERROR(__xludf.DUMMYFUNCTION("""COMPUTED_VALUE"""),"Chrono Field Range") -> Chrono Field Range | B75: =IFERROR(__xludf.DUMMYFUNCTION("""COMPUTED_VALUE"""),17.0) -> 17 | D75: =IFERROR(__xludf.DUMMYFUNCTION("""COMPUTED_VALUE"""),20.0) -> 20 | BE75: =IFERROR(__xludf.DUMMYFUNCTION("""COMPUTED_VALUE"""),"") | BJ75: =IFERROR(__xludf.DUMMYFUNCTION("""COMPUTED_VALUE"""),"") | BO75: =IFERROR(__xludf.DUMMYFUNCTION("""COMPUTED_VALUE"""),"") | BT75: =IFERROR(__xludf.DUMMYFUNCTION("""COMPUTED_VALUE"""),"")
A76: =IFERROR(__xludf.DUMMYFUNCTION("""COMPUTED_VALUE"""),"Missile Amplifier") -> Missile Amplifier | B76: =IFERROR(__xludf.DUMMYFUNCTION("""COMPUTED_VALUE"""),0.0) -> 0 | D76: =IFERROR(__xludf.DUMMYFUNCTION("""COMPUTED_VALUE"""),25.0) -> 25 | BE76: =IFERROR(__xludf.DUMMYFUNCTION("""COMPUTED_VALUE"""),"") | BJ76: =IFERROR(__xludf.DUMMYFUNCTION("""COMPUTED_VALUE"""),"") | BO76: =IFERROR(__xludf.DUMMYFUNCTION("""COMPUTED_VALUE"""),"") | BT76: =IFERROR(__xludf.DUMMYFUNCTION("""COMPUTED_VALUE"""),"")
A77: =IFERROR(__xludf.DUMMYFUNCTION("""COMPUTED_VALUE"""),"Missile Barrage") -> Missile Barrage | B77: =IFERROR(__xludf.DUMMYFUNCTION("""COMPUTED_VALUE"""),0.0) -> 0 | D77: =IFERROR(__xludf.DUMMYFUNCTION("""COMPUTED_VALUE"""),1.0) -> 1 | BE77: =IFERROR(__xludf.DUMMYFUNCTION("""COMPUTED_VALUE"""),"") | BJ77: =IFERROR(__xludf.DUMMYFUNCTION("""COMPUTED_VALUE"""),"") | BO77: =IFERROR(__xludf.DUMMYFUNCTION("""COMPUTED_VALUE"""),"") | BT77: =IFERROR(__xludf.DUMMYFUNCTION("""COMPUTED_VALUE"""),"")
A78: =IFERROR(__xludf.DUMMYFUNCTION("""COMPUTED_VALUE"""),"Missile Barrage Quantity") -> Missile Barrage Quantity | B78: =IFERROR(__xludf.DUMMYFUNCTION("""COMPUTED_VALUE"""),0.0) -> 0 | D78: =IFERROR(__xludf.DUMMYFUNCTION("""COMPUTED_VALUE"""),6.0) -> 6
